Workbook
Name IQ_CH: 110000
Name IQ_CQ: 5000
Name IQ_CY: 10000
Name IQ_DAILY: 500000
Name IQ_FH: 100000
Name IQ_FQ: 500
Name IQ_FY: 1000
Name IQ_LTM: 2000
Name IQ_MONTH: 15000
Name IQ_NTM: 6000
Name IQ_WEEK: 50000
Name IQ_YTD: 3000

Sheet Capa
B15: #VALUE!
B17: Valuation Model I 2025
B19: Autores:
B20: Carlos dos Anjos
B21: Eduardo Lima
B22: Heitor Crespo
B23: Lisa Mandetta
B24: Yago Santos
B26: Mentor:
B27: João Jaca
B29: Legenda:
B30: Input
B31: Premissas
B32: F'ormula

Sheet To do list
B2: To do list
B4: O que fazer | C4: Quem | D4: Data | E4: Check
B5: Arrumar Dívida | C5: Heitor | D5: 45973 | E5: Ok
B6: Acabar PP&E | C6: Heitor | D6: 45973 | E6: Ok
B7: Revolver | C7: Lisa | D7: 45973 | E7: Ok
B8: Melhorar premissas de Build up | C8: Eduardo | D8: 45973
B9: Arrumar COGS e SG&A | C9: Yago | D9: 45973 | E9: Ok
B10: Arrumar D&A de leasing e imob | C10: Lisa | D10: 45973
B11: Revenue Build-up | C11: Eduardo | D11: 45966 | E11: Ok
B12: COGS e SG&A | C12: Yago | D12: 45966 | E12: Ok
B13: Leasing | C13: Lisa | D13: 45965 | E13: Ok
B14: Unit Economics | C14: Carlos | D14: 45965 | E14: Ok
B15: Linkar Modelo | C15: Lisa | D15: 45961 | E15: Ok
B18: Considerações:
B19: D&A de imobilizado, intangivel e leasing continuam muito alto
B20: Checar revolver (ainda não esta linkado com o balanço)
B21: Olhar caixa para ver se faz sentido
B22: Net debt muito alto
B23: ebitda desproporcional
B25: Na aba de deal at a glance -> verificar todos os valores de % dos funders, preço pago na entrada, multiplo e etc. (apenas imputei qq coisa para testar)

Sheet Model 
D8: Unit | E8: Aux | G8: 44926 | H8: =EOMONTH(G8,12) -> 45291 | I8: =EOMONTH(H8,12) -> 45657 | J8: 1Q25 | K8: 2Q25 | L8: 3Q25 | M8: 4Q25 | N8: =EOMONTH(I8,12) -> 46022 | O8: =EOMONTH(N8,12) -> 46387 | P8: =EOMONTH(O8,12) -> 46752 | Q8: =EOMONTH(P8,12) -> 47118 | R8: =EOMONTH(Q8,12) -> 47483 | S8: =EOMONTH(R8,12) -> 47848 | T8: =EOMONTH(S8,12) -> 48213 | U8: =EOMONTH(T8,12) -> 48579 | V8: x
V9: x
C10: Overview | D10: Unit | E10: Aux | G10: 44926 | H10: =EOMONTH(G10,12) -> 45291 | I10: =EOMONTH(H10,12) -> 45657 | J10: 1Q25 | K10: 2Q25 | L10: 3Q25 | M10: 4Q25 | N10: =EOMONTH(I10,12) -> 46022 | O10: =EOMONTH(N10,12) -> 46387 | P10: =EOMONTH(O10,12) -> 46752 | Q10: =EOMONTH(P10,12) -> 47118 | R10: =EOMONTH(Q10,12) -> 47483 | S10: =EOMONTH(R10,12) -> 47848 | T10: =EOMONTH(S10,12) -> 48213 | U10: =EOMONTH(T10,12) -> 48579 | V10: x
V11: x
C12: Share Price | D12: {=_FV(Capa!B15,"Price")} -> 19.09 | J12: {=_FV(Capa!C15,"Price")} -> #VALUE! | K12: {=_FV(Capa!D15,"Price")} -> #VALUE! | L12: {=_FV(Capa!E15,"Price")} -> #VALUE! | M12: {=_FV(Capa!F15,"Price")} -> #VALUE! | V12: x
C13: Mkt Cap (mn) | D13: {=_FV(Capa!B15,"Market cap",TRUE)/1000000} -> 11761.918 | V13: x
C14: 52-week-high | D14: {=_FV(Capa!B15,"52 week high",TRUE)} -> 26.38 | V14: x
C15: % of week high | D15: =D12/D14 -> 0.72365428 | V15: x
C16: 52-week-low | D16: {=_FV(Capa!B15,"52 week low",TRUE)} -> 17.86 | V16: x
C17: Shares Outstanding (mn) | D17: {=_FV(Capa!B15,"Shares outstanding",TRUE)/1000000} -> 616.1298 | V17: x
V18: x
A19: • | B19: 1 | C19: P&L | D19: Unit | E19: Aux | G19: 44926 | H19: =EOMONTH(G19,12) -> 45291 | I19: =EOMONTH(H19,12) -> 45657 | J19: 1Q25 | K19: 2Q25 | L19: 3Q25 | M19: 4Q25 | N19: =EOMONTH(I19,12) -> 46022 | O19: =EOMONTH(N19,12) -> 46387 | P19: =EOMONTH(O19,12) -> 46752 | Q19: =EOMONTH(P19,12) -> 47118 | R19: =EOMONTH(Q19,12) -> 47483 | S19: =EOMONTH(R19,12) -> 47848 | T19: =EOMONTH(S19,12) -> 48213 | U19: =EOMONTH(T19,12) -> 48579 | V19: x
V20: x
C21: Gross Revenue | G21: 3151.8 | H21: 4539.3 | I21: 5946.1 | K21: 3682.7 | N21: =N25-N23 -> 7380.5436 | O21: =O25-O23 -> 8798.1155 | P21: =P25-P23 -> 10181.953 | Q21: =Q25-Q23 -> 11488.512 | R21: =R25-R23 -> 12752.093 | S21: =S25-S23 -> 13963.818 | T21: =T25-T23 -> 15114.091 | U21: =U25-U23 -> 16192.554 | V21: x
C22: % Growth | E22: -0.08 | H22: =H21/G21-1 -> 0.44022463 | I22: =I21/H21-1 -> 0.30991563 | N22: =N21/I21-1 -> 0.24124108 | O22: =O21/N21-1 -> 0.19206877 | P22: =P21/O21-1 -> 0.15728798 | Q22: =Q21/P21-1 -> 0.12832103 | R22: =R21/Q21-1 -> 0.10998645 | S22: =S21/R21-1 -> 0.095021654 | T22: =T21/S21-1 -> 0.08237527 | U22: =U21/T21-1 -> 0.07135479 | V22: x
C23: (-) Deductions | G23: =G25-G21 -> -221.4 | H23: =H25-H21 -> -294.6 | I23: =I25-I21 -> -365.8 | K23: =K25-K21 -> -213.4 | N23: =-N25*N24 -> -454.06477 | O23: =-O25*O24 -> -541.27643 | P23: =-P25*P24 -> -626.41271 | Q23: =-Q25*Q24 -> -706.79463 | R23: =-R25*R24 -> -784.53246 | S23: =-S25*S24 -> -859.08004 | T23: =-T25*T24 -> -929.84699 | U23: =-U25*U24 -> -996.19602 | V23: x
C24: % of Gross Revenue | G24: =-G23/G21 -> 0.070245574 | H24: =-H23/H21 -> 0.064899874 | I24: =-I23/I21 -> 0.061519315 | K24: =-K23/K21 -> 0.057946615 | N24: =AVERAGE(G24:I24) -> 0.065554921 | O24: =N24 -> 0.065554921 | P24: =O24 -> 0.065554921 | Q24: =P24 -> 0.065554921 | R24: =Q24 -> 0.065554921 | S24: =R24 -> 0.065554921 | T24: =S24 -> 0.065554921 | U24: =T24 -> 0.065554921 | V24: x
C25: (=) Net Revenue | G25: 2930.4 | H25: 4244.7 | I25: 5580.3 | K25: 3469.3 | N25: ='Build-Up'!L21 -> 6926.4788 | O25: ='Build-Up'!M21 -> 8256.839 | P25: ='Build-Up'!N21 -> 9555.5406 | Q25: ='Build-Up'!O21 -> 10781.717 | R25: ='Build-Up'!P21 -> 11967.56 | S25: ='Build-Up'!Q21 -> 13104.738 | T25: ='Build-Up'!R21 -> 14184.244 | U25: ='Build-Up'!S21 -> 15196.358 | V25: x
C26: % Growth | H26: =H25/G25-1 -> 0.44850532 | I26: =I25/H25-1 -> 0.31465121 | N26: =N25/I25-1 -> 0.24123771 | O26: =O25/N25-1 -> 0.19206877 | P26: =P25/O25-1 -> 0.15728798 | Q26: =Q25/P25-1 -> 0.12832103 | R26: =R25/Q25-1 -> 0.10998645 | S26: =S25/R25-1 -> 0.095021654 | T26: =T25/S25-1 -> 0.08237527 | U26: =U25/T25-1 -> 0.07135479 | V26: x
V27: x
C28: Smart Fit | G28: ='Build-Up'!I25 -> 2635.0583 | H28: ='Build-Up'!J25 -> 3862.887 | I28: ='Build-Up'!K25 -> 5095.6546 | J28: ='Build-Up'!L25 -> 6318.9501 | K28: ='Build-Up'!M25 -> 7519.5533 | L28: ='Build-Up'!N25 -> 8687.0622 | M28: ='Build-Up'!O25 -> 9784.0038 | N28: ='Build-Up'!L25 -> 6318.9501 | O28: ='Build-Up'!M25 -> 7519.5533 | P28: ='Build-Up'!N25 -> 8687.0622 | Q28: ='Build-Up'!O25 -> 9784.0038 | R28: ='Build-Up'!P25 -> 10839.276 | S28: ='Build-Up'!Q25 -> 11844.845 | T28: ='Build-Up'!R25 -> 12792.032 | U28: ='Build-Up'!S25 -> 13671.478 | V28: x
C29: Smart Fit Brazil | G29: ='Build-Up'!I26 -> 1224.3004 | H29: ='Build-Up'!J26 -> 1627.3657 | I29: ='Build-Up'!K26 -> 1974.5527 | J29: ='Build-Up'!L26 -> 2506.5214 | K29: ='Build-Up'!M26 -> 3034.2754 | L29: ='Build-Up'!N26 -> 3553.5493 | M29: ='Build-Up'!O26 -> 4048.9779 | N29: ='Build-Up'!L26 -> 2506.5214 | O29: ='Build-Up'!M26 -> 3034.2754 | P29: ='Build-Up'!N26 -> 3553.5493 | Q29: ='Build-Up'!O26 -> 4048.9779 | R29: ='Build-Up'!P26 -> 4532.5311 | S29: ='Build-Up'!Q26 -> 5001.2936 | T29: ='Build-Up'!R26 -> 5452.1089 | U29: ='Build-Up'!S26 -> 5881.5642 | V29: x
C30: Smart Fit Mexico | G30: ='Build-Up'!I27 -> 635.14394 | H30: ='Build-Up'!J27 -> 1001.8226 | I30: ='Build-Up'!K27 -> 1362.2397 | J30: ='Build-Up'!L27 -> 1640.6662 | K30: ='Build-Up'!M27 -> 1910.7528 | L30: ='Build-Up'!N27 -> 2170.1035 | M30: ='Build-Up'!O27 -> 2409.5632 | N30: ='Build-Up'!L27 -> 1640.6662 | O30: ='Build-Up'!M27 -> 1910.7528 | P30: ='Build-Up'!N27 -> 2170.1035 | Q30: ='Build-Up'!O27 -> 2409.5632 | R30: ='Build-Up'!P27 -> 2636.4064 | S30: ='Build-Up'!Q27 -> 2848.5213 | T30: ='Build-Up'!R27 -> 3043.6312 | U30: ='Build-Up'!S27 -> 3219.284 | V30: x
C31: Smart Fit Others LatAm | G31: ='Build-Up'!I28 -> 775.61392 | H31: ='Build-Up'!J28 -> 1233.6987 | I31: ='Build-Up'!K28 -> 1758.8621 | J31: ='Build-Up'!L28 -> 2171.7625 | K31: ='Build-Up'!M28 -> 2574.5252 | L31: ='Build-Up'!N28 -> 2963.4094 | M31: ='Build-Up'!O28 -> 3325.4627 | N31: ='Build-Up'!L28 -> 2171.7625 | O31: ='Build-Up'!M28 -> 2574.5252 | P31: ='Build-Up'!N28 -> 2963.4094 | Q31: ='Build-Up'!O28 -> 3325.4627 | R31: ='Build-Up'!P28 -> 3670.3385 | S31: ='Build-Up'!Q28 -> 3995.0298 | T31: ='Build-Up'!R28 -> 4296.2922 | U31: ='Build-Up'!S28 -> 4570.63 | V31: x
C32: Bio Ritmo and O2 | G32: ='Build-Up'!I30 -> 106.27873 | H32: ='Build-Up'!J34 -> 243.16305 | I32: ='Build-Up'!K34 -> 319.42629 | J32: ='Build-Up'!L30 -> 216.19562 | K32: ='Build-Up'!M30 -> 270.53801 | L32: ='Build-Up'!N30 -> 328.25279 | M32: ='Build-Up'!O30 -> 388.27615 | N32: ='Build-Up'!L34 -> 391.33309 | O32: ='Build-Up'!M34 -> 466.74773 | P32: ='Build-Up'!N34 -> 540.22557 | Q32: ='Build-Up'!O34 -> 609.43738 | R32: ='Build-Up'!P34 -> 676.18516 | S32: ='Build-Up'!Q34 -> 739.979 | T32: ='Build-Up'!R34 -> 800.28957 | U32: ='Build-Up'!S34 -> 856.54566 | V32: x
C33: Franchises | V33: x
C34: Digital | V34: x
V35: x
C36: (-) Costs | G36: -2018.4 | H36: -2533.9 | I36: -3267.4 | K36: -1977.8 | N36: ='Build-Up'!L204 -> -3712.439 | O36: ='Build-Up'!M204 -> -4503.0106 | P36: ='Build-Up'!N204 -> -5285.5253 | Q36: ='Build-Up'!O204 -> -6040.7217 | R36: ='Build-Up'!P204 -> -6778.5743 | S36: ='Build-Up'!Q204 -> -7494.5142 | T36: ='Build-Up'!R204 -> -8183.588 | U36: ='Build-Up'!S204 -> -8840.4328 | V36: x
C37: % of revenue | G37: =-G36/G25 -> 0.68877969 | H37: =-H36/H25 -> 0.5969562 | I37: =-I36/I25 -> 0.58552408 | K37: =-K36/K25 -> 0.57008618 | N37: =-N36/N25 -> 0.53597782 | O37: =-O36/O25 -> 0.54536737 | P37: =-P36/P25 -> 0.55313724 | Q37: =-Q36/Q25 -> 0.56027454 | R37: =-R36/R25 -> 0.56641239 | S37: =-S36/S25 -> 0.5718935 | T37: =-T36/T25 -> 0.57694919 | U37: =-U36/U25 -> 0.58174683 | V37: x
V38: x
C39: Gross Profit | G39: 912 | H39: 1710.9 | I39: 2312.9 | K39: 1491.5 | N39: =N25+N36 -> 3214.0398 | O39: =O25+O36 -> 3753.8284 | P39: =P25+P36 -> 4270.0153 | Q39: =Q25+Q36 -> 4740.9956 | R39: =R25+R36 -> 5188.9859 | S39: =S25+S36 -> 5610.2233 | T39: =T25+T36 -> 6000.6559 | U39: =U25+U36 -> 6355.9248 | V39: x
C40: % Margin | G40: =G39/G25 -> 0.31122031 | H40: =H39/H25 -> 0.40306735 | I40: =I39/I25 -> 0.41447592 | K40: =K39/K25 -> 0.42991382 | N40: =N39/N25 -> 0.46402218 | O40: =O39/O25 -> 0.45463263 | P40: =P39/P25 -> 0.44686276 | Q40: =Q39/Q25 -> 0.43972546 | R40: =R39/R25 -> 0.43358761 | S40: =S39/S25 -> 0.4281065 | T40: =T39/T25 -> 0.42305081 | U40: =U39/U25 -> 0.41825317 | V40: x
V41: x
C42: (-) SG&A | G42: -653.2 | H42: -664.9 | I42: -1050.1 | K42: -683 | N42: ='Build-Up'!L242 -> -1322.1653 | O42: ='Build-Up'!M242 -> -1561.4204 | P42: ='Build-Up'!N242 -> -1794.994 | Q42: ='Build-Up'!O242 -> -2015.461 | R42: ='Build-Up'!P242 -> -2228.8212 | S42: ='Build-Up'!Q242 -> -2433.591 | T42: ='Build-Up'!R242 -> -2628.1665 | U42: ='Build-Up'!S242 -> -2810.8165 | V42: x
C43: % of revenue | G43: =-G42/G25 -> 0.22290472 | H43: =-H42/H25 -> 0.1566424 | I43: =-I42/I25 -> 0.18817985 | K43: =-K42/K25 -> 0.19686969 | N43: =-N42/N25 -> 0.19088564 | O43: =-O42/O25 -> 0.18910632 | P43: =-P42/P25 -> 0.1878485 | Q43: =-Q42/Q25 -> 0.18693321 | R43: =-R42/R25 -> 0.18623856 | S43: =-S42/S25 -> 0.18570314 | T43: =-T42/T25 -> 0.18528774 | U43: =-U42/U25 -> 0.18496646 | V43: x
C44: Desespesas com vendas | G44: -292.3 | H44: -344.8 | I44: -451 | K44: -295 | V44: x
C45: Gerais e Administrativas | G45: -348 | H45: -468.4 | I45: -575.3 | K45: -367.4 | V45: x
C46: Aluguéis | G46: -5.1 | H46: -5.2 | I46: -7.7 | K46: -5.6 | V46: x
V47: x
C48: (+/-) Other revenue (expenses) | G48: -12.8 | H48: 148.2 | I48: -23.9 | K48: -20.7 | V48: x
V49: x
C50: (+/-) Equivalência Patrimonial | G50: 6.6 | H50: -1.1 | I50: 0.8 | K50: 1.6 | V50: x
V51: x
C52: (=) EBIT | G52: 265.4 | H52: 1044.9 | I52: 1263.6 | K52: 810 | N52: =N39+N42 -> 1891.8744 | O52: =O39+O42 -> 2192.408 | P52: =P39+P42 -> 2475.0213 | Q52: =Q39+Q42 -> 2725.5346 | R52: =R39+R42 -> 2960.1647 | S52: =S39+S42 -> 3176.6324 | T52: =T39+T42 -> 3372.4893 | U52: =U39+U42 -> 3545.1083 | V52: x
C53: % Margin | G53: =G52/G25 -> 0.090567841 | H53: =H52/H25 -> 0.24616581 | I53: =I52/I25 -> 0.22643944 | K53: =K52/K25 -> 0.23347649 | N53: =N52/N25 -> 0.27313653 | O53: =O52/O25 -> 0.26552631 | P53: =P52/P25 -> 0.25901426 | Q53: =Q52/Q25 -> 0.25279225 | R53: =R52/R25 -> 0.24734905 | S53: =S52/S25 -> 0.24240336 | T53: =T52/T25 -> 0.23776307 | U53: =U52/U25 -> 0.23328671 | V53: x
V54: x
C55: Financial Result | G55: -347.7 | H55: -473.3 | I55: -767.3 | K55: -449.6 | N55: =SUM(N56:N57) -> -1491.3488 | O55: =SUM(O56:O57) -> -1471.2007 | P55: =SUM(P56:P57) -> -1517.021 | Q55: =SUM(Q56:Q57) -> -1606.6695 | R55: =SUM(R56:R57) -> -1716.8844 | S55: =SUM(S56:S57) -> -1784.0727 | T55: =SUM(T56:T57) -> -1876.3328 | U55: =SUM(U56:U57) -> -1980.8482 | V55: x
C56: (+) Interest Income | V56: x
C57: (-) Financial expenses | G57: -346.8989 | H57: -472.57504 | I57: -766.64159 | K57: =SUM(K58:K59) -> -449.6 | N57: =SUM(N58:N59) -> -1491.3488 | O57: =SUM(O58:O59) -> -1471.2007 | P57: =SUM(P58:P59) -> -1517.021 | Q57: =SUM(Q58:Q59) -> -1606.6695 | R57: =SUM(R58:R59) -> -1716.8844 | S57: =SUM(S58:S59) -> -1784.0727 | T57: =SUM(T58:T59) -> -1876.3328 | U57: =SUM(U58:U59) -> -1980.8482 | V57: x
C58: Juros de Arrendamento Mercantil | G58: -277.9 | H58: -342.6 | I58: -428.1 | K58: -256.2 | N58: ='Build-Up'!L1047 -> -772.56602 | O58: ='Build-Up'!M1047 -> -652.99663 | P58: ='Build-Up'!N1047 -> -560.06691 | Q58: ='Build-Up'!O1047 -> -518.39055 | R58: ='Build-Up'!P1047 -> -501.63677 | S58: ='Build-Up'!Q1047 -> -447.1097 | T58: ='Build-Up'!R1047 -> -423.87737 | U58: ='Build-Up'!S1047 -> -420.16965 | V58: x
C59: Others | G59: -69.8 | H59: -130.7 | I59: -339.1 | K59: -193.4 | N59: ='Build-Up'!L413 -> -718.78283 | O59: ='Build-Up'!M413 -> -818.20406 | P59: ='Build-Up'!N413 -> -956.95405 | Q59: ='Build-Up'!O413 -> -1088.2789 | R59: ='Build-Up'!P413 -> -1215.2477 | S59: ='Build-Up'!Q413 -> -1336.963 | T59: ='Build-Up'!R413 -> -1452.4555 | U59: ='Build-Up'!S413 -> -1560.6785 | V59: x
V60: x
C61: (=) EBT | G61: =G52+G55 -> -82.3 | H61: =H52+H55 -> 571.6 | I61: =I52+I55 -> 496.3 | K61: =K52+K55 -> 360.4 | N61: =N52+N55 -> 400.52557 | O61: =O52+O55 -> 721.20732 | P61: =P52+P55 -> 958.00031 | Q61: =Q52+Q55 -> 1118.8651 | R61: =R52+R55 -> 1243.2803 | S61: =S52+S55 -> 1392.5596 | T61: =T52+T55 -> 1496.1565 | U61: =U52+U55 -> 1564.2601 | V61: x
C62: % Margin | G62: =G61/G25 -> -0.028084903 | H62: =H61/H25 -> 0.13466205 | I62: =I61/I25 -> 0.088937871 | K62: =K61/K25 -> 0.10388263 | N62: =N61/N25 -> 0.057825279 | O62: =O61/O25 -> 0.087346661 | P62: =P61/P25 -> 0.100256 | Q62: =Q61/Q25 -> 0.1037743 | R62: =R61/R25 -> 0.10388753 | S62: =S61/S25 -> 0.10626383 | T62: =T61/T25 -> 0.10548017 | U62: =U61/U25 -> 0.10293651 | V62: x
V63: x
C64: (-) Income Taxes | G64: -3.7 | H64: 472.6 | I64: -55.8 | K64: -78.6 | N64: =N65*-N61 -> -45.03189 | O64: =O65*-O61 -> -81.08678 | P64: =P65*-P61 -> -107.70989 | Q64: =Q65*-Q61 -> -125.79624 | R64: =R65*-R61 -> -139.78448 | S64: =S65*-S61 -> -156.56826 | T64: =T65*-T61 -> -168.21586 | U64: =U65*-U61 -> -175.87289 | V64: x
C65: % EBT | G65: =-G64/G61 -> -0.044957473 | H65: =-H64/H61 -> -0.82680196 | I65: =-I64/I61 -> 0.112432 | K65: =-K64/K61 -> 0.21809101 | N65: =I65 -> 0.112432 | O65: =N65 -> 0.112432 | P65: =O65 -> 0.112432 | Q65: =P65 -> 0.112432 | R65: =Q65 -> 0.112432 | S65: =R65 -> 0.112432 | T65: =S65 -> 0.112432 | U65: =T65 -> 0.112432 | V65: x
V66: x
C67: (=) Net Income | G67: -86.1 | H67: 1044.2 | I67: 440.6 | K67: 281.8 | N67: =N61+N64 -> 355.49368 | O67: =O61+O64 -> 640.12054 | P67: =P61+P64 -> 850.29042 | Q67: =Q61+Q64 -> 993.06889 | R67: =R61+R64 -> 1103.4958 | S67: =S61+S64 -> 1235.9914 | T67: =T61+T64 -> 1327.9406 | U67: =U61+U64 -> 1388.3872 | V67: x
C68: % Margin | G68: =G67/G25 -> -0.029381654 | H68: =H67/H25 -> 0.2460009 | I68: =I67/I25 -> 0.078956329 | K68: =K67/K25 -> 0.08122676 | N68: =N67/N25 -> 0.051323868 | O68: =O67/O25 -> 0.077526102 | P68: =P67/P25 -> 0.088984021 | Q68: =Q67/Q25 -> 0.092106746 | R68: =R67/R25 -> 0.092207248 | S68: =S67/S25 -> 0.094316377 | T68: =T67/T25 -> 0.093620826 | U68: =U67/U25 -> 0.091363157 | V68: x
C69: YoY | H69: =H67/G67-1 -> -13.127758 | I69: =I67/H67-1 -> -0.57805018 | J69: =J67/I67-1 -> -1 | K69: =K67/J67-1 -> #DIV/0! | L69: =L67/K67-1 -> -1 | M69: =M67/L67-1 -> #DIV/0! | N69: =N67/I67-1 -> -0.19316005 | O69: =O67/I67-1 -> 0.45283828 | P69: =P67/O67-1 -> 0.32832859 | Q69: =Q67/P67-1 -> 0.16791731 | R69: =R67/Q67-1 -> 0.11119761 | S69: =S67/R67-1 -> 0.12006895 | T69: =T67/S67-1 -> 0.074393122 | U69: =U67/T67-1 -> 0.045519037 | V69: x
V70: x
V71: x
C72: Depreciação e amortização | G72: 902.3 | H72: 1157.4 | I72: 1412.3 | K72: 835.5 | N72: =SUM(N73:N78) -> -2105.6357 | O72: =SUM(O73:O78) -> -2647.1122 | P72: =SUM(P73:P78) -> -3185.1785 | Q72: =SUM(Q73:Q78) -> -3711.4266 | R72: =SUM(R73:R78) -> -4227.7922 | S72: =SUM(S73:S78) -> -4731.2477 | T72: =SUM(T73:T78) -> -5218.5063 | U72: =SUM(U73:U78) -> -5686.0062 | V72: x
C73: Depreciação de Direito de Uso | G73: 454.5 | H73: 559.7 | I73: 660.3 | K73: 374.8 | N73: ='Build-Up'!L374 -> -819.58926 | O73: ='Build-Up'!M374 -> -977.00676 | P73: ='Build-Up'!N374 -> -1130.6782 | Q73: ='Build-Up'!O374 -> -1275.768 | R73: ='Build-Up'!P374 -> -1416.0852 | S73: ='Build-Up'!Q374 -> -1550.6439 | T73: ='Build-Up'!R374 -> -1678.3786 | U73: ='Build-Up'!S374 -> -1798.139 | V73: x
G74: =G73/G25 -> 0.15509828 | H74: =H73/H25 -> 0.13185855 | I74: =I73/I25 -> 0.11832697 | J74: =J73/J25 -> #DIV/0! | K74: =K73/K25 -> 0.10803332 | L74: =L73/L25 -> #DIV/0! | M74: =M73/M25 -> #DIV/0! | N74: =-N73/N25 -> 0.11832697 | O74: =-O73/O25 -> 0.11832697 | P74: =-P73/P25 -> 0.11832697 | Q74: =-Q73/Q25 -> 0.11832697 | R74: =-R73/R25 -> 0.11832697 | S74: =-S73/S25 -> 0.11832697 | T74: =-T73/T25 -> 0.11832697 | U74: =-U73/U25 -> 0.11832697 | V74: x
C75: Depreciação de Imobilizado | G75: 420.8 | H75: 549.4 | I75: 703.1 | K75: 429.5 | N75: ='Build-Up'!L341 -> -1286.3504 | O75: ='Build-Up'!M341 -> -1670.426 | P75: ='Build-Up'!N341 -> -2054.8337 | Q75: ='Build-Up'!O341 -> -2436.0029 | R75: ='Build-Up'!P341 -> -2812.0604 | S75: ='Build-Up'!Q341 -> -3180.9649 | T75: ='Build-Up'!R341 -> -3540.4957 | U75: ='Build-Up'!S341 -> -3888.2414 | V75: x | W75: Imobilizado + Intangível
G76: =G75/G25 -> 0.14359814 | H76: =H75/H25 -> 0.129432 | I76: =I75/I25 -> 0.12599681 | J76: =J75/J25 -> #DIV/0! | K76: =K75/K25 -> 0.12380019 | L76: =L75/L25 -> #DIV/0! | M76: =M75/M25 -> #DIV/0! | N76: =-N75/N25 -> 0.18571492 | O76: =-O75/O25 -> 0.20230818 | P76: =-P75/P25 -> 0.21504108 | Q76: =-Q75/Q25 -> 0.2259383 | R76: =-R75/R25 -> 0.23497357 | S76: =-S75/S25 -> 0.24273396 | T76: =-T75/T25 -> 0.24960764 | U76: =-U75/U25 -> 0.25586667 | V76: x
C77: Amortização de Intangível | G77: 27 | H77: 48.3 | I77: 48.8 | K77: 31.1 | N77: 0 | O77: 0 | P77: 0 | Q77: 0 | R77: 0 | S77: 0 | T77: 0 | U77: 0 | V77: x
C78: Outros | G78: 0 | H78: 0 | I78: 0 | K78: 0 | N78: 0 | O78: 0 | P78: 0 | Q78: 0 | R78: 0 | S78: 0 | T78: 0 | U78: 0 | V78: x
V79: x
C80: EBITDA | G80: 1167.7 | H80: 2202.3 | I80: 2675.9 | K80: 1645.5 | N80: =N52-N72 -> 3997.5101 | O80: =O52-O72 -> 4839.5202 | P80: =P52-P72 -> 5660.1998 | Q80: =Q52-Q72 -> 6436.9612 | R80: =R52-R72 -> 7187.9569 | S80: =S52-S72 -> 7907.8801 | T80: =T52-T72 -> 8590.9957 | U80: =U52-U72 -> 9231.1145 | V80: x
C81: % Margin | G81: =G80/G25 -> 0.39847802 | H81: =H80/H25 -> 0.51883525 | I81: =I80/I25 -> 0.47952619 | K81: =K80/K25 -> 0.47430317 | N81: =N80/N25 -> 0.57713453 | O81: =O80/O25 -> 0.58612262 | P81: =P80/P25 -> 0.59234742 | Q81: =Q80/Q25 -> 0.59702559 | R81: =R80/R25 -> 0.60062008 | S81: =S80/S25 -> 0.60343674 | T81: =T80/T25 -> 0.60567174 | U81: =U80/U25 -> 0.60745573 | V81: x
V82: x
A83: • | B83: 2 | C83: Balance Sheet | D83: Unit | E83: Aux | G83: 44926 | H83: =EOMONTH(G83,12) -> 45291 | I83: =EOMONTH(H83,12) -> 45657 | J83: 1Q25 | K83: 2Q25 | L83: 3Q25 | M83: 4Q25 | N83: =EOMONTH(I83,12) -> 46022 | O83: =EOMONTH(N83,12) -> 46387 | P83: =EOMONTH(O83,12) -> 46752 | Q83: =EOMONTH(P83,12) -> 47118 | R83: =EOMONTH(Q83,12) -> 47483 | S83: =EOMONTH(R83,12) -> 47848 | T83: =EOMONTH(S83,12) -> 48213 | U83: =EOMONTH(T83,12) -> 48579 | V83: x
V84: x
C85: Assets | G85: 12049.6 | H85: 14230.2 | I85: 18350.3 | K85: 18456 | N85: =N86+N91 -> 17851.641 | O85: =O86+O91 -> 18883.075 | P85: =P86+P91 -> 20566.882 | Q85: =Q86+Q91 -> 21843.541 | R85: =R86+R91 -> 22739.227 | S85: =S86+S91 -> 23913.769 | T85: =T86+T91 -> 25236.877 | U85: =U86+U91 -> 26618.755 | V85: x
C86: Current | G86: 3516.2 | H86: 3346.1 | I86: 4112.3 | K86: 3965.9 | N86: =SUM(N87:N90) -> 1089.6169 | O86: =SUM(O87:O90) -> -258.53263 | P86: =SUM(P87:P90) -> -678.64529 | Q86: =SUM(Q87:Q90) -> -656.87945 | R86: =SUM(R87:R90) -> -34.1157 | S86: =SUM(S87:S90) -> 1320.2945 | T86: =SUM(T87:T90) -> 3285.1583 | U86: =SUM(U87:U90) -> 5778.8619 | V86: x
C87: Caixa e equivalentes de caixa | G87: 1251.4 | H87: 1103.4 | I87: 1490.6 | K87: 1059.2 | N87: =N186 -> -252.66529 | O87: =O186 -> -1858.6253 | P87: =P186 -> -2530.4132 | Q87: =Q186 -> -2746.2682 | R87: =R186 -> -2353.3089 | S87: =S186 -> -1219.2722 | T87: =T186 -> 536.39401 | U87: =U186 -> 2833.9602 | V87: x | W87: Caixa
C88: Investimentos em ativos financeiros | G88: 1671.4 | H88: 1509.9 | I88: 1456.8 | K88: 1673.3 | N88: 0 | O88: 0 | P88: 0 | Q88: 0 | R88: 0 | S88: 0 | T88: 0 | U88: 0 | V88: x | W88: Caixa
C89: Clientes | G89: 271.7 | H89: 349 | I89: 554.1 | K89: 631.2 | N89: ='Build-Up'!L302 -> 630.48525 | O89: ='Build-Up'!M302 -> 751.58177 | P89: ='Build-Up'!N302 -> 869.79655 | Q89: ='Build-Up'!O302 -> 981.40974 | R89: ='Build-Up'!P302 -> 1089.3515 | S89: ='Build-Up'!Q302 -> 1192.8635 | T89: ='Build-Up'!R302 -> 1291.1259 | U89: ='Build-Up'!S302 -> 1383.254 | V89: x | W89: WK
C90: Outros | G90: 321.6 | H90: 383.8 | I90: 610.9 | K90: 602.1 | N90: ='Build-Up'!L314 -> 711.7969 | O90: ='Build-Up'!M314 -> 848.51085 | P90: ='Build-Up'!N314 -> 981.97141 | Q90: ='Build-Up'!O314 -> 1107.979 | R90: ='Build-Up'!P314 -> 1229.8417 | S90: ='Build-Up'!Q314 -> 1346.7033 | T90: ='Build-Up'!R314 -> 1457.6383 | U90: ='Build-Up'!S314 -> 1561.6478 | V90: x | W90: WK
C91: Non-Current | G91: 8533.4 | H91: 10884 | I91: 14238 | K91: 14490 | N91: =SUM(N92:N101) -> 16762.025 | O91: =SUM(O92:O101) -> 19141.608 | P91: =SUM(P92:P101) -> 21245.528 | Q91: =SUM(Q92:Q101) -> 22500.42 | R91: =SUM(R92:R101) -> 22773.343 | S91: =SUM(S92:S101) -> 22593.474 | T91: =SUM(T92:T101) -> 21951.719 | U91: =SUM(U92:U101) -> 20839.893 | V91: x
C92: Impostos a recuperar | G92: 52.5 | H92: 33.3 | I92: 6.1 | K92: 14 | N92: ='Build-Up'!L308 -> 51.32504 | O92: ='Build-Up'!M308 -> 61.182978 | P92: ='Build-Up'!N308 -> 70.806325 | Q92: ='Build-Up'!O308 -> 79.892265 | R92: ='Build-Up'!P308 -> 88.679332 | S92: ='Build-Up'!Q308 -> 97.105788 | T92: ='Build-Up'!R308 -> 105.1049 | U92: ='Build-Up'!S308 -> 112.60464 | V92: x | W92: WK
C93: Investimentos em ativos financeiros | G93: 47.2 | H93: 84.2 | I93: 140.7 | K93: 132.6 | N93: 0 | O93: 0 | P93: 0 | Q93: 0 | R93: 0 | S93: 0 | T93: 0 | U93: 0 | V93: x | W93: Caixa
C94: Ativos por imposto diferido | G94: 204.6 | H94: 798.3 | I94: 913.5 | K94: 925.2 | N94: =I94 -> 913.5 | O94: =N94 -> 913.5 | P94: =O94 -> 913.5 | Q94: =P94 -> 913.5 | R94: =Q94 -> 913.5 | S94: =R94 -> 913.5 | T94: =S94 -> 913.5 | U94: =T94 -> 913.5 | V94: x | W94: Flat
C95: Depósitos judiciais | G95: 79.8 | H95: 100.9 | I95: 81.7 | K95: 83.7 | N95: =I95 -> 81.7 | O95: =N95 -> 81.7 | P95: =O95 -> 81.7 | Q95: =P95 -> 81.7 | R95: =Q95 -> 81.7 | S95: =R95 -> 81.7 | T95: =S95 -> 81.7 | U95: =T95 -> 81.7 | V95: x | W95: Flat
C96: Outros | G96: 60.5 | H96: 73.3 | I96: 128.3 | K96: 84.1 | N96: =I96 -> 128.3 | O96: =N96 -> 128.3 | P96: =O96 -> 128.3 | Q96: =P96 -> 128.3 | R96: =Q96 -> 128.3 | S96: =R96 -> 128.3 | T96: =S96 -> 128.3 | U96: =T96 -> 128.3 | V96: x | W96: Flat
C97: Imobilizado | G97: 3132 | H97: 4044.6 | I97: 5537.4 | K97: 5774.3 | N97: ='Build-Up'!L325 -> 9986.393 | O97: ='Build-Up'!M325 -> 11681.757 | P97: ='Build-Up'!N325 -> 12995.624 | Q97: ='Build-Up'!O325 -> 13899.941 | R97: ='Build-Up'!P325 -> 14383.405 | S97: ='Build-Up'!Q325 -> 14435.281 | T97: ='Build-Up'!R325 -> 14045.481 | U97: ='Build-Up'!S325 -> 13204.658 | V97: x | W97: Build-Up
C98: Lease | G98: 3067.4 | H98: 3755 | I98: 4934.2 | K98: 5002.6 | N98: ='Build-Up'!L365 -> 5499.9065 | O98: ='Build-Up'!M365 -> 6174.2675 | P98: ='Build-Up'!N365 -> 6954.6975 | Q98: ='Build-Up'!O365 -> 7296.1871 | R98: ='Build-Up'!P365 -> 7076.858 | S98: ='Build-Up'!Q365 -> 6836.6878 | T98: ='Build-Up'!R365 -> 6576.7336 | U98: ='Build-Up'!S365 -> 6298.2304 | V98: x | W98: Build-Up
C99: Intangível | G99: 1412.5 | H99: 1913 | I99: 2395.1 | K99: 2426.9 | N99: 0 | O99: 0 | P99: 0 | Q99: 0 | R99: 0 | S99: 0 | T99: 0 | U99: 0 | V99: x | W99: Build-Up
C100: Investimentos em controladas e joint ventures | G100: 448 | H100: 40.9 | I100: 55.4 | K100: 1 | N100: =I100 -> 55.4 | O100: =N100 -> 55.4 | P100: =O100 -> 55.4 | Q100: =P100 -> 55.4 | R100: =Q100 -> 55.4 | S100: =R100 -> 55.4 | T100: =S100 -> 55.4 | U100: =T100 -> 55.4 | V100: x | W100: Flat
C101: Outros ativos fixos | G101: 28.9 | H101: 40.5 | I101: 45.5 | K101: 45.9 | N101: =I101 -> 45.5 | O101: =N101 -> 45.5 | P101: =O101 -> 45.5 | Q101: =P101 -> 45.5 | R101: =Q101 -> 45.5 | S101: =R101 -> 45.5 | T101: =S101 -> 45.5 | U101: =T101 -> 45.5 | V101: x | W101: Flat
C102: Revolver
V103: x
C104: Liabilities and Shareholders' Equity | G104: 12049.6 | H104: 14230.2 | I104: 18350.3 | K104: 18456 | N104: =N105+N114+N119 -> 17851.945 | O104: =O105+O114+O119 -> 18883.7 | P104: =P105+P114+P119 -> 20567.84 | Q104: =Q105+Q114+Q119 -> 21844.843 | R104: =R105+R114+R119 -> 22740.883 | S104: =S105+S114+S119 -> 23915.786 | T104: =T105+T114+T119 -> 25239.262 | U104: =U105+U114+U119 -> 26621.514 | V104: x
C105: Current | G105: 1746.4 | H105: 2244.2 | I105: 2791.7 | K105: 2726.1 | N105: =SUM(N106:N113) -> 2699.337 | O105: =SUM(O106:O113) -> 2962.7911 | P105: =SUM(P106:P113) -> 3300.0902 | Q105: =SUM(Q106:Q113) -> 3578.2987 | R105: =SUM(R106:R113) -> 3804.0494 | S105: =SUM(S106:S113) -> 4055.2622 | T105: =SUM(T106:T113) -> 4316.219 | U105: =SUM(U106:U113) -> 4575.7735 | V105: x
C106: Empréstimos | G106: 488.2 | H106: 594.4 | I106: 759.7 | K106: 831.2 | N106: ='Build-Up'!L408 -> 759.7 | O106: ='Build-Up'!M408 -> 864.78085 | P106: ='Build-Up'!N408 -> 1011.4293 | Q106: ='Build-Up'!O408 -> 1150.2299 | R106: ='Build-Up'!P408 -> 1284.4264 | S106: ='Build-Up'!Q408 -> 1413.0705 | T106: ='Build-Up'!R408 -> 1535.1374 | U106: ='Build-Up'!S408 -> 1649.5212 | V106: x | W106: Build-Up
C107: Passivos de arrendamentos | G107: 449.7 | H107: 542.2 | I107: 649.8 | K107: 684.1 | N107: ='Build-Up'!L1042 -> 584.54503 | O107: ='Build-Up'!M1042 -> 574.59536 | P107: ='Build-Up'!N1042 -> 599.44898 | Q107: ='Build-Up'!O1042 -> 580.07549 | R107: ='Build-Up'!P1042 -> 517.02226 | S107: ='Build-Up'!Q1042 -> 490.15719 | T107: ='Build-Up'!R1042 -> 485.86971 | U107: ='Build-Up'!S1042 -> 495.29032 | V107: x | W107: Build-Up
...

Sheet Build-Up
D8: Build - up | E8: Unit | F8: Aux 1 | G8: Aux 2 | I8: 44926 | J8: =EOMONTH(I8,12) -> 45291 | K8: =EOMONTH(J8,12) -> 45657 | L8: =EOMONTH(K8,12) -> 46022 | M8: =EOMONTH(L8,12) -> 46387 | N8: =EOMONTH(M8,12) -> 46752 | O8: =EOMONTH(N8,12) -> 47118 | P8: =EOMONTH(O8,12) -> 47483 | Q8: =EOMONTH(P8,12) -> 47848 | ... S8: =EOMONTH(R8,12) -> 48579 | T8: x
T9: x
D10: Macroeconomic indicators | T10: x
T11: x
D12: GDP Growth | E12: % | I12: 0.030167179 | J12: 0.032416518 | K12: 0.033958548 | L12: 0.021539771 | M12: 0.014746764 | N12: 0.015254131 | O12: 0.014640622 | P12: =O12 -> 0.014640622 | Q12: =P12 -> 0.014640622 | R12: =Q12 -> 0.014640622 | S12: =R12 -> 0.014640622 | T12: x
D13: IPCA | E13: % | I13: 0.057850929 | J13: 0.0462119 | K13: 0.048311967 | L13: 0.046805155 | M13: 0.042797908 | N13: 0.04 | O13: 0.035 | P13: =O13 -> 0.035 | Q13: =P13 -> 0.035 | R13: =Q13 -> 0.035 | S13: =R13 -> 0.035 | T13: x
D14: IGP-M | E14: % | I14: 0.054512856 | J14: -0.03175828 | K14: 0.065356584 | L14: 0.010751398 | M14: 0.034132099 | N14: 0.04 | O14: 0.035 | P14: =O14 -> 0.035 | Q14: =P14 -> 0.035 | R14: =Q14 -> 0.035 | S14: =R14 -> 0.035 | T14: x
D15: Selic | E15: % | I15: 0.1375 | J15: 0.1175 | K15: 0.1225 | L15: 0.15 | M15: 0.1275 | N15: 0.1125 | O15: 0.1025 | P15: =O15 -> 0.1025 | Q15: =P15 -> 0.1025 | R15: =Q15 -> 0.1025 | S15: =R15 -> 0.1025 | T15: x
D16: CDI | E16: % | I16: 0.12421569 | J16: 0.13198299 | K16: 0.10838193 | L16: 0.14305189 | M16: 0.13440971 | N16: 0.11727771 | O16: 0.10405011 | P16: 0.10405011 | Q16: 0.10405011 | R16: 0.10405011 | S16: =R16 -> 0.10405011 | T16: x
D17: BRL/USD | E17: % | I17: 5.2804 | J17: 4.8572 | K17: 6.1774 | L17: 5.35 | M17: 5.5 | N17: 5.7 | O17: 5.75 | P17: =O17 -> 5.75 | Q17: =P17 -> 5.75 | R17: =Q17 -> 5.75 | S17: =R17 -> 5.75 | T17: x
T18: x
A19: • | B19: 1 | D19: Revenue Build-up | T19: x
T20: x
D21: Net Revenue | I21: ='Model '!G25 -> 2930.4 | J21: ='Model '!H25 -> 4244.7 | K21: ='Model '!I25 -> 5580.3 | L21: =L25+L30+L34 -> 6926.4788 | M21: =M25+M30+M34 -> 8256.839 | N21: =N25+N30+N34 -> 9555.5406 | O21: =O25+O30+O34 -> 10781.717 | P21: =P25+P30+P34 -> 11967.56 | Q21: =Q25+Q30+Q34 -> 13104.738 | R21: =R25+R30+R34 -> 14184.244 | S21: =S25+S30+S34 -> 15196.358 | T21: x
T22: x
D23: By Region | T23: x
T24: x
D25: SmartFit | I25: 2635.0583 | J25: 3862.887 | K25: 5095.6546 | L25: =SUM(L26:L28) -> 6318.9501 | M25: =SUM(M26:M28) -> 7519.5533 | N25: =SUM(N26:N28) -> 8687.0622 | O25: =SUM(O26:O28) -> 9784.0038 | P25: =SUM(P26:P28) -> 10839.276 | Q25: =SUM(Q26:Q28) -> 11844.845 | R25: =SUM(R26:R28) -> 12792.032 | S25: =SUM(S26:S28) -> 13671.478 | T25: x
D26: Brasil | I26: 1224.3004 | J26: 1627.3657 | K26: 1974.5527 | L26: =L38 -> 2506.5214 | M26: =M38 -> 3034.2754 | N26: =N38 -> 3553.5493 | O26: =O38 -> 4048.9779 | P26: =P38 -> 4532.5311 | Q26: =Q38 -> 5001.2936 | R26: =R38 -> 5452.1089 | S26: =S38 -> 5881.5642 | T26: x
D27: México | I27: 635.14394 | J27: 1001.8226 | K27: 1362.2397 | L27: =L45 -> 1640.6662 | M27: =M45 -> 1910.7528 | N27: =N45 -> 2170.1035 | O27: =O45 -> 2409.5632 | P27: =P45 -> 2636.4064 | Q27: =Q45 -> 2848.5213 | R27: =R45 -> 3043.6312 | S27: =S45 -> 3219.284 | T27: x
D28: Other | I28: 775.61392 | J28: 1233.6987 | K28: 1758.8621 | L28: =L52 -> 2171.7625 | M28: =M52 -> 2574.5252 | N28: =N52 -> 2963.4094 | O28: =O52 -> 3325.4627 | P28: =P52 -> 3670.3385 | Q28: =Q52 -> 3995.0298 | R28: =R52 -> 4296.2922 | S28: =S52 -> 4570.63 | T28: x
T29: x
D30: Bio Ritmo & Others | I30: 106.27873 | J30: 138.6927 | K30: 165.2232 | L30: =L59 -> 216.19562 | M30: =M59 -> 270.53801 | N30: =N59 -> 328.25279 | O30: =O59 -> 388.27615 | P30: =P59 -> 452.09905 | Q30: =Q59 -> 519.9139 | R30: =R59 -> 591.92198 | S30: =S59 -> 668.33373 | T30: x
D31: Brasil | I31: 99.602608 | J31: 131.24883 | K31: 158.00247 | L31: =K31/K30*L30 -> 206.74726 | M31: =L31/L30*M30 -> 258.71473 | N31: =M31/M30*N30 -> 313.9072 | O31: =N31/N30*O30 -> 371.30738 | P31: =O31/O30*P30 -> 432.34103 | Q31: =P31/P30*Q30 -> 497.19218 | R31: =Q31/Q30*R30 -> 566.0533 | S31: =R31/R30*S30 -> 639.12563 | T31: x
D32: Other | I32: =I30-I31 -> 6.6761192 | J32: =J30-J31 -> 7.4438672 | K32: =K30-K31 -> 7.2207264 | L32: =L30-L31 -> 9.448367 | M32: =M30-M31 -> 11.823285 | N32: =N30-N31 -> 14.345586 | O32: =O30-O31 -> 16.968778 | P32: =P30-P31 -> 19.758021 | ... S32: =S30-S31 -> 29.208095 | T32: x
T33: x
D34: Other | I34: 189.10324 | J34: 243.16305 | K34: 319.42629 | L34: =L66 -> 391.33309 | M34: =M66 -> 466.74773 | N34: =N66 -> 540.22557 | O34: =O66 -> 609.43738 | P34: =P66 -> 676.18516 | Q34: =Q66 -> 739.979 | R34: =R66 -> 800.28957 | S34: =S66 -> 856.54566 | T34: x
T35: x
D36: Smartfit - Brasil | T36: x
T37: x
D38: Own gym revenue | I38: =I26 -> 1224.3004 | J38: =J26 -> 1627.3657 | K38: =K26 -> 1974.5527 | L38: =L39*L41 -> 2506.5214 | M38: =M39*M41 -> 3034.2754 | N38: =N39*N41 -> 3553.5493 | O38: =O39*O41 -> 4048.9779 | P38: =P39*P41 -> 4532.5311 | Q38: =Q39*Q41 -> 5001.2936 | R38: =R39*R41 -> 5452.1089 | S38: =S39*S41 -> 5881.5642 | T38: x
D39: Revenue per client (R$) | I39: =I38/I170 -> 1.0507429 | J39: =J38/J170 -> 1.2024908 | K39: =K38/K170 -> 1.2657138 | L39: =K39*(1+L13) -> 1.3249557 | M39: =L39*(1+M13) -> 1.381661 | N39: =M39*(1+N13) -> 1.4369275 | O39: =N39*(1+O13) -> 1.4872199 | P39: =O39*(1+P13) -> 1.5392726 | Q39: =P39*(1+Q13) -> 1.5931472 | R39: =Q39*(1+R13) -> 1.6489073 | S39: =R39*(1+S13) -> 1.7066191 | T39: x
D40: yoy growth (%) | J40: =J39/I39-1 -> 0.14441966 | K40: =K39/J39-1 -> 0.052576666 | L40: =L39/K39-1 -> 0.046805155 | M40: =M39/L39-1 -> 0.042797908 | N40: =N39/M39-1 -> 0.04 | O40: =O39/N39-1 -> 0.035 | P40: =P39/O39-1 -> 0.035 | Q40: =Q39/P39-1 -> 0.035 | ... S40: =S39/R39-1 -> 0.035 | T40: x
D41: # of clients | I41: =I170 -> 1165.176 | J41: =J170 -> 1353.329 | K41: =K170 -> 1560.031 | L41: =L170 -> 1891.7775 | M41: =M170 -> 2196.1069 | N41: =N170 -> 2473.0193 | O41: =O170 -> 2722.5146 | P41: =P170 -> 2944.5928 | ... S41: =S170 -> 3446.3251 | T41: x
T42: x
D43: Smartfit - Mexico | T43: x
T44: x
D45: Own gym revenue | I45: =I27 -> 635.14394 | J45: =J27 -> 1001.8226 | K45: =K27 -> 1362.2397 | L45: =L46*L48 -> 1640.6662 | M45: =M46*M48 -> 1910.7528 | N45: =N46*N48 -> 2170.1035 | O45: =O46*O48 -> 2409.5632 | P45: =P46*P48 -> 2636.4064 | Q45: =Q46*Q48 -> 2848.5213 | R45: =R46*R48 -> 3043.6312 | S45: =S46*S48 -> 3219.284 | T45: x
D46: Revenue per client (R$) | I46: =I45/I171 -> 0.97003195 | J46: =J45/J171 -> 1.1774789 | K46: =K45/K171 -> 1.4355186 | L46: =K46*(1+L13) -> 1.5027083 | M46: =L46*(1+M13) -> 1.5670211 | N46: =M46*(1+N13) -> 1.6297019 | O46: =N46*(1+O13) -> 1.6867415 | P46: =O46*(1+P13) -> 1.7457775 | Q46: =P46*(1+Q13) -> 1.8068797 | R46: =Q46*(1+R13) -> 1.8701205 | S46: =R46*(1+S13) -> 1.9355747 | T46: x
D47: yoy growth (%) | J47: =J46/I46-1 -> 0.21385578 | K47: =K46/J46-1 -> 0.21914597 | L47: =L46/K46-1 -> 0.046805155 | M47: =M46/L46-1 -> 0.042797908 | N47: =N46/M46-1 -> 0.04 | O47: =O46/N46-1 -> 0.035 | P47: =P46/O46-1 -> 0.035 | Q47: =Q46/P46-1 -> 0.035 | ... S47: =S46/R46-1 -> 0.035 | T47: x
D48: # of clients | I48: =I171 -> 654.766 | J48: =J171 -> 850.82 | K48: =K171 -> 948.953 | L48: =L171 -> 1091.8061 | M48: =M171 -> 1219.3536 | N48: =N171 -> 1331.5953 | O48: =O171 -> 1428.5314 | P48: =P171 -> 1510.1618 | ... S48: =S171 -> 1663.2187 | T48: x
T49: x
D50: Smartfit - Others | T50: x
T51: x
D52: Own gym revenue | I52: =I28 -> 775.61392 | J52: =J28 -> 1233.6987 | K52: =K28 -> 1758.8621 | L52: =L53*L55 -> 2171.7625 | M52: =M53*M55 -> 2574.5252 | N52: =N53*N55 -> 2963.4094 | O52: =O53*O55 -> 3325.4627 | P52: =P53*P55 -> 3670.3385 | Q52: =Q53*Q55 -> 3995.0298 | R52: =R53*R55 -> 4296.2922 | S52: =S53*S55 -> 4570.63 | T52: x
D53: Revenue per client (R$) | I53: =I52/I172 -> 0.91996793 | J53: =J52/J172 -> 1.2096461 | K53: =K52/K172 -> 1.311076 | L53: =K53*(1+L13) -> 1.3724411 | M53: =L53*(1+M13) -> 1.4311787 | N53: =M53*(1+N13) -> 1.4884258 | O53: =N53*(1+O13) -> 1.5405207 | P53: =O53*(1+P13) -> 1.5944389 | Q53: =P53*(1+Q13) -> 1.6502443 | R53: =Q53*(1+R13) -> 1.7080029 | S53: =R53*(1+S13) -> 1.767783 | T53: x
D54: yoy growth (%) | J54: =J53/I53-1 -> 0.31487858 | K54: =K53/J53-1 -> 0.083850823 | L54: =L53/K53-1 -> 0.046805155 | M54: =M53/L53-1 -> 0.042797908 | N54: =N53/M53-1 -> 0.04 | O54: =O53/N53-1 -> 0.035 | P54: =P53/O53-1 -> 0.035 | Q54: =Q53/P53-1 -> 0.035 | ... S54: =S53/R53-1 -> 0.035 | T54: x
D55: # of clients | I55: =I172 -> 843.088 | J55: =J172 -> 1019.884 | K55: =K172 -> 1341.541 | L55: =L172 -> 1582.4086 | M55: =M172 -> 1798.8845 | N55: =N172 -> 1990.9688 | O55: =O172 -> 2158.6614 | P55: =P172 -> 2301.9624 | ... S55: =S172 -> 2585.5154 | T55: x
T56: x
D57: Bio Ritmo & Others | T57: x
T58: x
D59: Own gym revenue | I59: =I30 -> 106.27873 | J59: =J30 -> 138.6927 | K59: =K30 -> 165.2232 | L59: =L60*L62 -> 216.19562 | M59: =M60*M62 -> 270.53801 | N59: =N60*N62 -> 328.25279 | O59: =O60*O62 -> 388.27615 | P59: =P60*P62 -> 452.09905 | Q59: =Q60*Q62 -> 519.9139 | R59: =R60*R62 -> 591.92198 | S59: =S60*S62 -> 668.33373 | T59: x
D60: Revenue per client (R$) | I60: =I59/I179 -> 2.1073669 | J60: =J59/J179 -> 2.7068857 | K60: =K59/K179 -> 3.1191845 | L60: =K60*(1+L13) -> 3.2651784 | M60: =L60*(1+M13) -> 3.4049212 | N60: =M60*(1+N13) -> 3.541118 | O60: =N60*(1+O13) -> 3.6650571 | P60: =O60*(1+P13) -> 3.7933341 | Q60: =P60*(1+Q13) -> 3.9261008 | R60: =Q60*(1+R13) -> 4.0635144 | S60: =R60*(1+S13) -> 4.2057374 | T60: x
D61: yoy growth (%) | J61: =J60/I60-1 -> 0.28448713 | K61: =K60/J60-1 -> 0.15231482 | L61: =L60/K60-1 -> 0.046805155 | M61: =M60/L60-1 -> 0.042797908 | N61: =N60/M60-1 -> 0.04 | O61: =O60/N60-1 -> 0.035 | P61: =P60/O60-1 -> 0.035 | Q61: =Q60/P60-1 -> 0.035 | ... S61: =S60/R60-1 -> 0.035 | T61: x
D62: # of clients | I62: =I179 -> 50.432 | J62: =J179 -> 51.237 | K62: =K179 -> 52.97 | L62: =L179 -> 66.2125 | M62: =M179 -> 79.455 | N62: =N179 -> 92.6975 | O62: =O179 -> 105.94 | P62: =P179 -> 119.1825 | ... S62: =S179 -> 158.91 | T62: x
T63: x
D64: Other | T64: x
T65: x
D66: Own gym revenue | I66: =I34 -> 189.10324 | J66: =J34 -> 243.16305 | K66: =K34 -> 319.42629 | L66: =L67*L69 -> 391.33309 | M66: =M67*M69 -> 466.74773 | N66: =N67*N69 -> 540.22557 | O66: =O67*O69 -> 609.43738 | P66: =P67*P69 -> 676.18516 | Q66: =Q67*Q69 -> 739.979 | R66: =R67*R69 -> 800.28957 | S66: =S67*S69 -> 856.54566 | T66: x
D67: Revenue per client (R$) | I67: =I66/I69 -> 0.55017775 | J67: =J66/J69 -> 0.77035167 | K67: =K66/K69 -> 0.85177165 | L67: =K67*(1+L13) -> 0.89163896 | M67: =L67*(1+M13) -> 0.92979924 | N67: =M67*(1+N13) -> 0.96699121 | O67: =N67*(1+O13) -> 1.0008359 | P67: =O67*(1+P13) -> 1.0358652 | Q67: =P67*(1+Q13) -> 1.0721204 | R67: =Q67*(1+R13) -> 1.1096447 | S67: =R67*(1+S13) -> 1.1484822 | T67: x
D68: yoy growth (%) | J68: =J67/I67-1 -> 0.40018689 | K68: =K67/J67-1 -> 0.10569197 | L68: =L67/K67-1 -> 0.046805155 | M68: =M67/L67-1 -> 0.042797908 | N68: =N67/M67-1 -> 0.04 | O68: =O67/N67-1 -> 0.035 | P68: =P67/O67-1 -> 0.035 | Q68: =Q67/P67-1 -> 0.035 | ... S68: =S67/R67-1 -> 0.035 | T68: x
D69: # of clients | I69: =I181+I183 -> 343.713 | J69: =J181+J183 -> 315.652 | K69: =K181+K183 -> 375.014 | L69: =L181+L183 -> 438.89187 | M69: =M181+M183 -> 501.98764 | N69: =N181+N183 -> 558.66648 | O69: =O181+O183 -> 608.92838 | P69: =P181+P183 -> 652.77334 | ... S69: =S181+S183 -> 745.80664 | T69: x
T70: x
D71: # of gyms | T71: x
T72: x
D73: Total # of gyms | F73: =SUM(F75,F86,F90) -> 911 | G73: =SUM(G75,G86,G90) -> 1077 | I73: =SUM(I75,I86,I90) -> 1236 | J73: =SUM(J75,J86,J90) -> 1459 | K73: =SUM(K75,K86,K90) -> 1878 | L73: =SUM(L75,L86,L90) -> 2228 | M73: =SUM(M75,M86,M90) -> 2552 | N73: =SUM(N75,N86,N90) -> 2850 | O73: =SUM(O75,O86,O90) -> 3122 | P73: =SUM(P75,P86,P90) -> 3368 | ... S73: =SUM(S75,S86,S90) -> 3950 | T73: x
L74: =L73/K73-1 -> 0.18636848 | M74: =M73/L73-1 -> 0.1454219 | N74: =N73/M73-1 -> 0.11677116 | O74: =O73/N73-1 -> 0.095438596 | P74: =P73/O73-1 -> 0.078795644 | Q74: =Q73/P73-1 -> 0.065320665 | R74: =R73/Q73-1 -> 0.054069119 | S74: =S73/R73-1 -> 0.044420941 | T74: x
D75: Smart Fit | F75: 867 | G75: 1033 | I75: 1196 | J75: 1410 | K75: 1711 | L75: =SUM(L76,L81) -> 2031 | M75: =SUM(M76,M81) -> 2321 | N75: =SUM(N76,N81) -> 2581 | O75: =SUM(O76,O81) -> 2811 | P75: =SUM(P76,P81) -> 3011 | Q75: =SUM(Q76,Q81) -> 3181 | R75: =SUM(R76,R81) -> 3321 | S75: =SUM(S76,S81) -> 3431 | T75: x
D76: Próprias | F76: 676 | G76: 807 | I76: 945 | J76: 1121 | K76: 1381 | L76: =K76+L98 -> 1637 | M76: =L76+M98 -> 1869 | N76: =M76+N98 -> 2077 | O76: =N76+O98 -> 2261 | P76: =O76+P98 -> 2421 | Q76: =P76+Q98 -> 2557 | R76: =Q76+R98 -> 2669 | S76: =R76+S98 -> 2757 | T76: x
D77: Brasil | F77: 343 | G77: 408 | I77: 429 | J77: 486 | K77: 569 | L77: =K77+L99 -> 690 | M77: =L77+M99 -> 801 | N77: =M77+N99 -> 902 | O77: =N77+O99 -> 993 | P77: =O77+P99 -> 1074 | Q77: =P77+Q99 -> 1145 | R77: =Q77+R99 -> 1206 | S77: =R77+S99 -> 1257 | T77: x
D78: México | F78: 172 | G78: 192 | I78: 245 | J78: 302 | K78: 372 | L78: =K78+L100 -> 428 | M78: =L78+M100 -> 478 | N78: =M78+N100 -> 522 | O78: =N78+O100 -> 560 | P78: =O78+P100 -> 592 | Q78: =P78+Q100 -> 618 | R78: =Q78+R100 -> 638 | S78: =R78+S100 -> 652 | T78: x
D79: Other | F79: 161 | G79: 207 | I79: 271 | J79: 333 | K79: 440 | L79: =K79+L101 -> 519 | M79: =L79+M101 -> 590 | N79: =M79+N101 -> 653 | O79: =N79+O101 -> 708 | P79: =O79+P101 -> 755 | Q79: =P79+Q101 -> 794 | R79: =Q79+R101 -> 825 | S79: =R79+S101 -> 848 | T79: x
T80: x
D81: Franquias | F81: 191 | G81: 226 | I81: 251 | J81: 289 | K81: 330 | L81: =K81+L103 -> 394 | M81: =L81+M103 -> 452 | N81: =M81+N103 -> 504 | O81: =N81+O103 -> 550 | P81: =O81+P103 -> 590 | Q81: =P81+Q103 -> 624 | R81: =Q81+R103 -> 652 | S81: =R81+S103 -> 674 | T81: x
D82: Brasil | F82: 154 | G82: 165 | I82: 179 | J82: 193 | K82: 224 | L82: =K82+L104 -> 254 | M82: =L82+M104 -> 281 | N82: =M82+N104 -> 305 | O82: =N82+O104 -> 326 | P82: =O82+P104 -> 344 | Q82: =P82+Q104 -> 359 | R82: =Q82+R104 -> 371 | S82: =R82+S104 -> 380 | T82: x
D83: México | F83: 10 | G83: 9 | I83: 9 | J83: 16 | K83: 23 | L83: =K83+L105 -> 37 | M83: =L83+M105 -> 50 | N83: =M83+N105 -> 62 | O83: =N83+O105 -> 73 | P83: =O83+P105 -> 83 | Q83: =P83+Q105 -> 92 | R83: =Q83+R105 -> 100 | S83: =R83+S105 -> 107 | T83: x
D84: Other | F84: 27 | G84: 52 | I84: 63 | J84: 80 | K84: 83 | L84: =K84+L106 -> 103 | M84: =L84+M106 -> 121 | N84: =M84+N106 -> 137 | O84: =N84+O106 -> 151 | P84: =O84+P106 -> 163 | Q84: =P84+Q106 -> 173 | R84: =Q84+R106 -> 181 | S84: =R84+S106 -> 187 | T84: x
T85: x
D86: Bio Ritmo & Others | F86: 33 | G86: 32 | I86: 27 | J86: 28 | K86: 32 | L86: =K86+L108 -> 40 | M86: =L86+M108 -> 48 | N86: =M86+N108 -> 56 | O86: =N86+O108 -> 64 | P86: =O86+P108 -> 72 | Q86: =P86+Q108 -> 80 | R86: =Q86+R108 -> 88 | S86: =R86+S108 -> 96 | T86: x
D87: Próprias | F87: 28 | G87: 27 | I87: 22 | J87: 23 | K87: 26 | L87: =K87+L109 -> 32 | M87: =L87+M109 -> 38 | N87: =M87+N109 -> 44 | O87: =N87+O109 -> 50 | P87: =O87+P109 -> 56 | Q87: =P87+Q109 -> 62 | R87: =Q87+R109 -> 68 | S87: =R87+S109 -> 74 | T87: x
D88: Franquias | F88: 5 | G88: 5 | I88: 5 | J88: 5 | K88: 6 | L88: =K88+L110 -> 8 | M88: =L88+M110 -> 10 | N88: =M88+N110 -> 12 | O88: =N88+O110 -> 14 | P88: =O88+P110 -> 16 | Q88: =P88+Q110 -> 18 | R88: =Q88+R110 -> 20 | S88: =R88+S110 -> 22 | T88: x
T89: x
D90: Studios | F90: 11 | G90: 12 | I90: 13 | J90: 21 | K90: 135 | L90: =K90+L112 -> 157 | M90: =L90+M112 -> 183 | N90: =M90+N112 -> 213 | O90: =N90+O112 -> 247 | P90: =O90+P112 -> 285 | Q90: =P90+Q112 -> 327 | R90: =Q90+R112 -> 373 | S90: =R90+S112 -> 423 | T90: x
T91: x
T92: x
D93: Net Openings | T93: x
T94: x
D95: Total Net Openigs | G95: =G73-F73 -> 166 | I95: =SUM(I97,I108,I112) -> 159 | J95: =SUM(J97,J108,J112) -> 223 | K95: =SUM(K97,K108,K112) -> 419 | L95: =SUM(L97,L108,L112) -> 350 | M95: =SUM(M97,M108,M112) -> 324 | N95: =SUM(N97,N108,N112) -> 298 | O95: =SUM(O97,O108,O112) -> 272 | P95: =SUM(P97,P108,P112) -> 246 | ... S95: =SUM(S97,S108,S112) -> 168 | T95: x
T96: x
D97: Smart Fit | I97: =SUM(I98,I103) -> 163 | J97: =SUM(J98,J103) -> 214 | K97: =SUM(K98,K103) -> 301 | L97: =SUM(L98,L103) -> 320 | M97: =SUM(M98,M103) -> 290 | N97: =SUM(N98,N103) -> 260 | O97: =SUM(O98,O103) -> 230 | P97: =SUM(P98,P103) -> 200 | ... S97: =SUM(S98,S103) -> 110 | T97: x
D98: Próprias | F98: =SUM(F99:F101) -> 256 | G98: =SUM(G99:G101) -> -24 | I98: =I76-G76 -> 138 | J98: =J76-I76 -> 176 | K98: =K76-J76 -> 260 | L98: =F98 -> 256 | M98: =L98+$G98 -> 232 | N98: =M98+$G98 -> 208 | O98: =N98+$G98 -> 184 | P98: =O98+$G98 -> 160 | Q98: =P98+$G98 -> 136 | R98: =Q98+$G98 -> 112 | S98: =R98+$G98 -> 88 | T98: x
D99: Brasil | F99: 121 | G99: -10 | I99: =I77-G77 -> 21 | J99: =J77-I77 -> 57 | K99: =K77-J77 -> 83 | L99: =F99 -> 121 | M99: =L99+$G99 -> 111 | N99: =M99+$G99 -> 101 | O99: =N99+$G99 -> 91 | P99: =O99+$G99 -> 81 | Q99: =P99+$G99 -> 71 | R99: =Q99+$G99 -> 61 | S99: =R99+$G99 -> 51 | T99: x
D100: México | F100: 56 | G100: -6 | I100: =I78-G78 -> 53 | J100: =J78-I78 -> 57 | K100: =K78-J78 -> 70 | L100: =F100 -> 56 | M100: =L100+$G100 -> 50 | N100: =M100+$G100 -> 44 | O100: =N100+$G100 -> 38 | P100: =O100+$G100 -> 32 | Q100: =P100+$G100 -> 26 | R100: =Q100+$G100 -> 20 | S100: =R100+$G100 -> 14 | T100: x
D101: Other | F101: 79 | G101: -8 | I101: =I79-G79 -> 64 | J101: =J79-I79 -> 62 | K101: =K79-J79 -> 107 | L101: =F101 -> 79 | M101: =L101+$G101 -> 71 | N101: =M101+$G101 -> 63 | O101: =N101+$G101 -> 55 | P101: =O101+$G101 -> 47 | Q101: =P101+$G101 -> 39 | R101: =Q101+$G101 -> 31 | S101: =R101+$G101 -> 23 | T101: x
T102: x
D103: Franquias | F103: =SUM(F104:F106) -> 64 | G103: =SUM(G104:G106) -> -6 | I103: =I81-G81 -> 25 | J103: =J81-I81 -> 38 | K103: =K81-J81 -> 41 | L103: =F103 -> 64 | M103: =L103+$G103 -> 58 | N103: =M103+$G103 -> 52 | O103: =N103+$G103 -> 46 | P103: =O103+$G103 -> 40 | Q103: =P103+$G103 -> 34 | R103: =Q103+$G103 -> 28 | S103: =R103+$G103 -> 22 | T103: x
D104: Brasil | F104: 30 | G104: -3 | I104: =I82-G82 -> 14 | J104: =J82-I82 -> 14 | K104: =K82-J82 -> 31 | L104: =F104 -> 30 | M104: =L104+$G104 -> 27 | N104: =M104+$G104 -> 24 | O104: =N104+$G104 -> 21 | P104: =O104+$G104 -> 18 | Q104: =P104+$G104 -> 15 | R104: =Q104+$G104 -> 12 | S104: =R104+$G104 -> 9 | T104: x
D105: México | F105: 14 | G105: -1 | I105: =I83-G83 -> 0 | J105: =J83-I83 -> 7 | K105: =K83-J83 -> 7 | L105: =F105 -> 14 | M105: =L105+$G105 -> 13 | N105: =M105+$G105 -> 12 | O105: =N105+$G105 -> 11 | P105: =O105+$G105 -> 10 | Q105: =P105+$G105 -> 9 | R105: =Q105+$G105 -> 8 | S105: =R105+$G105 -> 7 | T105: x
D106: Other | F106: 20 | G106: -2 | I106: =I84-G84 -> 11 | J106: =J84-I84 -> 17 | K106: =K84-J84 -> 3 | L106: =F106 -> 20 | M106: =L106+$G106 -> 18 | N106: =M106+$G106 -> 16 | O106: =N106+$G106 -> 14 | P106: =O106+$G106 -> 12 | Q106: =P106+$G106 -> 10 | R106: =Q106+$G106 -> 8 | S106: =R106+$G106 -> 6 | T106: x
T107: x
...

Sheet Unit Economics
C8: Premissas
C10: Growth Capex LTM | F10: 706.00633
C11: Maintenance Capex LTM | F11: 230.3
C13: New Units Opened | F13: =F14-F15 -> 289
C14: Units 2Q25 | F14: 1818
C15: Units 2Q24 | F15: 1529
C17: P&L | D17: Unit | E17: [aux1] | F17: [aux2] | G17: 1 | H17: 2 | I17: 3 | J17: 4 | K17: 5
C19: Revenue/Store | G19: =G20*$I$19 -> 2.8846154 | H19: =H20*$I$19 -> 4.0865385 | I19: =I25/I26 -> 4.8076923 | J19: =J20*$I$19 -> 4.8076923 | K19: =K20*$I$19 -> 4.8076923
C20: % Mature | G20: 0.6 | H20: 0.85 | I20: 1 | J20: 1 | K20: 1
C22: (-) Costs | G22: =G19*G23 -> 1.5460899 | H22: =H19*H23 -> 2.190294 | I22: =I19*I23 -> 2.5768165 | J22: =J19*J23 -> 2.5768165 | K22: =K19*K23 -> 2.5768165
C23: % of revenue | G23: ='Model '!N37 -> 0.53597782 | H23: =G23 -> 0.53597782 | I23: =H23 -> 0.53597782 | J23: =I23 -> 0.53597782 | K23: =J23 -> 0.53597782
C25: Gross Profit | G25: =G19-G22 -> 1.3385255 | H25: =H19-H22 -> 1.8962445 | I25: 2.5 | J25: =J19-J22 -> 2.2308758 | K25: =K19-K22 -> 2.2308758
C26: % Margin | G26: =G25/G$19 -> 0.46402218 | H26: =H25/H$19 -> 0.46402218 | I26: 0.52 | J26: =J25/J$19 -> 0.46402218 | K26: =K25/K$19 -> 0.46402218
C28: (-) SG&A | G28: =G$19*G29 -> 0.55063166 | H28: =H$19*H29 -> 0.78006151 | I28: =I$19*I29 -> 0.91771943 | J28: =J$19*J29 -> 0.91771943 | K28: =K$19*K29 -> 0.91771943
C29: % of revenue | G29: ='Model '!N43 -> 0.19088564 | H29: =G29 -> 0.19088564 | I29: =H29 -> 0.19088564 | J29: =I29 -> 0.19088564 | K29: =J29 -> 0.19088564
C31: EBITDA | G31: =G25-G28 -> 0.78789385 | H31: =H25-H28 -> 1.116183 | I31: =I25-I28 -> 1.5822806 | J31: =J25-J28 -> 1.3131564 | K31: =K25-K28 -> 1.3131564
C32: % of revenue | G32: =G31/G$19 -> 0.27313653 | H32: =H31/H$19 -> 0.27313653 | I32: =I31/I$19 -> 0.32911436 | J32: =J31/J$19 -> 0.27313653 | K32: =K31/K$19 -> 0.27313653
C34: (-) D&A | G34: =-('Build-Up'!$L$344/$F$14) -> 0.4979043 | H34: =G34 -> 0.4979043 | I34: =H34 -> 0.4979043 | J34: =I34 -> 0.4979043 | K34: =J34 -> 0.4979043
C35: % of revenue | G35: =G34/G$19 -> 0.17260682 | H35: =H34/H$19 -> 0.12184011 | I35: =I34/I$19 -> 0.10356409 | J35: =J34/J$19 -> 0.10356409 | K35: =K34/K$19 -> 0.10356409
C38: EBIT | G38: =G31-G34 -> 0.28998955 | H38: =H31-H34 -> 0.61827865 | I38: =I31-I34 -> 1.0843763 | J38: =J31-J34 -> 0.81525212 | K38: =K31-K34 -> 0.81525212
C39: % of revenue | G39: =G38/G$19 -> 0.10052971 | H39: =H38/H$19 -> 0.15129642 | I39: =I38/I$19 -> 0.22555026 | J39: =J38/J$19 -> 0.16957244 | K39: =K38/K$19 -> 0.16957244
C41: (-) Taxes | G41: =G38*G42 -> 0.098596447 | H41: =H38*H42 -> 0.21021474 | I41: =I38*I42 -> 0.36868793 | J41: =J38*J42 -> 0.27718572 | K41: =K38*K42 -> 0.27718572
C42: Tax Rate | G42: 0.34 | H42: =G42 -> 0.34 | I42: =H42 -> 0.34 | J42: =I42 -> 0.34 | K42: =J42 -> 0.34
C44: NOPAT | G44: =G38-G41 -> 0.1913931 | H44: =H38-H41 -> 0.40806391 | I44: =I38-I41 -> 0.71568834 | J44: =J38-J41 -> 0.5380664 | K44: =K38-K41 -> 0.5380664
C45: % of revenue | G45: =G44/G$19 -> 0.066349609 | H45: =H44/H$19 -> 0.09985564 | I45: =I44/I$19 -> 0.14886317 | J45: =J44/J$19 -> 0.11191781 | K45: =K44/K$19 -> 0.11191781
C47: Capex | G47: =SUM(G49:G50) -> 2.4429285 | H47: =SUM(H49:H50) -> 0.12667767 | I47: =SUM(I49:I50) -> 0.12667767 | J47: =SUM(J49:J50) -> 0.12667767 | K47: =SUM(K49:K50) -> 0.12667767
C48: % of revenue | G48: =G47/G$19 -> 0.84688187 | H48: =H47/H$19 -> 0.03099877 | I48: =I47/I$19 -> 0.026348955 | J48: =J47/J$19 -> 0.026348955 | K48: =K47/K$19 -> 0.026348955
C49: Opening Capex | G49: =F10/F13 -> 2.4429285
C50: Unit Maintenance Capex | H50: =F11/F14 -> 0.12667767 | I50: =H50 -> 0.12667767 | J50: =I50 -> 0.12667767 | K50: =J50 -> 0.12667767
C52: Cash Flow | D52: Unit | E52: [aux1] | F52: [aux2] | G52: 1 | H52: 2 | I52: 3 | J52: 4 | K52: 5
C54: Cash Flow | G54: =G56-G57-G58 -> -1.7536311 | H54: =H56-H57-H58 -> 0.77929054 | I54: =I56-I57-I58 -> 1.086915 | J54: =J56-J57-J58 -> 0.90929303 | K54: =K56-K57-K58 -> 0.90929303
C56: (+) EBITDA | G56: =G31 -> 0.78789385 | H56: =H31 -> 1.116183 | I56: =I31 -> 1.5822806 | J56: =J31 -> 1.3131564 | K56: =K31 -> 1.3131564
C57: (-) Taxes | G57: =G41 -> 0.098596447 | H57: =H41 -> 0.21021474 | I57: =I41 -> 0.36868793 | J57: =J41 -> 0.27718572 | K57: =K41 -> 0.27718572
C58: (-) Opening Capex | G58: =G47 -> 2.4429285 | H58: =H47 -> 0.12667767 | I58: =I47 -> 0.12667767 | J58: =J47 -> 0.12667767 | K58: =K47 -> 0.12667767
C60: Accumulated Cash Flow | G60: =SUM($G$54:G54) -> -1.7536311 | H60: =SUM($G$54:H54) -> -0.97434054 | I60: =SUM($G$54:I54) -> 0.11257443 | J60: =SUM($G$54:J54) -> 1.0218675 | K60: =SUM($G$54:K54) -> 1.9311605
G61: =IF(AND(G60>0,F60<0),-F60/G54+G17,0) -> 0 | H61: =IF(AND(H60>0,G60<0),-G60/H54+H17,0) -> 0 | I61: =IF(AND(I60>0,H60<0),-H60/I54+I17,0) -> 3.8964276 | J61: =IF(AND(J60>0,I60<0),-I60/J54+J17,0) -> 0 | K61: =IF(AND(K60>0,J60<0),-J60/K54+K17,0) -> 0
D62: Unit | E62: [aux1] | F62: [aux2] | G62: 1 | H62: 2 | I62: 3 | J62: 4 | K62: 5
C64: Payback | D64: =SUM(G61:J61) -> 3.8964276
C65: IRR 5y | D65: =IRR(G60:K60) -> 0.036734343

Sheet D@G
B7: D@G
B9: FX Rate | D9: 5.4 | H9: Deal Cash Flow (R$mn) | J9: 44926 | K9: =EOMONTH(J9,12) -> 45291 | L9: =EOMONTH(K9,12) -> 45657 | M9: =EOMONTH(L9,12) -> 46022 | N9: =EOMONTH(M9,12) -> 46387 | O9: =EOMONTH(N9,12) -> 46752 | P9: =EOMONTH(O9,12) -> 47118 | Q9: =EOMONTH(P9,12) -> 47483 | R9: =EOMONTH(Q9,12) -> 47848 | S9: =EOMONTH(R9,12) -> 48213 | T9: Acc | V9: Returns (R$mn)
H10: Money In | M10: =-D45 -> -5000 | N10: =N57 -> 0 | O10: =O57 -> 0 | P10: =P57 -> 0 | Q10: =Q57 -> 0 | R10: =R57 -> 0 | S10: =S57 -> 0 | T10: =SUM(M10:S10) -> -5000 | V10: MoM | W10: =-T15/M15 -> 0.70034857
B11: Entry Valuation (R$mn) | D11: 46022 | E11: =EOMONTH(D11,12) -> 46387 | F11: =EOMONTH(E11,12) -> 46752 | H11: Money Out | M11: =D44 -> 0 | N11: 0 | O11: 0 | P11: 0 | Q11: 0 | R11: 0 | S11: 0 | T11: =-SUM(M11:S11) -> 0 | V11: IRR | W11: =IRR(M15:S15) -> 0.11491929
H12: DD Costs | M12: =-D46 -> -10 | N12: 0 | O12: 0 | P12: 0 | Q12: 0 | R12: 0 | S12: 0 | T12: =SUM(M12:S12) -> -10 | V12: K-Gain | W12: =T15 -> 3508.7464
B13: EV / Revenue | D13: =D18/M22 -> 3.5716617 | E13: =E18/N22 -> 2.9961876 | F13: =F18/O22 -> 2.5889733 | H13: Dividends | N13: =-M58*$F$36 -> 52.338899 | O13: =-N58*$F$36 -> 94.244164 | P13: =-O58*$F$36 -> 125.18722 | Q13: =-P58*$F$36 -> 146.20832 | R13: =-Q58*$F$36 -> 162.46633 | S13: 0 | T13: =SUM(N13:S13) -> 580.44493
B14: EV / EBITDA | D14: 7 | E14: =E18/N28 -> 5.7820961 | F14: =F18/O28 -> 4.9437425 | H14: Exit Proceeds | N14: 0 | O14: 0 | P14: 0 | Q14: 0 | R14: =F36*E32 -> 7938.3014 | S14: 0 | T14: =-SUM(M14:S14) -> -7938.3014
B15: P / E Post-Money | D15: =D22/M34 -> 76.424993 | E15: =E22/N34 -> 38.104142 | F15: =F22/O34 -> 26.552967 | H15: (=) Deal Cash Flow | M15: =SUM(M10:M14) -> -5010 | N15: =SUM(N10:N14) -> 52.338899 | O15: =SUM(O10:O14) -> 94.244164 | P15: =SUM(P10:P14) -> 125.18722 | Q15: =SUM(Q10:Q14) -> 146.20832 | R15: =SUM(R10:R14) -> 8100.7678 | S15: =SUM(S10:S14) -> 0 | T15: =SUM(M15:S15) -> 3508.7464
B16: P / E Pre-Money | D16: =D20/M34 -> 62.360045 | V16: CAGR
H17: Income Statement (R$mn) | J17: 44926 | K17: =EOMONTH(J17,12) -> 45291 | L17: =EOMONTH(K17,12) -> 45657 | M17: =EOMONTH(L17,12) -> 46022 | N17: =EOMONTH(M17,12) -> 46387 | O17: =EOMONTH(N17,12) -> 46752 | P17: =EOMONTH(O17,12) -> 47118 | Q17: =EOMONTH(P17,12) -> 47483 | R17: =EOMONTH(Q17,12) -> 47848 | ... T17: =EOMONTH(S17,12) -> 48579 | V17: 2023-25 | W17: 2026-27 | X17: 2026-31 | AE17: Entry Multiple
B18: Enterprise Value | D18: =D14*M28 -> 27982.57 | E18: =D18 -> 27982.57 | F18: =E18 -> 27982.57 | AD18: =W11 -> 0.11491929 | AE18: 5 | AF18: 6 | AG18: 7 | AH18: 8 | AI18: 9
B19: (-) Net Debt | D19: =-M38 -> -5813.9685 | E19: =-N38 -> -8591.3261 | F19: =-O38 -> -10404.837 | H19: Gross Revenue | J19: ='Model '!G21 -> 3151.8 | K19: ='Model '!H21 -> 4539.3 | L19: ='Model '!I21 -> 5946.1 | M19: ='Model '!N21 -> 7380.5436 | N19: ='Model '!O21 -> 8798.1155 | O19: ='Model '!P21 -> 10181.953 | P19: ='Model '!Q21 -> 11488.512 | Q19: ='Model '!R21 -> 12752.093 | R19: ='Model '!S21 -> 13963.818 | S19: ='Model '!T21 -> 15114.091 | T19: ='Model '!U21 -> 16192.554 | V19: =(M19/K19)^(1/2)-1 -> 0.2751161 | W19: =(O19/N19)-1 -> 0.15728798 | X19: =(S19/N19)^(1/5)-1 -> 0.11429062 | AD19: 5 | AE19: 0.10041092 | AF19: 0.057915534 | AG19: 0.023588949 | AH19: -0.0050460186 | AI19: -0.029506622
B20: (=) Equity Value | D20: =D18+D19 -> 22168.602 | E20: =E18+E19 -> 19391.244 | F20: =F18+F19 -> 17577.734 | H20: (-) Taxes | J20: ='Model '!G23 -> -221.4 | K20: ='Model '!H23 -> -294.6 | L20: ='Model '!I23 -> -365.8 | M20: ='Model '!N23 -> -454.06477 | N20: ='Model '!O23 -> -541.27643 | O20: ='Model '!P23 -> -626.41271 | P20: ='Model '!Q23 -> -706.79463 | Q20: ='Model '!R23 -> -784.53246 | R20: ='Model '!S23 -> -859.08004 | S20: ='Model '!T23 -> -929.84699 | T20: ='Model '!U23 -> -996.19602 | V20: =(M20/K20)^(1/2)-1 -> 0.24148802 | W20: =(O20/N20)-1 -> 0.15728798 | X20: =(S20/N20)^(1/5)-1 -> 0.11429062 | AD20: 6 | AE20: 0.1534189 | AF20: 0.10905247 | AG20: 0.073198875 | AH20: 0.04327984 | AI20: 0.017715238
B21: (+) Money-In | D21: =$D$45 -> 5000 | E21: =$D$45 -> 5000 | F21: =$D$45 -> 5000 | H21: % Gross Revenue | J21: =-J20/J19 -> 0.070245574 | K21: =-K20/K19 -> 0.064899874 | L21: =-L20/L19 -> 0.061519315 | M21: =-M20/M19 -> 0.06152186 | N21: =-N20/N19 -> 0.06152186 | O21: =-O20/O19 -> 0.06152186 | P21: =-P20/P19 -> 0.06152186 | Q21: =-Q20/Q19 -> 0.06152186 | ... T21: =-T20/T19 -> 0.06152186 | AC21: Exit | AD21: 7 | AE21: 0.19801698 | AF21: 0.15206554 | AG21: 0.11491929 | AH21: 0.083913869 | AI21: 0.057415645
B22: (=) Equity Value Post Money | D22: =D20+D21 -> 27168.602 | E22: =E20+E21 -> 24391.244 | F22: =F20+F21 -> 22577.734 | H22: (=) Net Revenue | J22: =J19-J20 -> 3373.2 | K22: =K19-K20 -> 4833.9 | L22: =L19-L20 -> 6311.9 | M22: =M19-M20 -> 7834.6083 | N22: =N19-N20 -> 9339.3919 | O22: =O19-O20 -> 10808.366 | P22: =P19-P20 -> 12195.307 | Q22: =Q19-Q20 -> 13536.625 | ... T22: =T19-T20 -> 17188.75 | V22: =(M22/K22)^(1/2)-1 -> 0.27309207 | W22: =(O22/N22)-1 -> 0.15728798 | X22: =(S22/N22)^(1/5)-1 -> 0.11429062 | AD22: 8 | AE22: 0.23672386 | AF22: 0.18939009 | AG22: 0.15111706 | AH22: 0.11916501 | AI22: 0.091853541
H23: YoY Growth | K23: =K22/J22-1 -> 0.43303095 | L23: =L22/K22-1 -> 0.30575726 | M23: =M22/L22-1 -> 0.24124405 | N23: =N22/M22-1 -> 0.19206877 | O23: =O22/N22-1 -> 0.15728798 | P23: =P22/O22-1 -> 0.12832103 | Q23: =Q22/P22-1 -> 0.10998645 | R23: =R22/Q22-1 -> 0.095021654 | ... T23: =T22/S22-1 -> 0.07135479 | AD23: 9 | AE23: 0.27104909 | AF23: 0.22248498 | AG23: 0.18320943 | AH23: 0.15041541 | AI23: 0.12238078
B24: Exit Valuation (R$mn) | D24: 47483 | E24: =EOMONTH(D24,12) -> 47848 | F24: =EOMONTH(E24,12) -> 48213 | H24: (-) COGS | J24: ='Model '!G36 -> -2018.4 | K24: ='Model '!H36 -> -2533.9 | L24: ='Model '!I36 -> -3267.4 | M24: ='Model '!N36 -> -3712.439 | N24: ='Model '!O36 -> -4503.0106 | O24: ='Model '!P36 -> -5285.5253 | P24: ='Model '!Q36 -> -6040.7217 | Q24: ='Model '!R36 -> -6778.5743 | R24: ='Model '!S36 -> -7494.5142 | S24: ='Model '!T36 -> -8183.588 | T24: ='Model '!U36 -> -8840.4328 | V24: =(M24/K24)^(1/2)-1 -> 0.21041676 | W24: =(O24/N24)-1 -> 0.17377589 | X24: =(S24/N24)^(1/5)-1 -> 0.12690721
H25: (=) Gross Profit | J25: =J22+J24 -> 1354.8 | K25: =K22+K24 -> 2300 | L25: =L22+L24 -> 3044.5 | M25: =M22+M24 -> 4122.1693 | N25: =N22+N24 -> 4836.3813 | O25: =O22+O24 -> 5522.8407 | P25: =P22+P24 -> 6154.5849 | Q25: =Q22+Q24 -> 6758.0508 | ... T25: =T22+T24 -> 8348.3168 | V25: =(M25/K25)^(1/2)-1 -> 0.33874849 | W25: =(O25/N25)-1 -> 0.14193658 | X25: =(S25/N25)^(1/5)-1 -> 0.10200679 | AE25: Entry Multiple
B26: EV / Revenue | D26: =D30/Q22 -> 4.0892881 | E26: =E30/R22 -> 3.7344359 | F26: =F30/S22 -> 3.4502228 | H26: Gross Margin | J26: =J25/J22 -> 0.40163643 | K26: =K25/K22 -> 0.47580628 | L26: =L25/L22 -> 0.48234288 | M26: =M25/M22 -> 0.52614874 | N26: =N25/N22 -> 0.51784756 | O26: =O25/O22 -> 0.51097832 | P26: =P25/P22 -> 0.50466832 | Q26: =Q25/Q22 -> 0.49924193 | ... T26: =T25/T22 -> 0.48568494 | AD26: =W10 -> 0.70034857 | AE26: 5 | AF26: 6 | AG26: 7 | AH26: 8 | AI26: 9
B27: EV / EBITDA | D27: =D30/Q28 -> 7.701098 | E27: 7 | F27: =F30/S28 -> 6.4433929 | H27: (-) SG&A | J27: ='Model '!G42 -> -653.2 | K27: ='Model '!H42 -> -664.9 | L27: ='Model '!I42 -> -1050.1 | M27: ='Model '!N42 -> -1322.1653 | N27: ='Model '!O42 -> -1561.4204 | O27: ='Model '!P42 -> -1794.994 | P27: ='Model '!Q42 -> -2015.461 | Q27: ='Model '!R42 -> -2228.8212 | R27: ='Model '!S42 -> -2433.591 | S27: ='Model '!T42 -> -2628.1665 | T27: ='Model '!U42 -> -2810.8165 | V27: =(M27/K27)^(1/2)-1 -> 0.41014807 | W27: =(O27/N27)-1 -> 0.14959045 | X27: =(S27/N27)^(1/5)-1 -> 0.10975371 | AD27: 5 | AE27: 0.58613566 | AF27: 0.31249326 | AG27: 0.11937677 | AH27: -0.024199688 | AI27: -0.13513171
B28: P / E | D28: =D32/Q34 -> 39.088967 | E28: =E32/R34 -> 34.898715 | F28: =F32/S34 -> 32.482258 | H28: (=) EBITDA | J28: ='Model '!G80 -> 1167.7 | K28: ='Model '!H80 -> 2202.3 | L28: ='Model '!I80 -> 2675.9 | M28: ='Model '!N80 -> 3997.5101 | N28: ='Model '!O80 -> 4839.5202 | O28: ='Model '!P80 -> 5660.1998 | P28: ='Model '!Q80 -> 6436.9612 | Q28: ='Model '!R80 -> 7187.9569 | R28: ='Model '!S80 -> 7907.8801 | S28: ='Model '!T80 -> 8590.9957 | T28: ='Model '!U80 -> 9231.1145 | V28: =(M28/K28)^(1/2)-1 -> 0.34727591 | W28: =(O28/N28)-1 -> 0.16957872 | X28: =(S28/N28)^(1/5)-1 -> 0.12162644 | AD28: 6 | AE28: 0.99774868 | AF28: 0.6530942 | AG28: 0.40986267 | AH28: 0.22902715 | AI28: 0.089307512
H29: EBITDA Margin | J29: =J28/J22 -> 0.34616981 | K29: =K28/K22 -> 0.45559486 | L29: =L28/L22 -> 0.42394525 | M29: =M28/M22 -> 0.51023738 | N29: =N28/N22 -> 0.51818365 | O29: =O28/O22 -> 0.52368691 | P29: =P28/P22 -> 0.52782282 | Q29: =Q28/Q22 -> 0.53100067 | ... T29: =T28/T22 -> 0.53704398 | AC29: Exit | AD29: 7 | AE29: 1.4093617 | AF29: 0.99369515 | AG29: 0.70034857 | AH29: 0.48225398 | AI29: 0.31374673
B30: Enterprise Value | D30: =E30 -> 55355.16 | E30: =E27*R28 -> 55355.16 | F30: =E30 -> 55355.16 | H30: (-) D&A | J30: =-'Model '!G72 -> -902.3 | K30: =-'Model '!H72 -> -1157.4 | L30: =-'Model '!I72 -> -1412.3 | M30: ='Model '!N72 -> -2105.6357 | N30: ='Model '!O72 -> -2647.1122 | O30: ='Model '!P72 -> -3185.1785 | P30: ='Model '!Q72 -> -3711.4266 | Q30: ='Model '!R72 -> -4227.7922 | R30: ='Model '!S72 -> -4731.2477 | S30: ='Model '!T72 -> -5218.5063 | T30: ='Model '!U72 -> -5686.0062 | AD30: 8 | AE30: 1.8209747 | AF30: 1.3342961 | AG30: 0.99083448 | AH30: 0.73548081 | AI30: 0.53818595
B31: (-) Net Debt | D31: =E31 -> -12220.65 | E31: =-R38 -> -12220.65 | F31: =E31 -> -12220.65 | H31: (-) Financial Result | J31: ='Model '!G55 -> -347.7 | K31: ='Model '!H55 -> -473.3 | L31: ='Model '!I55 -> -767.3 | M31: ='Model '!N55 -> -1491.3488 | N31: ='Model '!O55 -> -1471.2007 | O31: ='Model '!P55 -> -1517.021 | P31: ='Model '!Q55 -> -1606.6695 | Q31: ='Model '!R55 -> -1716.8844 | R31: ='Model '!S55 -> -1784.0727 | S31: ='Model '!T55 -> -1876.3328 | T31: ='Model '!U55 -> -1980.8482 | AD31: 9 | AE31: 2.2325877 | AF31: 1.6748971 | AG31: 1.2813204 | AH31: 0.98870765 | AI31: 0.76262517
B32: (=) Equity Value | D32: =SUM(D30:D31) -> 43134.51 | E32: =SUM(E30:E31) -> 43134.51 | F32: =SUM(F30:F31) -> 43134.51 | H32: (-) Income Tax | J32: ='Model '!G64 -> -3.7 | K32: ='Model '!H64 -> 472.6 | L32: ='Model '!I64 -> -55.8 | M32: ='Model '!N64 -> -45.03189 | N32: ='Model '!O64 -> -81.08678 | O32: ='Model '!P64 -> -107.70989 | P32: ='Model '!Q64 -> -125.79624 | Q32: ='Model '!R64 -> -139.78448 | R32: ='Model '!S64 -> -156.56826 | S32: ='Model '!T64 -> -168.21586 | T32: ='Model '!U64 -> -175.87289
H33: Tax Rate | J33: =-J32/(J28+J30) -> 0.013941221 | K33: =-K32/(K28+K30) -> -0.45229209 | L33: =-L32/(L28+L30) -> 0.044159544 | M33: =-M32/(M28+M30) -> 0.02380279 | N33: =-N32/(N28+N30) -> 0.03698526 | O33: =-O32/(O28+O30) -> 0.043518772 | P33: =-P32/(P28+P30) -> 0.046154704 | Q33: =-Q32/(Q28+Q30) -> 0.04722186 | ... T33: =-T32/(T28+T30) -> 0.049610018
B34: Cap Table (R$mn) | E34: Pre-Deal | F34: Post-Deal | H34: Net Income | J34: =J28+J30+J31+J32 -> -86 | K34: =K28+K30+K31+K32 -> 1044.2 | L34: =L28+L30+L31+L32 -> 440.5 | M34: =M28+M30+M31+M32 -> 355.49368 | N34: =N28+N30+N31+N32 -> 640.12054 | O34: =O28+O30+O31+O32 -> 850.29042 | P34: =P28+P30+P31+P32 -> 993.06889 | Q34: =Q28+Q30+Q31+Q32 -> 1103.4958 | ... T34: =T28+T30+T31+T32 -> 1388.3872
B35: Founders + Others Funds | E35: 1 | F35: =E35-F36 -> 0.81596403 | H35: Net Margin % | J35: =J34/J22 -> -0.025495079 | K35: =K34/K22 -> 0.21601605 | L35: =L34/L22 -> 0.069788812 | M35: =M34/M22 -> 0.045374787 | N35: =N34/N22 -> 0.068539853 | O35: =O34/O22 -> 0.078669655 | P35: =P34/P22 -> 0.081430416 | Q35: =Q34/Q22 -> 0.081519269 | ... T35: =T34/T22 -> 0.080773019
B36: PEP | E36: 0 | F36: =(D44+D45)/D22 -> 0.18403597 | H36: Check
B37: Total | E37: =SUM(E35:E36) -> 1 | F37: =SUM(F35:F36) -> 1
H38: Net Debt | J38: ='Build-Up'!I417 -> 449.9 | K38: ='Build-Up'!J417 -> 1122.4 | L38: ='Build-Up'!K417 -> 2826.5 | M38: ='Build-Up'!L417 -> 5813.9685 | N38: ='Build-Up'!M417 -> 8591.3261 | O38: ='Build-Up'!N417 -> 10404.837 | P38: ='Build-Up'!O417 -> 11701.316 | Q38: ='Build-Up'!P417 -> 12353.136 | ... T38: ='Build-Up'!S417 -> 10008.291
B39: Sources ($mn) | D39: BRL | E39: USD | F39: % | H39: Net Debt / EBITDA | J39: ='Build-Up'!I418 -> 0.38528732 | K39: ='Build-Up'!J418 -> 0.509649 | L39: ='Build-Up'!K418 -> 1.0562801 | M39: ='Build-Up'!L418 -> 1.4543975 | N39: ='Build-Up'!M418 -> 1.7752434 | O39: ='Build-Up'!N418 -> 1.8382455 | P39: ='Build-Up'!O418 -> 1.8178323 | Q39: ='Build-Up'!P418 -> 1.7185879 | ... T39: ='Build-Up'!S418 -> 1.0841909
B40: PEP Equity Check | D40: =D41 -> 5010 | E40: =E41 -> 927.77778 | F40: =D40/D41 -> 1
B41: (=) Total Sources | D41: =D47 -> 5010 | E41: =E47 -> 927.77778 | F41: =F40 -> 1 | H41: Cash Flow (R$mn) | J41: 44926 | K41: =EOMONTH(J41,12) -> 45291 | L41: =EOMONTH(K41,12) -> 45657 | M41: =EOMONTH(L41,12) -> 46022 | N41: =EOMONTH(M41,12) -> 46387 | O41: =EOMONTH(N41,12) -> 46752 | P41: =EOMONTH(O41,12) -> 47118 | Q41: =EOMONTH(P41,12) -> 47483 | R41: =EOMONTH(Q41,12) -> 47848 | ... T41: =EOMONTH(S41,12) -> 48579
B43: Uses ($mn) | D43: BRL | E43: USD | F43: % | H43: EBITDA | K43: =K28 -> 2202.3 | L43: =L28 -> 2675.9 | M43: =M28 -> 3997.5101 | N43: =N28 -> 4839.5202 | O43: =O28 -> 5660.1998 | P43: =P28 -> 6436.9612 | Q43: =Q28 -> 7187.9569 | R43: =R28 -> 7907.8801 | ... T43: =T28 -> 9231.1145
B44: Money-Out | D44: 0 | E44: =D44/$D$9 -> 0 | F44: =D44/$D$47 -> 0 | H44: (-) Taxes | K44: ='Model '!H138 -> -121.1 | L44: ='Model '!I138 -> -171 | M44: ='Model '!N138 -> -45.03189 | N44: ='Model '!O138 -> -81.08678 | O44: ='Model '!P138 -> -107.70989 | P44: ='Model '!Q138 -> -125.79624 | Q44: ='Model '!R138 -> -139.78448 | R44: ='Model '!S138 -> -156.56826 | S44: ='Model '!T138 -> -168.21586 | T44: ='Model '!U138 -> -175.87289
B45: Money-In | D45: 5000 | E45: =D45/$D$9 -> 925.92593 | F45: =D45/$D$47 -> 0.99800399 | H45: (-) ∆ Working Capital | K45: ='Model '!H142 -> -15.2 | L45: ='Model '!I142 -> -192.6 | M45: ='Model '!N142 -> -19.46009 | N45: ='Model '!O142 -> 8.3387825 | O45: ='Model '!P142 -> 9.6201444 | P45: ='Model '!Q142 -> 11.326038 | Q45: ='Model '!R142 -> 12.002474 | R45: ='Model '!S142 -> 12.681119 | S45: ='Model '!T142 -> 13.360048 | T45: ='Model '!U142 -> 14.037139
B46: DD Costs | D46: 10 | E46: =D46/$D$9 -> 1.8518519 | F46: =D46/$D$47 -> 0.001996008 | H46: (-) Other Operational | K46: ='Model '!H149 -> -35.4 | L46: ='Model '!I149 -> 102.8 | M46: ='Model '!N149 -> -230.15511 | N46: ='Model '!O149 -> -107.68434 | O46: ='Model '!P149 -> -105.12176 | P46: ='Model '!Q149 -> -99.251335 | Q46: ='Model '!R149 -> -95.986556 | R46: ='Model '!S149 -> -92.04739 | S46: ='Model '!T149 -> -87.379278 | T46: ='Model '!U149 -> -81.924273
B47: (=) Total Uses | D47: =SUM(D44:D46) -> 5010 | E47: =SUM(E44:E46) -> 927.77778 | F47: =SUM(F44:F46) -> 1 | H47: (=) Operating Cash Flow | K47: =SUM(K43:K46) -> 2030.6 | L47: =SUM(L43:L46) -> 2415.1 | M47: =SUM(M43:M46) -> 3702.863 | N47: =SUM(N43:N46) -> 4659.0878 | O47: =SUM(O43:O46) -> 5456.9883 | P47: =SUM(P43:P46) -> 6223.2396 | Q47: =SUM(Q43:Q46) -> 6964.1884 | R47: =SUM(R43:R46) -> 7671.9455 | ... T47: =SUM(T43:T46) -> 8987.3545
H48: % of EBITDA | K48: =K47/K43 -> 0.92203605 | L48: =L47/L43 -> 0.90253746 | M48: =M47/M43 -> 0.92629235 | N48: =N47/N43 -> 0.9627169 | O48: =O47/O43 -> 0.96409817 | P48: =P47/P43 -> 0.96679776 | Q48: =Q47/Q43 -> 0.96886896 | R48: =R47/R43 -> 0.97016463 | ... T48: =T47/T43 -> 0.97359365
H49: (-) CAPEX | K49: ='Model '!H159 -> -1603.7 | L49: ='Model '!I159 -> -2741.3 | M49: ='Model '!N159 -> -3340.2434 | N49: ='Model '!O159 -> -3365.7902 | O49: ='Model '!P159 -> -3368.7004 | P49: ='Model '!Q159 -> -3340.32 | Q49: ='Model '!R159 -> -3295.5249 | R49: ='Model '!S159 -> -3232.8402 | S49: ='Model '!T159 -> -3150.6954 | T49: ='Model '!U159 -> -3047.4189
H50: (=) OCF after CAPEX | K50: =K47+K49 -> 426.9 | L50: =L47+L49 -> -326.2 | M50: =M47+M49 -> 362.61955 | N50: =N47+N49 -> 1293.2976 | O50: =O47+O49 -> 2088.2879 | P50: =P47+P49 -> 2882.9196 | Q50: =Q47+Q49 -> 3668.6635 | R50: =R47+R49 -> 4439.1053 | ... T50: =T47+T49 -> 5939.9356
H51: % of EBITDA | K51: =K50/K43 -> 0.1938428 | L51: =L50/L43 -> -0.12190291 | M51: =M50/M43 -> 0.090711353 | N51: =N50/N43 -> 0.26723674 | O51: =O50/O43 -> 0.36894244 | P51: =P50/P43 -> 0.44786966 | Q51: =Q50/Q43 -> 0.51039029 | R51: =R50/R43 -> 0.56135213 | ... T51: =T50/T43 -> 0.64346896
H52: (+/-) Loans | K52: ='Model '!H171 -> 400 | L52: ='Model '!I171 -> 2094.7 | M52: ='Model '!N171 -> 0 | N52: ='Model '!O171 -> 818.10081 | O52: ='Model '!P171 -> 1141.7228 | P52: ='Model '!Q171 -> 1080.624 | Q52: ='Model '!R171 -> 1044.7792 | R52: ='Model '!S171 -> 1001.5512 | S52: ='Model '!T171 -> 950.34482 | T52: ='Model '!U171 -> 890.52804
H53: (+/-) Revolver
H54: (+/-) Financial Result | K54: ='Model '!H169 -> -130.7 | L54: ='Model '!I169 -> -339.1 | M54: ='Model '!N169 -> -718.78283 | N54: ='Model '!O169 -> -818.20406 | O54: ='Model '!P169 -> -956.95405 | P54: ='Model '!Q169 -> -1088.2789 | Q54: ='Model '!R169 -> -1215.2477 | R54: ='Model '!S169 -> -1336.963 | S54: ='Model '!T169 -> -1452.4555 | T54: ='Model '!U169 -> -1560.6785
H55: (=) FCFF | K55: =K50+SUM(K52:K54) -> 696.2 | L55: =L50+SUM(L52:L54) -> 1429.4 | M55: =M50+SUM(M52:M54) -> -356.16328 | N55: =N50+SUM(N52:N54) -> 1293.1943 | O55: =O50+SUM(O52:O54) -> 2273.0567 | P55: =P50+SUM(P52:P54) -> 2875.2648 | Q55: =Q50+SUM(Q52:Q54) -> 3498.195 | R55: =R50+SUM(R52:R54) -> 4103.6934 | ... T55: =T50+SUM(T52:T54) -> 5269.7851
H56: % of EBITDA | K56: =K55/K43 -> 0.31612405 | L56: =L55/L43 -> 0.53417542 | M56: =M55/M43 -> -0.089096281 | N56: =N55/N43 -> 0.26721541 | O56: =O55/O43 -> 0.40158594 | P56: =P55/P43 -> 0.44668046 | Q56: =Q55/Q43 -> 0.48667445 | R56: =R55/R43 -> 0.51893723 | ... T56: =T55/T43 -> 0.57087203
H57: (+) Capital Increase | K57: ='Model '!H181 -> 0 | L57: ='Model '!I181 -> 0 | M57: ='Model '!N181 -> 0 | N57: ='Model '!O181 -> 0 | O57: ='Model '!P181 -> 0 | P57: ='Model '!Q181 -> 0 | Q57: ='Model '!R181 -> 0 | R57: ='Model '!S181 -> 0 | S57: ='Model '!T181 -> 0 | T57: ='Model '!U181 -> 0
H58: (-) Dividends | K58: ='Model '!H173 -> -236.3 | L58: ='Model '!I173 -> -430 | M58: ='Model '!N173 -> -284.39495 | N58: ='Model '!O173 -> -512.09644 | O58: ='Model '!P173 -> -680.23233 | P58: ='Model '!Q173 -> -794.45512 | Q58: ='Model '!R173 -> -882.79663 | R58: ='Model '!S173 -> -988.79309 | S58: ='Model '!T173 -> -1062.3525 | T58: ='Model '!U173 -> -1110.7098
H59: (=) Net Cash Flow | K59: =K55+SUM(K57:K58) -> 459.9 | L59: =L55+SUM(L57:L58) -> 999.4 | M59: =M55+SUM(M57:M58) -> -640.55823 | N59: =N55+SUM(N57:N58) -> 781.09791 | O59: =O55+SUM(O57:O58) -> 1592.8243 | P59: =P55+SUM(P57:P58) -> 2080.8096 | Q59: =Q55+SUM(Q57:Q58) -> 2615.3983 | R59: =R55+SUM(R57:R58) -> 3114.9003 | ... T59: =T55+SUM(T57:T58) -> 4159.0753
H60: % of EBITDA | K60: =K59/K43 -> 0.20882714 | L60: =L59/L43 -> 0.37348182 | M60: =M59/M43 -> -0.1602393 | N60: =N59/N43 -> 0.16139987 | O60: =O59/O43 -> 0.28140779 | P60: =P59/P43 -> 0.32325962 | Q60: =Q59/Q43 -> 0.36385838 | R60: =R59/R43 -> 0.39389828 | ... T60: =T59/T43 -> 0.45054964
H61: Check

Sheet AVP
B9: AVP (R$M) | C9: 6 | D9: =C9+1 -> 7 | E9: =D9+1 -> 8 | F9: =E9+1 -> 9 | G9: =F9+1 -> 10
B11: EBITDA | C11: ='D@G'!M28 -> 3997.5101 | D11: =C11 -> 3997.5101 | E11: =D11 -> 3997.5101 | F11: =E11 -> 3997.5101 | G11: =F11 -> 3997.5101
B12: (x) Multiple | C12: =C9 -> 6 | D12: =D9 -> 7 | E12: =E9 -> 8 | F12: =F9 -> 9 | G12: =G9 -> 10
B13: TEV (R$M) | C13: =C12*C11 -> 23985.06 | D13: =D12*D11 -> 27982.57 | E13: =E12*E11 -> 31980.081 | F13: =F12*F11 -> 35977.591 | G13: =G12*G11 -> 39975.101
B15: (-) Net Debt | C15: =-'D@G'!M38 -> -5813.9685 | D15: =C15 -> -5813.9685 | E15: =D15 -> -5813.9685 | F15: =E15 -> -5813.9685 | G15: =F15 -> -5813.9685
B16: Equity Value (R$M) | C16: =C13+C15 -> 18171.092 | D16: =D13+D15 -> 22168.602 | E16: =E13+E15 -> 26166.112 | F16: =F13+F15 -> 30163.622 | G16: =G13+G15 -> 34161.132
B18: Primary Check (R$M) | C18: ='D@G'!D45 -> 5000 | D18: =C18 -> 5000 | E18: =D18 -> 5000 | F18: =E18 -> 5000 | G18: =F18 -> 5000
B19: Equity Value Post Money (R$M) | C19: =C16+C18 -> 23171.092 | D19: =D16+D18 -> 27168.602 | E19: =E16+E18 -> 31166.112 | F19: =F16+F18 -> 35163.622 | G19: =G16+G18 -> 39161.132
B21: Cap Table
B22: Founders | C22: =1-C23 -> 0.78421388 | D22: =1-D23 -> 0.81596403 | E22: =1-E23 -> 0.83956934 | F22: =1-F23 -> 0.85780759 | G22: =1-G23 -> 0.87232238
B23: PEP | C23: =C18/C19 -> 0.21578612 | D23: =D18/D19 -> 0.18403597 | E23: =E18/E19 -> 0.16043066 | F23: =F18/F19 -> 0.14219241 | G23: =G18/G19 -> 0.12767762
B25: Equity Value at Exit (R$M) | C25: ='D@G'!D32 -> 43134.51 | D25: =C25 -> 43134.51 | E25: =D25 -> 43134.51 | F25: =E25 -> 43134.51 | G25: =F25 -> 43134.51
B26: PEP Stake Value (R$M) | C26: =C25*C23 -> 9307.8286 | D26: =D25*D23 -> 7938.3014 | E26: =E25*E23 -> 6920.0981 | F26: =F25*F23 -> 6133.3998 | G26: =G25*G23 -> 5507.3115
B28: Return Calcs
B29: 46022 | C29: {=TRANSPOSE('D@G'!M15:Q15)} -> -5010 | D29: =C29 -> -5010 | E29: =D29 -> -5010 | F29: =E29 -> -5010 | G29: =F29 -> -5010
B30: 46387 | C30: 52.338899 | D30: =C30 -> 52.338899 | E30: =D30 -> 52.338899 | F30: =E30 -> 52.338899 | G30: =F30 -> 52.338899
B31: 46752 | C31: 94.244164 | D31: =C31 -> 94.244164 | E31: =D31 -> 94.244164 | F31: =E31 -> 94.244164 | G31: =F31 -> 94.244164
B32: 47118 | C32: 125.18722 | D32: =C32 -> 125.18722 | E32: =D32 -> 125.18722 | F32: =E32 -> 125.18722 | G32: =F32 -> 125.18722
B33: 47483 | C33: 146.20832 | D33: =C33 -> 146.20832 | E33: =D33 -> 146.20832 | F33: =E33 -> 146.20832 | G33: =F33 -> 146.20832
B34: 47848 | C34: ='D@G'!$R$13+AVP!C26 -> 9470.2949 | D34: ='D@G'!$R$13+AVP!D26 -> 8100.7678 | E34: ='D@G'!$R$13+AVP!E26 -> 7082.5644 | F34: ='D@G'!$R$13+AVP!F26 -> 6295.8661 | G34: ='D@G'!$R$13+AVP!G26 -> 5669.7778
B35: IRR | C35: =XIRR(C29:C34,$B$29:$B$34) -> 0.14901999 | D35: =XIRR(D29:D34,$B$29:$B$34) -> 0.11485267 | E35: =XIRR(E29:E34,$B$29:$B$34) -> 0.086376014 | F35: =XIRR(F29:F34,$B$29:$B$34) -> 0.062087521 | G35: =XIRR(G29:G34,$B$29:$B$34) -> 0.040999237
B36: MOIC | C36: =-SUM(C29:C34)/C29 -> 0.97370729 | D36: =-SUM(D29:D34)/D29 -> 0.70034857 | E36: =-SUM(E29:E34)/E29 -> 0.49711437 | F36: =-SUM(F29:F34)/F29 -> 0.34008876 | G36: =-SUM(G29:G34)/G29 -> 0.21512103
B37: K-Gain | C37: =SUM(C29:C34) -> 4878.2735 | D37: =SUM(D29:D34) -> 3508.7464 | E37: =SUM(E29:E34) -> 2490.543 | F37: =SUM(F29:F34) -> 1703.8447 | G37: =SUM(G29:G34) -> 1077.7564

Sheet Macro
C2: 2001 | D2: 2002 | E2: 2003 | F2: 2004 | G2: 2005 | H2: 2006 | I2: 2007 | J2: 2008 | K2: 2009 | L2: 2010 | M2: 2011 | N2: 2012 | O2: 2013 | P2: 2014 | Q2: 2015 | R2: 2016 | S2: 2017 | T2: 2018 | U2: 2019 | V2: 2020 | W2: 2021 | X2: 2022 | Y2: 2023 | Z2: 2024 | AA2: 2025P | AB2: 2026P | AC2: 2027P | AD2: 2028P | AE2: 2029P | AF2: 2030P | AG2: 2031P
B3: World | C3: 37226 | D3: =EDATE(C3,12) -> 37591 | E3: =EDATE(D3,12) -> 37956 | F3: =EDATE(E3,12) -> 38322 | G3: =EDATE(F3,12) -> 38687 | H3: =EDATE(G3,12) -> 39052 | I3: =EDATE(H3,12) -> 39417 | J3: =EDATE(I3,12) -> 39783 | K3: =EDATE(J3,12) -> 40148 | ... AD3: =EDATE(AC3,12) -> 47088
B4: Atividade econômica
B5: Mundo – Crescimento real do PIB | C5: 0.02482 | D5: 0.02991 | E5: 0.04283 | F5: 0.05386 | G5: 0.04894 | H5: 0.05467 | I5: 0.05574 | J5: 0.03037 | K5: -0.0011 | L5: 0.05385 | M5: 0.04282 | N5: 0.03513 | O5: 0.03491 | P5: 0.0358 | Q5: 0.03451 | R5: 0.03268 | S5: 0.038 | T5: 0.036 | U5: 0.028 | V5: -0.028 | W5: 0.063 | X5: 0.035 | Y5: 0.032 | Z5: 0.032 | AA5: 0.03 | AB5: 0.028 | AC5: 0.03 | AD5: 0.028 | AE5: 0.028 | AF5: 0.028 | AG5: 0.028
B6: EUA – Crescimento real do PIB | C6: 0.0095559024 | D6: 0.017005488 | E6: 0.027956083 | F6: 0.038481445 | G6: 0.034835402 | H6: 0.02783963 | I6: 0.020038824 | J6: 0.001139455 | K6: -0.025766469 | L6: 0.026955612 | M6: 0.015640448 | N6: 0.022894138 | O6: 0.021177793 | P6: 0.025235513 | Q6: 0.029455089 | R6: 0.018197196 | S6: 0.02457462 | T6: 0.02966536 | U6: 0.025839486 | V6: -0.021630937 | W6: 0.060549843 | X6: 0.025122355 | Y6: 0.028877049 | Z6: 0.027960708 | AA6: 0.017033938 | AB6: 0.015471548 | AC6: 0.019480316 | AD6: 0.020273753 | AE6: 0.020273753 | AF6: 0.020273753 | AG6: 0.020273753
B7: Zona do Euro – Crescimento real do PIB | C7: 0.02157627 | D7: 0.0093073612 | E7: 0.0073945317 | F7: 0.020439338 | G7: 0.018945051 | H7: 0.034208119 | I7: 0.029798063 | J7: 0.0031340821 | K7: -0.044247315 | L7: 0.019925567 | M7: 0.017837627 | N7: -0.0090546627 | O7: -0.0012115599 | P7: 0.014549559 | Q7: 0.020028265 | R7: 0.017780583 | S7: 0.027434093 | T7: 0.017457827 | U7: 0.01645453 | V7: -0.061586562 | W7: 0.062768803 | X7: 0.035734917 | Y7: 0.006798068 | Z7: 0.0088561118 | AA7: 0.010616991 | AB7: 0.012304738 | AC7: 0.013310171 | AD7: 0.013 | AE7: 0.013 | AF7: 0.013 | AG7: 0.013
B8: China – Crescimento real do PIB | C8: 0.083684688 | D8: 0.091852882 | E8: 0.10114704 | F8: 0.10143211 | G8: 0.11364025 | H8: 0.1262411 | I8: 0.14108227 | J8: 0.097367809 | K8: 0.093133879 | L8: 0.10660741 | M8: 0.092799536 | N8: 0.07821025 | O8: 0.078149292 | P8: 0.074475807 | Q8: 0.071848511 | R8: 0.068686782 | S8: 0.068955838 | T8: 0.068666284 | U8: 0.06157624 | V8: 0.019765625 | W8: 0.077350091 | X8: 0.03 | Y8: 0.054383887 | Z8: 0.050421977 | AA8: 0.047234333 | AB8: 0.039721402 | AC8: 0.040080633 | AD8: 0.040080633 | AE8: 0.040080633 | AF8: 0.040080633 | AG8: 0.040080633
B10: Inflação
B11: EUA – CPI | C11: 0.016036655 | D11: 0.024802706 | E11: 0.020352035 | F11: 0.033423181 | G11: 0.033385498 | H11: 0.025239778 | I11: 0.041088134 | J11: -0.00022228003 | K11: 0.028141231 | L11: 0.01437793 | M11: 0.030620668 | N11: 0.01759505 | O11: 0.015128384 | P11: 0.0065312139 | Q11: 0.0063872475 | R11: 0.020507989 | S11: 0.021299307 | T11: 0.020023809 | U11: 0.023195275 | V11: 0.01304953 | W11: 0.071765806 | X11: 0.064114982 | Y11: 0.033208171 | Z11: 0.028723663 | AA11: 0.0378954 | AB11: 0.027791218 | AC11: 0.025493107 | AD11: 0.025493107 | AE11: 0.025493107 | AF11: 0.025493107 | AG11: 0.025493107
B12: Núcleo do CPI | C12: 0.027823241 | D12: 0.019639066 | E12: 0.010931806 | F12: 0.022657055 | G12: 0.021148036 | H12: 0.026134122 | I12: 0.024353676 | J12: 0.017624597 | K12: 0.018236718 | L12: 0.0066189487 | M12: 0.022766626 | N12: 0.018996944 | O12: 0.017408566 | P12: 0.016224195 | Q12: 0.020715073 | R12: 0.021971237 | S12: 0.017701665 | T12: 0.022485296 | U12: 0.022905988 | V12: 0.01623938 | W12: 0.055045498 | X12: 0.056805074 | Y12: 0.039170866 | Z12: 0.03213613 | AA12: 0.03826177 | AB12: 0.029546609 | AC12: 0.027555025 | AD12: 0.027555025 | AE12: 0.027555025 | AF12: 0.027555025 | AG12: 0.027555025
B13: Zona do Euro – CPI | C13: 0.020489095 | D13: 0.022776339 | E13: 0.019736148 | F13: 0.023597599 | G13: 0.022244692 | H13: 0.019188922 | I13: 0.030667702 | J13: 0.015819209 | K13: 0.009269559 | L13: 0.02213446 | M13: 0.027495732 | N13: 0.0222 | O13: 0.0085 | P13: -0.0016981321 | Q13: 0.0023013808 | R13: 0.011380653 | S13: 0.013522851 | T13: 0.016 | U13: 0.013 | V13: -0.003 | W13: 0.05 | X13: 0.092 | Y13: 0.029 | Z13: 0.024 | AA13: 0.02 | AB13: 0.02 | AC13: 0.02 | AD13: 0.02 | AE13: 0.02 | AF13: 0.02 | AG13: 0.02
B14: Brasil
B15: Atividade econômica
B16: PIB nominal – Bilhões de reais | C16: 1315.756 | D16: 1488.788 | E16: 1717.951 | F16: 1957.75 | G16: 2170.584 | H16: 2409.45 | I16: 2720.263 | J16: 3109.803 | K16: 3333.039 | L16: 3885.847 | M16: 4376.382 | N16: 4814.76 | O16: 5331.619 | P16: 5778.953 | Q16: 5995.787 | R16: 6269.327 | S16: 6585.479 | T16: 7004.141 | U16: 7389.131 | V16: 7609.597 | W16: 9012.142 | X16: 10079.676 | Y16: 10943.344 | Z16: 11744.709 | AA16: 12615.818 | AB16: 13330.956 | AC16: 14098.699 | AD16: 14870.566 | AE16: 14870.566 | AF16: 14870.566 | AG16: 14870.566
B17: PIB nominal – Bilhões de dólares | C17: 559.70986 | D17: 509.5627 | E17: 558.3091 | F17: 669.05906 | G17: 891.37147 | H17: 1107.7687 | I17: 1396.9992 | J17: 1693.769 | K17: 1667.0503 | L17: 2207.5775 | M17: 2612.4242 | N17: 2463.0438 | O17: 2468.3636 | P17: 2454.7591 | Q17: 1800.0682 | R17: 1798.0904 | S17: 2063.2762 | T17: 1915.8634 | U17: 1872.4912 | V17: 1474.5924 | W17: 1670.1807 | X17: 1951.4527 | Y17: 2192.2495 | Z17: 2179.1648 | AA17: 2238.3877 | AB17: 2423.8102 | AC17: 2539.0804 | AD17: 2628.596 | AE17: 2628.596 | AF17: 2628.596 | AG17: 2628.596
B18: Crescimento real do PIB | C18: 0.013898887 | D18: 0.030534605 | E18: 0.011408384 | F18: 0.057599566 | G18: 0.032021683 | H18: 0.03961956 | I18: 0.060698951 | J18: 0.050941771 | K18: -0.0012581413 | L18: 0.075282491 | M18: 0.039744027 | N18: 0.019211815 | O18: 0.030048269 | P18: 0.0050393459 | Q18: -0.035457553 | R18: -0.03275913 | S18: 0.013228684 | T18: 0.017836722 | U18: 0.012207619 | V18: -0.032767506 | W18: 0.047625989 | X18: 0.030167179 | Y18: 0.032416518 | Z18: 0.033958548 | AA18: 0.021999607 | AB18: 0.014787159 | AC18: 0.014835543 | AD18: 0.014034099 | AE18: 0.014034099 | AF18: 0.014034099 | AG18: 0.014034099
B19: Taxa de desemprego - média do ano | N19: 0.073950582 | O19: 0.071989325 | P19: 0.068863643 | Q19: 0.086234918 | R19: 0.11621862 | S19: 0.12832354 | T19: 0.12371062 | U19: 0.11986488 | V19: 0.13745821 | W19: 0.13237424 | X19: 0.092687284 | Y19: 0.079756966 | Z19: 0.068295125 | AA19: 0.062324079 | AB19: 0.066575812 | AC19: 0.071332986 | AD19: 0.074423181 | AE19: 0.074423181 | AF19: 0.074423181 | AG19: 0.074423181
B20: Taxa de desemprego - fim de período | N20: 0.075160108 | O20: 0.068673539 | P20: 0.072065892 | Q20: 0.097088794 | R20: 0.12796007 | S20: 0.12553533 | T20: 0.12338088 | U20: 0.11622086 | V20: 0.14686538 | W20: 0.11610701 | X20: 0.084211912 | Y20: 0.078782255 | Z20: 0.065888726 | AA20: 0.06402347 | AB20: 0.069063668 | AC20: 0.073063668 | AD20: 0.075583668 | AE20: 0.075583668 | AF20: 0.075583668 | AG20: 0.075583668
B21: Inflação
B22: IPCA | C22: 0.076734364 | D22: 0.12530273 | E22: 0.093005128 | F22: 0.075994958 | G22: 0.056892268 | H22: 0.031415161 | I22: 0.044576586 | J22: 0.059027244 | K22: 0.043116501 | L22: 0.059086887 | M22: 0.065033527 | N22: 0.058385947 | O22: 0.059106833 | P22: 0.064074708 | Q22: 0.10673028 | R22: 0.062879882 | S22: 0.029474213 | T22: 0.037455812 | U22: 0.043061516 | V22: 0.045174569 | W22: 0.10060983 | X22: 0.057850929 | Y22: 0.0462119 | Z22: 0.048311967 | AA22: 0.050645729 | AB22: 0.043688364 | AC22: 0.04 | AD22: 0.035 | AE22: 0.035 | AF22: 0.035 | AG22: 0.035
B23: INPC | C23: 0.094410288 | D23: 0.14739919 | E23: 0.10383958 | F23: 0.061327938 | G23: 0.050467647 | H23: 0.028130865 | I23: 0.051553415 | J23: 0.064809612 | K23: 0.041137975 | L23: 0.064652139 | M23: 0.060801878 | N23: 0.06197349 | O23: 0.055627485 | P23: 0.062283737 | Q23: 0.11276071 | R23: 0.065799493 | S23: 0.020672849 | T23: 0.034337249 | U23: 0.044815264 | V23: 0.054473159 | W23: 0.10160248 | X23: 0.059324644 | Y23: 0.037069301 | Z23: 0.047762057 | AA23: 0.049916111 | AB23: 0.042196155 | AC23: 0.04 | AD23: 0.035 | AE23: 0.035 | AF23: 0.035 | AG23: 0.035
B24: IGP-M | C24: 0.10384676 | D24: 0.25306829 | E24: 0.087083329 | F24: 0.12412763 | G24: 0.012087431 | H24: 0.038315732 | I24: 0.077543827 | J24: 0.09807505 | K24: -0.017192492 | L24: 0.11323143 | M24: 0.05096813 | N24: 0.078182448 | O24: 0.055106104 | P24: 0.036857551 | Q24: 0.10539167 | R24: 0.071729083 | S24: -0.0052094044 | T24: 0.075368734 | U24: 0.073039306 | V24: 0.23138351 | W24: 0.17783212 | X24: 0.054512856 | Y24: -0.03175828 | Z24: 0.065356584 | AA24: 0.017552157 | AB24: 0.036658264 | AC24: 0.04 | AD24: 0.035 | AE24: 0.035 | AF24: 0.035 | AG24: 0.035
B25: IPA-M (preços por atacado) | C25: 0.1188321 | D25: 0.33643973 | E25: 0.076478203 | F25: 0.15090038 | G25: -0.0095625769 | H25: 0.043996606 | I25: 0.091920844 | J25: 0.1084144 | K25: -0.044244218 | L25: 0.13898437 | M25: 0.043445261 | N25: 0.086333932 | O25: 0.051203319 | P25: 0.021270588 | Q25: 0.11199758 | R25: 0.076383134 | S25: -0.025474169 | T25: 0.094294981 | U25: 0.090768443 | V25: 0.31629742 | W25: 0.20566523 | X25: 0.052735292 | Y25: -0.055919134 | Z25: 0.072333724 | AA25: 0.0028100426 | AB25: 0.032917339 | AC25: 0.04 | AD25: 0.035 | AE25: 0.035 | AF25: 0.035 | AG25: 0.035
B26: Taxa de juros
B27: Selic – final do ano | C27: 0.19 | D27: 0.25 | E27: 0.165 | F27: 0.1775 | G27: 0.18 | H27: 0.1325 | I27: 0.1125 | J27: 0.1375 | K27: 0.0875 | L27: 0.1075 | M27: 0.11 | N27: 0.0725 | O27: 0.1 | P27: 0.1175 | Q27: 0.1425 | R27: 0.1375 | S27: 0.07 | T27: 0.065 | U27: 0.045 | V27: 0.02 | W27: 0.0925 | X27: 0.1375 | Y27: 0.1175 | Z27: 0.1225 | AA27: 0.15 | AB27: 0.1275 | AC27: 0.1125 | AD27: 0.1025 | AE27: 0.1025 | AF27: 0.1025 | AG27: 0.1025
B28: Selic – média do ano | C28: 0.17625 | D28: 0.19479167 | E28: 0.23083333 | F28: 0.164375 | G28: 0.19145833 | H28: 0.150625 | I28: 0.11979167 | J28: 0.12541667 | K28: 0.099166667 | L28: 0.1 | M28: 0.11708333 | N28: 0.084583333 | O28: 0.084375 | P28: 0.11020833 | Q28: 0.13583333 | R28: 0.14166667 | S28: 0.099166667 | T28: 0.065625 | U28: 0.059583333 | V28: 0.028125 | W28: 0.048125 | X28: 0.12625 | Y28: 0.1325 | Z28: 0.10916667 | AA28: 0.145625 | AB28: 0.13458333 | AC28: 0.11770833 | AD28: 0.10458333 | AE28: 0.10458333 | AF28: 0.10458333 | AG28: 0.10458333
B29: Taxa real de juros (Selic/IPCA) – fim de período | C29: =(1+C27)/(1+C22)-1 -> 0.10519367 | D29: =(1+D27)/(1+D22)-1 -> 0.1108122 | E29: =(1+E27)/(1+E22)-1 -> 0.065868741 | F29: =(1+F27)/(1+F22)-1 -> 0.094335982 | G29: =(1+G27)/(1+G22)-1 -> 0.11648087 | H29: =(1+H27)/(1+H22)-1 -> 0.098005965 | I29: =(1+I27)/(1+I22)-1 -> 0.06502483 | J29: =(1+J27)/(1+J22)-1 -> 0.074098902 | ... AG29: =(1+AG27)/(1+AG22)-1 -> 0.065217391
B30: CDI - final do ano (anualizado) | C30: 0.1905 | D30: 0.2291 | E30: 0.1681 | F30: 0.1746 | G30: 0.1815 | H30: 0.13110121 | I30: 0.1110997 | J30: 0.13610009 | K30: 0.086099475 | L30: 0.10609884 | M30: 0.10859925 | N30: 0.071098985 | O30: 0.0978 | P30: 0.1151 | Q30: 0.1414 | R30: 0.1363 | S30: 0.0699 | T30: 0.064 | U30: 0.0459 | V30: 0.019 | W30: 0.0876 | X30: 0.1365 | Y30: 0.1187 | Z30: 0.1177 | AA30: 0.14879866 | AB30: 0.1263286 | AC30: 0.11134838 | AD30: 0.10136404 | AE30: 0.10136404 | AF30: 0.10136404 | AG30: 0.10136404
B31: CDI - acumulado no ano | C31: 0.1742285 | D31: 0.19037731 | E31: 0.23224121 | F31: 0.16169691 | G31: 0.19072618 | H31: 0.15179871 | I31: 0.11905526 | J31: 0.12298305 | K31: 0.10004968 | L31: 0.097538638 | M31: 0.11610635 | N31: 0.084881229 | O31: 0.080172152 | P31: 0.10765296 | Q31: 0.13333478 | R31: 0.14059903 | S31: 0.10046304 | T31: 0.064757174 | U31: 0.059381227 | V31: 0.027847095 | W31: 0.043967663 | X31: 0.12421569 | Y31: 0.13198299 | Z31: 0.10838193 | AA31: 0.14305189 | AB31: 0.13440971 | AC31: 0.11727771 | AD31: 0.10405011 | AE31: 0.10405011 | AF31: 0.10405011 | AG31: 0.10405011
B32: TJLP (Taxa nominal) – fim de período | C32: 0.1 | D32: 0.1 | E32: 0.11 | F32: 0.0975 | G32: 0.0975 | H32: 0.0685 | I32: 0.0625 | J32: 0.0625 | K32: 0.06 | L32: 0.06 | M32: 0.06 | N32: 0.055 | O32: 0.05 | P32: 0.05 | Q32: 0.07 | R32: 0.075 | S32: 0.07 | T32: 0.0698 | U32: 0.0557 | V32: 0.0455 | W32: 0.0532 | X32: 0.072 | Y32: 0.0655 | Z32: 0.0743 | AA32: 0.088080029 | AB32: 0.07905442 | AC32: 0.072143815 | AD32: 0.069763359 | AE32: 0.069763359 | AF32: 0.069763359 | AG32: 0.069763359
B33: TLP (Taxa real) – fim de período | C33: - | D33: - | E33: - | F33: - | G33: - | H33: - | I33: - | J33: - | K33: - | L33: - | M33: - | N33: - | O33: - | P33: - | Q33: - | R33: - | S33: - | T33: 0.0298 | U33: 0.0168 | V33: 0.0183 | W33: 0.041 | X33: 0.0523 | Y33: 0.0556 | Z33: 0.0666 | AA33: 0.072926072 | AB33: 0.064309775 | AC33: 0.061888505 | AD33: 0.061191464 | AE33: 0.061191464 | AF33: 0.061191464 | AG33: 0.061191464
B34: Finanças públicas
B35: Resultado primário – % do PIB | C35: - | D35: - | E35: 0.032 | F35: 0.037 | G35: 0.037 | H35: 0.031507365 | I35: 0.03237848 | J35: 0.033308747 | K35: 0.019432367 | L35: 0.026170881 | M35: 0.029428566 | N35: 0.02183793 | O35: 0.017174249 | P35: -0.0057207907 | Q35: -0.018761145 | R35: -0.024857811 | S35: -0.016892206 | T35: -0.015454564 | U35: -0.008176222 | V35: -0.092196334 | W35: 0.0068614946 | X35: 0.012336076 | Y35: -0.022764888 | Z35: -0.0040487167 | AA35: -0.0061948442 | AB35: -0.009433348 | AC35: -0.0068973207 | AD35: -0.0059815591 | AE35: -0.0059815591 | AF35: -0.0059815591 | AG35: -0.0059815591
B36: Resultado nominal – % do PIB | C36: - | D36: - | E36: - | F36: - | G36: - | H36: -0.03569684 | I36: -0.027372534 | J36: -0.01991354 | K36: -0.031875435 | L36: -0.024106255 | M36: -0.024669424 | N36: -0.022620359 | O36: -0.029550043 | P36: -0.059511875 | Q36: -0.10224426 | R36: -0.089803173 | S36: -0.077656986 | T36: -0.069593418 | U36: -0.058079033 | V36: -0.13343542 | W36: -0.042571866 | X36: -0.045679323 | Y36: -0.088402362 | Z36: -0.084972366 | AA36: -0.088251402 | AB36: -0.09474215 | AC36: -0.10179327 | AD36: -0.098227063 | AE36: -0.098227063 | AF36: -0.098227063 | AG36: -0.098227063
B37: Dívida pública líquida - % do PIB | C37: - | D37: - | E37: 0.541 | F37: 0.502 | G37: 0.479 | H37: 0.46485822 | I37: 0.44545776 | J37: 0.37566313 | K37: 0.4088492 | L37: 0.37979359 | M37: 0.34491652 | N37: 0.32253672 | O37: 0.30590588 | P37: 0.33111383 | Q37: 0.36036742 | R37: 0.46159547 | S37: 0.51369721 | T37: 0.52766461 | U37: 0.54698838 | V37: 0.61370703 | W37: 0.55113661 | X37: 0.5613292 | Y37: 0.6042787 | Z37: 0.61480778 | AA37: 0.67375979 | AB37: 0.73235813 | AC37: 0.78746644 | AD37: 0.83599416 | AE37: 0.83599416 | AF37: 0.83599416 | AG37: 0.83599416
B38: Dívida pública bruta - % do PIB | C38: - | D38: - | E38: - | F38: - | G38: - | H38: 0.55475106 | I38: 0.56717011 | J38: 0.55980644 | K38: 0.59207932 | L38: 0.51765334 | M38: 0.51266176 | N38: 0.53667189 | O38: 0.51541506 | P38: 0.56280931 | Q38: 0.65452495 | R38: 0.69863462 | S38: 0.73717927 | T38: 0.75269505 | U38: 0.74435061 | V38: 0.86940722 | W38: 0.77305986 | X38: 0.71677718 | Y38: 0.73828165 | Z38: 0.76496034 | AA38: 0.79540567 | AB38: 0.84745679 | AC38: 0.90310189 | AD38: 0.95445284 | AE38: 0.95445284 | AF38: 0.95445284 | AG38: 0.95445284
B39: Taxa de câmbio
B40: BRL / USD – dez | C40: 2.3105 | D40: 3.54 | E40: 2.8915 | F40: 2.656 | G40: 2.3355 | H40: 2.1364 | I40: 1.78 | J40: 2.3145 | K40: 1.7445 | L40: 1.6613 | M40: 1.8668 | N40: 2.0516 | O40: 2.3621 | P40: 2.6576 | Q40: 3.9578 | R40: 3.2552 | S40: 3.3125 | T40: 3.8764 | U40: 4.031 | V40: 5.1926 | W40: 5.5699 | X40: 5.2804 | Y40: 4.8572 | Z40: 6.1774 | AA40: 5.5 | AB40: 5.5 | AC40: 5.7 | AD40: 5.75 | AE40: 5.75 | AF40: 5.75 | AG40: 5.75
B41: BRL / USD – média do ano | C41: 2.3507822 | D41: 2.9216974 | E41: 3.0770607 | F41: 2.9261243 | G41: 2.435106 | H41: 2.175048 | I41: 1.9472188 | J41: 1.8360255 | K41: 1.9993632 | L41: 1.7602313 | M41: 1.6752187 | N41: 1.9548008 | O41: 2.1599812 | P41: 2.3541833 | Q41: 3.3308667 | R41: 3.4866583 | S41: 3.1917583 | T41: 3.6558667 | U41: 3.94615 | V41: 5.160475 | W41: 5.3959083 | X41: 5.1652167 | Y41: 4.9918333 | Z41: 5.3895461 | AA41: 5.6361183 | AB41: 5.5 | AC41: 5.6083333 | AD41: 5.7270833 | AE41: 5.7270833 | AF41: 5.7270833 | AG41: 5.7270833
B42: Setor externo
B43: Balança comercial - USD bi | C43: =C44-C45 -> 1.4632741 | D43: =D44-D45 -> 11.872395 | E43: =E44-E45 -> 23.469584 | F43: =F44-F45 -> 31.308036 | G43: =G44-G45 -> 43.90562 | H43: =H44-H45 -> 45.050054 | I43: =I44-I45 -> 37.774435 | J43: =J44-J45 -> 21.057537 | ... AG43: =AG44-AG45 -> 78.323741
B44: Exportações – USD bi | C44: 58.032294 | D44: 60.147158 | E44: 72.776747 | F44: 95.121672 | G44: 118.59784 | H44: 137.58115 | I44: 159.81638 | J44: 195.76462 | K44: 151.79167 | L44: 200.43413 | M44: 253.66631 | N44: 239.95254 | O44: 232.54426 | P44: 220.92324 | Q44: 186.78236 | R44: 179.52613 | S44: 214.98811 | T44: 231.88952 | U44: 221.12681 | V44: 209.18024 | W44: 280.81458 | X44: 334.13604 | Y44: 339.67278 | Z44: 337.03628 | AA44: 338.27947 | AB44: 335.4261 | AC44: 367.07846 | AD44: 376.53907 | AE44: 376.53907 | AF44: 376.53907 | AG44: 376.53907
B45: Importações – USD bi | C45: 56.56902 | D45: 48.274764 | E45: 49.307163 | F45: 63.813637 | G45: 74.692216 | H45: 92.531097 | I45: 122.04195 | J45: 174.70709 | K45: 129.39761 | L45: 183.33696 | M45: 227.96976 | N45: 225.16643 | O45: 241.50089 | P45: 230.82302 | Q45: 173.10426 | R45: 139.32136 | S45: 158.95144 | T45: 185.32198 | U45: 185.92797 | V45: 158.78682 | W45: 219.40805 | X45: 272.61069 | Y45: 240.83462 | Z45: 262.48415 | AA45: 272.98312 | AB45: 277.00653 | AC45: 296.40334 | AD45: 298.21533 | AE45: 298.21533 | AF45: 298.21533 | AG45: 298.21533
B46: Conta corrente - % PIB | C46: -0.044481278 | D46: -0.018514121 | E46: 0.0039201255 | F46: 0.013385295 | G46: 0.013092985 | H46: 0.009731459 | I46: -0.0019714176 | J46: -0.021026956 | K46: -0.017534374 | L46: -0.039243235 | M46: -0.03196664 | N46: -0.03761978 | O46: -0.03580539 | P46: -0.045010254 | Q46: -0.035302313 | R46: -0.016959196 | S46: -0.012244951 | T46: -0.028085763 | U46: -0.034708004 | V46: -0.016884495 | W46: -0.024189892 | X46: -0.021601461 | Y46: -0.012748926 | Z46: -0.026574469 | AA46: -0.03 | AB46: -0.031 | AC46: -0.029931229 | AD46: -0.029073234 | AE46: -0.029073234 | AF46: -0.029073234 | AG46: -0.029073234
B47: Investimento direto no país - % PIB | C47: 0.041496225 | D47: 0.032550656 | E47: 0.018131558 | F47: 0.02714466 | G47: 0.017344039 | H47: 0.017529008 | I47: 0.031910894 | J47: 0.029942928 | K47: 0.018884212 | L47: 0.037321422 | M47: 0.039207732 | N47: 0.037582924 | O47: 0.030469996 | P47: 0.035732216 | Q47: 0.035964279 | R47: 0.041318627 | S47: 0.033386461 | T47: 0.040797651 | U47: 0.03694245 | V47: 0.030287338 | W47: 0.027781425 | X47: 0.047412603 | Y47: 0.028281453 | Z47: 0.032122399 | AA47: 0.037973761 | AB47: 0.037782545 | AC47: 0.041602922 | AD47: 0.040750131 | AE47: 0.040750131 | AF47: 0.040750131 | AG47: 0.040750131
B48: Inflação LatAm + Caribe | C48: 0.069 | D48: 0.064 | E48: 0.09 | F48: 0.061 | G48: 0.054 | H48: 0.042 | I48: 0.042 | J48: 0.065 | K48: 0.046 | L48: 0.042 | M48: 0.051 | N48: 0.046 | O48: 0.045 | P48: 0.048 | Q48: 0.053 | R48: 0.054 | S48: 0.063 | T48: 0.067 | U48: 0.076 | V48: 0.065 | W48: 0.099 | X48: 0.142 | Y48: 0.148 | Z48: 0.166 | AA48: 0.072 | AB48: 0.048 | AC48: 0.039 | AD48: 0.036 | AE48: 0.036 | AF48: 0.036 | AG48: 0.036
B49: Câmbio MXN/BRL | AA49: 0.29272237 | AB49: 0.30569948 | AC49: 0.31631135 | AD49: 0.32654028 | AE49: 0.32654028 | AF49: 0.32654028 | AG49: 0.32654028
B50: CPI MXN | AA50: 0.051 | AB50: 0.042 | AC50: 0.04 | AD50: 0.04 | AE50: 0.04 | AF50: 0.04 | AG50: 0.04
B51: Fonte: Itaú
