Workbook

Sheet Modelo
B1: R$ ´000 | C1: 2022 | D1: 2023 | E1: 2024 | F1: 2025 | G1: 2026E | H1: 2027E | I1: 2028E | J1: 2029E
A2: . | B2: Premissas Operacionais
B3: VGV Lançado | F3: ='Buildup da Receita'!Y6 * 1000 -> 6858000 | G3: 7543800 | H3: 7996428 | I3: 8396249 | J3: 8816062
B4: Crescimento VGV (% YoY) | G4: =G3/F3-1 -> 0.1 | H4: =H3/G3-1 -> 0.06 | I4: =I3/H3-1 -> 0.04999995 | J4: =J3/I3-1 -> 0.050000066
B5: Deduções (% Receita Bruta) | AC5: 0.13 | AD5: 0.16 | AE5: 0.19 | AF5: 0.22 | AG5: 0.25
B6: Margem Bruta (% Receita Líquida) | G6: 0.4 | H6: 0.39 | I6: 0.385 | J6: 0.385 | AB6: 0.34 | AC6: -0.424 | AD6: -0.344 | AE6: -0.272 | AF6: -0.212 | AG6: -0.166
B7: Despesas Comerciais (% Receita Líquida) | G7: 0.09 | H7: 0.089 | I7: 0.088 | J7: 0.087 | AB7: 0.36 | AC7: -0.193 | AD7: -0.103 | AE7: -0.024 | AF7: 0.039 | AG7: 0.088
B8: G&A (% Receita Líquida) | G8: 0.06 | H8: 0.059 | I8: 0.058 | J8: 0.057 | AB8: 0.38 | AC8: 0.038 | AD8: 0.138 | AE8: 0.223 | AF8: 0.29 | AG8: 0.342
B9: Outras Desp. Operacionais (% Receita Líquida) | G9: 0.02 | H9: 0.019 | I9: 0.018 | J9: 0.017 | AB9: 0.4 | AC9: 0.27 | AD9: 0.379 | AE9: 0.47 | AF9: 0.542 | AG9: 0.596
B10: Alíquota Efetiva (RET, % Receita Bruta) | G10: 0.04 | H10: 0.04 | I10: 0.04 | J10: 0.04 | AB10: 0.42 | AC10: 0.501 | AD10: 0.62 | AE10: 0.717 | AF10: 0.793 | AG10: 0.85
B11: Resultado de Equivalencia Patrimonial (% Receita Líquida) | G11: 0.018 | H11: =G11 -> 0.018 | I11: =H11 -> 0.018 | J11: =I11 -> 0.018
B12: Payout (% Lucro Líquido) | G12: =25% + Multiplos!L13 -> 0.25 | H12: =60% + Multiplos!L13 -> 0.6 | I12: =70% + Multiplos!L13 -> 0.7 | J12: =80% + Multiplos!L13 -> 0.8
B13: Minoritários (% Lucro Líq. Consolidado) | G13: 0.15 | H13: 0.15 | I13: =H13 -> 0.15 | J13: =I13 -> 0.15
B14: IR / CS (% da Receita Líquida) | G14: 0.021 | H14: =G14 -> 0.021 | I14: =H14 -> 0.021 | J14: =I14 -> 0.021
A15: . | B15: Demonstração de Resultados (DRE)
B17: (=) Receita Bruta
B18: (−) Deduções (PIS/COFINS/RET)
B19: (=) Receita Líquida | C19: ='Inputs - DRE'!R5 -> 2162616 | D19: ='Inputs - DRE'!M5 -> 2355183 | E19: ='Inputs - DRE'!H5 -> 3348470 | F19: ='Inputs - DRE'!C5 -> 4343008 | G19: ='Buildup da Receita'!AE40*1000 -> 5465102.8 | H19: ='Buildup da Receita'!AK40*1000 -> 6499946.9 | I19: ='Buildup da Receita'!AQ40*1000 -> 7256210.6 | J19: ='Buildup da Receita'!AW40*1000 -> 7715735.9
B20: (−) Custos de Imóveis Vendidos (CMV) | C20: ='Inputs - DRE'!R6 -> -1428891 | D20: ='Inputs - DRE'!M6 -> -1550208 | E20: ='Inputs - DRE'!H6 -> -2130127 | F20: ='Inputs - DRE'!C6 -> -2620591 | G20: =-G19*(1-G6) -> -3279061.7 | H20: =-H19*(1-H6) -> -3964967.6 | I20: =-I19*(1-I6) -> -4462569.5 | J20: =-J19*(1-J6) -> -4745177.6
B21: (=) Lucro Bruto | C21: =C19+C20 -> 733725 | D21: =D19+D20 -> 804975 | E21: =E19+E20 -> 1218343 | F21: =F19+F20 -> 1722417 | G21: =G19+G20 -> 2186041.1 | H21: =H19+H20 -> 2534979.3 | I21: =I19+I20 -> 2793641.1 | J21: =J19+J20 -> 2970558.3
B22: Margem Bruta (%) | C22: =C21/C19 -> 0.3392766 | D22: =D21/D19 -> 0.34178873 | E22: =E21/E19 -> 0.36385065 | F22: =F21/F19 -> 0.3965954 | G22: =G6 -> 0.4 | H22: =H6 -> 0.39 | I22: =I6 -> 0.385 | J22: =J6 -> 0.385
B24: (−) Despesas Comerciais | C24: ='Inputs - DRE'!R9 -> -203082 | D24: ='Inputs - DRE'!M9 -> -202241.82 | E24: ='Inputs - DRE'!H9 -> -289706 | F24: ='Inputs - DRE'!C9 -> -408037 | G24: =-G7*G19 -> -491859.25 | H24: =-H7*H19 -> -578495.27 | I24: =-I7*I19 -> -638546.54 | J24: =-J7*J19 -> -671269.02
B25: (−) Despesas Gerais e Administrativas (G&A) | C25: ='Inputs - DRE'!R8 -> -151631 | D25: ='Inputs - DRE'!M8 -> -174709.76 | E25: ='Inputs - DRE'!H8 -> -210307 | F25: ='Inputs - DRE'!C8 -> -254781 | G25: =-G8*G19 -> -327906.17 | H25: =-H8*H19 -> -383496.87 | I25: =-I8*I19 -> -420860.22 | J25: =-J8*J19 -> -439796.95
B26: (+/−) Outras Receitas/Despesas Operacionais | C26: ='Inputs - DRE'!R11 -> -25357 | D26: ='Inputs - DRE'!M11 -> -58989.301 | E26: ='Inputs - DRE'!H11 -> -49879 | F26: ='Inputs - DRE'!C11 -> -119095 | G26: =-G9*G19 -> -109302.06 | H26: =-H9*H19 -> -123498.99 | I26: =-I9*I19 -> -130611.79 | J26: =-J9*J19 -> -131167.51
B27: (+) Resultado de Equivalência Patrimonial | C27: ='Inputs - DRE'!R10 -> 21758 | D27: ='Inputs - DRE'!M10 -> 53700.914 | E27: ='Inputs - DRE'!H10 -> 86528 | F27: ='Inputs - DRE'!C10 -> 62631 | G27: =G11*G19 -> 98371.85 | H27: =H11*H19 -> 116999.04 | I27: =I11*I19 -> 130611.79 | J27: =J11*J19 -> 138883.25
B28: (-) Depreciação | G28: =G199 -> -105429.43 | H28: =H199 -> -105337.76 | I28: =I199 -> -113356.13 | J28: =J199 -> -124024.71
B29: (=) EBIT Ex - Depreciação | C29: =C27+C26+C25+C24+C21 -> 375413 | D29: =D27+D26+D25+D24+D21 -> 422735.03 | E29: =E27+E26+E25+E24+E21 -> 754979 | F29: =F27+F26+F25+F24+F21 -> 1003135 | G29: =G27+G26+G25+G24+G21 -> 1355345.5 | H29: =H27+H26+H25+H24+H21 -> 1566487.2 | I29: =I27+I26+I25+I24+I21 -> 1734234.3 | J29: =J27+J26+J25+J24+J21 -> 1867208.1
B30: (=) EBIT | C30: =C21+C27+C26+C25+C24 -> 375413 | D30: =D21+D27+D26+D25+D24 -> 422735.03 | E30: =E21+E27+E26+E25+E24 -> 754979 | F30: =F21+F27+F26+F25+F24 -> 1003135 | G30: =G21+G27+G26+G25+G24+G28 -> 1249916.1 | H30: =H21+H27+H26+H25+H24+H28 -> 1461149.4 | I30: =I21+I27+I26+I25+I24+I28 -> 1620878.2 | J30: =J21+J27+J26+J25+J24+J28 -> 1743183.4
B31: Margem EBIT (%) | C31: =C30/C19 -> 0.17359208 | D31: =D30/D19 -> 0.17949137 | E31: =E30/E19 -> 0.22546984 | F31: =F30/F19 -> 0.23097701 | G31: =G30/G19 -> 0.22870861 | H31: =H30/H19 -> 0.22479406 | I31: =I30/I19 -> 0.22337805 | J31: =J30/J19 -> 0.22592574
B33: (+/−) Resultado Financeiro | C33: =SUM('Inputs - DRE'!R12,'Inputs - DRE'!R13) -> -73878 | D33: =SUM('Inputs - DRE'!M12,'Inputs - DRE'!M13) -> 14123.897 | E33: =SUM('Inputs - DRE'!H12,'Inputs - DRE'!H13) -> 37319 | F33: =SUM('Inputs - DRE'!C12,'Inputs - DRE'!C13) -> 75360 | G33: =G191+G206 -> -50746.381 | H33: =H191+H206 -> 25976.481 | I33: =I191+I206 -> 28971.062 | J33: =J191+J206 -> 47379.948
B35: (=) EBT | C35: =C30+C33 -> 301535 | D35: =D30+D33 -> 436858.93 | E35: =E30+E33 -> 792298 | F35: =F30+F33 -> 1078495 | G35: =G30+G33 -> 1199169.7 | H35: =H30+H33 -> 1487125.9 | I35: =I30+I33 -> 1649849.3 | J35: =J30+J33 -> 1790563.3
B36: (-) IR / CS | C36: ='Inputs - DRE'!R15 -> -45846 | D36: ='Inputs - DRE'!M15 -> -49981.552 | E36: ='Inputs - DRE'!H15 -> -64630.454 | F36: ='Inputs - DRE'!C15 -> -98803 | G36: =-G14*G19 -> -114767.16 | H36: =-H14*H19 -> -136498.88 | I36: =-I14*I19 -> -152380.42 | J36: =-J14*J19 -> -162030.45
B37: (=) Lucro Líquido Antes de SPEs | C37: =C35+C36 -> 255689 | D37: =D35+D36 -> 386877.38 | E37: =E35+E36 -> 727667.55 | F37: =F35+F36 -> 979692 | G37: =G35+G36 -> 1084402.5 | H37: =H35+H36 -> 1350627 | I37: =I35+I36 -> 1497468.9 | J37: =J35+J36 -> 1628532.9
B38: (−) Participação de Minoritários | C38: ='Inputs - DRE'!R17 -> -65669 | D38: ='Inputs - DRE'!M17 -> -55317.086 | E38: ='Inputs - DRE'!H17 -> -89290.163 | F38: ='Inputs - DRE'!C17 -> -190350 | G38: =-G13*G37 -> -162660.38 | H38: =-H13*H37 -> -202594.05 | I38: =-I13*I37 -> -224620.33 | J38: =-J13*J37 -> -244279.93
B39: (=) Lucro Líquido | C39: =C37+C38 -> 190020 | D39: =D37+D38 -> 331560.3 | E39: =E37+E38 -> 638377.38 | F39: =F37+F38 -> 789342 | G39: =G37+G38 -> 921742.14 | H39: =H37+H38 -> 1148033 | I39: =I37+I38 -> 1272848.5 | J39: =J37+J38 -> 1384252.9
B40: Margem Líquida (%) | C40: =C39/C19 -> 0.087865807 | D40: =D39/D19 -> 0.14077899 | E40: =E39/E19 -> 0.19064748 | F40: =F39/F19 -> 0.18175007 | G40: =G39/G19 -> 0.16865962 | H40: =H39/H19 -> 0.1766219 | I40: =I39/I19 -> 0.17541505 | J40: =J39/J19 -> 0.17940647
B42: # Ações em Circulação (mn) | C42: 519000 | D42: =C42 -> 519000 | E42: =D42 -> 519000 | F42: =E42 -> 519000 | G42: =F42 -> 519000 | H42: =G42 -> 519000 | I42: =H42 -> 519000 | J42: =I42 -> 519000
B43: Lucro por Ação - LPA (R$)
A47: . | B47: Balanço Patrimonial
A49: . | B49: ATIVO CIRCULANTE | C49: 2777103 | D49: 3583354.8 | E49: 4571386 | F49: 6128834 | G49: =SUM(G50:G59) -> 6978965.7 | H49: =SUM(H50:H59) -> 7701069.7 | I49: =SUM(I50:I59) -> 8607141.9 | J49: =SUM(J50:J59) -> 9096853.5
B50: Caixa e equivalentes de caixa | C50: 733124 | D50: 633978 | E50: 792054 | F50: 1199343 | G50: =G139 -> 1397048.1 | H50: =H139 -> 1271205.3 | I50: =I139 -> 1560329 | J50: =J139 -> 1689909.5
B51: Aplicações financeiras | C51: 454248 | D51: 693193 | E51: 823127 | F51: 983456 | G51: =F51 -> 983456 | H51: =G51 -> 983456 | I51: =H51 -> 983456 | J51: =I51 -> 983456
B52: Contas a receber | C52: 363372 | D52: 521946.46 | E52: 992821 | F52: 1438700 | G52: =G151 -> 1715408.3 | H52: =H151 -> 2040229.3 | I52: =I151 -> 2277608.4 | J52: =J151 -> 2421846 | K52: wk
B53: Estoques | C53: 960135 | D53: 1420698.9 | E53: 1643111 | F53: 2086835 | G53: =G156 -> 2447966.1 | H53: =H156 -> 2960025.5 | I53: =I156 -> 3331507.6 | J53: =J156 -> 3542487.2 | K53: wk
B54: Terrenos disponíveis para vendas | C54: 0 | D54: 0 | E54: 0 | F54: 0
B55: Crédito com partes relacionadas | C55: 64551 | D55: 67184.39 | E55: 71054 | F55: 92922 | G55: =F55 -> 92922 | H55: =G55 -> 92922 | I55: =H55 -> 92922 | J55: =I55 -> 92922
B56: Tributos a recuperar | C56: 23122 | D56: 25753 | E56: 37062 | F56: 43855 | G56: =G160 -> 58442.266 | H56: =H160 -> 69508.597 | I56: =I160 -> 77595.868 | J56: =J160 -> 82509.901 | K56: wk
B57: Despesas comerciais a apropriar | C57: 0 | D57: 0 | E57: 0 | F57: 0
B58: Contas a receber por alienação de investimentos | C58: 501 | D58: 0 | E58: 5833 | F58: 1718 | G58: =F58 -> 1718 | H58: =G58 -> 1718 | I58: =H58 -> 1718 | J58: =I58 -> 1718
B59: Outros créditos | C59: 178050 | D59: 220602 | E59: 206324 | F59: 282005 | G59: =F59 -> 282005 | H59: =G59 -> 282005 | I59: =H59 -> 282005 | J59: =I59 -> 282005
A61: . | B61: ATIVO NÃO CIRCULANTE | C61: 3712312 | D61: 3988243 | E61: 5496020 | F61: 7090801 | G61: =G62+G71 -> 7090574.8 | H61: =H62+H71 -> 7110361 | I61: =I62+I71 -> 7136686.9 | J61: =J62+J71 -> 7161190.1
B62: Realizável a longo prazo | C62: 3407532 | D62: 3671816 | E62: 5028708 | F62: 6673444 | G62: =F62 -> 6673444 | H62: =G62 -> 6673444 | I62: =H62 -> 6673444 | J62: =I62 -> 6673444
B63: Aplicações financeiras | E63: 99714 | F63: 230360 | G63: =F63 -> 230360 | H63: =G63 -> 230360 | I63: =H63 -> 230360 | J63: =I63 -> 230360
B64: Contas a receber | C64: 314813 | D64: 464034.95 | E64: 846706 | F64: 1389073 | G64: =F64 -> 1389073 | H64: =G64 -> 1389073 | I64: =H64 -> 1389073 | J64: =I64 -> 1389073
B65: Estoque | C65: 3018121 | D65: 3041218 | E65: 3888979 | F65: 4864673 | G65: =F65 -> 4864673 | H65: =G65 -> 4864673 | I65: =H65 -> 4864673 | J65: =I65 -> 4864673
B66: Depósitos judiciais | C66: 17367 | D66: 18111 | E66: 21555 | F66: 24277 | G66: =F66 -> 24277 | H66: =G66 -> 24277 | I66: =H66 -> 24277 | J66: =I66 -> 24277
B67: Crédito com partes relacionadas | C67: 0 | D67: 0 | E67: 0 | F67: 0 | G67: =F67 -> 0 | H67: =G67 -> 0 | I67: =H67 -> 0 | J67: =I67 -> 0
B68: Tributos a recuperar | C68: 6440 | D68: 27548 | E68: 20611 | F68: 11059 | G68: =F68 -> 11059 | H68: =G68 -> 11059 | I68: =H68 -> 11059 | J68: =I68 -> 11059
B69: Contas a receber por alienação de investimentos | C69: 7129 | D69: 7630 | E69: 7630 | F69: 5798 | G69: =F69 -> 5798 | H69: =G69 -> 5798 | I69: =H69 -> 5798 | J69: =I69 -> 5798
B70: Outros créditos | C70: 43662 | D70: 113274 | E70: 143513 | F70: 148204 | G70: =F70 -> 148204 | H70: =G70 -> 148204 | I70: =H70 -> 148204 | J70: =I70 -> 148204
B71: Permanente | C71: 304780 | D71: 316427 | E71: 467312 | F71: 417357 | G71: =SUM(G72:G74) -> 417130.79 | H71: =SUM(H72:H74) -> 436917.01 | I71: =SUM(I72:I74) -> 463242.93 | J71: =SUM(J72:J74) -> 487746.14
B72: Investimentos | C72: 143717 | D72: 169375 | E72: 212504 | F72: 124135 | G72: =F72 -> 124135 | H72: =G72 -> 124135 | I72: =H72 -> 124135 | J72: =I72 -> 124135
B73: Imobilizado | C73: 140115 | D73: 111474 | E73: 220762 | F73: 260159 | G73: =G200 -> 259932.79 | H73: =H200 -> 279719.01 | I73: =I200 -> 306044.93 | J73: =J200 -> 330548.14
B74: Intangível | C74: 20948 | D74: 35578 | E74: 34046 | F74: 33063 | G74: =F74 -> 33063 | H74: =G74 -> 33063 | I74: =H74 -> 33063 | J74: =I74 -> 33063
A76: . | B76: TOTAL DO ATIVO | C76: 6489415 | D76: 7571598 | E76: 10067406 | F76: 13219635 | G76: =G61+G49 -> 14069541 | H76: =H61+H49 -> 14811431 | I76: =I61+I49 -> 15743829 | J76: =J61+J49 -> 16258044
A78: . | B78: PASSIVO CIRCULANTE | C78: 918216 | D78: 1042766 | E78: 1508358 | F78: 1621183 | G78: =SUM(G79:G94) -> 1899121.5 | H78: =SUM(H79:H94) -> 1969204.5 | I78: =SUM(I79:I94) -> 2467127.7 | J78: =SUM(J79:J94) -> 1960212.1
B79: Empréstimos e financiamentos | C79: 309722 | D79: 234933 | E79: 202562 | F79: 274805 | G79: =-H185 -> 282000 | H79: =-I185 -> 190000 | I79: =-J185 -> 572000 | J79: =-K185 -> 0
B80: Cessão de Recebíveis | C80: 13826 | D80: 58926 | E80: 169847 | F80: 296402 | G80: =F80 -> 296402 | H80: =G80 -> 296402 | I80: =H80 -> 296402 | J80: =I80 -> 296402
B81: Fornecedores | C81: 112474 | D81: 121652 | E81: 128837 | F81: 181281 | G81: =G166 -> 235147.81 | H81: =H166 -> 284335.45 | I81: =I166 -> 320019.44 | J81: =J166 -> 340285.8 | K81: wk
B82: Fornecedores - Risco sacado¹ | C82: 10220 | D82: 7879 | E82: 7576 | F82: 12949 | G82: =F82 -> 12949 | H82: =G82 -> 12949 | I82: =H82 -> 12949 | J82: =I82 -> 12949
B83: Obrigações trab. + trib. | C83: =SUM(C84:C85) -> 67923 | D83: =SUM(D84:D85) -> 81590 | E83: =SUM(E84:E85) -> 123927 | F83: =SUM(F84:F85) -> 154908 | G83: =G178 -> 196296.38 | H83: =H178 -> 229574.96 | I83: =I178 -> 251942 | J83: =J178 -> 263278.21 | K83: wk
B84: Obrigações trabalhistas | C84: 39233 | D84: 45411 | E84: 68360 | F84: 87815 | K84: wk
B85: Obrigações tributárias | C85: 28690 | D85: 36179 | E85: 55567 | F85: 67093 | K85: wk
B86: Impostos de Renda e Contribuição Social a pagar corrente | C86: 0 | D86: 0 | E86: 0 | F86: 0
B87: Impostos de Renda e Contribuição Social a pagar diferido | C87: 0 | D87: 0 | E87: 0 | F87: 0
B88: Financiamento por arrendamento | C88: 11324 | D88: 7456 | E88: 7911 | F88: 12686 | G88: =F88 -> 12686 | H88: =G88 -> 12686 | I88: =H88 -> 12686 | J88: =I88 -> 12686
B89: Credores por imóveis compromissados | C89: 113361 | D89: 146827 | E89: 194059 | F89: 131775 | G89: =G174 -> 279436.77 | H89: =H174 -> 337888.66 | I89: =I174 -> 380293.55 | J89: =J174 -> 404376.99 | K89: wk
B90: Adiantamento de clientes | C90: 28540 | D90: 69264 | E90: 66546 | F90: 83947 | G90: =G170 -> 111773.57 | H90: =H170 -> 132938.45 | I90: =I170 -> 148405.73 | J90: =J170 -> 157804.05 | K90: wk
B91: Outras contas a pagar | C91: 84799 | D91: 120996 | E91: 184636 | F91: 222844 | G91: =F91 -> 222844 | H91: =G91 -> 222844 | I91: =H91 -> 222844 | J91: =I91 -> 222844
B92: Dividendos a pagar | C92: 104287 | D92: 81162 | E92: 299399 | F92: 11519 | G92: =F92 -> 11519 | H92: =G92 -> 11519 | I92: =H92 -> 11519 | J92: =I92 -> 11519
B93: Provisão para garantia | C93: 28392 | D93: 24259 | E93: 21964 | F93: 23533 | G93: =F93 -> 23533 | H93: =G93 -> 23533 | I93: =H93 -> 23533 | J93: =I93 -> 23533
B94: Débitos com partes relacionadas | C94: 33348 | D94: 87822 | E94: 101094 | F94: 214534 | G94: =F94 -> 214534 | H94: =G94 -> 214534 | I94: =H94 -> 214534 | J94: =I94 -> 214534
A96: . | B96: PASSIVO NÃO CIRCULANTE | C96: 4121504 | D96: 4418246 | E96: 6335297 | F96: 9278301 | G96: =SUM(G97:G107) -> 8996301 | H96: =SUM(H97:H107) -> 9006301 | I96: =SUM(I97:I107) -> 8834301 | J96: =SUM(J97:J107) -> 9334301
B97: Empréstimos e financiamentos | C97: 1080104 | D97: 1088111 | E97: 1347099 | F97: 2483542 | G97: =G186-G79 -> 2201542 | H97: =H186-H79 -> 2211542 | I97: =I186-I79 -> 2039542 | J97: =J186-J79 -> 2539542
B98: Cessão de Recebíveis | C98: 74494 | D98: 128260 | E98: 524452 | F98: 900748 | G98: =F98 -> 900748 | H98: =G98 -> 900748 | I98: =H98 -> 900748 | J98: =I98 -> 900748
B99: Fornecedores | C99: 9471 | D99: 10004 | E99: 11116 | F99: 14082 | G99: =F99 -> 14082 | H99: =G99 -> 14082 | I99: =H99 -> 14082 | J99: =I99 -> 14082
B100: Obrigações tributárias | C100: 12737 | D100: 18589 | E100: 28523 | F100: 60531 | G100: =F100 -> 60531 | H100: =G100 -> 60531 | I100: =H100 -> 60531 | J100: =I100 -> 60531
B101: Impostos de Renda e Contribuição Social a pagar diferido | C101: 0 | D101: 0 | E101: 0 | F101: 0 | G101: =F101 -> 0 | H101: =G101 -> 0 | I101: =H101 -> 0 | J101: =I101 -> 0
A102: . | B102: Financiamento por arrendamento | C102: 19821 | D102: 13648 | E102: 75773 | F102: 76290 | G102: =F102 -> 76290 | H102: =G102 -> 76290 | I102: =H102 -> 76290 | J102: =I102 -> 76290
B103: Credores por imóveis compromissados | C103: 2388485 | D103: 2668090 | E103: 3655700 | F103: 5088473 | G103: =F103 -> 5088473 | H103: =G103 -> 5088473 | I103: =H103 -> 5088473 | J103: =I103 -> 5088473
B104: Adiantamento de clientes | C104: 398915 | D104: 378427 | E104: 568086 | F104: 521793 | G104: =F104 -> 521793 | H104: =G104 -> 521793 | I104: =H104 -> 521793 | J104: =I104 -> 521793
B105: Provisão para garantia | C105: 13887 | D105: 16303 | E105: 21072 | F105: 24866 | G105: =F105 -> 24866 | H105: =G105 -> 24866 | I105: =H105 -> 24866 | J105: =I105 -> 24866
B106: Provisão p/riscos tributários, trabalhistas e cíveis | C106: 26198 | D106: 27657 | E106: 34319 | F106: 39280 | G106: =F106 -> 39280 | H106: =G106 -> 39280 | I106: =H106 -> 39280 | J106: =I106 -> 39280
B107: Outras contas a pagar | C107: 97392 | D107: 69157 | E107: 69157 | F107: 68696 | G107: =F107 -> 68696 | H107: =G107 -> 68696 | I107: =H107 -> 68696 | J107: =I107 -> 68696
B108: Partes relacionadas | C108: 0 | D108: 0 | E108: 0 | F108: 0
B110: PATRIMÔNIO LÍQUIDO | C110: 1289981 | D110: 1953405 | E110: 2015457 | F110: 1916621 | G110: =SUM(G111:G117) -> 2770588 | H110: =SUM(H111:H117) -> 3432395.2 | I110: =SUM(I111:I117) -> 4038870.1 | J110: =SUM(J111:J117) -> 4560000.6
B111: Capital social | C111: 752982 | D111: 1181857 | E111: 1181857 | F111: 1181857 | G111: =F111 -> 1181857 | H111: =G111 -> 1181857 | I111: =H111 -> 1181857 | J111: =I111 -> 1181857
B112: Gastos com emissões de ações | D112: -21994 | E112: -21994 | F112: -21994 | G112: =F112 -> -21994 | H112: =G112 -> -21994 | I112: =H112 -> -21994 | J112: =I112 -> -21994
B113: Ações em tesouraria | C113: -9749 | D113: -7748 | E113: -9536 | F113: -22571 | G113: =F113 -> -22571 | H113: =G113 -> -22571 | I113: =H113 -> -22571 | J113: =I113 -> -22571
B114: Reservas de capital | C114: 148323 | D114: 184240 | E114: 185178 | F114: 192734 | G114: =F114 -> 192734 | H114: =G114 -> 192734 | I114: =H114 -> 192734 | J114: =I114 -> 192734
...

Sheet FCFF
C1: 2026E | D1: 2027E | E1: 2028E | F1: 2029E | G1: Perpetuidade
A2: . | B2: Free Cash Flow to Firm (FCFF)
B3: NOPAT = EBIT × (1 - T) | C3: =Modelo!G30*(1-FCFF!$C$36) -> 1137423.6 | D3: =Modelo!H30*(1-FCFF!$C$36) -> 1329646 | E3: =Modelo!I30*(1-FCFF!$C$36) -> 1474999.2 | F3: =Modelo!J30*(1-FCFF!$C$36) -> 1586296.9
B4: (+) Depreciação e Amortização | C4: =-Modelo!G28 -> 105429.43 | D4: =-Modelo!H28 -> 105337.76 | E4: =-Modelo!I28 -> 113356.13 | F4: =-Modelo!J28 -> 124024.71
B5: (+/−) Δ Working Capital | C5: =-Modelo!G145 -> -381683.12 | D5: =-Modelo!H145 -> -685863.79 | E5: =-Modelo!I145 -> -501025.24 | F5: =-Modelo!J145 -> -295046.86
B6: (−) CAPEX | C6: =-Modelo!G198 -> -105203.23 | D6: =-Modelo!H198 -> -125123.98 | E6: =-Modelo!I198 -> -139682.05 | F6: =-Modelo!J198 -> -148527.92
B7: (=) Free Cash Flow to Firm (FCFF) | C7: =C3+C4+C5+C6 -> 755966.69 | D7: =D3+D4+D5+D6 -> 623995.98 | E7: =E3+E4+E5+E6 -> 947648.01 | F7: =F3+F4+F5+F6 -> 1266746.8 | G7: =F7*(1+C39)/(C37-C39) -> 11709259
B9: Valor Presente do FCFF | C9: =C7/(1+$C$37)^C10 -> 655930.32 | D9: =D7/(1+$C$37)^D10 -> 469777.14 | E9: =E7/(1+$C$37)^E10 -> 619030.69 | F9: =F7/(1+$C$37)^F10 -> 717976.11 | G9: =G7/(1+C37)^4 -> 6636660.5
B10: t (anos) | C10: 1 | D10: 2 | E10: 3 | F10: 4
A12: . | B12: Valuation
B13: PV Cash Flow Explícito (2026-2029) | C13: =SUM(C9:F9) -> 2462714.3
B14: PV Perpetuidade | C14: =G9 -> 6636660.5
B15: (=) Enterprise Value (EV) | C15: =C14+C13 -> 9099374.8
B16: (−) Dívida Líquida (4T25) | C16: =-(Modelo!F79+Modelo!F97-Modelo!F50-Modelo!F51-Modelo!F63) -> -345188
B17: (=) Equity Value | C17: =C15+C16 -> 8754186.8
B18: # Ações em Circulação (mn) | C18: 519000
B19: Target Price (R$/ação) | C19: =C17/C18 -> 16.867412
B20: Current Price (R$/ação) | C20: 13.3
B21: Upside % | C21: =(C19-C20)/C20 -> 0.26822646
G22: =C21 -> 0.26822646 | H22: 0.1725 | I22: 0.1625 | J22: 0.1525 | K22: 0.1425 | L22: 0.1325
A23: . | B23: Cost of Equity (CAPM) | G23: 0.03 | H23: -0.0067297636 | I23: 0.08008992 | J23: 0.18137378 | K23: 0.30099215 | L23: 0.44432646
B24: Beta (5Y Mensal) | C24: 1.1 | G24: 0.035 | H24: 0.022322816 | I24: 0.11466283 | J24: 0.22301698 | K24: 0.35186794 | L24: 0.50753819
B25: Risk-Free Rate (USA 10Y Treasury) | C25: 0.045 | G25: 0.04 | H25: 0.053568044 | I25: 0.15205801 | J25: 0.26836179 | K25: 0.40770723 | L25: 0.57758363
B26: Equity Risk Premium (USA mature) | C26: 0.045 | G26: 0.045 | H26: 0.087263877 | I26: 0.19263576 | J26: 0.31792473 | K26: 0.46927362 | L26: 0.65563426
B27: CRP Brasil (Damodaran) | C27: 0.0324 | G27: 0.05 | H27: 0.12371039 | I27: 0.23682042 | J27: 0.37232308 | K27: 0.53749584 | L27: 0.74314557
B28: Devaluation Risk (Inflação BR-USA) | C28: 0.02
B29: Cost of Equity (Ke) | C29: =C25+C24*C26+C27+C28+2% -> 0.1669
A31: . | B31: WACC
B32: Cost of Debt (Kd) | C32: 0.14 | G32: =C21 -> 0.26822646 | H32: 0.36 | I32: 0.38 | J32: 0.4 | K32: 0.42 | L32: 0.44
B33: D / (D+E) | C33: ='Inputs - BP'!H137/('Inputs - BP'!H137 +FCFF!C40) -> 0.36428672 | G33: 0.16 | H33: -0.129 | I33: 0.035 | J33: 0.199 | K33: 0.254 | L33: 0.294
B34: E / (D+E) | C34: =1-C33 -> 0.63571328 | G34: 0.18 | H34: -0.1 | I34: 0.068 | J34: 0.236 | K34: 0.264 | L34: 0.304
B35: Tax Rate 2 | C35: 0.25
B36: Tax Rate | C36: 0.09 | G36: 0.2 | H36: -0.075 | I36: 0.096 | J36: 0.268 | K36: 0.272 | L36: 0.312
B37: WACC (nominal em R$) | C37: =C29*C34+C32*C33*(1-C36) -> 0.15251067 | G37: 0.22 | H37: -0.053 | I37: 0.12 | J37: 0.294 | K37: 0.279 | L37: 0.319
G38: 0.24 | H38: -0.035 | I38: 0.14 | J38: 0.316 | K38: 0.285 | L38: 0.325
A39: ● | B39: Perpetuity Growth (g) | C39: 0.04
B40: Current Mkt Cap (R$ mn) | C40: 6902700

Sheet Multiplos
B2: R$ '000 | C2: 2026E | D2: 2027E | E2: 2028E | F2: 2029E
B4: Lucro Líquido | C4: =Modelo!G39 -> 921742.14 | D4: =Modelo!H39 -> 1148033 | E4: =Modelo!I39 -> 1272848.5 | F4: =Modelo!J39 -> 1384252.9
B7: (-) Valor de Entrada | C7: =-FCFF!C40 -> -6902700
B8: (+) Dividendos | C8: =-Modelo!G133 -> 230435.53 | D8: =-Modelo!H133 -> 688819.78 | E8: =-Modelo!I133 -> 890993.97 | F8: =-Modelo!J133 -> 1107402.4
B9: (+) Valor de Saída | D9: =IF(C14=2027,C18*E4,0) -> 0 | E9: =IF(C14=2028,C18*F4,0) -> 0 | F9: =IF(C14=2029,F4*(1+FCFF!C39)*C18,0) -> 8637738.3
B11: Fluxo de Caixa | C11: =C7+C8 -> -6672264.5 | D11: =D7+D8+D9 -> 688819.78 | E11: =E7+E8+E9 -> 890993.97 | F11: =F7+F8+F9 -> 9745140.7
K13: Delta Payout | L13: 0
B14: Ano de Saída | C14: 2029
B16: Múltiplo de Entrada | C16: =-C7/D4 -> 6.0126322
I17: =C20 -> 0.21042681 | J17: 3 | K17: 4 | L17: 6 | M17: 7 | N17: 8
B18: Múltiplo de Saída | C18: 6 | I18: 1184253 | J18: -0.01664997 | K18: 0.050247373 | L18: 0.16175042 | M18: 0.20981471 | N18: 0.25412479
I19: 1284253 | J19: 0.001227837 | K19: 0.070878801 | L19: 0.18662106 | M19: 0.23641274 | N19: 0.28227397
B20: TIR | C20: =IF(C14=2027,IRR(C11:D11),IF(C14=2028,IRR(C11:E11),IF(C14=2029,IRR(C11:F11),0))) -> 0.21042681 | I20: 1384253 | J20: 0.01843626 | K20: 0.090686282 | L20: 0.21042683 | M20: 0.26184775 | N20: 0.30917226
I21: 1484253 | J21: 0.035035164 | K21: 0.10974805 | L21: 0.23327553 | M21: 0.28623977 | N21: 0.33495067
B22: MOIC | C22: =(SUM(C8:F8)+F9)/-C7 -> 1.6740391 | I22: 1584253 | J22: 0.05107625 | K22: 0.12813104 | L22: 0.25525845 | M22: 0.30969009 | N22: 0.3597195
I26: =C20 -> 0.21042681 | J26: 4 | K26: 5 | L26: 6 | M26: 7 | N26: 8
I27: 2027 | J27: -0.13369533 | K27: 0.05707177 | L27: 0.24783887 | M27: 0.43860596 | N27: 0.62937306
I28: 2028 | J28: 0.034499803 | K28: 0.13490947 | L28: 0.22677083 | M28: 0.31195444 | N28: 0.3917343
I29: 2029 | J29: 0.09068627 | K29: 0.15388 | L29: 0.21042681 | M29: 0.26184774 | N29: 0.30917225
I35: =C20 -> 0.21042681 | J35: 4 | K35: 5 | L35: 6 | M35: 7 | N35: 8
I36: -0.1 | J36: 0.079395109 | K36: 0.14432988 | L36: 0.20227598 | M36: 0.25486353 | N36: 0.30318707
I37: -0.05 | J37: 0.085064251 | K37: 0.14912252 | L37: 0.20636516 | M37: 0.2583668 | N37: 0.30618897
I38: 0 | J38: 0.09068627 | K38: 0.15388 | L38: 0.21042681 | M38: 0.26184774 | N38: 0.30917225
I39: 0.05 | J39: 0.096262288 | K39: 0.15860315 | L39: 0.21446162 | M39: 0.26530694 | N39: 0.31213743
I40: 0.1 | J40: 0.10179342 | K40: 0.16329281 | L40: 0.21847029 | M40: 0.26874501 | N40: 0.31508507

Sheet Buildup da Receita
B1: [R$ milhões] | C1: 2022A | I1: 2023A | O1: 2024A | U1: 2025A | AA1: 2026E | AG1: 2027E | AM1: 2028E | AS1: 2029E
C2: 1T22 | D2: 2T22 | E2: 3T22 | F2: 4T22 | G2: Total 2022 | I2: 1T23 | J2: 2T23 | K2: 3T23 | L2: 4T23 | M2: Total 2023 | O2: 1T24 | P2: 2T24 | Q2: 3T24 | R2: 4T24 | S2: Total 2024 | U2: 1T25 | V2: 2T25 | W2: 3T25 | X2: 4T25 | Y2: Total 2025 | AA2: 1T26 | AB2: 2T26 | AC2: 3T26 | AD2: 4T26 | AE2: Total 2026 | AG2: 1T27 | AH2: 2T27 | AI2: 3T27 | AJ2: 4T27 | AK2: Total 2027 | AM2: 1T28 | AN2: 2T28 | AO2: 3T28 | AP2: 4T28 | AQ2: Total 2028 | AS2: 1T29 | AT2: 2T29 | AU2: 3T29 | AV2: 4T29 | AW2: Total 2029
B4: BLOCO TRIMESTRAL
B6: Lançamentos | C6: 599 | D6: 790 | E6: 1189 | F6: 1057 | G6: 3635 | I6: 611 | J6: 1457 | K6: 1399 | L6: 1390 | M6: 4857 | O6: 896 | P6: 1361 | Q6: 1664 | R6: 1562 | S6: 5483 | U6: 901 | V6: 1904 | W6: 2152 | X6: 1901 | Y6: 6858 | AA6: =$AE$34*$AE$30 -> 991.25532 | AB6: =$AE$34*$AE$31 -> 2094.1589 | AC6: =$AE$34*$AE$32 -> 2367.2444 | AD6: =$AE$34*$AE$33 -> 2091.1414 | AE6: =SUM(AA6:AD6) -> 7543.8 | AG6: =$AK$34*$AK$30 -> 1050.7306 | AH6: =$AK$34*$AK$31 -> 2219.8084 | AI6: =$AK$34*$AK$32 -> 2509.2791 | AJ6: =$AK$34*$AK$33 -> 2216.6098 | AK6: =SUM(AG6:AJ6) -> 7996.428 | AM6: =$AQ$34*$AQ$30 -> 1103.2672 | AN6: =$AQ$34*$AQ$31 -> 2330.7988 | AO6: =$AQ$34*$AQ$32 -> 2634.7431 | AP6: =$AQ$34*$AQ$33 -> 2327.4403 | AQ6: =SUM(AM6:AP6) -> 8396.2494 | AS6: =$AW$34*$AW$30 -> 1158.4305 | AT6: =$AW$34*$AW$31 -> 2447.3388 | AU6: =$AW$34*$AW$32 -> 2766.4802 | AV6: =$AW$34*$AW$33 -> 2443.8124 | AW6: =SUM(AS6:AV6) -> 8816.0619
B7: VSO Lançamento | C7: 0.32 | D7: 0.32 | E7: 0.32 | F7: 0.32 | I7: 0.32 | J7: 0.32 | K7: 0.32 | L7: 0.32 | O7: 0.32 | P7: 0.32 | Q7: 0.32 | R7: 0.32 | U7: 0.32 | V7: 0.32 | W7: 0.32 | X7: 0.32 | AA7: =$AE$25 -> 0.3 | AB7: =$AE$25 -> 0.3 | AC7: =$AE$25 -> 0.3 | AD7: =$AE$25 -> 0.3 | AG7: =$AK$25 -> 0.3 | AH7: =$AK$25 -> 0.3 | AI7: =$AK$25 -> 0.3 | AJ7: =$AK$25 -> 0.3 | AM7: =$AQ$25 -> 0.3 | AN7: =$AQ$25 -> 0.3 | AO7: =$AQ$25 -> 0.3 | AP7: =$AQ$25 -> 0.3 | AS7: =$AW$25 -> 0.3 | AT7: =$AW$25 -> 0.3 | AU7: =$AW$25 -> 0.3 | AV7: =$AW$25 -> 0.3
B8: Venda de Lançamento | C8: 191.68 | D8: 252.8 | E8: 380.48 | F8: 338.24 | G8: 1163.2 | I8: 195.52 | J8: 466.24 | K8: 447.68 | L8: 444.8 | M8: 1554.24 | O8: 286.72 | P8: 435.52 | Q8: 532.48 | R8: 499.84 | S8: 1754.56 | U8: 288.32 | V8: 609.28 | W8: 688.64 | X8: 608.32 | Y8: 2194.56 | AA8: =AA7*AA6 -> 297.3766 | AB8: =AB7*AB6 -> 628.24766 | AC8: =AC7*AC6 -> 710.17333 | AD8: =AD7*AD6 -> 627.34241 | AE8: =SUM(AA8:AD8) -> 2263.14 | AG8: =AG7*AG6 -> 315.21919 | AH8: =AH7*AH6 -> 665.94252 | AI8: =AI7*AI6 -> 752.78373 | AJ8: =AJ7*AJ6 -> 664.98295 | AK8: =SUM(AG8:AJ8) -> 2398.9284 | AM8: =AM7*AM6 -> 330.98015 | AN8: =AN7*AN6 -> 699.23965 | AO8: =AO7*AO6 -> 790.42292 | AP8: =AP7*AP6 -> 698.2321 | AQ8: =SUM(AM8:AP8) -> 2518.8748 | AS8: =AS7*AS6 -> 347.52916 | AT8: =AT7*AT6 -> 734.20163 | AU8: =AU7*AU6 -> 829.94406 | AV8: =AV7*AV6 -> 733.14371 | AW8: =SUM(AS8:AV8) -> 2644.8186
B10: Estoque Inicial | C10: 3257 | D10: 3310 | E10: 3266 | F10: 3693 | G10: 3257 | I10: 4203 | J10: 4043 | K10: 4583 | L10: 5021 | M10: 4203 | O10: 5146 | P10: 4778 | Q10: 4592 | R10: 4491 | S10: 5146 | U10: 4787 | V10: 4458 | W10: 4716 | X10: 5296 | Y10: 4787 | AA10: =X22 -> 5696 | AB10: =AA22 -> 5250.6787 | AC10: =AB22 -> 5666.4542 | AD10: =AC22 -> 6190.2345 | AE10: =AA10 -> 5696 | AG10: =AD22 -> 6415.9865 | AH10: =AG22 -> 5868.3007 | AI10: =AH22 -> 6248.5064 | AJ10: =AI22 -> 6755.3005 | AK10: =AG10 -> 6415.9865 | AM10: =AJ22 -> 6955.8673 | AN10: =AM22 -> 6336.9809 | AO10: =AN22 -> 6701.1439 | AP10: =AO22 -> 7205.2352 | AQ10: =AM10 -> 6955.8673 | AS10: =AP22 -> 7393.3964 | AT10: =AS22 -> 6799.5525 | AU10: =AT22 -> 7220.7746 | AV10: =AU22 -> 7785.3636 | AW10: =AS10 -> 7393.3964
B11: VSO Estoque | C11: 0.21 | D11: 0.21 | E11: 0.21 | F11: 0.21 | I11: 0.21 | J11: 0.21 | K11: 0.21 | L11: 0.21 | O11: 0.21 | P11: 0.21 | Q11: 0.21 | R11: 0.21 | U11: 0.21 | V11: 0.21 | W11: 0.21 | X11: 0.21 | AA11: =$AE$26 -> 0.2 | AB11: =$AE$26 -> 0.2 | AC11: =$AE$26 -> 0.2 | AD11: =$AE$26 -> 0.2 | AG11: =$AK$26 -> 0.2 | AH11: =$AK$26 -> 0.2 | AI11: =$AK$26 -> 0.2 | AJ11: =$AK$26 -> 0.2 | AM11: =$AQ$26 -> 0.2 | AN11: =$AQ$26 -> 0.2 | AO11: =$AQ$26 -> 0.2 | AP11: =$AQ$26 -> 0.2 | AS11: =$AW$26 -> 0.19 | AT11: =$AW$26 -> 0.19 | AU11: =$AW$26 -> 0.19 | AV11: =$AW$26 -> 0.19
B12: Venda de Estoque | C12: 683.97 | D12: 695.1 | E12: 685.86 | F12: 775.53 | G12: 2840.46 | I12: 882.63 | J12: 849.03 | K12: 962.43 | L12: 1054.41 | M12: 3748.5 | O12: 1080.66 | P12: 1003.38 | Q12: 964.32 | R12: 943.11 | S12: 3991.47 | U12: 1005.27 | V12: 936.18 | W12: 990.36 | X12: 1112.16 | Y12: 4043.97 | AA12: =AA11*AA10 -> 1139.2 | AB12: =AB11*AB10 -> 1050.1357 | AC12: =AC11*AC10 -> 1133.2908 | AD12: =AD11*AD10 -> 1238.0469 | AE12: =SUM(AA12:AD12) -> 4560.6735 | AG12: =AG11*AG10 -> 1283.1973 | AH12: =AH11*AH10 -> 1173.6601 | AI12: =AI11*AI10 -> 1249.7013 | AJ12: =AJ11*AJ10 -> 1351.0601 | AK12: =SUM(AG12:AJ12) -> 5057.6188 | AM12: =AM11*AM10 -> 1391.1735 | AN12: =AN11*AN10 -> 1267.3962 | AO12: =AO11*AO10 -> 1340.2288 | AP12: =AP11*AP10 -> 1441.047 | AQ12: =SUM(AM12:AP12) -> 5439.8455 | AS12: =AS11*AS10 -> 1404.7453 | AT12: =AT11*AT10 -> 1291.915 | AU12: =AU11*AU10 -> 1371.9472 | AV12: =AV11*AV10 -> 1479.2191 | AW12: =SUM(AS12:AV12) -> 5547.8266
B13: Vendas Líquidas | C13: 622 | D13: 836 | E13: 847 | F13: 695 | G13: 3000 | I13: 803 | J13: 962 | K13: 1005 | L13: 1220 | M13: 3990 | O13: 1308 | P13: 1619 | Q13: 1765 | R13: 1308 | S13: 6000 | U13: 1326 | V13: 1677 | W13: 1642 | X13: 1517 | Y13: 6162 | AA13: =AA8+AA12 -> 1436.5766 | AB13: =AB8+AB12 -> 1678.3834 | AC13: =AC8+AC12 -> 1843.4642 | AD13: =AD8+AD12 -> 1865.3893 | AE13: =SUM(AA13:AD13) -> 6823.8135 | AG13: =AG8+AG12 -> 1598.4165 | AH13: =AH8+AH12 -> 1839.6027 | AI13: =AI8+AI12 -> 2002.485 | AJ13: =AJ8+AJ12 -> 2016.0431 | AK13: =SUM(AG13:AJ13) -> 7456.5472 | AM13: =AM8+AM12 -> 1722.1536 | AN13: =AN8+AN12 -> 1966.6358 | AO13: =AO8+AO12 -> 2130.6517 | AP13: =AP8+AP12 -> 2139.2791 | AQ13: =SUM(AM13:AP13) -> 7958.7203 | AS13: =AS8+AS12 -> 1752.2745 | AT13: =AT8+AT12 -> 2026.1166 | AU13: =AU8+AU12 -> 2201.8912 | AV13: =AV8+AV12 -> 2212.3628 | AW13: =SUM(AS13:AV13) -> 8192.6451
B15: REF Inicial | C15: 854 | D15: 938 | E15: 1068 | F15: 1135 | G15: 854 | I15: 1071 | J15: 1119 | K15: 1084 | L15: 1333 | M15: 1071 | O15: 1708 | P15: 1926 | Q15: 2331 | R15: 2618 | S15: 1708 | U15: 2845 | V15: 3116 | W15: 3398 | X15: 3686 | Y15: 2845 | AA15: =X21 -> 3822 | AB15: =AA21 -> 4017.9813 | AC15: =AB21 -> 4402.7703 | AD15: =AC21 -> 4833.1111 | AE15: =AA15 -> 3822 | AG15: =AD21 -> 5180.7107 | AH15: =AG21 -> 5245.571 | AI15: =AH21 -> 5525.8637 | AJ15: =AI21 -> 5868.8032 | AK15: =AG15 -> 5180.7107 | AM15: =AJ21 -> 6137.3111 | AN15: =AM21 -> 6115.7121 | AO15: =AN21 -> 6330.288 | AP15: =AO21 -> 6619.8946 | AQ15: =AM15 -> 6137.3111 | AS15: =AP21 -> 6839.8207 | AT15: =AS21 -> 6725.8454 | AU15: =AT21 -> 6883.0289 | AV15: =AU21 -> 7131.6731 | AW15: =AS15 -> 6839.8207
B16: Receita de Lançamento | C16: 38.336 | D16: 50.56 | E16: 76.096 | F16: 67.648 | G16: 232.64 | I16: 39.104 | J16: 93.248 | K16: 89.536 | L16: 88.96 | M16: 310.848 | O16: 57.344 | P16: 87.104 | Q16: 106.496 | R16: 99.968 | S16: 350.912 | U16: 57.664 | V16: 121.856 | W16: 137.728 | X16: 121.664 | Y16: 438.912 | AA16: =$AE$27*AA8 -> 59.475319 | AB16: =$AE$27*AB8 -> 125.64953 | AC16: =$AE$27*AC8 -> 142.03467 | AD16: =$AE$27*AD8 -> 125.46848 | AE16: =SUM(AA16:AD16) -> 452.628 | AG16: =$AK$27*AG8 -> 63.043838 | AH16: =$AK$27*AH8 -> 133.1885 | AI16: =$AK$27*AI8 -> 150.55675 | AJ16: =$AK$27*AJ8 -> 132.99659 | AK16: =SUM(AG16:AJ16) -> 479.78568 | AM16: =$AQ$27*AM8 -> 66.19603 | AN16: =$AQ$27*AN8 -> 139.84793 | AO16: =$AQ$27*AO8 -> 158.08458 | AP16: =$AQ$27*AP8 -> 139.64642 | AQ16: =SUM(AM16:AP16) -> 503.77496 | AS16: =$AW$27*AS8 -> 69.505832 | AT16: =$AW$27*AT8 -> 146.84033 | AU16: =$AW$27*AU8 -> 165.98881 | AV16: =$AW$27*AV8 -> 146.62874 | AW16: =SUM(AS16:AV16) -> 528.96371
B17: Receita de Estoque | C17: 341.985 | D17: 347.55 | E17: 342.93 | F17: 387.765 | G17: 1420.23 | I17: 441.315 | J17: 424.515 | K17: 481.215 | L17: 527.205 | M17: 1874.25 | O17: 540.33 | P17: 501.69 | Q17: 482.16 | R17: 471.555 | S17: 1995.735 | U17: 502.635 | V17: 468.09 | W17: 495.18 | X17: 556.08 | Y17: 2021.985 | AA17: =$AE$28*AA12 -> 569.6 | AB17: =$AE$28*AB12 -> 525.06787 | AC17: =$AE$28*AC12 -> 566.64542 | AD17: =$AE$28*AD12 -> 619.02345 | AE17: =SUM(AA17:AD17) -> 2280.3367 | AG17: =$AK$28*AG12 -> 641.59865 | AH17: =$AK$28*AH12 -> 586.83007 | AI17: =$AK$28*AI12 -> 624.85064 | AJ17: =$AK$28*AJ12 -> 675.53005 | AK17: =SUM(AG17:AJ17) -> 2528.8094 | AM17: =$AQ$28*AM12 -> 695.58673 | AN17: =$AQ$28*AN12 -> 633.69809 | AO17: =$AQ$28*AO12 -> 670.11439 | AP17: =$AQ$28*AP12 -> 720.52352 | AQ17: =SUM(AM17:AP17) -> 2719.9227 | AS17: =$AW$28*AS12 -> 702.37266 | AT17: =$AW$28*AT12 -> 645.95749 | AU17: =$AW$28*AU12 -> 685.97359 | AV17: =$AW$28*AV12 -> 739.60954 | AW17: =SUM(AS17:AV17) -> 2773.9133
B18: Receita Evolução REF | C18: 136.64 | D18: 150.08 | E18: 170.88 | F18: 181.6 | G18: 639.2 | I18: 171.36 | J18: 179.04 | K18: 173.44 | L18: 213.28 | M18: 737.12 | O18: 273.28 | P18: 308.16 | Q18: 372.96 | R18: 418.88 | S18: 1373.28 | U18: 455.2 | V18: 498.56 | W18: 543.68 | X18: 589.76 | Y18: 2087.2 | AA18: =$AE$29*AA15 -> 611.52 | AB18: =$AE$29*AB15 -> 642.877 | AC18: =$AE$29*AC15 -> 704.44324 | AD18: =$AE$29*AD15 -> 773.29778 | AE18: =SUM(AA18:AD18) -> 2732.138 | AG18: =$AK$29*AG15 -> 828.91371 | AH18: =$AK$29*AH15 -> 839.29136 | AI18: =$AK$29*AI15 -> 884.1382 | AJ18: =$AK$29*AJ15 -> 939.00851 | AK18: =SUM(AG18:AJ18) -> 3491.3518 | AM18: =$AQ$29*AM15 -> 981.96977 | AN18: =$AQ$29*AN15 -> 978.51394 | AO18: =$AQ$29*AO15 -> 1012.8461 | AP18: =$AQ$29*AP15 -> 1059.1831 | AQ18: =SUM(AM18:AP18) -> 4032.5129 | AS18: =$AW$29*AS15 -> 1094.3713 | AT18: =$AW$29*AT15 -> 1076.1353 | AU18: =$AW$29*AU15 -> 1101.2846 | AV18: =$AW$29*AV15 -> 1141.0677 | AW18: =SUM(AS18:AV18) -> 4412.8589
B19: Receita Total | C19: 468 | D19: 586 | E19: 574 | F19: 534 | G19: 2162 | I19: 557 | J19: 605 | K19: 558 | L19: 635 | M19: 2355 | O19: 669 | P19: 844 | Q19: 911 | R19: 924 | S19: 3348 | U19: 894 | V19: 1065 | W19: 1158 | X19: 1226 | Y19: 4343 | AA19: =AA16+AA17+AA18 -> 1240.5953 | AB19: =AB16+AB17+AB18 -> 1293.5944 | AC19: =AC16+AC17+AC18 -> 1413.1233 | AD19: =AD16+AD17+AD18 -> 1517.7897 | AE19: =SUM(AA19:AD19) -> 5465.1028 | AG19: =AG16+AG17+AG18 -> 1533.5562 | AH19: =AH16+AH17+AH18 -> 1559.3099 | AI19: =AI16+AI17+AI18 -> 1659.5456 | AJ19: =AJ16+AJ17+AJ18 -> 1747.5351 | AK19: =SUM(AG19:AJ19) -> 6499.9469 | AM19: =AM16+AM17+AM18 -> 1743.7525 | AN19: =AN16+AN17+AN18 -> 1752.06 | AO19: =AO16+AO17+AO18 -> 1841.0451 | AP19: =AP16+AP17+AP18 -> 1919.3531 | AQ19: =SUM(AM19:AP19) -> 7256.2106 | AS19: =AS16+AS17+AS18 -> 1866.2498 | AT19: =AT16+AT17+AT18 -> 1868.9331 | AU19: =AU16+AU17+AU18 -> 1953.247 | AV19: =AV16+AV17+AV18 -> 2027.306 | AW19: =SUM(AS19:AV19) -> 7715.7359
B21: REF Final | C21: 938 | D21: 1068 | E21: 1135 | F21: 1071 | G21: 1071 | I21: 1119 | J21: 1084 | K21: 1333 | L21: 1708 | M21: 1708 | O21: 1926 | P21: 2331 | Q21: 2618 | R21: 2845 | S21: 2845 | U21: 3116 | V21: 3398 | W21: 3686 | X21: 3822 | Y21: 3822 | AA21: =AA15+AA13-AA19 -> 4017.9813 | AB21: =AB15+AB13-AB19 -> 4402.7703 | AC21: =AC15+AC13-AC19 -> 4833.1111 | AD21: =AD15+AD13-AD19 -> 5180.7107 | AE21: =AD21 -> 5180.7107 | AG21: =AG15+AG13-AG19 -> 5245.571 | AH21: =AH15+AH13-AH19 -> 5525.8637 | AI21: =AI15+AI13-AI19 -> 5868.8032 | AJ21: =AJ15+AJ13-AJ19 -> 6137.3111 | AK21: =AJ21 -> 6137.3111 | AM21: =AM15+AM13-AM19 -> 6115.7121 | AN21: =AN15+AN13-AN19 -> 6330.288 | AO21: =AO15+AO13-AO19 -> 6619.8946 | AP21: =AP15+AP13-AP19 -> 6839.8207 | AQ21: =AP21 -> 6839.8207 | AS21: =AS15+AS13-AS19 -> 6725.8454 | AT21: =AT15+AT13-AT19 -> 6883.0289 | AU21: =AU15+AU13-AU19 -> 7131.6731 | AV21: =AV15+AV13-AV19 -> 7316.7299 | AW21: =AV21 -> 7316.7299
B22: Estoque Final | C22: 3310 | D22: 3266 | E22: 3693 | F22: 4203 | G22: 4203 | I22: 4043 | J22: 4583 | K22: 5021 | L22: 5146 | M22: 5146 | O22: 4778 | P22: 4592 | Q22: 4491 | R22: 4787 | S22: 4787 | U22: 4458 | V22: 4716 | W22: 5296 | X22: 5696 | Y22: 5696 | AA22: =AA10+AA6-AA13 -> 5250.6787 | AB22: =AB10+AB6-AB13 -> 5666.4542 | AC22: =AC10+AC6-AC13 -> 6190.2345 | AD22: =AD10+AD6-AD13 -> 6415.9865 | AE22: =AD22 -> 6415.9865 | AG22: =AG10+AG6-AG13 -> 5868.3007 | AH22: =AH10+AH6-AH13 -> 6248.5064 | AI22: =AI10+AI6-AI13 -> 6755.3005 | AJ22: =AJ10+AJ6-AJ13 -> 6955.8673 | AK22: =AJ22 -> 6955.8673 | AM22: =AM10+AM6-AM13 -> 6336.9809 | AN22: =AN10+AN6-AN13 -> 6701.1439 | AO22: =AO10+AO6-AO13 -> 7205.2352 | AP22: =AP10+AP6-AP13 -> 7393.3964 | AQ22: =AP22 -> 7393.3964 | AS22: =AS10+AS6-AS13 -> 6799.5525 | AT22: =AT10+AT6-AT13 -> 7220.7746 | AU22: =AU10+AU6-AU13 -> 7785.3636 | AV22: =AV10+AV6-AV13 -> 8016.8132 | AW22: =AV22 -> 8016.8132
B24: PREMISSAS
B25: VSO Lançamento (% Lançamentos) | AE25: 0.3 | AK25: 0.3 | AQ25: 0.3 | AW25: 0.3
B26: VSO Estoque (% Estoque Inicial) | AE26: 0.2 | AK26: 0.2 | AQ26: 0.2 | AW26: 0.19
B27: PoC Lançamento (% Vendas Lanç.) | AE27: 0.2 | AK27: 0.2 | AQ27: 0.2 | AW27: 0.2
B28: PoC Estoque (% Vendas Est.) | AE28: 0.5 | AK28: 0.5 | AQ28: 0.5 | AW28: 0.5
B29: Drenagem REF (% REF Inicial) | AE29: 0.16 | AK29: 0.16 | AQ29: 0.16 | AW29: 0.16
B30: % VGV no 1T | AE30: 0.1314 | AK30: 0.1314 | AQ30: 0.1314 | AW30: 0.1314
B31: % VGV no 2T | AE31: 0.2776 | AK31: 0.2776 | AQ31: 0.2776 | AW31: 0.2776
B32: % VGV no 3T | AE32: 0.3138 | AK32: 0.3138 | AQ32: 0.3138 | AW32: 0.3138
B33: % VGV no 4T | AE33: 0.2772 | AK33: 0.2772 | AQ33: 0.2772 | AW33: 0.2772
B34: VGV Anual Lançado | G34: 3636 | M34: 4857 | S34: 5484 | Y34: 6858 | AC34: 0.1 | AE34: =Y34*(1+AC34) -> 7543.8 | AK34: 7996.428 | AQ34: 8396.2494 | AW34: 8816.0619
B35: Check Sazonalidade (= 100%) | AE35: =SUM(AE30:AE33) -> 1 | AK35: =SUM(AK30:AK33) -> 1 | AQ35: =SUM(AQ30:AQ33) -> 1 | AW35: =SUM(AW30:AW33) -> 1
B37: RESUMO ANUAL
B38: VGV Lançado | G38: 3635 | M38: 4857 | S38: 5483 | Y38: 6858 | AE38: =AE6 -> 7543.8 | AK38: =AK6 -> 7996.428 | AQ38: =AQ6 -> 8396.2494 | AW38: =AW6 -> 8816.0619
B39: Vendas Líquidas | G39: 3000 | M39: 3990 | S39: 6000 | Y39: 6162 | AE39: =AE13 -> 6823.8135 | AK39: =AK13 -> 7456.5472 | AQ39: =AQ13 -> 7958.7203 | AW39: =AW13 -> 8192.6451
B40: Receita Reconhecida | G40: 2162 | M40: 2355 | S40: 3348 | Y40: 4343 | AE40: =AE19 -> 5465.1028 | AK40: =AK19 -> 6499.9469 | AQ40: =AQ19 -> 7256.2106 | AW40: =AW19 -> 7715.7359
B41: Estoque Final | G41: 4203 | M41: 5146 | S41: 4787 | Y41: 5696 | AD41: Ef | AE41: =AE22 -> 6415.9865 | AJ41: Ef | AK41: =AK22 -> 6955.8673 | AP41: Ef | AQ41: =AQ22 -> 7393.3964 | AV41: Ef | AW41: =AW22 -> 8016.8132
B42: REF Final | G42: 1071 | M42: 1708 | S42: 2845 | Y42: 3822 | AE42: =AE21 -> 5180.7107 | AK42: =AK21 -> 6137.3111 | AQ42: =AQ21 -> 6839.8207 | AW42: =AW21 -> 7316.7299

Sheet Inputs - BP
B2: DIRECIONAL ENGENHARIA S.A.
B4: BALANÇO PATRIMONIAL (MILHARES DE R$) | C4: 2025 | D4: 4T25 | E4: 3T25 | F4: 2T25 | G4: 1T25 | H4: 2024 | I4: 4T24 | J4: 3T24 | K4: 2T24 | L4: 1T24 | M4: 2023 | N4: 4T23 | O4: 3T23 | P4: 2T23 | Q4: 1T23 | R4: 2022 | S4: 2021 | T4: 2020 | U4: 2019 | V4: 2018 | W4: 2017 | X4: 2016 | Y4: 2015 | Z4: 2014 | AA4: 2013 | AB4: 2012
B5: ATIVO CIRCULANTE | C5: 6128834 | D5: 6128834 | E5: 5613159 | F5: 5250822 | G5: 4685810 | H5: 4571386 | I5: 4571386 | J5: 4331445.2 | K5: 4280991.1 | L5: 3356579.9 | M5: 3583354.8 | N5: 3583354.8 | O5: 3359245.4 | P5: 3272452.7 | Q5: 2979504.3 | R5: 2777103 | S5: 2832036 | T5: 2657226 | U5: 2333425 | V5: 2251114 | W5: 2351425 | X5: 2518272 | Y5: 2434863 | Z5: 2720652 | AA5: 2441768 | AB5: 2566313
B6: Caixa e equivalentes de caixa | C6: 1199343 | D6: 1199343 | E6: 1575523 | F6: 1251709 | G6: 837999 | H6: 792054 | I6: 792054 | J6: 858169 | K6: 649740 | L6: 445832 | M6: 633978 | N6: 633978 | O6: 813714 | P6: 637397 | Q6: 605952 | R6: 733124 | S6: 723954 | T6: 731569 | U6: 533795 | V6: 715294 | W6: 413048 | X6: 432735 | Y6: 436624 | Z6: 636110 | AA6: 489776 | AB6: 374580
B7: Aplicações financeiras | C7: 983456 | D7: 983456 | E7: 873983 | F7: 872871 | G7: 791523 | H7: 823127 | I7: 823127 | J7: 687599 | K7: 772261 | L7: 730530 | M7: 693193 | N7: 693193 | O7: 527447 | P7: 475806 | Q7: 465975 | R7: 454248 | S7: 325206 | T7: 195360 | U7: 195587 | V7: 144050 | W7: 70709 | X7: 134816 | Y7: 62541 | Z7: 29099 | AA7: 52775 | AB7: 75313
B8: Contas a receber | C8: 1438700 | D8: 1438700 | E8: 1348006 | F8: 1280505 | G8: 1106026 | H8: 992821 | I8: 992821 | J8: 844423.5 | K8: 789183.92 | L8: 634970.39 | M8: 521946.46 | N8: 521946.46 | O8: 407922.5 | P8: 399289.04 | Q8: 403426.98 | R8: 363372 | S8: 231761 | T8: 246717 | U8: 347538 | V8: 394942 | W8: 702949 | X8: 949979 | Y8: 1122388 | Z8: 1172496 | AA8: 1391817 | AB8: 1325430
B9: Estoques | C9: 2086835 | D9: 2086835 | E9: 1442734 | F9: 1497527 | G9: 1598745 | H9: 1643111 | I9: 1643111 | J9: 1570926.3 | K9: 1710111.8 | L9: 1222127.2 | M9: 1420698.9 | N9: 1420698.9 | O9: 1318928.1 | P9: 1369589.3 | Q9: 1206108 | R9: 960135 | S9: 1239177 | T9: 1270816 | U9: 1080673 | V9: 823164 | W9: 971225 | X9: 805817 | Y9: 656290 | Z9: 735011 | AA9: 396119 | AB9: 680201
B10: Terrenos disponíveis para vendas | C10: 0 | D10: 0 | E10: 0 | F10: 0 | G10: 0 | H10: 0 | I10: 0 | J10: 0 | K10: 0 | L10: 0 | M10: 0 | N10: 0 | O10: 0 | P10: 0 | Q10: 0 | R10: 0 | S10: 0 | T10: 0 | U10: 0 | V10: 0 | W10: 0 | X10: 0 | Y10: 0 | Z10: 0 | AA10: 0 | AB10: 0
B11: Crédito com partes relacionadas | C11: 92922 | D11: 92922 | E11: 80933 | F11: 75761 | G11: 65055 | H11: 71054 | I11: 71054 | J11: 110101.35 | K11: 81642.802 | L11: 71760.298 | M11: 67184.39 | N11: 67184.39 | O11: 70725.503 | P11: 74512.348 | Q11: 66674.309 | R11: 64551 | S11: 82261 | T11: 37363 | U11: 44973 | V11: 71227 | W11: 81576 | X11: 76926 | Y11: 50104 | Z11: 41949 | AA11: 37046 | AB11: 44673
B12: Tributos a recuperar | C12: 43855 | D12: 43855 | E12: 38964 | F12: 46453 | G12: 42178 | H12: 37062 | I12: 37062 | J12: 49451 | K12: 42229.628 | L12: 35185 | M12: 25753 | N12: 25753 | O12: 37992.243 | P12: 34158 | Q12: 26556 | R12: 23122 | S12: 24462 | T12: 21185 | U12: 24560 | V12: 26135 | W12: 24684 | X12: 22424 | Y12: 26814 | Z12: 23256 | AA12: 17315 | AB12: 14122
B13: Despesas comerciais a apropriar | C13: 0 | D13: 0 | E13: 0 | F13: 0 | G13: 0 | H13: 0 | I13: 0 | J13: 0 | K13: 0 | L13: 0 | M13: 0 | N13: 0 | O13: 0 | P13: 0 | Q13: 0 | R13: 0 | S13: 0 | T13: 0 | U13: 0 | V13: 0 | W13: 0 | X13: 0 | Y13: 0 | Z13: 0 | AA13: 0 | AB13: 0
B14: Contas a receber por alienação de investimentos | C14: 1718 | D14: 1718 | E14: 2744 | F14: 3774 | G14: 36303 | H14: 5833 | I14: 5833 | J14: 0 | K14: 0 | L14: 0 | M14: 0 | N14: 0 | O14: 0 | P14: 68332 | Q14: 501 | R14: 501 | S14: 17540 | T14: 50000 | U14: 22514 | V14: 2013 | W14: 4000 | X14: 34102 | Y14: 0 | Z14: 0 | AA14: 0 | AB14: 0
B15: Outros créditos | C15: 282005 | D15: 282005 | E15: 250272 | F15: 222222 | G15: 207981 | H15: 206324 | I15: 206324 | J15: 210776 | K15: 235821 | L15: 216176 | M15: 220602 | N15: 220602 | O15: 182516 | P15: 213370 | Q15: 204311 | R15: 178050 | S15: 187675 | T15: 104216 | U15: 83786 | V15: 74289 | W15: 83234 | X15: 61473 | Y15: 80102 | Z15: 82731 | AA15: 56920 | AB15: 51994
B16: ATIVO NÃO CIRCULANTE | C16: 7090801 | D16: 7090801 | E16: 6802575 | F16: 6316036 | G16: 5926440 | H16: 5496020 | I16: 5496020 | J16: 5189567.2 | K16: 4519837 | L16: 4521375.7 | M16: 3988243 | N16: 3988243 | O16: 3830456.7 | P16: 3534217.6 | Q16: 3502521.6 | R16: 3712312 | S16: 2823260 | T16: 2435058 | U16: 2321291 | V16: 2400571 | W16: 1790339 | X16: 1571495 | Y16: 1452589 | Z16: 1234868 | AA16: 991888 | AB16: 615561
B17: Realizável a longo prazo | C17: 6673444 | D17: 6673444 | E17: 6390858 | F17: 5885790 | G17: 5496068 | H17: 5028708 | I17: 5028708 | J17: 4765579.6 | K17: 4108832 | L17: 4133368.7 | M17: 3671816 | N17: 3671816 | O17: 3514699.7 | P17: 3236455.6 | Q17: 3207918.3 | R17: 3407532 | S17: 2587211 | T17: 2258264 | U17: 2162619 | V17: 2265702 | W17: 1682866 | X17: 1447635 | Y17: 1324998 | Z17: 1085627 | AA17: 852001 | AB17: 529143
B18: Aplicações financeiras | C18: 230360 | D18: 230360 | E18: 168215 | F18: 149823 | G18: 102698 | H18: 99714 | I18: 99714 | J18: 54841.215 | K18: 54200
B19: Contas a receber | C19: 1389073 | D19: 1389073 | E19: 1271939 | F19: 1104148 | G19: 987445 | H19: 846706 | I19: 846706 | J19: 770586.48 | K19: 658009.96 | L19: 574103.74 | M19: 464034.95 | N19: 464034.95 | O19: 412750.7 | P19: 340819.6 | Q19: 334608.5 | R19: 314813 | S19: 244585 | T19: 128727 | U19: 96579 | V19: 121262 | W19: 132436 | X19: 138364 | Y19: 152137 | Z19: 240735 | AA19: 180454 | AB19: 138458
B20: Estoque | C20: 4864673 | D20: 4864673 | E20: 4761035 | F20: 4416854 | G20: 4208796 | H20: 3888979 | I20: 3888979 | J20: 3758232.6 | K20: 3210466 | L20: 3378229 | M20: 3041218 | N20: 3041218 | O20: 2971545 | P20: 2774269 | Q20: 2777860.4 | R20: 3018121 | S20: 2303436 | T20: 2071074 | U20: 2008992 | V20: 2090294 | W20: 1516643 | X20: 1276593 | Y20: 1134083 | Z20: 805869 | AA20: 615178 | AB20: 259356
B21: Depósitos judiciais | C21: 24277 | D21: 24277 | E21: 23484 | F21: 23959 | G21: 22544 | H21: 21555 | I21: 21555 | J21: 21719.038 | K21: 21046 | L21: 18973 | M21: 18111 | N21: 18111 | O21: 17739 | P21: 17832 | Q21: 17601.353 | R21: 17367 | S21: 16097 | T21: 15928 | U21: 16472 | V21: 15143 | W21: 18128 | X21: 0 | Y21: 0 | Z21: 0 | AA21: 0 | AB21: 0
B22: Crédito com partes relacionadas | C22: 0 | D22: 0 | E22: 0 | F22: 0 | G22: 0 | H22: 0 | I22: 0 | J22: 0 | K22: 0 | L22: 0 | M22: 0 | N22: 0 | O22: 0 | P22: 0 | Q22: 0 | R22: 0 | S22: 1636 | T22: 1636 | U22: 0 | V22: 649 | W22: 5400 | X22: 8089 | Y22: 13249 | Z22: 15910 | AA22: 20489 | AB22: 65801
B23: Tributos a recuperar | C23: 11059 | D23: 11059 | E23: 9461 | F23: 9574 | G23: 10363 | H23: 20611 | I23: 20611 | J23: 11151.789 | K23: 15973 | L23: 25156 | M23: 27548 | N23: 27548 | O23: 6526 | P23: 6526 | Q23: 6526 | R23: 6440 | S23: 0 | T23: 0 | U23: 0 | V23: 0 | W23: 0 | X23: 0 | Y23: 0 | Z23: 0 | AA23: 0 | AB23: 0
B24: Contas a receber por alienação de investimentos | C24: 5798 | D24: 5798 | E24: 5799 | F24: 5799 | G24: 7630 | H24: 7630 | I24: 7630 | J24: 7630.0841 | K24: 7630 | L24: 7630 | M24: 7630 | N24: 7630 | O24: 7630 | P24: 7129 | Q24: 7129 | R24: 7129 | S24: 0 | T24: 30685 | U24: 29722 | V24: 27985 | W24: 0 | X24: 0 | Y24: 0 | Z24: 0 | AA24: 0 | AB24: 0
B25: Outros créditos | C25: 148204 | D25: 148204 | E25: 150924 | F25: 175633 | G25: 156592 | H25: 143513 | I25: 143513 | J25: 141418.39 | K25: 141507 | L25: 129277 | M25: 113274 | N25: 113274 | O25: 98509 | P25: 89880 | Q25: 64193 | R25: 43662 | S25: 21457 | T25: 10214 | U25: 10854 | V25: 10369 | W25: 10259 | X25: 24589 | Y25: 25529 | Z25: 23113 | AA25: 35880 | AB25: 65528
B26: Permanente | C26: 417357 | D26: 417357 | E26: 411718 | F26: 430246 | G26: 430372 | H26: 467312 | I26: 467312 | J26: 423986.63 | K26: 411005 | L26: 388007 | M26: 316427 | N26: 316427 | O26: 315757 | P26: 297762 | Q26: 294604.33 | R26: 304780 | S26: 236049 | T26: 176794 | U26: 158672 | V26: 134869 | W26: 107473 | X26: 123860 | Y26: 127591 | Z26: 149241 | AA26: 139887 | AB26: 86418
B27: Investimentos | C27: 124135 | D27: 124135 | E27: 105527 | F27: 138434 | G27: 161671 | H27: 212504 | I27: 212504 | J27: 193959.47 | K27: 193645 | L27: 174396 | M27: 169375 | N27: 169375 | O27: 171047 | P27: 142090 | Q27: 133771 | R27: 143717 | S27: 117961 | T27: 73045 | U27: 48885 | V27: 64161 | W27: 49501 | X27: 50593 | Y27: 37783 | Z27: 36839 | AA27: 37154 | AB27: 24730
B28: Imobilizado | C28: 260159 | D28: 260159 | E28: 266560 | F28: 252372 | G28: 230724 | H28: 220762 | I28: 220762 | J28: 197255.89 | K28: 184863 | L28: 181833 | M28: 111474 | N28: 111474 | O28: 113832 | P28: 129142 | Q28: 136224.85 | R28: 140115 | S28: 99075 | T28: 89594 | U28: 101972 | V28: 66272 | W28: 55265 | X28: 69777 | Y28: 87086 | Z28: 109968 | AA28: 100908 | AB28: 59340
B29: Intangível | C29: 33063 | D29: 33063 | E29: 39631 | F29: 39440 | G29: 37977 | H29: 34046 | I29: 34046 | J29: 32771.273 | K29: 32497 | L29: 31778 | M29: 35578 | N29: 35578 | O29: 30878 | P29: 26530 | Q29: 24608.486 | R29: 20948 | S29: 19013 | T29: 14155 | U29: 7815 | V29: 4436 | W29: 2707 | X29: 3490 | Y29: 2722 | Z29: 2434 | AA29: 1825 | AB29: 2348
B30: Ativos de Direito de Uso | C30: 0 | D30: 0 | E30: 0 | F30: 0 | G30: 0 | H30: 0 | I30: 0 | J30: 0 | K30: 0 | L30: 0 | M30: 0 | N30: 0 | O30: 0 | P30: 0 | Q30: 0 | R30: 0 | S30: 0 | T30: 0 | U30: 0 | V30: 0 | W30: 0 | X30: 0 | Y30: 0 | Z30: 0 | AA30: 0 | AB30: 0
... B63: Capital social | C63: 1181857 | D63: 1181857 | E63: 1181857 | F63: 1181857 | G63: 1181857 | H63: 1181857 | I63: 1181857 | J63: 1181857 | K63: 1181857 | L63: 1181857 | M63: 1181857 | N63: 1181857 | O63: 1181857 | P63: 752982 | Q63: 752982 | R63: 752982 | S63: 752982 | T63: 752982 | U63: 752982 | V63: 752982 | W63: 752982 | X63: 752982 | Y63: 752982 | Z63: 702982 | AA63: 702982 | AB63: 497158
B64: Gastos com emissões de ações | C64: -21994 | D64: -21994 | E64: -21994 | F64: -21994 | G64: -21994 | H64: -21994 | I64: -21994 | J64: -21994 | K64: -21994 | L64: -21994 | M64: -21994 | N64: -21994 | O64: -20766
B65: Ações em tesouraria | C65: -22571 | D65: -22571 | E65: -8042 | F65: -4065 | G65: -4065 | H65: -9536 | I65: -9536 | J65: -2301 | K65: -2301 | L65: -2301 | M65: -7748 | N65: -7748 | O65: -7748 | P65: -7748 | Q65: -9749 | R65: -9749 | S65: -7360 | T65: -52129 | U65: -32076 | V65: -37531 | W65: -40793 | X65: -41511 | Y65: -41791 | Z65: -23118 | AA65: -28137 | AB65: -12659
B66: Reservas de capital | C66: 192734 | D66: 192734 | E66: 185857 | F66: 185540 | G66: 182348 | H66: 185178 | I66: 185178 | J66: 151029 | K66: 148551 | L66: 147249 | M66: 184240 | N66: 184240 | O66: 150757 | P66: 149179 | Q66: 149880 | R66: 148323 | S66: 150102 | T66: 193511 | U66: 194989 | V66: 196714 | W66: 193184 | X66: 189339 | Y66: 189115 | Z66: 212898 | AA66: 229111 | AB66: 445767
B67: Outorga de opção de ações | C67: 0 | D67: 0 | E67: 0 | F67: 0 | G67: 0 | H67: 0 | I67: 0 | J67: 0 | K67: 0 | L67: 0 | M67: 0 | N67: 0 | O67: 0 | P67: 0 | Q67: 0 | R67: 0 | S67: 0 | T67: 0 | U67: 0 | V67: 0 | W67: 0 | X67: 0 | Y67: 0 | Z67: 0 | AA67: 0 | AB67: 0
B68: Ajuste de avaliação patrimonial | C68: 238956 | D68: 238956 | E68: 167444 | F68: 151699 | G68: -33268 | H68: -31759 | I68: -31759 | J68: 0 | K68: 0 | L68: 0 | M68: -31760 | N68: -31760 | O68: 0 | P68: 0 | Q68: 0 | R68: 0 | S68: 0 | T68: 0 | U68: 0 | V68: 0 | W68: 0 | X68: 0 | Y68: 0 | Z68: 0 | AA68: 0 | AB68: 0
B69: Reservas de lucros | C69: 347639 | D69: 347639 | E69: 362661 | F69: 362333 | G69: 708997 | H69: 711711 | I69: 711711 | J69: 649936 | K69: 649925 | L69: 649917 | M69: 648810 | N69: 648810 | O69: 398412 | P69: 398425 | Q69: 398423 | R69: 398425 | S69: 383147 | T69: 323843 | U69: 341032 | V69: 370526 | W69: 549591 | X69: 693373 | Y69: 745235 | Z69: 711584 | AA69: 568872 | AB69: 397726
B70: Dividendos adicionais propostos | C70: 0 | D70: 0 | E70: 0 | F70: 0 | G70: 0 | H70: 0 | I70: 0 | J70: 0 | K70: 0 | L70: 0 | M70: 0 | N70: 0 | O70: 0 | P70: 0 | Q70: 0 | R70: 0 | S70: 0 | T70: 0 | U70: 0 | V70: 0 | W70: 0 | X70: 0 | Y70: 0 | Z70: 11690 | AA70: 0 | AB70: 0
B71: Lucros acumulados | C71: 0 | D71: 0 | E71: 577910 | F71: 348258 | G71: 164516 | H71: 0 | I71: 0 | J71: 100001 | K71: 296453 | L71: 150284 | M71: 0 | N71: 0 | O71: 231954 | P71: 163193 | Q71: 58754 | R71: 0 | S71: 0 | T71: 0 | U71: 0 | V71: 0 | W71: 0 | X71: 0 | Y71: 0 | Z71: 0 | AA71: 0 | AB71: 0
B72: Participantes em SCPs e SPEs | C72: 403530 | D72: 403530 | E72: 274489 | F72: 267022 | G72: 188319 | H72: 208294 | I72: 208294 | J72: 186929 | K72: 186075 | L72: 166217 | M72: 157181 | N72: 157181 | O72: 159045 | P72: 154579 | Q72: 160701 | R72: 159714 | S72: 155586 | T72: 112666 | U72: 112417 | V72: 110585 | W72: 149351 | X72: 153235 | Y72: 131944 | Z72: 119495 | AA72: 128603 | AB72: 187315
B73: TOTAL DO PASSIVO E PATRIMÔNIO LÍQUIDO | C73: 13219635 | D73: 13219635 | E73: 12415734 | F73: 11566858 | G73: 10612250 | H73: 10067406 | I73: 10067406 | J73: 9521012.3 | K73: 8800828 | L73: 7877956 | M73: 7571598 | N73: 7571598 | O73: 7189702 | P73: 6806671 | Q73: 6482026 | R73: 6489415 | S73: 5655296 | T73: 5092284 | U73: 4654716 | V73: 4651685 | W73: 4141764 | X73: 4089767 | Y73: 3887452 | Z73: 3955520 | AA73: 3433656 | AB73: 3181874
B76: 1 - Apuração feita apenas a partir de 2020, conforme nota explicativa nº 10 das Demonstrações Financeiras de 31/12/2022
B79: BALANÇO PATRIMONIAL (MILHARES DE R$) | C79: 2022 | D79: 2023 | E79: 2024 | F79: 2025
B80: ATIVO CIRCULANTE | C80: 2777103 | D80: 3583354.8 | E80: 4571386 | F80: 6128834
B81: Caixa e equivalentes de caixa | C81: 733124 | D81: 633978 | E81: 792054 | F81: 1199343
B82: Aplicações financeiras | C82: 454248 | D82: 693193 | E82: 823127 | F82: 983456
B83: Contas a receber | C83: 363372 | D83: 521946.46 | E83: 992821 | F83: 1438700
B84: Estoques | C84: 960135 | D84: 1420698.9 | E84: 1643111 | F84: 2086835
B85: Terrenos disponíveis para vendas | C85: 0 | D85: 0 | E85: 0 | F85: 0
B86: Crédito com partes relacionadas | C86: 64551 | D86: 67184.39 | E86: 71054 | F86: 92922
B87: Tributos a recuperar | C87: 23122 | D87: 25753 | E87: 37062 | F87: 43855
B88: Despesas comerciais a apropriar | C88: 0 | D88: 0 | E88: 0 | F88: 0
B89: Contas a receber por alienação de investimentos | C89: 501 | D89: 0 | E89: 5833 | F89: 1718
B90: Outros créditos | C90: 178050 | D90: 220602 | E90: 206324 | F90: 282005
... B92: Realizável a longo prazo | C92: 3407532 | D92: 3671816 | E92: 5028708 | F92: 6673444
B93: Aplicações financeiras | E93: 99714 | F93: 230360
B94: Contas a receber | C94: 314813 | D94: 464034.95 | E94: 846706 | F94: 1389073
B95: Estoque | C95: 3018121 | D95: 3041218 | E95: 3888979 | F95: 4864673
B96: Depósitos judiciais | C96: 17367 | D96: 18111 | E96: 21555 | F96: 24277
B97: Crédito com partes relacionadas | C97: 0 | D97: 0 | E97: 0 | F97: 0
B98: Tributos a recuperar | C98: 6440 | D98: 27548 | E98: 20611 | F98: 11059
B99: Contas a receber por alienação de investimentos | C99: 7129 | D99: 7630 | E99: 7630 | F99: 5798
B100: Outros créditos | C100: 43662 | D100: 113274 | E100: 143513 | F100: 148204
B101: Permanente | C101: 304780 | D101: 316427 | E101: 467312 | F101: 417357
B102: Investimentos | C102: 143717 | D102: 169375 | E102: 212504 | F102: 124135
B103: Imobilizado | C103: 140115 | D103: 111474 | E103: 220762 | F103: 260159
B104: Intangível | C104: 20948 | D104: 35578 | E104: 34046 | F104: 33063
B105: Ativos de Direito de Uso | C105: 0 | D105: 0 | E105: 0 | F105: 0
... B135: Outras contas a pagar | C135: 97392 | D135: 69157 | E135: 69157 | F135: 68696
B136: Partes relacionadas | C136: 0 | D136: 0 | E136: 0 | F136: 0 | H136: Dívida 2025
B137: PATRIMÔNIO LÍQUIDO | C137: 1289981 | D137: 1953405 | E137: 2015457 | F137: 1916621 | H137: =F125+F109+F110+F126 -> 3955497
B138: Capital social | C138: 752982 | D138: 1181857 | E138: 1181857 | F138: 1181857
B139: Gastos com emissões de ações | D139: -21994 | E139: -21994 | F139: -21994
B140: Ações em tesouraria | C140: -9749 | D140: -7748 | E140: -9536 | F140: -22571
B141: Reservas de capital | C141: 148323 | D141: 184240 | E141: 185178 | F141: 192734
B142: Outorga de opção de ações | C142: 0 | D142: 0 | E142: 0 | F142: 0
B143: Ajuste de avaliação patrimonial | C143: 0 | D143: -31760 | E143: -31759 | F143: 238956
B144: Reservas de lucros | C144: 398425 | D144: 648810 | E144: 711711 | F144: 347639
B145: Dividendos adicionais propostos | C145: 0 | D145: 0 | E145: 0 | F145: 0
B146: Lucros acumulados | C146: 0 | D146: 0 | E146: 0 | F146: 0
B147: Participantes em SCPs e SPEs | C147: 159714 | D147: 157181 | E147: 208294 | F147: 403530
B148: TOTAL DO PASSIVO E PATRIMÔNIO LÍQUIDO | C148: 6489415 | D148: 7571598 | E148: 10067406 | F148: 13219635

Sheet Inputs - DRE
B2: DIRECIONAL ENGENHARIA S.A.
B4: DEMONSTRAÇÃO DO RESULTADO (MILHARES DE R$) | C4: 2025 | D4: 4T25 | E4: 3T25 | F4: 2T25 | G4: 1T25 | H4: 2024 | I4: 4T24 | J4: 3T24 | K4: 2T24 | L4: 1T24 | M4: 2023 | N4: 4T23 | O4: 3T23 | P4: 2T23 | Q4: 1T23 | R4: 2022 | S4: 4T22 | T4: 3T22 | U4: 2T22 | V4: 1T22 | W4: 2021 | X4: 4T21 | Y4: 3T21 | Z4: 2T21 | AA4: 1T21 | AB4: 2020 | AC4: 4T20 | AD4: 3T20 | AE4: 2T20 | AF4: 1T20 | AG4: 2019 | AH4: 4T19 | AI4: 3T19 | AJ4: 2T19 | AK4: 1T19 | AL4: 2018 | AM4: 4T18 | AN4: 3T18 | AO4: 2T18 | AP4: 1T18 | AQ4: 2017 | AR4: 4T17 | AS4: 3T17 | AT4: 2T17 | AU4: 1T17 | AV4: 2016 | AW4: 4T16 | AX4: 3T16 | AY4: 2T16 | AZ4: 1T16 | BA4: 2015 | BB4: 4T15 | BC4: 3T15 | BD4: 2T15 | BE4: 1T15 | BF4: 2014 | BG4: 4T14 | BH4: 3T14 | BI4: 2T14 | BJ4: 1T14 | BK4: 2013 | BL4: 4T13 | BM4: 3T13 | BN4: 2T13 | BO4: 1T13 | BP4: 2012 | BQ4: 4T12 | BR4: 3T12 | BS4: 2T12 | BT4: 1T12
B5: RECEITA OPERACIONAL LÍQUIDA | C5: 4343008 | D5: 1225843 | E5: 1157823 | F5: 1065210 | G5: 894132 | H5: 3348470 | I5: 924210 | J5: 910598 | K5: 844220 | L5: 669442 | M5: 2355183 | N5: 634838 | O5: 557668 | P5: 605408 | Q5: 557269 | R5: 2162616 | S5: 533985 | T5: 574411 | U5: 586126 | V5: 468094 | W5: 1776380 | X5: 486971 | Y5: 453362 | Z5: 422162 | AA5: 413885 | AB5: 1500723.4 | AC5: 425314.5 | AD5: 375532 | AE5: 408408 | AF5: 291469 | AG5: 1458228 | AH5: 367685 | AI5: 367239 | AJ5: 374504 | AK5: 348800 | AL5: 1166048 | AM5: 393071 | AN5: 309919 | AO5: 270902 | AP5: 192155 | AQ5: 751857 | AR5: 169575 | AS5: 201247 | AT5: 181730 | AU5: 199305 | AV5: 1358078 | AW5: 254553 | AX5: 314586 | AY5: 383099 | AZ5: 405840 | BA5: 1569577 | BB5: 398013 | BC5: 392344 | BD5: 379400 | BE5: 399820 | BF5: 1835613 | BG5: 551144 | BH5: 462292 | BI5: 425050 | BJ5: 397128 | BK5: 1743929 | BL5: 438225 | BM5: 450848 | BN5: 466327 | BO5: 388529 | BP5: 1448779 | BQ5: 375589 | BR5: 390999 | BS5: 338164 | BT5: 344027
B6: Custo da Venda de Imóveis e Serviços Prestados | C6: -2620591 | D6: -726736 | E6: -694023 | F6: -650982 | G6: -548851 | H6: -2130127 | I6: -581814 | J6: -577881 | K6: -541592 | L6: -428840 | M6: -1550208 | N6: -425257 | O6: -365299 | P6: -400227 | Q6: -359425 | R6: -1428891 | S6: -343252 | T6: -379234 | U6: -403298 | V6: -303106 | W6: -1146299 | X6: -324610.79 | Y6: -291574.27 | Z6: -263110.64 | AA6: -267002.3 | AB6: -987413 | AC6: -281958.77 | AD6: -241802 | AE6: -276269 | AF6: -187383 | AG6: -967112 | AH6: -238010 | AI6: -244499 | AJ6: -249646 | AK6: -234958 | AL6: -849225 | AM6: -283586 | AN6: -223408 | AO6: -200676 | AP6: -141554 | AQ6: -714399 | AR6: -184646 | AS6: -186702 | AT6: -161717 | AU6: -181334 | AV6: -1201779 | AW6: -280083 | AX6: -289413 | AY6: -309670 | AZ6: -322613 | BA6: -1239094 | BB6: -317886 | BC6: -311611 | BD6: -294316 | BE6: -315281 | BF6: -1408650 | BG6: -431251 | BH6: -350223 | BI6: -322469 | BJ6: -304707 | BK6: -1340379 | BL6: -339465 | BM6: -340156 | BN6: -369432 | BO6: -291326 | BP6: -1049974 | BQ6: -269615 | BR6: -286154 | BS6: -246282 | BT6: -247923
B7: LUCRO BRUTO | C7: 1722417 | D7: 499107 | E7: 463800 | F7: 414228 | G7: 345280.63 | H7: 1218343 | I7: 342396 | J7: 332717 | K7: 302628 | L7: 240602 | M7: 804975 | N7: 209581 | O7: 192369 | P7: 205181 | Q7: 197844 | R7: 733725 | S7: 190733 | T7: 195177 | U7: 182828 | V7: 164988 | W7: 630081 | X7: 162360.21 | Y7: 161787.73 | Z7: 159051.36 | AA7: 146882.7 | AB7: 513310.43 | AC7: 143355.74 | AD7: 133730 | AE7: 132140 | AF7: 104086 | AG7: 491115 | AH7: 129675 | AI7: 122740 | AJ7: 124858 | AK7: 113842 | AL7: 316823 | AM7: 109485 | AN7: 86511 | AO7: 70226 | AP7: 50601 | AQ7: 37458 | AR7: -15071 | AS7: 14545 | AT7: 20013 | AU7: 17971 | AV7: 156299 | AW7: -25530 | AX7: 25173 | AY7: 73429 | AZ7: 83227 | BA7: 330483 | BB7: 80127 | BC7: 80733 | BD7: 85084 | BE7: 84539 | BF7: 426963 | BG7: 119893 | BH7: 112069 | BI7: 102581 | BJ7: 92420 | BK7: 403550 | BL7: 98760 | BM7: 110692 | BN7: 96895 | BO7: 97203 | BP7: 398805 | BQ7: 105974 | BR7: 104845 | BS7: 91882 | BT7: 96104
B8: Despesas Gerais e Administrativas | C8: -254781 | D8: -70378 | E8: -68636 | F8: -60634 | G8: -55133 | H8: -210307 | I8: -56546 | J8: -52276 | K8: -52355 | L8: -49129.601 | M8: -174709.76 | N8: -44598 | O8: -44731.595 | P8: -43423 | Q8: -41957 | R8: -151631 | S8: -40183 | T8: -39730 | U8: -36394 | V8: -35322 | W8: -132511 | X8: -34558.15 | Y8: -33785.25 | Z8: -33690.229 | AA8: -30477.159 | AB8: -115572 | AC8: -31595.821 | AD8: -27916 | AE8: -24736 | AF8: -31324 | AG8: -112406 | AH8: -30217 | AI8: -27314 | AJ8: -26838 | AK8: -28037 | AL8: -100301 | AM8: -25633 | AN8: -24745 | AO8: -25438 | AP8: -24485 | AQ8: -107644 | AR8: -24333 | AS8: -28267 | AT8: -28419 | AU8: -26625 | AV8: -105135 | AW8: -23840 | AX8: -25955 | AY8: -26819 | AZ8: -28521 | BA8: -105265 | BB8: -26218 | BC8: -25697 | BD8: -26394 | BE8: -26956 | BF8: -114675 | BG8: -31089 | BH8: -27917 | BI8: -25764 | BJ8: -29905 | BK8: -104395 | BL8: -25952 | BM8: -28449 | BN8: -24294 | BO8: -25700 | BP8: -97640 | BQ8: -18244 | BR8: -26905 | BS8: -25302 | BT8: -27189
B9: Despesas Comerciais | C9: -408037 | D9: -116252 | E9: -113940 | F9: -96860 | G9: -80985 | H9: -289706 | I9: -83000 | J9: -80402 | K9: -71239 | L9: -55064.805 | M9: -202241.82 | N9: -56898 | O9: -48465.697 | P9: -53518 | Q9: -43360 | R9: -203082 | S9: -52665 | T9: -52788 | U9: -52798 | V9: -44831 | W9: -190902 | X9: -53126.282 | Y9: -49548.637 | Z9: -45477.113 | AA9: -42749.82 | AB9: -158044 | AC9: -43723.28 | AD9: -39705 | AE9: -39904 | AF9: -34711 | AG9: -146206 | AH9: -38950 | AI9: -38153 | AJ9: -36432 | AK9: -32671 | AL9: -105046 | AM9: -34381 | AN9: -26864 | AO9: -24170 | AP9: -19631 | AQ9: -63288 | AR9: -21782 | AS9: -16158 | AT9: -13014 | AU9: -12334 | AV9: -50741 | AW9: -11942 | AX9: -12696 | AY9: -13056 | AZ9: -13047 | BA9: -42910 | BB9: -12611 | BC9: -11455 | BD9: -10764 | BE9: -8080 | BF9: -51723 | BG9: -12876 | BH9: -13950 | BI9: -14321 | BJ9: -10576 | BK9: -41188 | BL9: -14436 | BM9: -10276 | BN9: -10348 | BO9: -6128 | BP9: -40329 | BQ9: -8986 | BR9: -12455 | BS9: -9917 | BT9: -8971
B10: Resultado com Equivalência Patrimonial | C10: 62631 | D10: 19179 | E10: 16173 | F10: 14911 | G10: 12368 | H10: 86528 | I10: 22152 | J10: 18500 | K10: 19423 | L10: 26452.982 | M10: 53700.914 | N10: 15345 | O10: 19669.193 | P10: 11933 | Q10: 6754 | R10: 21758 | S10: 5065 | T10: 8302 | U10: 4860 | V10: 3531 | W10: 17559 | X10: 6261.0558 | Y10: 6060.0069 | Z10: 2536.5453 | AA10: 2701.3919 | AB10: 3445 | AC10: 856.3791 | AD10: 2906 | AE10: -1059 | AF10: 742 | AG10: 2394 | AH10: 369 | AI10: -383 | AJ10: 1100 | AK10: 1308 | AL10: -2339 | AM10: 501 | AN10: -1197 | AO10: -614 | AP10: -1029 | AQ10: -1380 | AR10: 115 | AS10: -513 | AT10: -350 | AU10: -632 | AV10: -1480 | AW10: -306 | AX10: 127 | AY10: -713 | AZ10: -588 | BA10: -1774 | BB10: -833 | BC10: -248 | BD10: 1439 | BE10: -2132 | BF10: 5750 | BG10: 548 | BH10: 747 | BI10: 1275 | BJ10: 3180 | BK10: 11790 | BL10: 3828 | BM10: 3475 | BN10: 3548 | BO10: 939 | BP10: 271 | BQ10: -1160 | BR10: 200 | BS10: 805 | BT10: 426
B11: Outras Receitas e Despesas Operacionais | C11: -119095 | D11: -33062 | E11: -14319 | F11: -46633 | G11: -25081 | H11: -49879 | I11: 3441 | J11: -31522 | K11: -17150 | L11: -4647.5087 | M11: -58989.301 | N11: -42231 | O11: -9689.9401 | P11: 9315 | Q11: -16383 | R11: -25357 | S11: 23575 | T11: -21872 | U11: -18234 | V11: -8827 | W11: -18387 | X11: -1387.172 | Y11: 1896.5962 | Z11: -6099.9556 | AA11: -12796.632 | AB11: -31054 | AC11: 3285.9967 | AD11: -12336 | AE11: -17526 | AF11: -4478 | AG11: -41881 | AH11: -11607 | AI11: -9019 | AJ11: -12450 | AK11: -8805 | AL11: -139954 | AM11: -19581 | AN11: -108260 | AO11: -7332 | AP11: -4782 | AQ11: 2984 | AR11: 1206 | AS11: 4983 | AT11: -2549 | AU11: -656 | AV11: 4016 | AW11: -5056 | AX11: 14387 | AY11: -1672 | AZ11: -3643 | BA11: -17267 | BB11: -48 | BC11: -4411 | BD11: -8018 | BE11: -4790 | BF11: -22657 | BG11: -13437 | BH11: -7577 | BI11: -2231 | BJ11: 588 | BK11: -11036 | BL11: -3260 | BM11: -4327 | BN11: -396 | BO11: -3053 | BP11: -7165 | BQ11: -4164 | BR11: -2335 | BS11: -1230 | BT11: 564
B12: Despesas Financeiras | C12: -347061 | D12: -113765 | E12: -92014 | F12: -79992 | G12: -61290 | H12: -256789 | I12: -91503 | J12: -59330 | K12: -65707 | L12: -40248.694 | M12: -288045.12 | N12: -73935 | O12: -75550.891 | P12: -69299 | Q12: -69260 | R12: -269367 | S12: -74805 | T12: -68711 | U12: -65049 | V12: -60801 | W12: -157347 | X12: -61886.735 | Y12: -39944.088 | Z12: -26862.088 | AA12: -28654.088 | AB12: -84083 | AC12: -30413.681 | AD12: -16297 | AE12: -17375 | AF12: -19997 | AG12: -80156 | AH12: -18376 | AI12: -20972 | AJ12: -19842 | AK12: -20966 | AL12: -58858 | AM12: -14281 | AN12: -15823 | AO12: -15042 | AP12: -13712 | AQ12: -42998 | AR12: -9977 | AS12: -13221 | AT12: -8709 | AU12: -11091 | AV12: -50278 | AW12: -11515 | AX12: -14181 | AY12: -14451 | AZ12: -10131 | BA12: -48752 | BB12: -12210 | BC12: -12279 | BD12: -12196 | BE12: -12067 | BF12: -45969 | BG12: -12406 | BH12: -12812 | BI12: -12383 | BJ12: -8368 | BK12: -31111 | BL12: -8115 | BM12: -8707 | BN12: -6686 | BO12: -7603 | BP12: -15108 | BQ12: -6860 | BR12: -2970 | BS12: -2570 | BT12: -2708
B13: Receitas Financeiras | C13: 422421 | D13: 127549 | E13: 119310 | F13: 98161 | G13: 77401 | H13: 294108 | I13: 84674 | J13: 76764.078 | K13: 69213 | L13: 63456.853 | M13: 302169.02 | N13: 120692 | O13: 63367.256 | P13: 68147 | Q13: 49962 | R13: 195489 | S13: 54132 | T13: 70823 | U13: 34226 | V13: 36308 | W13: 80632 | X13: 38182.27 | Y13: 20724.728 | Z13: 12895.798 | AA13: 8828.9353 | AB13: 44116 | AC13: 10449.83 | AD13: 8381 | AE13: 15982 | AF13: 9304 | AG13: 40941 | AH13: 9377 | AI13: 12780 | AJ13: 9122 | AK13: 9662 | AL13: 38347 | AM13: 9744 | AN13: 10278 | AO13: 8762 | AP13: 9563 | AQ13: 54158 | AR13: 14234 | AS13: 14058 | AT13: 10303 | AU13: 15563 | AV13: 67521 | AW13: 16622 | AX13: 19314 | AY13: 17980 | AZ13: 13605 | BA13: 64983 | BB13: 15437 | BC13: 16336 | BD13: 16043 | BE13: 17167 | BF13: 57838 | BG13: 16896 | BH13: 16263 | BI13: 14289 | BJ13: 10390 | BK13: 32586 | BL13: 9255 | BM13: 8180 | BN13: 8348 | BO13: 6803 | BP13: 38870 | BQ13: 10730 | BR13: 7030 | BS13: 10078 | BT13: 11032
B14: RESULTADO ANTES DO IMPOSTO DE RENDA E CONTRIBUIÇÃO SOCIAL | C14: 1078495 | D14: 312379 | E14: 310375 | F14: 243181 | G14: 212561 | H14: 792298 | I14: 221614 | J14: 204451.08 | K14: 184813 | L14: 181420.23 | M14: 436858.93 | N14: 127956 | O14: 96966.326 | P14: 128335 | Q14: 83600 | R14: 301535 | S14: 105851 | T14: 91199 | U14: 49439 | V14: 55046 | W14: 229125 | X14: 55845.193 | Y14: 67191.087 | Z14: 62354.318 | AA14: 43735.33 | AB14: 172118.43 | AC14: 52215.159 | AD14: 48761 | AE14: 47521 | AF14: 23620 | AG14: 153801 | AH14: 40272 | AI14: 39678 | AJ14: 39518 | AK14: 34333 | AL14: -51328 | AM14: 25854 | AN14: -80100 | AO14: 6392 | AP14: -3475 | AQ14: -120710 | AR14: -55608 | AS14: -24573 | AT14: -22725 | AU14: -17804 | AV14: 20202 | AW14: -61567 | AX14: 6169 | AY14: 34698 | AZ14: 40902 | BA14: 179498 | BB14: 43644 | BC14: 42979 | BD14: 45194 | BE14: 47681 | BF14: 255527 | BG14: 67529 | BH14: 66823 | BI14: 63446 | BJ14: 57729 | BK14: 260196 | BL14: 60080 | BM14: 70588 | BN14: 67067 | BO14: 62461 | BP14: 277704 | BQ14: 77290 | BR14: 67410 | BS14: 63746 | BT14: 69258
B15: Imposto de Renda e Contribuição Social - Corrente e Diferido | C15: -98803 | D15: -27756 | E15: -27400 | F15: -22538 | G15: -21109 | H15: -64630.454 | I15: -17545 | J15: -19761.094 | K15: -14901 | L15: -12423.359 | M15: -49981.552 | N15: -13991 | O15: -11091.38 | P15: -13564 | Q15: -11335 | R15: -45846 | S15: -11224 | T15: -12246 | U15: -12572 | V15: -9805 | W15: -35563 | X15: -9904.0602 | Y15: -8254.5454 | Z15: -9448.27 | AA15: -7956.2747 | AB15: -31110 | AC15: -9178.8077 | AD15: -7567 | AE15: -8468 | AF15: -5897 | AG15: -32986 | AH15: -9331 | AI15: -8516 | AJ15: -7560 | AK15: -7579 | AL15: -22608 | AM15: -7463 | AN15: -4787 | AO15: -5805 | AP15: -4553 | AQ15: -16725 | AR15: -5079 | AS15: -4218 | AT15: -3237 | AU15: -4191 | AV15: -21599 | AW15: -4818 | AX15: -4747 | AY15: -5585 | AZ15: -6449 | BA15: -23288 | BB15: -5271 | BC15: -5900 | BD15: -6652 | BE15: -5465 | BF15: -23311 | BG15: -7001 | BH15: -5273 | BI15: -5836 | BJ15: -5201 | BK15: -23742 | BL15: -6038 | BM15: -6167 | BN15: -5942 | BO15: -5595 | BP15: -20237 | BQ15: 4367 | BR15: -7680 | BS15: -7907 | BT15: -9017
B16: RESULTADO LÍQUIDO ANTES DOS PARTICIPANTES EM SCPs E SPEs | C16: 979692 | D16: 284623 | E16: 282974 | F16: 220643 | G16: 191452 | H16: 727668.38 | I16: 204069 | J16: 184689.98 | K16: 169912 | L16: 168996.87 | M16: 386877.38 | N16: 113965 | O16: 85874.946 | P16: 114771 | Q16: 72265 | R16: 255689 | S16: 94628 | T16: 78953 | U16: 36867 | V16: 45241 | W16: 193562 | X16: 45941.133 | Y16: 58936.542 | Z16: 52906.048 | AA16: 35779.055 | AB16: 141008.43 | AC16: 43036.351 | AD16: 41194 | AE16: 39053 | AF16: 17723 | AG16: 120816 | AH16: 30941 | AI16: 31163 | AJ16: 31958 | AK16: 26754 | AL16: -73936 | AM16: 18391 | AN16: -84887 | AO16: 587 | AP16: -8028 | AQ16: -137435 | AR16: -60687 | AS16: -28791 | AT16: -25962 | AU16: -21995 | AV16: -1397 | AW16: -66385 | AX16: 1422 | AY16: 29113 | AZ16: 34453 | BA16: 156210 | BB16: 38373 | BC16: 37079 | BD16: 38542 | BE16: 42216 | BF16: 232216 | BG16: 60528 | BH16: 61550 | BI16: 57610 | BJ16: 52528 | BK16: 236454 | BL16: 54042 | BM16: 64421 | BN16: 61125 | BO16: 56866 | BP16: 257467 | BQ16: 81657 | BR16: 59730 | BS16: 55839 | BT16: 60241
... B18: LUCRO LÍQUIDO DO PERÍODO | C18: 789342 | D18: 211432 | E18: 229652 | F18: 183742 | G18: 164516 | H18: 638378.21 | I18: 181461 | J18: 160463.98 | K18: 146169 | L18: 150283.7 | M18: 331560.3 | N18: 99606 | O18: 68762.946 | P18: 104439 | Q18: 58754 | R18: 190020 | S18: 78605 | T18: 62272 | U18: 22436 | V18: 26707 | W18: 146603 | X18: 31958.815 | Y18: 47210.112 | Z18: 40623.207 | AA18: 26811.644 | AB18: 104968.43 | AC18: 32465.014 | AD18: 28555 | AE18: 33894 | AF18: 10052 | AG18: 100477 | AH18: 28213 | AI18: 25951 | AJ18: 25900 | AK18: 20413 | AL18: -77495 | AM18: 18197 | AN18: -83821 | AO18: -3778 | AP18: -8093 | AQ18: -143781 | AR18: -61884 | AS18: -29390 | AT18: -29727 | AU18: -22780 | AV18: -11862 | AW18: -64811 | AX18: 1116 | AY18: 22195 | AZ18: 29638 | BA18: 123647 | BB18: 30824 | BC18: 28804 | BD18: 27784 | BE18: 36235 | BF18: 205870 | BG18: 60735 | BH18: 52246 | BI18: 46566 | BJ18: 46323 | BK18: 228197 | BL18: 50484 | BM18: 62112 | BN18: 60864 | BO18: 54737 | BP18: 225038 | BQ18: 72745 | BR18: 54675 | BS18: 46485 | BT18: 51133
C20: =C11/C5 -> -0.027422238 | D20: =D11/D5 -> -0.026970827 | E20: =E11/E5 -> -0.012367175 | F20: =F11/F5 -> -0.043778222 | G20: =G11/G5 -> -0.028050668 | H20: =H11/H5 -> -0.014896057 | I20: =I11/I5 -> 0.0037231798 | J20: =J11/J5 -> -0.034616812 | ... R20: =R11/R5 -> -0.011725151
E27: =AVERAGE(C20,H20,M20,R20) -> -0.019772509

Sheet Inputs - Operacionais
B2: DIRECIONAL ENGENHARIA S.A.
B4: DADOS OPERACIONAIS (MILHARES DE R$) | C4: 2025 | D4: 4T25 | E4: 3T25 | F4: 2T25 | G4: 1T25 | H4: 2024 | I4: 4T24 | J4: 3T24 | K4: 2T24 | L4: 1T24 | M4: 2023 | N4: 4T23 | O4: 3T23 | P4: 2T23 | Q4: 1T23 | R4: 2022 | S4: 4T22 | T4: 3T22 | U4: 2T22 | V4: 1T22 | W4: 2021 | X4: 4T21 | Y4: 3T21 | Z4: 2T21 | AA4: 1T21 | AB4: 2020 | AC4: 4T20 | AD4: 3T20 | AE4: 2T20 | AF4: 1T20 | AG4: 2019 | AH4: 4T19 | AI4: 3T19 | AJ4: 2T19 | AK4: 1T19 | AL4: 2018 | AM4: 4T18 | AN4: 3T18 | AO4: 2T18 | AP4: 1T18 | AQ4: 2017 | AR4: 4T17 | AS4: 3T17 | AT4: 2T17 | AU4: 1T17 | AV4: 2016 | AW4: 4T16 | AX4: 3T16 | AY4: 2T16 | AZ4: 1T16 | BA4: 2015 | BB4: 4T15 | BC4: 3T15 | BD4: 2T15 | BE4: 1T15 | BF4: 2014 | BG4: 4T14 | BH4: 3T14 | BI4: 2T14 | BJ4: 1T14 | BK4: 2013 | BL4: 4T13 | BM4: 3T13 | BN4: 2T13 | BO4: 1T13 | BP4: 2012 | BQ4: 4T12 | BR4: 3T12 | BS4: 2T12 | BT4: 1T12
B5: LANÇAMENTOS
B6: VGV Lançado (R$ mil) | C6: 6857548 | D6: 1900910.3 | E6: 2151576.7 | F6: 1903899.2 | G6: 901161.78 | H6: 5754715.4 | I6: 1833172.7 | J6: 1664372.7 | K6: 1360653 | L6: 896517.01 | M6: 4857453.4 | N6: 1390197 | O6: 1399420.2 | P6: 1456646.1 | Q6: 611190.03 | R6: 3636218.9 | S6: 1057713.1 | T6: 1189068.1 | U6: 790369.12 | V6: 599068.63 | W6: 3137983.8 | X6: 693380.72 | Y6: 1080620.3 | Z6: 786922.92 | AA6: 577059.8 | AB6: 1762850.4 | AC6: 697306.98 | AD6: 574480.16 | AE6: 351171 | AF6: 139892 | AG6: 1946038 | AH6: 555128 | AI6: 436682 | AJ6: 562020 | AK6: 392208 | AL6: 1904853 | AM6: 528679 | AN6: 528371 | AO6: 366245 | AP6: 481559 | AQ6: 1108693 | AR6: 490673 | AS6: 115290 | AT6: 299477 | AU6: 203253 | AV6: 832435.62 | AW6: 352335.43 | AX6: 169574.89 | AY6: 209544.97 | AZ6: 100980.33 | BA6: 501833.7 | BB6: 227169.87 | BC6: 72428.052 | BD6: 174331.77 | BE6: 27904 | BF6: 1798989.9 | BG6: 351772.69 | BH6: 412789.31 | BI6: 262924 | BJ6: 771503.9 | BK6: 2851266.7 | BL6: 972083.04 | BM6: 908112.16 | BN6: 551274.07 | BO6: 419797.38 | BP6: 2502500 | BQ6: 1222262.5 | BR6: 604949.61 | BS6: 531950.14 | BT6: 143337.76
B7: MCMV Faixa 1 (FAR) | C7: 0 | D7: 0 | E7: 0 | F7: 0 | G7: 0 | H7: 0 | I7: 0 | J7: 0 | K7: 0 | L7: 0 | M7: 0 | N7: 0 | O7: 0 | P7: 0 | Q7: 0 | R7: 0 | S7: 0 | T7: 0 | U7: 0 | V7: 0 | W7: 0 | X7: 0 | Y7: 0 | Z7: 0 | AA7: 0 | AB7: 0 | AC7: 0 | AD7: 0 | AE7: 0 | AF7: 0 | AG7: 0 | AH7: 0 | AI7: 0 | AJ7: 0 | AK7: 0 | AL7: 224304 | AM7: 41395 | AN7: 47876 | AO7: 0 | AP7: 135033 | AQ7: 183339 | AR7: 70862 | AS7: 0 | AT7: 112477 | AU7: 0 | AV7: 0 | AW7: 0 | AX7: 0 | AY7: 0 | AZ7: 0 | BA7: 0 | BB7: 0 | BC7: 0 | BD7: 0 | BE7: 0 | BF7: 1306291.8 | BG7: 193965.31 | BH7: 340822.58 | BI7: 0 | BJ7: 771503.9 | BK7: 2265403.9 | BL7: 783415.35 | BM7: 601015.36 | BN7: 476377.2 | BO7: 404596 | BP7: 1647147.1 | BQ7: 987733.3 | BR7: 400425.8 | BS7: 258988 | BT7: 0
B8: Incorporação | C8: 6857548 | D8: 1900910.3 | E8: 2151576.7 | F8: 1903899.2 | G8: 901161.78 | H8: 5754715.4 | I8: 1833172.7 | J8: 1664372.7 | K8: 1360653 | L8: 896517.01 | M8: 4857453.4 | N8: 1390197 | O8: 1399420.2 | P8: 1456646.1 | Q8: 611190.03 | R8: 3636218.9 | S8: 1057713.1 | T8: 1189068.1 | U8: 790369.12 | V8: 599068.63 | W8: 3137983.8 | X8: 693380.72 | Y8: 1080620.3 | Z8: 786922.92 | AA8: 577059.8 | AB8: 1762850.4 | AC8: 697306.98 | AD8: 574480.16 | AE8: 351171 | AF8: 139892 | AG8: 1946038 | AH8: 555128 | AI8: 436682 | AJ8: 562020 | AK8: 392208 | AL8: 1680549 | AM8: 487284 | AN8: 480495 | AO8: 366245 | AP8: 346526 | AQ8: 925354 | AR8: 419811 | AS8: 115290 | AT8: 187000 | AU8: 203253 | AV8: 832435.62 | AW8: 352335.43 | AX8: 169574.89 | AY8: 209544.97 | AZ8: 100980.33 | BA8: 501833.7 | BB8: 227169.87 | BC8: 72428.052 | BD8: 174331.77 | BE8: 27904 | BF8: 492698.11 | BG8: 157807.37 | BH8: 71966.737 | BI8: 262924 | BJ8: 0 | BK8: 585862.74 | BL8: 188667.7 | BM8: 307096.8 | BN8: 74896.87 | BO8: 15201.379 | BP8: 855352.89 | BQ8: 234529.17 | BR8: 204523.81 | BS8: 272962.14 | BT8: 143337.76
B9: VGV Lançado - % Direcional (R$ mil) | C9: 5893250 | D9: 1680227 | E9: 2017616.7 | F9: 1392984.6 | G9: 802421.66 | H9: 4700248.7 | I9: 1405792.3 | J9: 1444222.8 | K9: 1196750.5 | L9: 653483.05 | M9: 4295273.2 | N9: 1336559.4 | O9: 1259317 | P9: 1088942.4 | Q9: 610454.43 | R9: 3123736.8 | S9: 896097.38 | T9: 966706.77 | U9: 703651.43 | V9: 557281.26 | W9: 2677634.5 | X9: 633816.74 | Y9: 927227.63 | Z9: 662360.56 | AA9: 454229.6 | AB9: 1526596.6 | AC9: 650259.14 | AD9: 458126.52 | AE9: 295794 | AF9: 122417 | AG9: 1712229 | AH9: 501926 | AI9: 397578 | AJ9: 496662 | AK9: 316063 | AL9: 1694954 | AM9: 468984 | AN9: 423166 | AO9: 366245 | AP9: 436559 | AQ9: 980391 | AR9: 451272 | AS9: 115290 | AT9: 290645 | AU9: 123183 | AV9: 768535.24 | AW9: 316162.11 | AX9: 151095.83 | AY9: 200296.97 | AZ9: 100980.33 | BA9: 438043.77 | BB9: 207965.17 | BC9: 36214.026 | BD9: 174331.77 | BE9: 19532.8 | BF9: 1653924.2 | BG9: 347702.29 | BH9: 304114.35 | BI9: 230603.66 | BJ9: 771503.9 | BK9: 2564709.9 | BL9: 918916.64 | BM9: 779858.59 | BN9: 446137.25 | BO9: 419797.38 | BP9: 2345616.2 | BQ9: 1189035.6 | BR9: 543124.08 | BS9: 470208.28 | BT9: 143248.17
B10: MCMV Faixa 1 (FAR) | C10: 0 | D10: 0 | E10: 0 | F10: 0 | G10: 0 | H10: 0 | I10: 0 | J10: 0 | K10: 0 | L10: 0 | M10: 0 | N10: 0 | O10: 0 | P10: 0 | Q10: 0 | R10: 0 | S10: 0 | T10: 0 | U10: 0 | V10: 0 | W10: 0 | X10: 0 | Y10: 0 | Z10: 0 | AA10: 0 | AB10: 0 | AC10: 0 | AD10: 0 | AE10: 0 | AF10: 0 | AG10: 0 | AH10: 0 | AI10: 0 | AJ10: 0 | AK10: 0 | AL10: 224304 | AM10: 41395 | AN10: 47876 | AO10: 0 | AP10: 135033 | AQ10: 183339 | AR10: 70862 | AS10: 0 | AT10: 112477 | AU10: 0 | AV10: 0 | AW10: 0 | AX10: 0 | AY10: 0 | AZ10: 0 | BA10: 0 | BB10: 0 | BC10: 0 | BD10: 0 | BE10: 0 | BF10: 1197616.8 | BG10: 193965.31 | BH10: 232147.61 | BI10: 0 | BJ10: 771503.9 | BK10: 2041272.2 | BL10: 730248.95 | BM10: 503921.27 | BN10: 402505.97 | BO10: 404596 | BP10: 1647147.1 | BQ10: 987733.3 | BR10: 400425.8 | BS10: 258988 | BT10: 0
B11: Incorporação | C11: 5893250 | D11: 1680227 | E11: 2017616.7 | F11: 1392984.6 | G11: 802421.66 | H11: 4700248.7 | I11: 1405792.3 | J11: 1444222.8 | K11: 1196750.5 | L11: 653483.05 | M11: 4295273.2 | N11: 1336559.4 | O11: 1259317 | P11: 1088942.4 | Q11: 610454.43 | R11: 3123736.8 | S11: 896097.38 | T11: 966706.77 | U11: 703651.43 | V11: 557281.26 | W11: 2677634.5 | X11: 633816.74 | Y11: 927227.63 | Z11: 662360.56 | AA11: 454229.6 | AB11: 1526596.6 | AC11: 650259.14 | AD11: 458126.52 | AE11: 295794 | AF11: 122417 | AG11: 1712229 | AH11: 501926 | AI11: 397578 | AJ11: 496662 | AK11: 316063 | AL11: 1470650 | AM11: 427589 | AN11: 375290 | AO11: 366245 | AP11: 301526 | AQ11: 797052 | AR11: 380411 | AS11: 115290 | AT11: 178168 | AU11: 123183 | AV11: 768535.24 | AW11: 316162.11 | AX11: 151095.83 | AY11: 200296.97 | AZ11: 100980.33 | BA11: 438043.77 | BB11: 207965.17 | BC11: 36214.026 | BD11: 174331.77 | BE11: 19532.8 | BF11: 456307.37 | BG11: 153736.97 | BH11: 71966.737 | BI11: 230603.66 | BJ11: 0 | BK11: 523437.68 | BL11: 188667.7 | BM11: 275937.32 | BN11: 43631.285 | BO11: 15201.379 | BP11: 698469.06 | BQ11: 201302.34 | BR11: 142698.28 | BS11: 211220.28 | BT11: 143248.17
B12: Unidades Lançadas (unidades) | C12: 19749 | D12: 4780 | E12: 6449 | F12: 5096 | G12: 3424 | H12: 18135 | I12: 5763 | J12: 5947 | K12: 4187 | L12: 2238 | M12: 17180 | N12: 4998 | O12: 4152 | P12: 5268 | Q12: 2762 | R12: 14525 | S12: 4320 | T12: 4113 | U12: 3261 | V12: 2831 | W12: 13534 | X12: 3146 | Y12: 3764 | Z12: 4153 | AA12: 2471 | AB12: 10043 | AC12: 3701 | AD12: 3358 | AE12: 2132 | AF12: 852 | AG12: 11212 | AH12: 3248 | AI12: 2546 | AJ12: 3128 | AK12: 2290 | AL12: 11879 | AM12: 3307 | AN12: 3275 | AO12: 2104 | AP12: 3193 | AQ12: 7904 | AR12: 3380 | AS12: 740 | AT12: 2396 | AU12: 1388 | AV12: 4535 | AW12: 2032 | AX12: 620 | AY12: 1395 | AZ12: 488 | BA12: 2408 | BB12: 1000 | BC12: 512 | BD12: 640 | BE12: 256 | BF12: 19117 | BG12: 2725 | BH12: 4864 | BI12: 1332 | BJ12: 10196 | BK12: 36355 | BL12: 12700 | BM12: 9709 | BN12: 7650 | BO12: 6296 | BP12: 26376 | BQ12: 13210 | BR12: 7015 | BS12: 5060 | BT12: 1091
B13: MCMV Faixa 1 (FAR) (unidades) | C13: 0 | D13: 0 | E13: 0 | F13: 0 | G13: 0 | H13: 0 | I13: 0 | J13: 0 | K13: 0 | L13: 0 | M13: 0 | N13: 0 | O13: 0 | P13: 0 | Q13: 0 | R13: 0 | S13: 0 | T13: 0 | U13: 0 | V13: 0 | W13: 0 | X13: 0 | Y13: 0 | Z13: 0 | AA13: 0 | AB13: 0 | AC13: 0 | AD13: 0 | AE13: 0 | AF13: 0 | AG13: 0 | AH13: 0 | AI13: 0 | AJ13: 0 | AK13: 0 | AL13: 2345 | AM13: 440 | AN13: 544 | AO13: 0 | AP13: 1361 | AQ13: 1900 | AR13: 600 | AS13: 0 | AT13: 1300 | AU13: 0 | AV13: 0 | AW13: 0 | AX13: 0 | AY13: 0 | AZ13: 0 | BA13: 0 | BB13: 0 | BC13: 0 | BD13: 0 | BE13: 0 | BF13: 17284 | BG13: 2448 | BH13: 4640 | BI13: 0 | BJ13: 10196 | BK13: 34372 | BL13: 12100 | BM13: 8768 | BN13: 7244 | BO13: 6260 | BP13: 23234 | BQ13: 12836 | BR13: 6398 | BS13: 4000 | BT13: 0
B14: Incorporação (unidades) | C14: 19749 | D14: 4780 | E14: 6449 | F14: 5096 | G14: 3424 | H14: 18135 | I14: 5763 | J14: 5947 | K14: 4187 | L14: 2238 | M14: 17180 | N14: 4998 | O14: 4152 | P14: 5268 | Q14: 2762 | R14: 14525 | S14: 4320 | T14: 4113 | U14: 3261 | V14: 2831 | W14: 13534 | X14: 3146 | Y14: 3764 | Z14: 4153 | AA14: 2471 | AB14: 10043 | AC14: 3701 | AD14: 3358 | AE14: 2132 | AF14: 852 | AG14: 11212 | AH14: 3248 | AI14: 2546 | AJ14: 3128 | AK14: 2290 | AL14: 9534 | AM14: 2867 | AN14: 2731 | AO14: 2104 | AP14: 1832 | AQ14: 6004 | AR14: 2780 | AS14: 740 | AT14: 1096 | AU14: 1388 | AV14: 4535 | AW14: 2032 | AX14: 620 | AY14: 1395 | AZ14: 488 | BA14: 2408 | BB14: 1000 | BC14: 512 | BD14: 640 | BE14: 256 | BF14: 1833 | BG14: 277 | BH14: 224 | BI14: 1332 | BJ14: 0 | BK14: 1983 | BL14: 600 | BM14: 941 | BN14: 406 | BO14: 36 | BP14: 3142 | BQ14: 374 | BR14: 617 | BS14: 1060 | BT14: 1091
B15: % Direcional Médio | C15: 0.8594 | D15: 0.8839 | E15: 0.93773869 | F15: 0.73164827 | G15: 0.89043019 | H15: 0.81676475 | I15: 0.76686299 | J15: 0.86772801 | K15: 0.87954131 | L15: 0.72891316 | M15: 0.88426443 | N15: 0.96141728 | O15: 0.8998848 | P15: 0.74756825 | Q15: 0.99879645 | R15: 0.85906182 | S15: 0.8472027 | T15: 0.81299531 | U15: 0.89028203 | V15: 0.9302461 | W15: 0.85329776 | X15: 0.91409628 | Y15: 0.85805125 | Z15: 0.84170958 | AA15: 0.78714476 | AB15: 0.86598192 | AC15: 0.93252923 | AD15: 0.79746273 | AE15: 0.84 | AF15: 0.88 | AG15: 0.88 | AH15: 0.9 | AI15: 0.91 | AJ15: 0.88 | AK15: 0.81 | AL15: 0.88980806 | AM15: 0.89 | AN15: 0.8 | AO15: 1 | AP15: 0.91 | AQ15: 0.88 | AR15: 0.92 | AS15: 1 | AT15: 0.97 | AU15: 0.61 | AV15: 0.92323685 | AW15: 0.89733273 | AX15: 0.89102713 | AY15: 0.95586628 | AZ15: 1 | BA15: 0.87288632 | BB15: 0.91546106 | BC15: 0.5 | BD15: 1 | BE15: 0.7 | BF15: 0.91936269 | BG15: 0.98842889 | BH15: 0.73673018 | BI15: 0.87707347 | BJ15: 1 | BK15: 0.89949842 | BL15: 0.94530673 | BM15: 0.85876902 | BN15: 0.80928394 | BO15: 1 | BP15: 0.93730916 | BQ15: 0.9728153 | BR15: 0.89780053 | BS15: 0.88393298 | BT15: 0.99937497
B16: Preço Médio (R$/unidade) | C16: 347235.2 | D16: 397679.98 | E16: 333629.51 | F16: 373606.6 | G16: 263189.77 | H16: 317326.46 | I16: 318093.47 | J16: 279867.62 | K16: 324970.87 | L16: 400588.48 | M16: 282738.85 | N16: 278150.66 | O16: 337047.26 | P16: 276508.37 | Q16: 221285.31 | R16: 250342.09 | S16: 244840.99 | T16: 289099.95 | U16: 242370.17 | V16: 211610.25 | W16: 231859.3 | X16: 220400.74 | Y16: 287093.61 | Z16: 189483.01 | AA16: 233532.9 | AB16: 175530.26 | AC16: 188410.43 | AD16: 171078.07 | AE16: 164714 | AF16: 164193 | AG16: 173567 | AH16: 170914 | AI16: 171517 | AJ16: 179674 | AK16: 171270 | AL16: 160355 | AM16: 159867 | AN16: 161335 | AO16: 174071 | AP16: 150817 | AQ16: 140270 | AR16: 145169 | AS16: 155797 | AT16: 124990 | AU16: 146436 | AV16: 183558.02 | AW16: 173393.42 | AX16: 273507.89 | AY16: 150211.45 | AZ16: 206926.91 | BA16: 208402.7 | BB16: 227169.87 | BC16: 141461.04 | BD16: 272393.39 | BE16: 109000 | BF16: 94104.195 | BG16: 129090.89 | BH16: 84866.224 | BI16: 197390.39 | BJ16: 75667.311 | BK16: 78428.46 | BL16: 76541.972 | BM16: 93533.027 | BN16: 72061.97 | BO16: 66676.839 | BP16: 94877.919 | BQ16: 92525.547 | BR16: 86236.581 | BS16: 105128.49 | BT16: 131381.99
B18: VENDAS
B19: VGV Contratado (R$ mil) | C19: 6163133.7 | D19: 1517513.4 | E19: 1641806.9 | F19: 1677312.5 | G19: 1326500.9 | H19: 6271470.8 | I19: 1579893 | J19: 1765137.2 | K19: 1618771.7 | L19: 1307668.9 | M19: 3991086.7 | N19: 1220638.7 | O19: 1004596.7 | P19: 962491.65 | Q19: 803359.61 | R19: 2998855.8 | S19: 694367.82 | T19: 846854.98 | U19: 835691.46 | V19: 621941.51 | W19: 2439934.1 | X19: 667757.72 | Y19: 642716.12 | Z19: 614495.93 | AA19: 514964.29 | AB19: 1680301.7 | AC19: 522749.29 | AD19: 458406.89 | AE19: 401096 | AF19: 298049 | AG19: 1320407 | AH19: 370616 | AI19: 326166 | AJ19: 336236 | AK19: 287389 | AL19: 1450714 | AM19: 427865 | AN19: 319160 | AO19: 319030 | AP19: 384658 | AQ19: 914494 | AR19: 267524 | AS19: 198168 | AT19: 298124 | AU19: 150678 | AV19: 494170.16 | AW19: 202461.53 | AX19: 90671.877 | AY19: 76310.529 | AZ19: 124726.21 | BA19: 389889.89 | BB19: 121567.8 | BC19: 103970.27 | BD19: 121767.05 | BE19: 42584.769 | BF19: 1773940.5 | BG19: 343312.98 | BH19: 408063.21 | BI19: 133906.95 | BJ19: 888657.32 | BK19: 2962209.3 | BL19: 1001571.2 | BM19: 756782.04 | BN19: 655900.95 | BO19: 547955.18 | BP19: 2390755.4 | BQ19: 1155011 | BR19: 593670.66 | BS19: 485317.86 | BT19: 156755.84
B20: MCMV Faixa 1 (FAR) | C20: 0 | D20: 0 | E20: 0 | F20: 0 | G20: 0 | H20: 0 | I20: 0 | J20: 0 | K20: 0 | L20: 0 | M20: 0 | N20: 0 | O20: 0 | P20: 0 | Q20: 0 | R20: 0 | S20: 0 | T20: 0 | U20: 0 | V20: 0 | W20: 0 | X20: 0 | Y20: 0 | Z20: 0 | AA20: 0 | AB20: 0 | AC20: 0 | AD20: 0 | AE20: 0 | AF20: 0 | AG20: 0 | AH20: 0 | AI20: 0 | AJ20: 0 | AK20: 0 | AL20: 224304 | AM20: 41395 | AN20: 47876 | AO20: 0 | AP20: 135033 | AQ20: 183339 | AR20: 70862 | AS20: 0 | AT20: 112477 | AU20: 0 | AV20: 0 | AW20: 0 | AX20: 0 | AY20: 0 | AZ20: 0 | BA20: 0 | BB20: 0 | BC20: 0 | BD20: 0 | BE20: 0 | BF20: 1306291.8 | BG20: 193965.31 | BH20: 340822.58 | BI20: 0 | BJ20: 771503.9 | BK20: 2265403.9 | BL20: 783415.35 | BM20: 601015.36 | BN20: 476377.2 | BO20: 404596 | BP20: 1647147.1 | BQ20: 987733.3 | BR20: 400425.8 | BS20: 258988 | BT20: 0
B21: Incorporação | C21: 6163133.7 | D21: 1517513.4 | E21: 1641806.9 | F21: 1677312.5 | G21: 1326500.9 | H21: 6271470.8 | I21: 1579893 | J21: 1765137.2 | K21: 1618771.7 | L21: 1307668.9 | M21: 3991086.7 | N21: 1220638.7 | O21: 1004596.7 | P21: 962491.65 | Q21: 803359.61 | R21: 2998855.8 | S21: 694367.82 | T21: 846854.98 | U21: 835691.46 | V21: 621941.51 | W21: 2439934.1 | X21: 667757.72 | Y21: 642716.12 | Z21: 614495.93 | AA21: 514964.29 | AB21: 1680301.7 | AC21: 522749.29 | AD21: 458406.89 | AE21: 401096 | AF21: 298049 | AG21: 1320407 | AH21: 370616 | AI21: 326166 | AJ21: 336236 | AK21: 287389 | AL21: 1226410 | AM21: 386470 | AN21: 271285 | AO21: 319030 | AP21: 249625 | AQ21: 731155 | AR21: 196662 | AS21: 198168 | AT21: 185647 | AU21: 150678 | AV21: 494170.16 | AW21: 202461.53 | AX21: 90671.877 | AY21: 76310.529 | AZ21: 124726.21 | BA21: 389889.89 | BB21: 121567.8 | BC21: 103970.27 | BD21: 121767.05 | BE21: 42584.769 | BF21: 467648.67 | BG21: 149347.67 | BH21: 67240.633 | BI21: 133906.95 | BJ21: 117153.42 | BK21: 696805.42 | BL21: 218155.81 | BM21: 155766.68 | BN21: 179523.75 | BO21: 143359.18 | BP21: 743608.26 | BQ21: 167277.7 | BR21: 193244.86 | BS21: 226329.86 | BT21: 156755.84
B22: VGV Contratado - % Direcional (R$ mil) | C22: 5136577 | D22: 1305147.5 | E22: 1435255.2 | F22: 1296399.6 | G22: 1099774.7 | H22: 4880241.3 | I22: 1242920.1 | J22: 1373024.8 | K22: 1260095.6 | L22: 1004200.9 | M22: 3122619.9 | N22: 994436.04 | O22: 751415.72 | P22: 733884.74 | Q22: 642883.36 | R22: 2416011.1 | S22: 551492.17 | T22: 682313.57 | U22: 674214.81 | V22: 507990.55 | W22: 2017273.5 | X22: 537662.34 | Y22: 525001.79 | Z22: 515664.99 | AA22: 438944.36 | AB22: 1407755.8 | AC22: 446741.28 | AD22: 368943.51 | AE22: 344066 | AF22: 248005 | AG22: 1153185 | AH22: 322598 | AI22: 285593 | AJ22: 291204 | AK22: 253790 | AL22: 1334511 | AM22: 375919 | AN22: 298413 | AO22: 295388 | AP22: 364792 | AQ22: 807487 | AR22: 242372 | AS22: 168674 | AT22: 262496 | AU22: 133944 | AV22: 448100.01 | AW22: 179379.52 | AX22: 84153.884 | AY22: 66158.612 | AZ22: 118410 | BA22: 345062.99 | BB22: 104118.64 | BC22: 92980.302 | BD22: 111508.34 | BE22: 36455.712 | BF22: 1634306 | BG22: 330680.25 | BH22: 295613.75 | BI22: 126458.92 | BJ22: 881553.1 | BK22: 2651523.6 | BL22: 936926.61 | BM22: 641942.88 | BN22: 542804.84 | BO22: 529849.31 | BP22: 2267338.2 | BQ22: 1128773.9 | BR22: 558392.21 | BS22: 447647.34 | BT22: 132524.74
B23: MCMV Faixa 1 | C23: 0 | D23: 0 | E23: 0 | F23: 0 | G23: 0 | H23: 0 | I23: 0 | J23: 0 | K23: 0 | L23: 0 | M23: 0 | N23: 0 | O23: 0 | P23: 0 | Q23: 0 | R23: 0 | S23: 0 | T23: 0 | U23: 0 | V23: 0 | W23: 0 | X23: 0 | Y23: 0 | Z23: 0 | AA23: 0 | AB23: 0 | AC23: 0 | AD23: 0 | AE23: 0 | AF23: 0 | AG23: 0 | AH23: 0 | AI23: 0 | AJ23: 0 | AK23: 0 | AL23: 224304 | AM23: 41395 | AN23: 47876 | AO23: 0 | AP23: 135033 | AQ23: 183339 | AR23: 70862 | AS23: 0 | AT23: 112477 | AU23: 0 | AV23: 0 | AW23: 0 | AX23: 0 | AY23: 0 | AZ23: 0 | BA23: 0 | BB23: 0 | BC23: 0 | BD23: 0 | BE23: 0 | BF23: 1197616.8 | BG23: 193965.31 | BH23: 232147.61 | BI23: 0 | BJ23: 771503.9 | BK23: 2041272.2 | BL23: 730248.95 | BM23: 503921.27 | BN23: 402505.97 | BO23: 404596 | BP23: 1647147.1 | BQ23: 987733.3 | BR23: 400425.8 | BS23: 258988 | BT23: 0
B24: Incorporação | C24: 5136577 | D24: 1305147.5 | E24: 1435255.2 | F24: 1296399.6 | G24: 1099774.7 | H24: 4880241.3 | I24: 1242920.1 | J24: 1373024.8 | K24: 1260095.6 | L24: 1004200.9 | M24: 3122619.9 | N24: 994436.04 | O24: 751415.72 | P24: 733884.74 | Q24: 642883.36 | R24: 2416011.1 | S24: 551492.17 | T24: 682313.57 | U24: 674214.81 | V24: 507990.55 | W24: 2017273.5 | X24: 537662.34 | Y24: 525001.79 | Z24: 515664.99 | AA24: 438944.36 | AB24: 1407755.8 | AC24: 446741.28 | AD24: 368943.51 | AE24: 344066 | AF24: 248005 | AG24: 1153185 | AH24: 322598 | AI24: 285593 | AJ24: 291204 | AK24: 253790 | AL24: 1110207 | AM24: 334524 | AN24: 250537 | AO24: 295388 | AP24: 229759 | AQ24: 624148 | AR24: 171510 | AS24: 168674 | AT24: 150019 | AU24: 133944 | AV24: 448100.01 | AW24: 179379.52 | AX24: 84153.884 | AY24: 66158.612 | AZ24: 118410 | BA24: 345062.99 | BB24: 104118.64 | BC24: 92980.302 | BD24: 111508.34 | BE24: 36455.712 | BF24: 436689.2 | BG24: 136714.94 | BH24: 63466.144 | BI24: 126458.92 | BJ24: 110049.2 | BK24: 610251.45 | BL24: 206677.66 | BM24: 138021.61 | BN24: 140298.87 | BO24: 125253.31 | BP24: 620191.1 | BQ24: 141040.61 | BR24: 157966.41 | BS24: 188659.34 | BT24: 132524.74
B25: Unidades Contratadas (unidades) | C25: 18590 | D25: 4227 | E25: 4857 | F25: 5176 | G25: 4330 | H25: 21060 | I25: 5186 | J25: 6293 | K25: 5354 | L25: 4227 | M25: 14785 | N25: 4506 | O25: 3458 | P25: 3575 | Q25: 3246 | R25: 13167 | S25: 2899 | T25: 3403 | U25: 3920 | V25: 2945 | W25: 12227 | X25: 3146 | Y25: 3211 | Z25: 3168 | AA25: 2702 | AB25: 9061 | AC25: 2749 | AD25: 2457 | AE25: 2207 | AF25: 1648 | AG25: 7601 | AH25: 2072 | AI25: 1854 | AJ25: 1923 | AK25: 1752 | AL25: 9843 | AM25: 2700 | AN25: 2151 | AO25: 1997 | AP25: 2995 | AQ25: 6243 | AR25: 1888 | AS25: 1111 | AT25: 2412 | AU25: 832 | AV25: 2209 | AW25: 923 | AX25: 347 | AY25: 360 | AZ25: 579 | BA25: 1620 | BB25: 547 | BC25: 425 | BD25: 460 | BE25: 188 | BF25: 18835 | BG25: 2800 | BH25: 4969 | BI25: 555 | BJ25: 10511 | BK25: 36650 | BL25: 12703 | BM25: 9259 | BN25: 7925 | BO25: 6763 | BP25: 27057 | BQ25: 13403 | BR25: 7351 | BS25: 5276 | BT25: 1027
B26: MCMV Faixa 1 (FAR) (unidades) | C26: 0 | D26: 0 | E26: 0 | F26: 0 | G26: 0 | H26: 0 | I26: 0 | J26: 0 | K26: 0 | L26: 0 | M26: 0 | N26: 0 | O26: 0 | P26: 0 | Q26: 0 | R26: 0 | S26: 0 | T26: 0 | U26: 0 | V26: 0 | W26: 0 | X26: 0 | Y26: 0 | Z26: 0 | AA26: 0 | AB26: 0 | AC26: 0 | AD26: 0 | AE26: 0 | AF26: 0 | AG26: 0 | AH26: 0 | AI26: 0 | AJ26: 0 | AK26: 0 | AL26: 2345 | AM26: 440 | AN26: 544 | AO26: 0 | AP26: 1361 | AQ26: 1900 | AR26: 600 | AS26: 0 | AT26: 1300 | AU26: 0 | AV26: 0 | AW26: 0 | AX26: 0 | AY26: 0 | AZ26: 0 | BA26: 0 | BB26: 0 | BC26: 0 | BD26: 0 | BE26: 0 | BF26: 17284 | BG26: 2448 | BH26: 4640 | BI26: 0 | BJ26: 10196 | BK26: 34372 | BL26: 12100 | BM26: 8768 | BN26: 7244 | BO26: 6260 | BP26: 23234 | BQ26: 12836 | BR26: 6398 | BS26: 4000 | BT26: 0
B27: Incorporação (unidades) | C27: 18590 | D27: 4227 | E27: 4857 | F27: 5176 | G27: 4330 | H27: 21060 | I27: 5186 | J27: 6293 | K27: 5354 | L27: 4227 | M27: 14785 | N27: 4506 | O27: 3458 | P27: 3575 | Q27: 3246 | R27: 13167 | S27: 2899 | T27: 3403 | U27: 3920 | V27: 2945 | W27: 12227 | X27: 3146 | Y27: 3211 | Z27: 3168 | AA27: 2702 | AB27: 9061 | AC27: 2749 | AD27: 2457 | AE27: 2207 | AF27: 1648 | AG27: 7601 | AH27: 2072 | AI27: 1854 | AJ27: 1923 | AK27: 1752 | AL27: 7498 | AM27: 2260 | AN27: 1607 | AO27: 1997 | AP27: 1634 | AQ27: 4343 | AR27: 1288 | AS27: 1111 | AT27: 1112 | AU27: 832 | AV27: 2209 | AW27: 923 | AX27: 347 | AY27: 360 | AZ27: 579 | BA27: 1620 | BB27: 547 | BC27: 425 | BD27: 460 | BE27: 188 | BF27: 1551 | BG27: 352 | BH27: 329 | BI27: 555 | BJ27: 315 | BK27: 2278 | BL27: 603 | BM27: 491 | BN27: 681 | BO27: 503 | BP27: 3823 | BQ27: 567 | BR27: 953 | BS27: 1276 | BT27: 1027
B28: Preço Médio (R$/unidade) | C28: 331529.5 | D28: 359004.82 | E28: 338029.01 | F28: 324055.74 | G28: 306351.25 | H28: 297790.64 | I28: 304645.78 | J28: 280492.17 | K28: 302348.09 | L28: 309360.98 | M28: 269941.61 | N28: 270891.85 | O28: 290513.8 | P28: 269228.43 | Q28: 247492.18 | R28: 227755.43 | S28: 239519.77 | T28: 248855.42 | U28: 213186.6 | V28: 211185.57 | W28: 199552.96 | X28: 212256.11 | Y28: 200160.73 | Z28: 193969.67 | AA28: 190586.34 | AB28: 185443.29 | AC28: 190159.8 | AD28: 186571.79 | AE28: 181738 | AF28: 180855 | AG28: 173715 | AH28: 178869 | AI28: 175926 | AJ28: 174850 | AK28: 164035 | AL28: 147385 | AM28: 158469 | AN28: 148378 | AO28: 159755 | AP28: 128433 | AQ28: 146483 | AR28: 141697 | AS28: 178369 | AT28: 123600 | AU28: 181104 | AV28: 223707.63 | AW28: 219351.61 | AX28: 261302.24 | AY28: 211973.69 | AZ28: 215416.61 | BA28: 240672.77 | BB28: 222244.61 | BC28: 244635.93 | BD28: 264710.98 | BE28: 226514.73 | BF28: 94183.194 | BG28: 122611.78 | BH28: 82121.797 | BI28: 241273.79 | BJ28: 84545.459 | BK28: 80824.265 | BL28: 78845.246 | BM28: 81734.749 | BN28: 82763.526 | BO28: 81022.503 | BP28: 88359.957 | BQ28: 86175.558 | BR28: 80760.53 | BS28: 91985.948 | BT28: 152634.7
B29: VSO (Vendas Sobre Oferta) - MCMV | C29: 0.507 | D29: 0.191 | E29: 0.2131 | F29: 0.26062419 | G29: 0.22902505 | H29: 0.55700896 | I29: 0.24797751 | J29: 0.24972891 | K29: 0.26245725 | L29: 0.2138381 | M29: 0.4371367 | N29: 0.17246346 | O29: 0.15414466 | P29: 0.17288286 | Q29: 0.18826291 | R29: 0.47323471 | S29: 0.16669912 | T29: 0.19288339 | U29: 0.23129287 | V29: 0.17850967 | W29: 0.445 | X29: 0.169 | Y29: 0.157 | Z29: 0.172 | AA29: 0.167 | AB29: 0.427 | AC29: 0.183 | AD29: 0.179 | AE29: 0.165 | AF29: 0.131 | AG29: 0.383 | AH29: 0.126 | AI29: 0.141 | AJ29: 0.16 | AK29: 0.152 | AL29: 0.443 | AM29: 0.197 | AN29: 0.162 | AO29: 0.219 | AP29: 0.202 | AQ29: 0.422 | AR29: 0.18 | AS29: 0.18825631 | AT29: 0.1934927 | AU29: 0.15016694 | AV29: 0.3 | AW29: 0.164 | AX29: 0.086651779 | AY29: 0.080940536 | AZ29: 0.25678921 | BA29: 0.43308037 | BB29: 0.21699308 | BC29: 0.20276602 | BD29: 0.23569308 | BE29: 0.20013088 | BF29: 0 | BG29: 0 | BH29: 0 | BI29: 0 | BJ29: 0 | BK29: 0 | BL29: 0 | BM29: 0 | BN29: 0 | BO29: 0 | BP29: 0 | BQ29: 0 | BR29: 0 | BS29: 0 | BT29: 0
B30: VSO (Vendas Sobre Oferta) - Consolidada | C30: 0.529 | D30: 0.211 | E30: 0.239 | F30: 0.26365574 | G30: 0.23320129 | H30: 0.56447881 | I30: 0.24978796 | J30: 0.24963679 | K30: 0.2637176 | L30: 0.21639895 | M30: 0.4274709 | N30: 0.16350925 | O30: 0.16793178 | P30: 0.1750219 | Q30: 0.16686563 | R30: 0.43502893 | S30: 0.14615323 | T30: 0.19008916 | U30: 0.20379111 | V30: 0.16127881 | W30: 0.433 | X30: 0.172 | Y30: 0.169 | Z30: 0.184 | AA30: 0.167 | AB30: 0.4 | AC30: 0.173 | AD30: 0.163 | AE30: 0.153 | AF30: 0.116 | AG30: 0.353 | AH30: 0.138 | AI30: 0.127 | AJ30: 0.137 | AK30: 0.131 | AL30: 0.368 | AM30: 0.177 | AN30: 0.122 | AO30: 0.154 | AP30: 0.125 | AQ30: 0.307 | AR30: 0.10580435 | AS30: 0.122 | AT30: 0.106 | AU30: 0.091 | AV30: 0.253 | AW30: 0.12 | AX30: 0.064786221 | AY30: 0.05738951 | AZ30: 0.10180182 | BA30: 0.26695967 | BB30: 0.09643886 | BC30: 0.094069679 | BD30: 0.106 | BE30: 0.043165225 | BF30: 0.35242518 | BG30: 0.13627886 | BH30: 0.070139908 | BI30: 0.13448669 | BJ30: 0.14043023 | BK30: 0.46049776 | BL30: 0.21076712 | BM30: 0.153979 | BN30: 0.21224156 | BO30: 0.15210594 | BP30: 0.44078533 | BQ30: 0.15234096 | BR30: 0.18655136 | BS30: 0.21166202 | BT30: 0.16077644
B32: ESTOQUE
B33: Estoque Total a Valor de Mercado (R$ mil) | C33: 5696074.3 | D33: 5696074.3 | E33: 5296306.8 | F33: 4716030 | G33: 4457853 | H33: 4787061 | I33: 4787061 | J33: 4491763.9 | K33: 4591683.9 | L33: 4777623.9 | M33: 5146344.4 | N33: 5146344.4 | O33: 5021448.7 | P33: 4582751.3 | Q33: 4042618.1 | R33: 4203220.2 | S33: 4203220.2 | T33: 3693244.8 | U33: 3265972.8 | V33: 3310356.6 | W33: 3257244 | X33: 3257244 | Y33: 3178010.9 | Z33: 2721703.4 | AA33: 2555988.9 | AB33: 2502447.3 | AC33: 2502447.3 | AD33: 2328376.2 | AE33: 2235027 | AF33: 2276753 | AG33: 2434918 | AH33: 2434918 | AI33: 2234885 | AJ33: 2123418 | AK33: 1898446 | AL33: 1796351 | AM33: 1796351 | AN33: 1695938 | AO33: 1741948 | AP33: 1705208 | AQ33: 1648147 | AR33: 1648147 | AS33: 1438923 | AT33: 1507911 | AU33: 1562353 | AV33: 1459759.2 | AW33: 1459759.2 | AX33: 1333791 | AY33: 1229980.1 | AZ33: 1120149.8 | BA33: 1124206.2 | BB33: 1124206.2 | BC33: 1033398.8 | BD33: 1032819.4 | BE33: 972189.71 | BF33: 958648.68 | BG33: 958648.68 | BH33: 938090.18 | BI33: 886697.66 | BJ33: 732765.27 | BK33: 834246.44 | BL33: 834246.44 | BM33: 846388.46 | BN33: 704513.11 | BO33: 770949.45 | BP33: 927294.27 | BQ33: 927294.27 | BR33: 863518.9 | BS33: 831356.38 | BT33: 796336.26
B34: Empreendimentos Concluídos (R$ mil) | C34: 182496.2 | D34: 182496.2 | E34: 176208.05 | F34: 193638.42 | G34: 191092.19 | H34: 108427.44 | I34: 108427.44 | J34: 74694.146 | K34: 85112.631 | L34: 161356.39 | M34: 73573.923 | N34: 73573.923 | O34: 79214.305 | P34: 68045.524 | Q34: 75570.192 | R34: 88082.439 | S34: 88082.439 | T34: 66875.967 | U34: 75156.636 | V34: 186250.66 | W34: 162976.36 | X34: 162976.36 | Y34: 129395.71 | Z34: 120898.47 | AA34: 154429.16 | AB34: 180565.26 | AC34: 180565.26 | AD34: 229072.3 | AE34: 260345 | AF34: 279324 | AG34: 293125 | AH34: 293125 | AI34: 316921 | AJ34: 333125 | AK34: 347706 | AL34: 365461 | AM34: 365461 | AN34: 394808 | AO34: 628117 | AP34: 658957 | AQ34: 541772 | AR34: 541772 | AS34: 472679 | AT34: 433075 | AU34: 433157 | AV34: 354844.22 | AW34: 354844.22 | AX34: 368321 | AY34: 326359.18 | AZ34: 338113.47 | BA34: 319324.36 | BB34: 319324.36 | BC34: 282286.62 | BD34: 284279.3 | BE34: 237059.98 | BF34: 239410.34 | BG34: 239410.34 | BH34: 219594.24 | BI34: 199490.98 | BJ34: 206699.52 | BK34: 173090.7 | BL34: 173090.7 | BM34: 135365.54 | BN34: 104277.21 | BO34: 120254.95 | BP34: 144945.03 | BQ34: 144945.03 | BR34: 115089.13 | BS34: 88547.579 | BT34: 94194.517
B35: Unidades em Estoque (unidades) | C35: 15844 | D35: 15844 | E35: 15284 | F35: 13709 | G35: 13801 | H35: 14730 | I35: 14730 | J35: 14121 | K35: 14580 | L35: 15747 | M35: 17734 | N35: 17734 | O35: 17617 | P35: 16923 | Q35: 15224 | R35: 15781 | S35: 15781 | T35: 14386 | U35: 13676 | V35: 14513 | W35: 14627 | X35: 14627 | Y35: 14573 | Z35: 14045 | AA35: 13112 | AB35: 13381 | AC35: 13381 | AD35: 12429 | AE35: 11649 | AF35: 11724 | AG35: 12519 | AH35: 12519 | AI35: 11342 | AJ35: 10634 | AK35: 9418 | AL35: 8880 | AM35: 8880 | AN35: 8272 | AO35: 7589 | AP35: 7495 | AQ35: 7300 | AR35: 7300 | AS35: 5804 | AT35: 6175 | AU35: 6152 | AV35: 5622 | AW35: 5622 | AX35: 4533 | AY35: 4272 | AZ35: 3255 | BA35: 3346 | BB35: 3346 | BC35: 2960 | BD35: 2858 | BE35: 2723 | BF35: 2655 | BG35: 2655 | BH35: 2739 | BI35: 2852 | BJ35: 2114 | BK35: 2482 | BL35: 2482 | BM35: 2466 | BN35: 2028 | BO35: 2350 | BP35: 2866 | BQ35: 2866 | BR35: 3083 | BS35: 3435 | BT35: 3877
B36: Estoque Total a Valor de Mercado - % Direcional (R$ mil) | C36: 4778531.9 | D36: 4778531.9 | E36: 4496955.9 | F36: 3861641.6 | G36: 3694096.5 | H36: 3939039.6 | I36: 3939039.6 | J36: 3785343.7 | K36: 3827516.5 | L36: 3967910.4 | M36: 4339141 | N36: 4339141 | O36: 4064312.5 | P36: 3788923.3 | Q36: 3437201.7 | R36: 3430448.8 | S36: 3430448.8 | T36: 3146086.6 | U36: 2787042.2 | V36: 2718625.3 | W36: 2662254.9 | X36: 2662254.9 | Y36: 2686462.2 | Z36: 2281022.8 | AA36: 2225560.7 | AB36: 2213873.2 | AC36: 2213873.2 | AD36: 2044091.3 | AE36: 1967693 | AF36: 2007732 | AG36: 2116856 | AH36: 2116856 | AI36: 1924912 | AJ36: 1811865 | AK36: 1609028 | AL36: 1551351 | AM36: 1551351 | AN36: 1596177 | AO36: 1561832 | AP36: 1500874 | AQ36: 1470992 | AR36: 1470992 | AS36: 1275381 | AT36: 1320697 | AU36: 1339914 | AV36: 1307915 | AW36: 1307915 | AX36: 1194839.9 | AY36: 1103330 | AZ36: 989638.49 | BA36: 988693.76 | BB36: 988693.76 | BC36: 897113.01 | BD36: 924576.91 | BE36: 854932.75 | BF36: 846151.45 | BG36: 846151.45 | BH36: 812690.79 | BI36: 764504.57 | BJ36: 631255.65 | BK36: 725240.5 | BL36: 725240.5 | BM36: 726914.96 | BN36: 603423.4 | BO36: 666584.11 | BP36: 799927.87 | BQ36: 799927.87 | BR36: 742672.88 | BS36: 717686.56 | BT36: 705912.82
B37: Empreendimentos Concluídos - % Direcional (R$ mil) | C37: 125852.9 | D37: 125852.9 | E37: 118025.92 | F37: 135352.03 | G37: 133556.93 | H37: 65051.698 | I37: 65051.698 | J37: 49263.384 | K37: 53735.315 | L37: 91455.262 | M37: 57675.547 | N37: 57675.547 | O37: 61521.459 | P37: 45729.829 | Q37: 59242.016 | R37: 71745.694 | S37: 71745.694 | T37: 49273.966 | U37: 55721.948 | V37: 164436.87 | W37: 139006.6 | X37: 139006.6 | Y37: 101834.58 | Z37: 107411.9 | AA37: 140612.85 | AB37: 160004.77 | AC37: 160004.77 | AD37: 199608.2 | AE37: 227542 | AF37: 244194 | AG37: 255874 | AH37: 255874 | AI37: 277745 | AJ37: 290549 | AK37: 298451 | AL37: 308699 | AM37: 308699 | AN37: 329993 | AO37: 534213 | AP37: 561906 | AQ37: 449794 | AR37: 449794 | AS37: 392171 | AT37: 369220 | AU37: 357585 | AV37: 275139.19 | AW37: 275139.19 | AX37: 296532.06 | AY37: 259169.77 | AZ37: 264442.84 | BA37: 256548.12 | BB37: 256548.12 | BC37: 234863.29 | BD37: 235301.53 | BE37: 215885.72 | BF37: 217604.16 | BG37: 217604.16 | BH37: 183097.33 | BI37: 168704.63 | BJ37: 179396.32 | BK37: 154121.6 | BL37: 154121.6 | BM37: 123813.75 | BN37: 88442.795 | BO37: 105713.61 | BP37: 129919.48 | BQ37: 129919.48 | BR37: 103698.63 | BS37: 70359.858 | BT37: 72731.75
B39: LAND BANK
B40: Land Bank Total (R$ mil) | C40: 58452264 | D40: 58452264 | E40: 51251929 | F40: 49901268 | G40: 46253336 | H40: 46239914 | I40: 46239914 | J40: 43238920 | K40: 39678348 | L40: 37282561 | M40: 36301445 | N40: 36301445 | O40: 35769587 | P40: 35133506 | Q40: 32505331 | R40: 32458540 | S40: 32458540 | T40: 28896881 | U40: 28203973 | V40: 27797921 | W40: 26806722 | X40: 26806722 | Y40: 25474475 | Z40: 26486852 | AA40: 24936829 | AB40: 24799480 | AC40: 24799480 | AD40: 24506867 | AE40: 23227370 | AF40: 23092927 | AG40: 22326962 | AH40: 22326962 | AI40: 21029801 | AJ40: 21695053 | AK40: 21501897 | AL40: 20334373 | AM40: 20334373 | AN40: 19940900 | AO40: 16721513 | AP40: 16847273 | AQ40: 16222476 | AR40: 16222476 | AS40: 15569769 | AT40: 14749497 | AU40: 13242673 | AV40: 13044853 | AW40: 13044853 | AX40: 12787634 | AY40: 12799649 | AZ40: 12343696 | BA40: 11759865 | BB40: 11759865 | BC40: 11421123 | BD40: 10918758 | BE40: 11165126 | BF40: 11101527 | BG40: 11101527 | BH40: 10340010 | BI40: 9732939.1 | BJ40: 9602849.5 | BK40: 9633184.9 | BL40: 9633184.9 | BM40: 8388960.2 | BN40: 8785036.5 | BO40: 8647417 | BP40: 8890232.8 | BQ40: 8890232.8 | BR40: 9008558.2 | BS40: 9107633.6 | BT40: 9189705.4
B41: Land Bank - % Direcional (R$ mil) | C41: 53559355 | D41: 53559355 | E41: 46208978 | F41: 44854370 | G41: 42574672 | H41: 41540061 | I41: 41540061 | J41: 39225749 | K41: 35637130 | L41: 33955742 | M41: 32914714 | N41: 32914714 | O41: 32296125 | P41: 31558918 | Q41: 29758724 | R41: 29726437 | S41: 29726437 | T41: 26281909 | U41: 25503272 | V41: 25276489 | W41: 24701365 | X41: 24701365 | Y41: 23589821 | Z41: 24454650 | AA41: 23036675 | AB41: 22965510 | AC41: 22965510 | AD41: 22559250 | AE41: 21103145 | AF41: 20926593 | AG41: 20142835 | AH41: 20142835 | AI41: 18731620 | AJ41: 19261462 | AK41: 19032426 | AL41: 17806201 | AM41: 17806201 | AN41: 17457252 | AO41: 14329272 | AP41: 13912283 | AQ41: 13803583 | AR41: 13803583 | AS41: 13084431 | AT41: 12306719 | AU41: 10970259 | AV41: 10751539 | AW41: 10751539 | AX41: 10563138 | AY41: 10637343 | AZ41: 10219501 | BA41: 9770212.4 | BB41: 9770212.4 | BC41: 9415408.4 | BD41: 9050772.9 | BE41: 9332323.1 | BF41: 9261044.7 | BG41: 9261044.7 | BH41: 8524410.6 | BI41: 7952065.2 | BJ41: 7820120.3 | BK41: 7382311.3 | BL41: 7382311.3 | BM41: 6171559.3 | BN41: 6548978.2 | BO41: 6447338 | BP41: 6733605.5 | BQ41: 6733605.5 | BR41: 6820417.5 | BS41: 6895392.6 | BT41: 6934289.8
B42: Land Bank (unidades) | C42: 241470 | D42: 241470 | E42: 220267 | F42: 217749 | G42: 198296 | H42: 209504 | I42: 209504 | J42: 205534 | K42: 195189 | L42: 186181 | M42: 181519 | N42: 181519 | O42: 181036 | P42: 179670 | Q42: 169819 | R42: 170693 | S42: 170693 | T42: 158073 | U42: 156148 | V42: 156004 | W42: 151744 | X42: 151744 | Y42: 147702 | Z42: 151357 | AA42: 144223 | AB42: 143844 | AC42: 143844 | AD42: 142379 | AE42: 136729 | AF42: 136593 | AG42: 133475 | AH42: 133475 | AI42: 124454 | AJ42: 127716 | AK42: 126255 | AL42: 117895 | AM42: 117895 | AN42: 115706 | AO42: 98513 | AP42: 100809 | AQ42: 94060 | AR42: 94060 | AS42: 90262 | AT42: 84910 | AU42: 74386 | AV42: 72810 | AW42: 72810 | AX42: 70451 | AY42: 69457 | AZ42: 67184 | BA42: 63163 | BB42: 63163 | BC42: 60487 | BD42: 57657 | BE42: 59034 | BF42: 58670 | BG42: 58670 | BH42: 52680 | BI42: 51540 | BJ42: 52115 | BK42: 60080 | BL42: 60080 | BM42: 56007 | BN42: 60702 | BO42: 63461 | BP42: 66381 | BQ42: 66381 | BR42: 66559 | BS42: 66859 | BT42: 67089
B44: REPASSE
B45: Repasses (R$ mil)¹ | C45: 4173573.6 | D45: 1195024.2 | E45: 1075231 | F45: 1129328.7 | G45: 773989.78 | H45: 3363489.5 | I45: 885069.66 | J45: 899363.82 | K45: 1028917.4 | L45: 550138.58 | M45: 2228637.7 | N45: 539876.45 | O45: 556142.81 | P45: 631928.89 | Q45: 500689.54 | R45: 2376088.6 | S45: 491082.74 | T45: 647319.68 | U45: 776957.54 | V45: 460728.68 | W45: 2045644.7 | X45: 502298.88 | Y45: 536881.23 | Z45: 550091.13 | AA45: 456373.51 | AB45: 1308878.8 | AC45: 426714.85 | AD45: 446137.99 | AE45: 436025.97
B46: Unidades | C46: 14058 | D46: 3856 | E46: 3632 | F46: 3817 | G46: 2753 | H46: 12304 | I46: 3093 | J46: 3275 | K46: 3727 | L46: 2209 | M46: 9499 | N46: 2129 | O46: 2370 | P46: 2746 | Q46: 2254 | R46: 11413 | S46: 2287 | T46: 3052 | U46: 3851 | V46: 2223 | W46: 11264 | X46: 2707 | Y46: 2985 | Z46: 2963 | AA46: 2609 | AB46: 9025 | AC46: 2305 | AD46: 2389 | AE46: 2462 | AF46: 1869 | AG46: 7973 | AH46: 2301 | AI46: 1587 | AJ46: 1991 | AK46: 2094 | AL46: 7561 | AM46: 1796 | AN46: 2092 | AO46: 2288 | AP46: 1385 | AQ46: 3330 | AR46: 1161 | AS46: 1304 | AT46: 570 | AU46: 295 | AV46: 993 | AW46: 231 | AX46: 200 | AY46: 305 | AZ46: 257 | BA46: 463 | BB46: 170 | BC46: 142 | BD46: 100 | BE46: 51 | BF46: 207 | BG46: 58 | BH46: 87 | BI46: 43 | BJ46: 19 | BK46: 130 | BL46: 36 | BM46: 41 | BN46: 23 | BO46: 30 | BP46: 132 | BQ46: 33 | BR46: 51 | BS46: 33 | BT46: 15
B49: 1 - Considera o valor total do imóvel (VGV)

Sheet Projeções Macro
B4: Indicador | C4: 2022 | D4: 2023 | E4: 2024 | F4: 2025 | G4: 2026E | H4: 2027E | I4: 2028E | J4: 2029E
B5: Selic (% a.a.) | C5: 0.1375 | D5: 0.1175 | E5: 0.1225 | F5: 0.1475 | G5: 0.13 | H5: 0.13 | I5: 0.13 | J5: 0.13
B6: CDI (% a.a.) | C6: 0.1365 | D6: 0.1165 | E6: 0.1215 | F6: 0.1465 | G6: 0.13 | H6: 0.13 | I6: 0.13 | J6: 0.13
B7: IPCA (% a.a.) | C7: 0.0579 | D7: 0.0462 | E7: 0.0483 | F7: 0.0483 | G7: 0.049 | H7: 0.049 | I7: 0.049 | J7: 0.049
B8: INCC (% a.a.) | C8: 0.0911 | D8: 0.0349 | E8: 0.07 | F8: 0.07 | G8: 0.059 | H8: 0.059 | I8: 0.059 | J8: 0.059
B9: TR — Taxa Referencial (% a.a.) | C9: 0.0073 | D9: 0.0136 | E9: 0.0096 | F9: 0.005 | G9: 0.005 | H9: 0.005 | I9: 0.005 | J9: 0.005
B10: Câmbio USD/BRL (Year-End) | C10: 5.22 | D10: 4.84 | E10: 6.18 | F10: 5.53 | G10: 4.9 | H10: 4.9 | I10: 4.9 | J10: 4.9
B13: Fontes: Projeções BTG Pactual

Sheet Unit Direcional
B6: Premissas do Empreendimento
B8: VGV Total | C8: =C9*C10 -> 80500000 | H8: VGV Liquido = VGV Total - Corretagem
B9: Unidades | C9: 350 | H9: Repasse é pelo VGV Líquido
B10: Ticket Médio | C10: 230000
B11: VGV Líquido | C11: =C8-(C8*C19) -> 77280000 | E11: =C8*C13 -> 48300000
B13: CMV (% VGV) | C13: =C14+C17+(C16*C9/C8) -> 0.6
B14: Sinal / Terreno | C14: 0.01
B16: Custo de Obra (R$/unid) | C16: 117300
B17: Permuta | C17: 0.08
B19: Corretagem | C19: 0.04
B20: G&A | C20: 0.03
B21: Juros de Obra | C21: 0
B22: RET | C22: 0.04
B24: Desp. Comercial Extra | C24: 0.01
A28: . | D28: 0 | E28: 1 | F28: 2 | G28: 3 | H28: 4 | I28: 5 | J28: 6 | K28: 7 | L28: 8 | M28: 9 | N28: 10 | O28: 11 | P28: 12 | Q28: 13 | R28: 14 | S28: 15 | T28: 16 | U28: 17 | V28: 18 | W28: 19 | X28: 20 | Y28: 21 | Z28: 22 | AA28: 23 | AB28: 24 | AC28: 25 | AD28: 26 | AE28: 27 | AF28: 28 | AG28: =AF28+1 -> 29 | AH28: =AG28+1 -> 30 | AI28: =AH28+1 -> 31 | AJ28: =AI28+1 -> 32 | AK28: =AJ28+1 -> 33 | AL28: =AK28+1 -> 34 | AM28: =AL28+1 -> 35 | AN28: =AM28+1 -> 36
B30: VSO Mensal | D30: 0 | E30: 0.13 | F30: 0.1 | G30: 0.08 | H30: 0.05 | I30: 0.05 | J30: 0.05 | K30: 0.04 | L30: 0.04 | M30: 0.04 | N30: 0.04 | O30: 0.03 | P30: 0.03 | Q30: 0.03 | R30: 0.03 | S30: 0.03 | T30: 0.03 | U30: 0.02 | V30: 0.02 | W30: 0.02 | X30: 0.02 | Y30: 0.02 | Z30: 0.02 | AA30: 0.02 | AB30: 0.02 | AC30: 0.01 | AD30: 0.01 | AE30: 0.01 | AF30: 0.01 | AG30: 0 | AH30: 0 | AI30: 0 | AJ30: 0 | AK30: 0 | AL30: 0 | AM30: 0 | AN30: 0
B32: VSO Acumulado | D32: =D30 -> 0 | E32: =E30+D32 -> 0.13 | F32: =F30+E32 -> 0.23 | G32: =G30+F32 -> 0.31 | H32: =H30+G32 -> 0.36 | I32: =I30+H32 -> 0.41 | J32: =J30+I32 -> 0.46 | K32: =K30+J32 -> 0.5 | L32: =L30+K32 -> 0.54 | ... AN32: =AN30+AM32 -> 1
B33: Un. Vendidas no mês | D33: =$C$9*D30 -> 0 | E33: =$C$9*E30 -> 45.5 | F33: =$C$9*F30 -> 35 | G33: =$C$9*G30 -> 28 | H33: =$C$9*H30 -> 17.5 | I33: =$C$9*I30 -> 17.5 | J33: =$C$9*J30 -> 17.5 | K33: =$C$9*K30 -> 14 | ... AN33: =$C$9*AN30 -> 0
B34: Un. Vendidas Acumulado | D34: =D33 -> 0 | E34: =E33+D34 -> 45.5 | F34: =F33+E34 -> 80.5 | G34: =G33+F34 -> 108.5 | H34: =H33+G34 -> 126 | I34: =I33+H34 -> 143.5 | J34: =J33+I34 -> 161 | K34: =K33+J34 -> 175 | L34: =L33+K34 -> 189 | ... AN34: =AN33+AM34 -> 350
B35: VGV Vendido Acumulado | D35: =D32*C8 -> 0 | E35: =E32*$C$8 -> 10465000 | F35: =F32*$C$8 -> 18515000 | G35: =G32*$C$8 -> 24955000 | H35: =H32*$C$8 -> 28980000 | I35: =I32*$C$8 -> 33005000 | J35: =J32*$C$8 -> 37030000 | K35: =K32*$C$8 -> 40250000 | L35: =L32*$C$8 -> 43470000 | ... AN35: =AN32*$C$8 -> 80500000
B37: Avanço de Obra no Trimestre | D37: 0 | E37: 0 | F37: 0 | G37: 0 | H37: 0.02 | I37: 0.03 | J37: 0.04 | K37: 0.05 | L37: 0.06 | M37: 0.07 | N37: 0.08 | O37: 0.08 | P37: 0.09 | Q37: 0.09 | R37: 0.08 | S37: 0.08 | T37: 0.07 | U37: 0.06 | V37: 0.05 | W37: 0.03 | X37: 0.01 | Y37: 0.01 | Z37: 0 | AA37: 0 | AB37: 0 | AC37: 0 | AD37: 0 | AE37: 0 | AF37: 0 | AG37: 0 | AH37: 0 | AI37: 0 | AJ37: 0 | AK37: 0 | AL37: 0 | AM37: 0 | AN37: 0
B38: Obra Acumulada | D38: =D37 -> 0 | E38: =E37+D38 -> 0 | F38: =F37+E38 -> 0 | G38: =G37+F38 -> 0 | H38: =H37+G38 -> 0.02 | I38: =I37+H38 -> 0.05 | J38: =J37+I38 -> 0.09 | K38: =K37+J38 -> 0.14 | L38: =L37+K38 -> 0.2 | ... AN38: =AN37+AM38 -> 1
B39: Pré - Obra | D39: 0 | E39: 0 | F39: 0 | G39: 0 | H39: 0 | I39: 0 | J39: 0 | K39: 0 | L39: 0 | M39: 0 | N39: 0 | O39: 0 | P39: 0 | Q39: 0 | R39: 0 | S39: 0 | T39: 0 | U39: 0 | V39: 0 | W39: 0 | X39: 0 | Y39: 0 | Z39: 0 | AA39: 0 | AB39: 0 | AC39: 0 | AD39: 0 | AE39: 0 | AF39: 0 | AG39: 0 | AH39: 0 | AI39: 0 | AJ39: 0 | AK39: 0 | AL39: 0 | AM39: 0 | AN39: 0
B40: Custo do Terreno | D40: =C14*C8 -> 805000 | E40: =$C$17*$C$8*E30 -> 837200 | F40: =$C$17*$C$8*F30 -> 644000 | G40: =$C$17*$C$8*G30 -> 515200 | H40: =$C$17*$C$8*H30 -> 322000 | I40: =$C$17*$C$8*I30 -> 322000 | J40: =$C$17*$C$8*J30 -> 322000 | K40: =$C$17*$C$8*K30 -> 257600 | L40: =$C$17*$C$8*L30 -> 257600 | ... AN40: =$C$17*$C$8*AN30 -> 0
B41: Custo Incorrido no Mês | D41: =D40+(D39*$C$8)+(D37*$C$16*$C$9) -> 805000 | E41: =E40+(E39*$C$8)+(E37*$C$16*$C$9) -> 837200 | F41: =F40+(F39*$C$8)+(F37*$C$16*$C$9) -> 644000 | G41: =G40+(G39*$C$8)+(G37*$C$16*$C$9) -> 515200 | H41: =H40+(H39*$C$8)+(H37*$C$16*$C$9) -> 1143100 | I41: =I40+(I39*$C$8)+(I37*$C$16*$C$9) -> 1553650 | J41: =J40+(J39*$C$8)+(J37*$C$16*$C$9) -> 1964200 | K41: =K40+(K39*$C$8)+(K37*$C$16*$C$9) -> 2310350 | ... AN41: =AN40+(AN39*$C$8)+(AN37*$C$16*$C$9) -> 0
B42: Custo Incorrido Total | D42: =D41 -> 805000 | E42: =E41+D42 -> 1642200 | F42: =F41+E42 -> 2286200 | G42: =G41+F42 -> 2801400 | H42: =H41+G42 -> 3944500 | I42: =I41+H42 -> 5498150 | J42: =J41+I42 -> 7462350 | K42: =K41+J42 -> 9772700 | L42: =L41+K42 -> 12493600 | ... AN42: =AN41+AM42 -> 48300000
B44: PoC (Custo Incorrido / Custo Total) | D44: =D42/$E$11 -> 0.016666667 | E44: =E42/$E$11 -> 0.034 | F44: =F42/$E$11 -> 0.047333333 | G44: =G42/$E$11 -> 0.058 | H44: =H42/$E$11 -> 0.081666667 | I44: =I42/$E$11 -> 0.11383333 | J44: =J42/$E$11 -> 0.1545 | K44: =K42/$E$11 -> 0.20233333 | ... AN44: =AN42/$E$11 -> 1
B45: delta PoC (Incremental) | D45: =D44 -> 0.016666667 | E45: =E44-D44 -> 0.017333333 | F45: =F44-E44 -> 0.013333333 | G45: =G44-F44 -> 0.010666667 | H45: =H44-G44 -> 0.023666667 | I45: =I44-H44 -> 0.032166667 | J45: =J44-I44 -> 0.040666667 | K45: =K44-J44 -> 0.047833333 | L45: =L44-K44 -> 0.056333333 | ... AN45: =AN44-AM44 -> 0
B46: Receita Reconhecida Acumulada | D46: =D44*$C$11*D32 -> 0 | E46: =E44*$C$11*E32 -> 341577.6 | F46: =F44*$C$11*F32 -> 841321.6 | G46: =G44*$C$11*G32 -> 1389494.4 | H46: =H44*$C$11*H32 -> 2272032 | I46: =I44*$C$11*I32 -> 3606786.4 | J46: =J44*$C$11*J32 -> 5492289.6 | K46: =K44*$C$11*K32 -> 7818160 | ... AN46: =AN44*$C$11*AN32 -> 77280000
B47: Receita Incremental (Repasse) | D47: =D46 -> 0 | E47: =E46-D46 -> 341577.6 | F47: =F46-E46 -> 499744 | G47: =G46-F46 -> 548172.8 | H47: =H46-G46 -> 882537.6 | I47: =I46-H46 -> 1334754.4 | J47: =J46-I46 -> 1885503.2 | K47: =K46-J46 -> 2325870.4 | L47: =L46-K46 -> 2976310.4 | ... AN47: =AN46-AM46 -> 0
A49: . | B49: DRE
B51: Receita | D51: =D47 -> 0 | E51: =E47 -> 341577.6 | F51: =F47 -> 499744 | G51: =G47 -> 548172.8 | H51: =H47 -> 882537.6 | I51: =I47 -> 1334754.4 | J51: =J47 -> 1885503.2 | K51: =K47 -> 2325870.4 | ... AN51: =AN47 -> 0
B54: (-) COGS | D54: =D45*$C$13*$C$8 -> 805000 | E54: =E45*$C$13*$C$8 -> 837200 | F54: =F45*$C$13*$C$8 -> 644000 | G54: =G45*$C$13*$C$8 -> 515200 | H54: =H45*$C$13*$C$8 -> 1143100 | I54: =I45*$C$13*$C$8 -> 1553650 | J54: =J45*$C$13*$C$8 -> 1964200 | K54: =K45*$C$13*$C$8 -> 2310350 | ... AN54: =AN45*$C$13*$C$8 -> 0
B55: Custos Pré-Obra
B56: % da Receita
B58: (=) Lucro Bruto | D58: =D51-D54 -> -805000 | E58: =E51-E54 -> -495622.4 | F58: =F51-F54 -> -144256 | G58: =G51-G54 -> 32972.8 | H58: =H51-H54 -> -260562.4 | I58: =I51-I54 -> -218895.6 | J58: =J51-J54 -> -78696.8 | K58: =K51-K54 -> 15520.4 | ... AN58: =AN51-AN54 -> 0
B59: Margem Bruta [%] | E59: =IFERROR(E58/E51,0) -> -1.4509804 | F59: =IFERROR(F58/F51,0) -> -0.28865979 | G59: =IFERROR(G58/G51,0) -> 0.060150376 | H59: =IFERROR(H58/H51,0) -> -0.29524227 | I59: =IFERROR(I58/I51,0) -> -0.16399691 | J59: =IFERROR(J58/J51,0) -> -0.041737824 | K59: =IFERROR(K58/K51,0) -> 0.0066729427 | L59: =IFERROR(L58/L51,0) -> 0.085814437 | ... AK59: =IFERROR(AK58/AK51,0) -> 0
B61: (-) G&A | D61: =$C$20*$C$8/27 -> 89444.444 | E61: =$C$20*$C$8/27 -> 89444.444 | F61: =$C$20*$C$8/27 -> 89444.444 | G61: =$C$20*$C$8/27 -> 89444.444 | H61: =$C$20*$C$8/27 -> 89444.444 | I61: =$C$20*$C$8/27 -> 89444.444 | J61: =$C$20*$C$8/27 -> 89444.444 | K61: =$C$20*$C$8/27 -> 89444.444 | ... AD61: =$C$20*$C$8/27 -> 89444.444 | AE61: 0 | AF61: 0 | AG61: 0 | AH61: 0 | AI61: 0 | AJ61: 0 | AK61: 0 | AL61: 0 | AM61: 0 | AN61: 0
B62: (-) Despesas de Incorporação | D62: =$C$23*$C$8*0.075 -> 0 | E62: =$C$23*$C$8*0.075 -> 0 | F62: =$C$23*$C$8*0.075 -> 0 | G62: =$C$23*$C$8*0.075 -> 0 | H62: =$C$23*$C$8*0.025 -> 0 | I62: =$C$23*$C$8*0.025 -> 0 | J62: =$C$23*$C$8*0.025 -> 0 | K62: =$C$23*$C$8*0.025 -> 0 | L62: =$C$23*$C$8*0.025 -> 0 | M62: =$C$23*$C$8*0.025 -> 0 | N62: =$C$23*$C$8*0.025 -> 0 | O62: =$C$23*$C$8*0.025 -> 0 | ... S62: =$C$23*$C$8*0.025 -> 0 | T62: =$C$23*$C$8*0.0666666666666667 -> 0 | U62: =$C$23*$C$8*0.0666666666666667 -> 0 | V62: =$C$23*$C$8*0.0666666666666667 -> 0 | W62: =$C$23*$C$8*0.0666666666666667 -> 0 | X62: =$C$23*$C$8*0.0666666666666667 -> 0 | Y62: =$C$23*$C$8*0.0666666666666667 -> 0 | Z62: 0 | AA62: 0 | AB62: 0 | AC62: 0 | AD62: 0 | AE62: 0 | AF62: 0 | AG62: 0 | AH62: 0 | AI62: 0 | AJ62: 0 | AK62: 0 | AL62: 0 | AM62: 0 | AN62: 0
B63: (-) Despesas Comerciais Extras | D63: =$C$24*$C$8*0.175 -> 140875 | E63: =$C$24*$C$8*0.175 -> 140875 | F63: =$C$24*$C$8*0.175 -> 140875 | G63: =$C$24*$C$8*0.175 -> 140875 | H63: =$C$24*$C$8*0.0166666666666667 -> 13416.667 | I63: =$C$24*$C$8*0.0166666666666667 -> 13416.667 | J63: =$C$24*$C$8*0.0166666666666667 -> 13416.667 | K63: =$C$24*$C$8*0.0166666666666667 -> 13416.667 | L63: =$C$24*$C$8*0.0166666666666667 -> 13416.667 | M63: =$C$24*$C$8*0.0166666666666667 -> 13416.667 | N63: =$C$24*$C$8*0.0166666666666667 -> 13416.667 | O63: =$C$24*$C$8*0.0166666666666667 -> 13416.667 | ... Y63: =$C$24*$C$8*0.0166666666666667 -> 13416.667 | Z63: 0 | AA63: 0 | AB63: 0 | AC63: 0 | AD63: 0 | AE63: 0 | AF63: 0 | AG63: 0 | AH63: 0 | AI63: 0 | AJ63: 0 | AK63: 0 | AL63: 0 | AM63: 0 | AN63: 0
B65: (-) Juros de Obra | D65: =D37*$C$8*$C$21 -> 0 | E65: =E37*$C$8*$C$21 -> 0 | F65: =F37*$C$8*$C$21 -> 0 | G65: =G37*$C$8*$C$21 -> 0 | H65: =H37*$C$8*$C$21 -> 0 | I65: =I37*$C$8*$C$21 -> 0 | J65: =J37*$C$8*$C$21 -> 0 | K65: =K37*$C$8*$C$21 -> 0 | ... AN65: =AN37*$C$8*$C$21 -> 0
A68: . | B68: (=) EBIT | D68: =D58-D61-D62-D63-D65 -> -1035319.4 | E68: =E58-E61-E62-E63-E65 -> -725941.84 | F68: =F58-F61-F62-F63-F65 -> -374575.44 | G68: =G58-G61-G62-G63-G65 -> -197346.64 | H68: =H58-H61-H62-H63-H65 -> -363423.51 | I68: =I58-I61-I62-I63-I65 -> -321756.71 | J68: =J58-J61-J62-J63-J65 -> -181557.91 | K68: =K58-K61-K62-K63-K65 -> -87340.711 | ... AN68: =AN58-AN61-AN62-AN63-AN65 -> 0
B71: (-) Taxes | D71: =$C$22*D51 -> 0 | E71: =$C$22*E51 -> 13663.104 | F71: =$C$22*F51 -> 19989.76 | G71: =$C$22*G51 -> 21926.912 | H71: =$C$22*H51 -> 35301.504 | I71: =$C$22*I51 -> 53390.176 | J71: =$C$22*J51 -> 75420.128 | K71: =$C$22*K51 -> 93034.816 | ... AN71: =$C$22*AN51 -> 0
B73: FCFF | D73: 0 | E73: 1 | F73: 2 | G73: 3 | H73: 4 | I73: 5 | J73: 6 | K73: 7 | L73: 8 | M73: 9 | N73: 10 | O73: 11 | P73: 12 | Q73: 13 | R73: 14 | S73: 15 | T73: 16 | U73: 17 | V73: 18 | W73: 19 | X73: 20 | Y73: 21 | Z73: 22 | AA73: 23 | AB73: 24 | AC73: 25 | AD73: 26 | AE73: 27 | AF73: 28 | AG73: =AF73+1 -> 29 | AH73: =AG73+1 -> 30 | AI73: =AH73+1 -> 31 | AJ73: =AI73+1 -> 32 | AK73: =AJ73+1 -> 33 | AL73: =AK73+1 -> 34 | AM73: =AL73+1 -> 35 | AN73: =AM73+1 -> 36
B74: (+) Repasse Líq. | D74: =D47 -> 0 | E74: =E47 -> 341577.6 | F74: =F47 -> 499744 | G74: =G47 -> 548172.8 | H74: =H47 -> 882537.6 | I74: =I47 -> 1334754.4 | J74: =J47 -> 1885503.2 | K74: =K47 -> 2325870.4 | ... AN74: =AN47 -> 0
B75: (-) G&A | D75: =-$C$20*$C$8/27 -> -89444.444 | E75: =-$C$20*$C$8/27 -> -89444.444 | F75: =-$C$20*$C$8/27 -> -89444.444 | G75: =-$C$20*$C$8/27 -> -89444.444 | H75: =-$C$20*$C$8/27 -> -89444.444 | I75: =-$C$20*$C$8/27 -> -89444.444 | J75: =-$C$20*$C$8/27 -> -89444.444 | K75: =-$C$20*$C$8/27 -> -89444.444 | ... AD75: =-$C$20*$C$8/27 -> -89444.444 | AE75: 0 | AF75: 0 | AG75: 0 | AH75: 0 | AI75: 0 | AJ75: 0 | AK75: 0 | AL75: 0 | AM75: 0 | AN75: 0
B76: (-) Sinal Terreno | D76: =-$C$14*$C$8 -> -805000 | E76: 0 | F76: 0 | G76: 0 | H76: 0 | I76: 0 | J76: 0 | K76: 0 | L76: 0 | M76: 0 | N76: 0 | O76: 0 | P76: 0 | Q76: 0 | R76: 0 | S76: 0 | T76: 0 | U76: 0 | V76: 0 | W76: 0 | X76: 0 | Y76: 0 | Z76: 0 | AA76: 0 | AB76: 0 | AC76: 0 | AD76: 0 | AE76: 0 | AF76: 0 | AG76: 0 | AH76: 0 | AI76: 0 | AJ76: 0 | AK76: 0 | AL76: 0 | AM76: 0 | AN76: 0
B77: (-) Pré-Obra | D77: =-D39*$C$8 -> 0 | E77: =-E39*$C$8 -> 0 | F77: =-F39*$C$8 -> 0 | G77: =-G39*$C$8 -> 0 | H77: =-H39*$C$8 -> 0 | I77: =-I39*$C$8 -> 0 | J77: =-J39*$C$8 -> 0 | K77: =-K39*$C$8 -> 0 | ... AN77: =-AN39*$C$8 -> 0
B78: (-) Obra | D78: =-D37*$C$16*$C$9 -> 0 | E78: =-E37*$C$16*$C$9 -> 0 | F78: =-F37*$C$16*$C$9 -> 0 | G78: =-G37*$C$16*$C$9 -> 0 | H78: =-H37*$C$16*$C$9 -> -821100 | I78: =-I37*$C$16*$C$9 -> -1231650 | J78: =-J37*$C$16*$C$9 -> -1642200 | K78: =-K37*$C$16*$C$9 -> -2052750 | ... AN78: =-AN37*$C$16*$C$9 -> 0
B79: (-) Permuta | D79: =-D37*$C$8*$C$17 -> 0 | E79: =-E37*$C$8*$C$17 -> 0 | F79: =-F37*$C$8*$C$17 -> 0 | G79: =-G37*$C$8*$C$17 -> 0 | H79: =-H37*$C$8*$C$17 -> -128800 | I79: =-I37*$C$8*$C$17 -> -193200 | J79: =-J37*$C$8*$C$17 -> -257600 | K79: =-K37*$C$8*$C$17 -> -322000 | ... AN79: =-AN37*$C$8*$C$17 -> 0
B80: (-) Despesas de Incorporação | D80: =-$C$23*$C$8*0.075 -> 0 | E80: =-$C$23*$C$8*0.075 -> 0 | F80: =-$C$23*$C$8*0.075 -> 0 | G80: =-$C$23*$C$8*0.075 -> 0 | H80: =-$C$23*$C$8*0.025 -> 0 | I80: =-$C$23*$C$8*0.025 -> 0 | J80: =-$C$23*$C$8*0.025 -> 0 | K80: =-$C$23*$C$8*0.025 -> 0 | L80: =-$C$23*$C$8*0.025 -> 0 | M80: =-$C$23*$C$8*0.025 -> 0 | N80: =-$C$23*$C$8*0.025 -> 0 | O80: =-$C$23*$C$8*0.025 -> 0 | ... S80: =-$C$23*$C$8*0.025 -> 0 | T80: =-$C$23*$C$8*0.0666666666666667 -> 0 | U80: =-$C$23*$C$8*0.0666666666666667 -> 0 | V80: =-$C$23*$C$8*0.0666666666666667 -> 0 | W80: =-$C$23*$C$8*0.0666666666666667 -> 0 | X80: =-$C$23*$C$8*0.0666666666666667 -> 0 | Y80: =-$C$23*$C$8*0.0666666666666667 -> 0 | Z80: 0 | AA80: 0 | AB80: 0 | AC80: 0 | AD80: 0 | AE80: 0 | AF80: 0 | AG80: 0 | AH80: 0 | AI80: 0 | AJ80: 0 | AK80: 0 | AL80: 0 | AM80: 0 | AN80: 0
B81: (-) Despesas Comerciais Extras | D81: =-$C$24*$C$8*0.175 -> -140875 | E81: =-$C$24*$C$8*0.175 -> -140875 | F81: =-$C$24*$C$8*0.175 -> -140875 | G81: =-$C$24*$C$8*0.175 -> -140875 | H81: =-$C$24*$C$8*0.0166666666666667 -> -13416.667 | I81: =-$C$24*$C$8*0.0166666666666667 -> -13416.667 | J81: =-$C$24*$C$8*0.0166666666666667 -> -13416.667 | K81: =-$C$24*$C$8*0.0166666666666667 -> -13416.667 | L81: =-$C$24*$C$8*0.0166666666666667 -> -13416.667 | M81: =-$C$24*$C$8*0.0166666666666667 -> -13416.667 | N81: =-$C$24*$C$8*0.0166666666666667 -> -13416.667 | O81: =-$C$24*$C$8*0.0166666666666667 -> -13416.667 | ... Y81: =-$C$24*$C$8*0.0166666666666667 -> -13416.667 | Z81: 0 | AA81: 0 | AB81: 0 | AC81: 0 | AD81: 0 | AE81: 0 | AF81: 0 | AG81: 0 | AH81: 0 | AI81: 0 | AJ81: 0 | AK81: 0 | AL81: 0 | AM81: 0 | AN81: 0
B82: (-) Juros Obra | D82: =-D37*$C$8*$C$21 -> 0 | E82: =-E37*$C$8*$C$21 -> 0 | F82: =-F37*$C$8*$C$21 -> 0 | G82: =-G37*$C$8*$C$21 -> 0 | H82: =-H37*$C$8*$C$21 -> 0 | I82: =-I37*$C$8*$C$21 -> 0 | J82: =-J37*$C$8*$C$21 -> 0 | K82: =-K37*$C$8*$C$21 -> 0 | ... AN82: =-AN37*$C$8*$C$21 -> 0
B83: (-) RET | D83: =-D47*$C$22 -> 0 | E83: =-E47*$C$22 -> -13663.104 | F83: =-F47*$C$22 -> -19989.76 | G83: =-G47*$C$22 -> -21926.912 | H83: =-H47*$C$22 -> -35301.504 | I83: =-I47*$C$22 -> -53390.176 | J83: =-J47*$C$22 -> -75420.128 | K83: =-K47*$C$22 -> -93034.816 | ... AN83: =-AN47*$C$22 -> 0
B86: (=) FCFF | D86: =D75+D74+D76+D77+D78+D79+D80+D81+D82+D83-D71 -> -1035319.4 | E86: =E75+E74+E76+E77+E78+E79+E80+E81+E82+E83-E71 -> 83931.948 | F86: =F75+F74+F76+F77+F78+F79+F80+F81+F82+F83-F71 -> 229445.04 | G86: =G75+G74+G76+G77+G78+G79+G80+G81+G82+G83-G71 -> 273999.53 | H86: =H75+H74+H76+H77+H78+H79+H80+H81+H82+H83-H71 -> -240826.52 | I86: =I75+I74+I76+I77+I78+I79+I80+I81+I82+I83-I71 -> -299737.06 | J86: =J75+J74+J76+J77+J78+J79+J80+J81+J82+J83-J71 -> -267998.17 | K86: =K75+K74+K76+K77+K78+K79+K80+K81+K82+K83-K71 -> -337810.34 | ... AN86: =AN75+AN74+AN76+AN77+AN78+AN79+AN80+AN81+AN82+AN83-AN71 -> 0
B87: (=) FCFF Acumulado | D87: =D86 -> -1035319.4 | E87: =D87+E86 -> -951387.5 | F87: =E87+F86 -> -721942.46 | G87: =F87+G86 -> -447942.93 | H87: =G87+H86 -> -688769.45 | I87: =H87+I86 -> -988506.51 | J87: =I87+J86 -> -1256504.7 | K87: =J87+K86 -> -1594315 | L87: =K87+L86 -> -1808670.6 | ... AN87: =AM87+AN86 -> 19577600
B89: TIR Mensal | D89: =IRR(D86:AN86) -> 0.17647004
B90: TIR Anualizada | D90: =(1+D89)^12 -1 -> 6.0302451
B92: Lucro Líquido | D92: =AN87 -> 19577600
B93: Exposição Máxima | D93: =-MIN(D87:AM87) -> 1827051.8
B94: Exposição em Relação ao VGV (%) | D94: =D93/C8 -> 0.022696295
B95: Margem Líquida | D95: =D92/AN46 -> 0.25333333
B96: WACC | D96: 0.1266
B97: WACC Mensal | D97: =(1+D96)^(1/12) - 1 -> 0.0099831901
A98: . | B98: VPL | D98: =D86+NPV(D97,E86:AN86) -> 15896166
F105: Sensibilidade TIR por CMV x VSO
E107: Margem bruta | F107: =D89 -> 0.17647004 | G107: 0.17 | H107: 0.19 | I107: 0.21 | J107: 0.23 | K107: 0.25
E108: =1-F108 -> 0.33 | F108: 0.67 | G108: 0.14449204 | H108: 0.14449204 | I108: 0.14449204 | J108: 0.14449204 | K108: 0.14449204
E109: =1-F109 -> 0.35 | F109: 0.65 | G109: 0.16413442 | H109: 0.16413442 | I109: 0.16413442 | J109: 0.16413442 | K109: 0.16413442
E110: =1-F110 -> 0.37 | F110: 0.63 | G110: 0.18423684 | H110: 0.18423684 | I110: 0.18423684 | J110: 0.18423684 | K110: 0.18423684
E111: =1-F111 -> 0.39 | F111: 0.61 | G111: 0.20480546 | H111: 0.20480546 | I111: 0.20480546 | J111: 0.20480546 | K111: 0.20480546
E112: =1-F112 -> 0.41 | F112: 0.59 | G112: 0.22585946 | H112: 0.22585946 | I112: 0.22585946 | J112: 0.22585946 | K112: 0.22585946
E113: =1-F113 -> 0.43 | F113: 0.57 | G113: 0.24743219 | H113: 0.24743219 | I113: 0.24743219 | J113: 0.24743219 | K113: 0.24743219
E114: =1-F114 -> 0.45 | F114: 0.55 | G114: 0.26957215 | H114: 0.26957215 | I114: 0.26957215 | J114: 0.26957215 | K114: 0.26957215

Sheet Unit Riva
A1: hoi
B6: Premissas do Empreendimento
B8: VGV Total | C8: =C9*C10 -> 140000000 | H8: VGV Liquido = VGV Total - Corretagem
B9: Unidades | C9: 350 | H9: Repasse é pelo VGV Líquido
B10: Ticket Médio | C10: 400000
B11: VGV Líquido | C11: =C8-(C8*C19) -> 134400000 | E11: =C8*C13 -> 81200000
H12: =D89 -> 0.31895099 | I12: 0.68 | J12: 0.66 | K12: 0.64 | L12: 0.62 | M12: 0.6 | N12: 0.58
B13: CMV (% VGV) | C13: =C14+C16+C17 -> 0.58 | H13: 0 | I13: 0.11855127 | J13: 0.13373139 | K13: 0.14897294 | L13: 0.1643445 | M13: 0.17990847 | N13: 0.19572401
B14: Sinal / Terreno | C14: 0.01 | H14: 0.02 | I14: 0.13334056 | J14: 0.15012119 | K14: 0.16703002 | L14: 0.18414335 | M14: 0.20153135 | N14: 0.21926147
H15: 0.04 | I15: 0.1503202 | J15: 0.16899537 | K15: 0.18788127 | L15: 0.20706095 | M15: 0.2266115 | N15: 0.24660797
B16: Custo de Obra | C16: 0.49 | H16: 0.06 | I16: 0.1700818 | J16: 0.19102042 | K16: 0.21226335 | L16: 0.23389689 | M16: 0.25600185 | N16: 0.2786582
B17: Permuta | C17: 0.08 | H17: 0.08 | I17: 0.19342248 | J17: 0.21707204 | K17: 0.24111337 | L17: 0.2656286 | M17: 0.29069623 | N17: 0.31639682
H18: 0.1 | I18: 0.22139579 | J18: 0.24825426 | K18: 0.27554482 | L18: 0.30333606 | M18: 0.33169952 | N18: 0.36071598
B19: Corretagem | C19: 0.04
B20: G&A | C20: 0.03
B21: Juros de Obra | C21: 0
B22: RET | C22: 0.04
B23: Desp. Incorporação | C23: 0
B24: Desp. Comercial Extra | C24: 0.01
B25: VSO Trimestral | F25: 0.25 | I25: =(1-F25) * 20/75 -> 0.2 | L25: =(1-F25)*16/75 -> 0.16 | O25: =(1-F25)*10/75 -> 0.1 | R25: =(1-F25)*6/75 -> 0.06 | U25: =(1-F25)*6/75 -> 0.06 | X25: =(1-F25)*5/75 -> 0.05 | AA25: =(1-F25)*5/75 -> 0.05 | AD25: =(1-F25)*4/75 -> 0.04 | AG25: =(1-F25)*3/75 -> 0.03
D28: 0 | E28: 1 | F28: 2 | G28: 3 | H28: 4 | I28: 5 | J28: 6 | K28: 7 | L28: 8 | M28: 9 | N28: 10 | O28: 11 | P28: 12 | Q28: 13 | R28: 14 | S28: 15 | T28: 16 | U28: 17 | V28: 18 | W28: 19 | X28: 20 | Y28: 21 | Z28: 22 | AA28: 23 | AB28: 24 | AC28: 25 | AD28: 26 | AE28: 27 | AF28: 28 | AG28: =AF28+1 -> 29 | AH28: =AG28+1 -> 30 | AI28: =AH28+1 -> 31 | AJ28: =AI28+1 -> 32 | AK28: =AJ28+1 -> 33 | AL28: =AK28+1 -> 34 | AM28: =AL28+1 -> 35 | AN28: =AM28+1 -> 36
B30: VSO Mensal | D30: 0 | E30: 0.15 | F30: 0.12 | G30: 0.09 | H30: 0.07 | I30: 0.06 | J30: 0.06 | K30: 0.05 | L30: 0.05 | M30: 0.04 | N30: 0.04 | O30: 0.04 | P30: 0.03 | Q30: 0.03 | R30: 0.03 | S30: 0.03 | T30: 0.02 | U30: 0.02 | V30: 0.02 | W30: 0.02 | X30: 0.02 | Y30: 0.01 | Z30: 0 | AA30: 0 | AB30: 0 | AC30: 0 | AD30: 0 | AE30: 0 | AF30: 0 | AG30: 0 | AH30: 0 | AI30: 0 | AJ30: 0 | AK30: 0 | AL30: 0 | AM30: 0 | AN30: 0
B32: VSO Acumulado | D32: =D30 -> 0 | E32: =E30+D32 -> 0.15 | F32: =F30+E32 -> 0.27 | G32: =G30+F32 -> 0.36 | H32: =H30+G32 -> 0.43 | I32: =I30+H32 -> 0.49 | J32: =J30+I32 -> 0.55 | K32: =K30+J32 -> 0.6 | L32: =L30+K32 -> 0.65 | ... AN32: =AN30+AM32 -> 1
B33: Un. Vendidas no mês | D33: =$C$9*D30 -> 0 | E33: =$C$9*E30 -> 52.5 | F33: =$C$9*F30 -> 42 | G33: =$C$9*G30 -> 31.5 | H33: =$C$9*H30 -> 24.5 | I33: =$C$9*I30 -> 21 | J33: =$C$9*J30 -> 21 | K33: =$C$9*K30 -> 17.5 | ... AN33: =$C$9*AN30 -> 0
B34: Un. Vendidas Acumulado | D34: =D33 -> 0 | E34: =E33+D34 -> 52.5 | F34: =F33+E34 -> 94.5 | G34: =G33+F34 -> 126 | H34: =H33+G34 -> 150.5 | I34: =I33+H34 -> 171.5 | J34: =J33+I34 -> 192.5 | K34: =K33+J34 -> 210 | L34: =L33+K34 -> 227.5 | ... AN34: =AN33+AM34 -> 350
B35: VGV Vendido Acumulado | D35: =D32*C8 -> 0 | E35: =E32*$C$8 -> 21000000 | F35: =F32*$C$8 -> 37800000 | G35: =G32*$C$8 -> 50400000 | H35: =H32*$C$8 -> 60200000 | I35: =I32*$C$8 -> 68600000 | J35: =J32*$C$8 -> 77000000 | K35: =K32*$C$8 -> 84000000 | L35: =L32*$C$8 -> 91000000 | ... AN35: =AN32*$C$8 -> 1.4e+08
B37: Avanço de Obra no Trimestre | D37: 0 | E37: 0 | F37: 0 | G37: 0 | H37: 0.03 | I37: 0.04 | J37: 0.05 | K37: 0.06 | L37: 0.06 | M37: 0.07 | N37: 0.07 | O37: 0.07 | P37: 0.07 | Q37: 0.07 | R37: 0.07 | S37: 0.06 | T37: 0.05 | U37: 0.05 | V37: 0.04 | W37: 0.03 | X37: 0.03 | Y37: 0.02 | Z37: 0.02 | AA37: 0.02 | AB37: 0.01 | AC37: 0.01 | AD37: 0 | AE37: 0 | AF37: 0 | AG37: 0 | AH37: 0 | AI37: 0 | AJ37: 0 | AK37: 0 | AL37: 0 | AM37: 0 | AN37: 0
B38: Obra Acumulada | D38: =D37 -> 0 | E38: =E37+D38 -> 0 | F38: =F37+E38 -> 0 | G38: =G37+F38 -> 0 | H38: =H37+G38 -> 0.03 | I38: =I37+H38 -> 0.07 | J38: =J37+I38 -> 0.12 | K38: =K37+J38 -> 0.18 | L38: =L37+K38 -> 0.24 | ... AN38: =AN37+AM38 -> 1
B39: Pré - Obra | D39: 0 | E39: 0 | F39: 0 | G39: 0 | H39: 0 | I39: 0 | J39: 0 | K39: 0 | L39: 0 | M39: 0 | N39: 0 | O39: 0 | P39: 0 | Q39: 0 | R39: 0 | S39: 0 | T39: 0 | U39: 0 | V39: 0 | W39: 0 | X39: 0 | Y39: 0 | Z39: 0 | AA39: 0 | AB39: 0 | AC39: 0 | AD39: 0 | AE39: 0 | AF39: 0 | AG39: 0 | AH39: 0 | AI39: 0 | AJ39: 0 | AK39: 0 | AL39: 0 | AM39: 0 | AN39: 0
B40: Custo do Terreno | D40: =C14*C8 -> 1400000 | E40: =$C$17*$C$8*E30 -> 1680000 | F40: =$C$17*$C$8*F30 -> 1344000 | G40: =$C$17*$C$8*G30 -> 1008000 | H40: =$C$17*$C$8*H30 -> 784000 | I40: =$C$17*$C$8*I30 -> 672000 | J40: =$C$17*$C$8*J30 -> 672000 | K40: =$C$17*$C$8*K30 -> 560000 | L40: =$C$17*$C$8*L30 -> 560000 | ... AN40: =$C$17*$C$8*AN30 -> 0
B41: Custo Incorrido no Mês | D41: =D40+(D39*$C$8)+(D37*$C$16*$C$8) -> 1400000 | E41: =E40+(E39*$C$8)+(E37*$C$16*$C$8) -> 1680000 | F41: =F40+(F39*$C$8)+(F37*$C$16*$C$8) -> 1344000 | G41: =G40+(G39*$C$8)+(G37*$C$16*$C$8) -> 1008000 | H41: =H40+(H39*$C$8)+(H37*$C$16*$C$8) -> 2842000 | I41: =I40+(I39*$C$8)+(I37*$C$16*$C$8) -> 3416000 | J41: =J40+(J39*$C$8)+(J37*$C$16*$C$8) -> 4102000 | K41: =K40+(K39*$C$8)+(K37*$C$16*$C$8) -> 4676000 | ... AN41: =AN40+(AN39*$C$8)+(AN37*$C$16*$C$8) -> 0
B42: Custo Incorrido Total | D42: =D41 -> 1400000 | E42: =E41+D42 -> 3080000 | F42: =F41+E42 -> 4424000 | G42: =G41+F42 -> 5432000 | H42: =H41+G42 -> 8274000 | I42: =I41+H42 -> 11690000 | J42: =J41+I42 -> 15792000 | K42: =K41+J42 -> 20468000 | L42: =L41+K42 -> 25144000 | ... AN42: =AN41+AM42 -> 81200000
B44: PoC (Custo Incorrido / Custo Total) | D44: =D42/$E$11 -> 0.017241379 | E44: =E42/$E$11 -> 0.037931034 | F44: =F42/$E$11 -> 0.054482759 | G44: =G42/$E$11 -> 0.066896552 | H44: =H42/$E$11 -> 0.10189655 | I44: =I42/$E$11 -> 0.14396552 | J44: =J42/$E$11 -> 0.19448276 | K44: =K42/$E$11 -> 0.25206897 | ... AN44: =AN42/$E$11 -> 1
B45: delta PoC (Incremental) | D45: =D44 -> 0.017241379 | E45: =E44-D44 -> 0.020689655 | F45: =F44-E44 -> 0.016551724 | G45: =G44-F44 -> 0.012413793 | H45: =H44-G44 -> 0.035 | I45: =I44-H44 -> 0.042068966 | J45: =J44-I44 -> 0.050517241 | K45: =K44-J44 -> 0.057586207 | L45: =L44-K44 -> 0.057586207 | ... AN45: =AN44-AM44 -> 0
B46: Receita Reconhecida Acumulada | D46: =D44*$C$8*D32 -> 0 | E46: =E44*$C$11*E32 -> 764689.66 | F46: =F44*$C$11*F32 -> 1977070.3 | G46: =G44*$C$11*G32 -> 3236722.8 | H46: =H44*$C$11*H32 -> 5888805.5 | I46: =I44*$C$11*I32 -> 9480993.1 | J46: =J44*$C$11*J32 -> 14376166 | K46: =K44*$C$11*K32 -> 20326841 | L46: =L44*$C$11*L32 -> 27051476 | ... AN46: =AN44*$C$11*AN32 -> 1.344e+08
B47: Receita Incremental (Repasse) | D47: =D46 -> 0 | E47: =E46-D46 -> 764689.66 | F47: =F46-E46 -> 1212380.7 | G47: =G46-F46 -> 1259652.4 | H47: =H46-G46 -> 2652082.8 | I47: =I46-H46 -> 3592187.6 | J47: =J46-I46 -> 4895172.4 | K47: =K46-J46 -> 5950675.9 | L47: =L46-K46 -> 6724634.5 | ... AN47: =AN46-AM46 -> 0
A49: . | B49: DRE
B51: Receita | D51: =D47 -> 0 | E51: =E47 -> 764689.66 | F51: =F47 -> 1212380.7 | G51: =G47 -> 1259652.4 | H51: =H47 -> 2652082.8 | I51: =I47 -> 3592187.6 | J51: =J47 -> 4895172.4 | K51: =K47 -> 5950675.9 | ... AN51: =AN47 -> 0 | AO51: =SUM(D51:AK51) -> 1.344e+08
B54: (-) COGS | D54: =D45*$C$13*$C$8 -> 1400000 | E54: =E45*$C$13*$C$8 -> 1680000 | F54: =F45*$C$13*$C$8 -> 1344000 | G54: =G45*$C$13*$C$8 -> 1008000 | H54: =H45*$C$13*$C$8 -> 2842000 | I54: =I45*$C$13*$C$8 -> 3416000 | J54: =J45*$C$13*$C$8 -> 4102000 | K54: =K45*$C$13*$C$8 -> 4676000 | ... AN54: =AN45*$C$13*$C$8 -> 0
B55: Custos Pré-Obra
B56: % da Receita
B58: (=) Lucro Bruto | D58: =D51-D54 -> -1400000 | E58: =E51-E54 -> -915310.34 | F58: =F51-F54 -> -131619.31 | G58: =G51-G54 -> 251652.41 | H58: =H51-H54 -> -189917.24 | I58: =I51-I54 -> 176187.59 | J58: =J51-J54 -> 793172.41 | K58: =K51-K54 -> 1274675.9 | ... AN58: =AN51-AN54 -> 0
B61: (-) G&A | D61: =$C$20*$C$8/22 -> 190909.09 | E61: =$C$20*$C$8/22 -> 190909.09 | F61: =$C$20*$C$8/22 -> 190909.09 | G61: =$C$20*$C$8/22 -> 190909.09 | H61: =$C$20*$C$8/22 -> 190909.09 | I61: =$C$20*$C$8/22 -> 190909.09 | J61: =$C$20*$C$8/22 -> 190909.09 | K61: =$C$20*$C$8/22 -> 190909.09 | ... AC61: =$C$20*$C$8/22 -> 190909.09 | AD61: 0 | AE61: 0 | AF61: 0 | AG61: 0 | AH61: 0 | AI61: 0 | AJ61: 0 | AK61: 0
B62: (-) Despesas de Incorporação | D62: =$C$23*$C$8*0.075 -> 0 | E62: =$C$23*$C$8*0.075 -> 0 | F62: =$C$23*$C$8*0.075 -> 0 | G62: =$C$23*$C$8*0.075 -> 0 | H62: =$C$23*$C$8*0.01875 -> 0 | I62: =$C$23*$C$8*0.01875 -> 0 | J62: =$C$23*$C$8*0.01875 -> 0 | K62: =$C$23*$C$8*0.01875 -> 0 | L62: =$C$23*$C$8*0.01875 -> 0 | M62: =$C$23*$C$8*0.01875 -> 0 | N62: =$C$23*$C$8*0.01875 -> 0 | O62: =$C$23*$C$8*0.01875 -> 0 | ... W62: =$C$23*$C$8*0.01875 -> 0 | X62: =$C$23*$C$8*0.0666666666666667 -> 0 | Y62: =$C$23*$C$8*0.0666666666666667 -> 0 | Z62: =$C$23*$C$8*0.0666666666666667 -> 0 | AA62: =$C$23*$C$8*0.0666666666666667 -> 0 | AB62: =$C$23*$C$8*0.0666666666666667 -> 0 | AC62: =$C$23*$C$8*0.0666666666666667 -> 0 | AD62: 0 | AE62: 0 | AF62: 0 | AG62: 0 | AH62: 0 | AI62: 0 | AJ62: 0 | AK62: 0 | AL62: 0 | AM62: 0 | AN62: 0
B63: (-) Despesas Comerciais Extras | D63: =$C$24*$C$8*0.175 -> 245000 | E63: =$C$24*$C$8*0.175 -> 245000 | F63: =$C$24*$C$8*0.175 -> 245000 | G63: =$C$24*$C$8*0.175 -> 245000 | H63: =$C$24*$C$8*0.0136363636363636 -> 19090.909 | I63: =$C$24*$C$8*0.0136363636363636 -> 19090.909 | J63: =$C$24*$C$8*0.0136363636363636 -> 19090.909 | K63: =$C$24*$C$8*0.0136363636363636 -> 19090.909 | L63: =$C$24*$C$8*0.0136363636363636 -> 19090.909 | M63: =$C$24*$C$8*0.0136363636363636 -> 19090.909 | N63: =$C$24*$C$8*0.0136363636363636 -> 19090.909 | O63: =$C$24*$C$8*0.0136363636363636 -> 19090.909 | ... AC63: =$C$24*$C$8*0.0136363636363636 -> 19090.909 | AD63: 0 | AE63: 0 | AF63: 0 | AG63: 0 | AH63: 0 | AI63: 0 | AJ63: 0 | AK63: 0 | AL63: 0 | AM63: 0 | AN63: 0
A68: . | B68: (=) EBIT | D68: =D58-D61-D62-D63-D65 -> -1835909.1 | E68: =E58-E61-E62-E63-E65 -> -1351219.4 | F68: =F58-F61-F62-F63-F65 -> -567528.4 | G68: =G58-G61-G62-G63-G65 -> -184256.68 | H68: =H58-H61-H62-H63-H65 -> -399917.24 | I68: =I58-I61-I62-I63-I65 -> -33812.414 | J68: =J58-J61-J62-J63-J65 -> 583172.41 | K68: =K58-K61-K62-K63-K65 -> 1064675.9 | ... AN68: =AN58-AN61-AN62-AN63-AN65 -> 0
B71: (-) Taxes | D71: =$C$22*D51 -> 0 | E71: =$C$22*E51 -> 30587.586 | F71: =$C$22*F51 -> 48495.228 | G71: =$C$22*G51 -> 50386.097 | H71: =$C$22*H51 -> 106083.31 | I71: =$C$22*I51 -> 143687.5 | J71: =$C$22*J51 -> 195806.9 | K71: =$C$22*K51 -> 238027.03 | ... AN71: =$C$22*AN51 -> 0
B73: FCFF | D73: 0 | E73: 1 | F73: 2 | G73: 3 | H73: 4 | I73: 5 | J73: 6 | K73: 7 | L73: 8 | M73: 9 | N73: 10 | O73: 11 | P73: 12 | Q73: 13 | R73: 14 | S73: 15 | T73: 16 | U73: 17 | V73: 18 | W73: 19 | X73: 20 | Y73: 21 | Z73: 22 | AA73: 23 | AB73: 24 | AC73: 25 | AD73: 26 | AE73: 27 | AF73: 28 | AG73: =AF73+1 -> 29 | AH73: =AG73+1 -> 30 | AI73: =AH73+1 -> 31 | AJ73: =AI73+1 -> 32 | AK73: =AJ73+1 -> 33 | AL73: =AK73+1 -> 34 | AM73: =AL73+1 -> 35 | AN73: =AM73+1 -> 36
B74: (+) Repasse Líq. | D74: =D47 -> 0 | E74: =E47 -> 764689.66 | F74: =F47 -> 1212380.7 | G74: =G47 -> 1259652.4 | H74: =H47 -> 2652082.8 | I74: =I47 -> 3592187.6 | J74: =J47 -> 4895172.4 | K74: =K47 -> 5950675.9 | ... AN74: =AN47 -> 0
B75: (-) G&A | D75: =-$C$20*$C$8/22 -> -190909.09 | E75: =-$C$20*$C$8/22 -> -190909.09 | F75: =-$C$20*$C$8/22 -> -190909.09 | G75: =-$C$20*$C$8/22 -> -190909.09 | H75: =-$C$20*$C$8/22 -> -190909.09 | I75: =-$C$20*$C$8/22 -> -190909.09 | J75: =-$C$20*$C$8/22 -> -190909.09 | K75: =-$C$20*$C$8/22 -> -190909.09 | ... AC75: =-$C$20*$C$8/22 -> -190909.09 | AD75: 0 | AE75: 0 | AF75: 0 | AG75: 0 | AH75: 0 | AI75: 0 | AJ75: 0 | AK75: 0 | AL75: 0 | AM75: 0 | AN75: 0
B76: (-) Sinal Terreno | D76: =-$C$14*$C$8 -> -1400000 | E76: 0 | F76: 0 | G76: 0 | H76: 0 | I76: 0 | J76: 0 | K76: 0 | L76: 0 | M76: 0 | N76: 0 | O76: 0 | P76: 0 | Q76: 0 | R76: 0 | S76: 0 | T76: 0 | U76: 0 | V76: 0 | W76: 0 | X76: 0 | Y76: 0 | Z76: 0 | AA76: 0 | AB76: 0 | AC76: 0 | AD76: 0 | AE76: 0 | AF76: 0 | AG76: 0 | AH76: 0 | AI76: 0 | AJ76: 0 | AK76: 0 | AL76: 0 | AM76: 0 | AN76: 0
B77: (-) Pré-Obra | D77: =-D39*$C$8 -> 0 | E77: =-E39*$C$8 -> 0 | F77: =-F39*$C$8 -> 0 | G77: =-G39*$C$8 -> 0 | H77: =-H39*$C$8 -> 0 | I77: =-I39*$C$8 -> 0 | J77: =-J39*$C$8 -> 0 | K77: =-K39*$C$8 -> 0 | ... AN77: =-AN39*$C$8 -> 0
B78: (-) Obra | D78: =-D37*$C$16*$C$8 -> 0 | E78: =-E37*$C$16*$C$8 -> 0 | F78: =-F37*$C$16*$C$8 -> 0 | G78: =-G37*$C$16*$C$8 -> 0 | H78: =-H37*$C$16*$C$8 -> -2058000 | I78: =-I37*$C$16*$C$8 -> -2744000 | J78: =-J37*$C$16*$C$8 -> -3430000 | K78: =-K37*$C$16*$C$8 -> -4116000 | ... AN78: =-AN37*$C$16*$C$8 -> 0
B79: (-) Permuta | D79: =-D37*$C$8*$C$17 -> 0 | E79: =-E37*$C$8*$C$17 -> 0 | F79: =-F37*$C$8*$C$17 -> 0 | G79: =-G37*$C$8*$C$17 -> 0 | H79: =-H37*$C$8*$C$17 -> -336000 | I79: =-I37*$C$8*$C$17 -> -448000 | J79: =-J37*$C$8*$C$17 -> -560000 | K79: =-K37*$C$8*$C$17 -> -672000 | ... AN79: =-AN37*$C$8*$C$17 -> 0
B80: (-) Despesas de Incorporação | D80: =-$C$23*$C$8*0.075 -> 0 | E80: =-$C$23*$C$8*0.075 -> 0 | F80: =-$C$23*$C$8*0.075 -> 0 | G80: =-$C$23*$C$8*0.075 -> 0 | H80: =-$C$23*$C$8*0.01875 -> 0 | I80: =-$C$23*$C$8*0.01875 -> 0 | J80: =-$C$23*$C$8*0.01875 -> 0 | K80: =-$C$23*$C$8*0.01875 -> 0 | L80: =-$C$23*$C$8*0.01875 -> 0 | M80: =-$C$23*$C$8*0.01875 -> 0 | N80: =-$C$23*$C$8*0.01875 -> 0 | O80: =-$C$23*$C$8*0.01875 -> 0 | ... W80: =-$C$23*$C$8*0.01875 -> 0 | X80: =-$C$23*$C$8*0.0666666666666667 -> 0 | Y80: =-$C$23*$C$8*0.0666666666666667 -> 0 | Z80: =-$C$23*$C$8*0.0666666666666667 -> 0 | AA80: =-$C$23*$C$8*0.0666666666666667 -> 0 | AB80: =-$C$23*$C$8*0.0666666666666667 -> 0 | AC80: =-$C$23*$C$8*0.0666666666666667 -> 0 | AD80: 0 | AE80: 0 | AF80: 0 | AG80: 0 | AH80: 0 | AI80: 0 | AJ80: 0 | AK80: 0 | AL80: 0 | AM80: 0 | AN80: 0
B81: (-) Despesas Comerciais Extras | D81: =-$C$24*$C$8*0.175 -> -245000 | E81: =-$C$24*$C$8*0.175 -> -245000 | F81: =-$C$24*$C$8*0.175 -> -245000 | G81: =-$C$24*$C$8*0.175 -> -245000 | H81: =-$C$24*$C$8*0.0136 -> -19040 | I81: =-$C$24*$C$8*0.0136 -> -19040 | J81: =-$C$24*$C$8*0.0136 -> -19040 | K81: =-$C$24*$C$8*0.0136 -> -19040 | L81: =-$C$24*$C$8*0.0136 -> -19040 | M81: =-$C$24*$C$8*0.0136 -> -19040 | N81: =-$C$24*$C$8*0.0136 -> -19040 | O81: =-$C$24*$C$8*0.0136 -> -19040 | ... AC81: =-$C$24*$C$8*0.0136 -> -19040 | AD81: 0 | AE81: 0 | AF81: 0 | AG81: 0 | AH81: 0 | AI81: 0 | AJ81: 0 | AK81: 0 | AL81: 0 | AM81: 0 | AN81: 0
B82: (-) Juros Obra | D82: =-D37*$C$8*$C$21 -> 0 | E82: =-E37*$C$8*$C$21 -> 0 | F82: =-F37*$C$8*$C$21 -> 0 | G82: =-G37*$C$8*$C$21 -> 0 | H82: =-H37*$C$8*$C$21 -> 0 | I82: =-I37*$C$8*$C$21 -> 0 | J82: =-J37*$C$8*$C$21 -> 0 | K82: =-K37*$C$8*$C$21 -> 0 | ... P82: =-P37*$C$8*$C$21 -> 0 | Q82: =-$C$24*$C$8*0.0136363636363636 -> -19090.909 | R82: =-R37*$C$8*$C$21 -> 0 | S82: =-S37*$C$8*$C$21 -> 0 | T82: =-T37*$C$8*$C$21 -> 0 | U82: =-U37*$C$8*$C$21 -> 0 | V82: =-V37*$C$8*$C$21 -> 0 | W82: =-W37*$C$8*$C$21 -> 0 | X82: =-X37*$C$8*$C$21 -> 0 | Y82: =-Y37*$C$8*$C$21 -> 0 | ... AN82: =-AN37*$C$8*$C$21 -> 0
B83: (-) RET | D83: =-D47*$C$22 -> 0 | E83: =-E47*$C$22 -> -30587.586 | F83: =-F47*$C$22 -> -48495.228 | G83: =-G47*$C$22 -> -50386.097 | H83: =-H47*$C$22 -> -106083.31 | I83: =-I47*$C$22 -> -143687.5 | J83: =-J47*$C$22 -> -195806.9 | K83: =-K47*$C$22 -> -238027.03 | ... P83: =-P47*$C$22 -> -353360.77 | Q83: =-$C$24*$C$8*0.0136363636363636 -> -19090.909 | R83: =-R47*$C$22 -> -394181.3 | S83: =-S47*$C$22 -> -374169.6 | T83: =-T47*$C$22 -> -300601.82 | U83: =-U47*$C$22 -> -310278.62 | V83: =-V47*$C$22 -> -276808.39 | W83: =-W47*$C$22 -> -240613.08 | X83: =-X47*$C$22 -> -246656.44 | Y83: =-Y47*$C$22 -> -148303.45 | ... AN83: =-AN47*$C$22 -> 0
B86: (=) FCFF | D86: =D75+D74+D76+D77+D78+D79+D80+D81+D82+D83-D71 -> -1835909.1 | E86: =E75+E74+E76+E77+E78+E79+E80+E81+E82+E83-E71 -> 267605.39 | F86: =F75+F74+F76+F77+F78+F79+F80+F81+F82+F83-F71 -> 679481.14 | G86: =G75+G74+G76+G77+G78+G79+G80+G81+G82+G83-G71 -> 722971.13 | H86: =H75+H74+H76+H77+H78+H79+H80+H81+H82+H83-H71 -> -164032.95 | I86: =I75+I74+I76+I77+I78+I79+I80+I81+I82+I83-I71 -> -97136.512 | J86: =J75+J74+J76+J77+J78+J79+J80+J81+J82+J83-J71 -> 303609.53 | K86: =K75+K74+K76+K77+K78+K79+K80+K81+K82+K83-K71 -> 476672.7 | ... AN86: =AN75+AN74+AN76+AN77+AN78+AN79+AN80+AN81+AN82+AN83-AN71 -> 0
B87: (=) FCFF Acumulado | D87: =D86 -> -1835909.1 | E87: =D87+E86 -> -1568303.7 | F87: =E87+F86 -> -888822.56 | G87: =F87+G86 -> -165851.43 | H87: =G87+H86 -> -329884.38 | I87: =H87+I86 -> -427020.89 | J87: =I87+J86 -> -123411.36 | K87: =J87+K86 -> 353261.34 | L87: =K87+L86 -> 1541976 | ... AN87: =AM87+AN86 -> 36421073
B89: TIR Mensal | D89: =IRR(D86:AN86) -> 0.31895099
B90: TIR Anualizada | D90: =(1+D89)^12 -1 -> 26.716851
B92: Lucro Líquido | D92: =AN87 -> 36421073
B93: Exposição Máxima | D93: =-MIN(D87:AM87) -> 1835909.1
B94: Exposição em Relação ao VGV (%) | D94: =D93/C8 -> 0.013113636
B95: Margem Líquida | D95: =D92/AN46 -> 0.27099013
B96: WACC | D96: 0.1266
B97: WACC Mensal | D97: =(1+D96)^(1/12) - 1 -> 0.0099831901
A98: . | B98: VPL | D98: =D86+NPV(D97,E86:AN86) -> 31311652
D99: =D98/C11 -> 0.2329736

Sheet Unit INCC
B6: Premissas do Empreendimento
M7: Repasse de INCC
B8: VGV Total | C8: =C9*C10 -> 98000000 | H8: VGV Liquido = VGV Total - Corretagem
B9: Unidades | C9: 350 | H9: Repasse é pelo VGV Líquido | J9: =F20 -> 0.37890625 | K9: 0 | L9: 0.2 | M9: 0.4 | N9: 0.6 | O9: 0.8 | P9: 1 | R9: Margem REF | S9: 0.44 | X9: INCC
B10: Ticket Médio | C10: 280000 | J10: 0.12 | K10: 0.328 | L10: 0.34375 | M10: 0.35877863 | N10: 0.37313433 | O10: 0.38686131 | P10: 0.4 | R10: Margem Bruta | S10: =S9-(1-S9)*C27 -> 0.4064
B11: VGV Líquido | C11: =C8-(C8*C20) -> 94080000 | E11: =C8*C13 -> 58800000 | J11: 0.1 | K11: 0.34 | L11: 0.35294118 | M11: 0.36538462 | N11: 0.37735849 | O11: 0.38888889 | P11: 0.4
J12: 0.08 | K12: 0.352 | L12: 0.36220472 | M12: 0.37209302 | N12: 0.38167939 | O12: 0.39097744 | P12: 0.4 | T12: =S10 -> 0.4064 | U12: 0.12 | V12: 0.1 | W12: 0.08 | X12: 0.06 | Y12: 0.04 | Z12: 0.02
B13: CMV (% VGV) | C13: =SUM(C14:C17)+C24 -> 0.6 | E13: Custo Base (CMV) | F13: =C11*C13 -> 56448000 | I13: INCC | J13: 0.06 | K13: 0.364 | L13: 0.3715415 | M13: 0.37890625 | N13: 0.38610039 | O13: 0.39312977 | P13: 0.4 | T13: 0.36 | U13: 0.2832 | V13: 0.296 | W13: 0.3088 | X13: 0.3216 | Y13: 0.3344 | Z13: 0.3472
B14: Sinal / Terreno | C14: 0.02 | E14: VGV | F14: =C11 -> 94080000 | J14: 0.04 | K14: 0.376 | L14: 0.38095238 | M14: 0.38582677 | N14: 0.390625 | O14: 0.39534884 | P14: 0.4 | T14: 0.38 | U14: 0.3056 | V14: 0.318 | W14: 0.3304 | X14: 0.3428 | Y14: 0.3552 | Z14: 0.3676
J15: 0.02 | K15: 0.388 | L15: 0.39043825 | M15: 0.39285714 | N15: 0.39525692 | O15: 0.3976378 | P15: 0.4 | S15: Margem REF | T15: 0.4 | U15: 0.328 | V15: 0.34 | W15: 0.352 | X15: 0.364 | Y15: 0.376 | Z15: 0.388
B16: Custo de Obra | C16: 0.5 | E16: Custo Ajustado com INCC | F16: =F13*(1+C27) -> 59834880 | J16: 0.01 | T16: 0.42 | U16: 0.3504 | V16: 0.362 | W16: 0.3736 | X16: 0.3852 | Y16: 0.3968 | Z16: 0.4084
B17: Permuta | C17: 0.08 | E17: Preço Ajustado com INCC | F17: =F14*(1+C27*C28) -> 96337920 | T17: 0.44 | U17: 0.3728 | V17: 0.384 | W17: 0.3952 | X17: 0.4064 | Y17: 0.4176 | Z17: 0.4288
T18: 0.46 | U18: 0.3952 | V18: 0.406 | W18: 0.4168 | X18: 0.4276 | Y18: 0.4384 | Z18: 0.4492
I19: VSO Anual
B20: Corretagem | C20: 0.04 | E20: Margem Bruta | F20: =(F17-F16)/F17 -> 0.37890625 | I20: =SUM(F26:O26) -> 0
B21: G&A | C21: 0.03 | M21: CMV x LL
B22: Juros de Obra | C22: 0.02 | M22: Meses p 100% x TIR
B23: RET | C23: 0.04
B27: INCC | C27: 0.06
B28: % Repasse | C28: 0.4
D29: 0 | E29: 1 | F29: 2 | G29: 3 | H29: 4 | I29: 5 | J29: 6 | K29: 7 | L29: 8 | M29: 9 | N29: 10 | O29: 11 | P29: 12 | Q29: 13 | R29: 14 | S29: 15 | T29: 16 | U29: 17 | V29: 18 | W29: 19 | X29: 20 | Y29: 21 | Z29: 22 | AA29: 23 | AB29: 24 | AC29: 25 | AD29: 26 | AE29: 27 | AF29: 28 | AG29: =AF29+1 -> 29 | AH29: =AG29+1 -> 30 | AI29: =AH29+1 -> 31 | AJ29: =AI29+1 -> 32 | AK29: =AJ29+1 -> 33 | AL29: =AK29+1 -> 34 | AM29: =AL29+1 -> 35 | AN29: =AM29+1 -> 36
B31: VSO Mensal | D31: 0 | E31: 0.14 | F31: 0.1 | G31: 0.09 | H31: 0.06 | I31: 0.06 | J31: 0.05 | K31: 0.05 | L31: 0.05 | M31: 0.04 | N31: 0.04 | O31: 0.03 | P31: 0.03 | Q31: 0.03 | R31: 0.03 | S31: 0.02 | T31: 0.02 | U31: 0.02 | V31: 0.02 | W31: 0.02 | X31: 0.02 | Y31: 0.01 | Z31: 0.01 | AA31: 0.02 | AB31: 0.02 | AC31: 0.02 | AD31: 0 | AE31: =AD26*0.1 -> 0 | AF31: =AG26*0.6 -> 0 | AG31: =AG26*0.3 -> 0 | AH31: =AG26*0.1 -> 0 | AI31: 0 | AJ31: 0 | AK31: 0 | AL31: 0 | AM31: 0 | AN31: 0
B33: VSO Acumulado | D33: =D31 -> 0 | E33: =E31+D33 -> 0.14 | F33: =F31+E33 -> 0.24 | G33: =G31+F33 -> 0.33 | H33: =H31+G33 -> 0.39 | I33: =I31+H33 -> 0.45 | J33: =J31+I33 -> 0.5 | K33: =K31+J33 -> 0.55 | L33: =L31+K33 -> 0.6 | ... AN33: =AN31+AM33 -> 1
B34: Un. Vendidas no mês | D34: =$C$9*D31 -> 0 | E34: =$C$9*E31 -> 49 | F34: =$C$9*F31 -> 35 | G34: =$C$9*G31 -> 31.5 | H34: =$C$9*H31 -> 21 | I34: =$C$9*I31 -> 21 | J34: =$C$9*J31 -> 17.5 | K34: =$C$9*K31 -> 17.5 | ... AN34: =$C$9*AN31 -> 0
B35: Un. Vendidas Acumulado | D35: =D34 -> 0 | E35: =E34+D35 -> 49 | F35: =F34+E35 -> 84 | G35: =G34+F35 -> 115.5 | H35: =H34+G35 -> 136.5 | I35: =I34+H35 -> 157.5 | J35: =J34+I35 -> 175 | K35: =K34+J35 -> 192.5 | L35: =L34+K35 -> 210 | ... AN35: =AN34+AM35 -> 350
B36: VGV Vendido Acumulado | D36: =D33*C8 -> 0 | E36: =E33*$C$8 -> 13720000 | F36: =F33*$C$8 -> 23520000 | G36: =G33*$C$8 -> 32340000 | H36: =H33*$C$8 -> 38220000 | I36: =I33*$C$8 -> 44100000 | J36: =J33*$C$8 -> 49000000 | K36: =K33*$C$8 -> 53900000 | L36: =L33*$C$8 -> 58800000 | ... AN36: =AN33*$C$8 -> 98000000
B38: Avanço de Obra no Trimestre | D38: 0 | E38: 0 | F38: 0 | G38: 0 | H38: 0.01 | I38: 0.02 | J38: 0.02 | K38: 0.03 | L38: 0.03 | M38: 0.03 | N38: 0.04 | O38: 0.05 | P38: 0.05 | Q38: 0.06 | R38: 0.07 | S38: 0.07 | T38: 0.06 | U38: 0.05 | V38: 0.05 | W38: 0.05 | X38: 0.04 | Y38: 0.04 | Z38: 0.03 | AA38: 0.03 | AB38: 0.02 | AC38: 0.02 | AD38: 0.02 | AE38: 0.02 | AF38: 0.02 | AG38: 0.02 | AH38: 0.02 | AI38: 0.01 | AJ38: 0.01 | AK38: 0.01 | AL38: 0 | AM38: 0 | AN38: 0
B39: Obra Acumulada | D39: =D38 -> 0 | E39: =E38+D39 -> 0 | F39: =F38+E39 -> 0 | G39: =G38+F39 -> 0 | H39: =H38+G39 -> 0.01 | I39: =I38+H39 -> 0.03 | J39: =J38+I39 -> 0.05 | K39: =K38+J39 -> 0.08 | L39: =L38+K39 -> 0.11 | ... AN39: =AN38+AM39 -> 1
B40: Pré - Obra | D40: 0 | E40: 0 | F40: 0 | G40: 0 | H40: 0 | I40: 0 | J40: 0 | K40: 0 | L40: 0 | M40: 0 | N40: 0 | O40: 0 | P40: 0 | Q40: 0 | R40: 0 | S40: 0 | T40: 0 | U40: 0 | V40: 0 | W40: 0 | X40: 0 | Y40: 0 | Z40: 0 | AA40: 0 | AB40: 0 | AC40: 0 | AD40: 0 | AE40: 0 | AF40: 0 | AG40: 0 | AH40: 0 | AI40: 0 | AJ40: 0 | AK40: 0 | AL40: 0 | AM40: 0 | AN40: 0
B41: Custo do Terreno | D41: =C14*C8 -> 1960000 | E41: =$C$17*$C$8*E31 -> 1097600 | F41: =$C$17*$C$8*F31 -> 784000 | G41: =$C$17*$C$8*G31 -> 705600 | H41: =$C$17*$C$8*H31 -> 470400 | I41: =$C$17*$C$8*I31 -> 470400 | J41: =$C$17*$C$8*J31 -> 392000 | K41: =$C$17*$C$8*K31 -> 392000 | L41: =$C$17*$C$8*L31 -> 392000 | ... AN41: =$C$17*$C$8*AN31 -> 0
B42: Custo Incorrido no Mês | D42: =D41+(D40*$C$8)+(D38*$C$16*$C$8) -> 1960000 | E42: =E41+(E40*$C$8)+(E38*$C$16*$C$8) -> 1097600 | F42: =F41+(F40*$C$8)+(F38*$C$16*$C$8) -> 784000 | G42: =G41+(G40*$C$8)+(G38*$C$16*$C$8) -> 705600 | H42: =H41+(H40*$C$8)+(H38*$C$16*$C$8) -> 960400 | I42: =I41+(I40*$C$8)+(I38*$C$16*$C$8) -> 1450400 | J42: =J41+(J40*$C$8)+(J38*$C$16*$C$8) -> 1372000 | K42: =K41+(K40*$C$8)+(K38*$C$16*$C$8) -> 1862000 | ... AN42: =AN41+(AN40*$C$8)+(AN38*$C$16*$C$8) -> 0
B43: Custo Incorrido Total | D43: =D42 -> 1960000 | E43: =E42+D43 -> 3057600 | F43: =F42+E43 -> 3841600 | G43: =G42+F43 -> 4547200 | H43: =H42+G43 -> 5507600 | I43: =I42+H43 -> 6958000 | J43: =J42+I43 -> 8330000 | K43: =K42+J43 -> 10192000 | L43: =L42+K43 -> 12054000 | ... AN43: =AN42+AM43 -> 58800000
B45: PoC (Custo Incorrido / Custo Total) | D45: =D43/$E$11 -> 0.033333333 | E45: =E43/$E$11 -> 0.052 | F45: =F43/$E$11 -> 0.065333333 | G45: =G43/$E$11 -> 0.077333333 | H45: =H43/$E$11 -> 0.093666667 | I45: =I43/$E$11 -> 0.11833333 | J45: =J43/$E$11 -> 0.14166667 | K45: =K43/$E$11 -> 0.17333333 | ... AN45: =AN43/$E$11 -> 1
B46: delta PoC (Incremental) | D46: =D45 -> 0.033333333 | E46: =E45-D45 -> 0.018666667 | F46: =F45-E45 -> 0.013333333 | G46: =G45-F45 -> 0.012 | H46: =H45-G45 -> 0.016333333 | I46: =I45-H45 -> 0.024666667 | J46: =J45-I45 -> 0.023333333 | K46: =K45-J45 -> 0.031666667 | L46: =L45-K45 -> 0.031666667 | ... AN46: =AN45-AM45 -> 0
B47: Receita Reconhecida Acumulada | D47: =D45*$C$8*D33 -> 0 | E47: =E45*$C$11*E33 -> 684902.4 | F47: =F45*$C$11*F33 -> 1475174.4 | G47: =G45*$C$11*G33 -> 2400921.6 | H47: =H45*$C$11*H33 -> 3436742.4 | I47: =I45*$C$11*I33 -> 5009760 | J47: =J45*$C$11*J33 -> 6664000 | K47: =K45*$C$11*K33 -> 8968960 | L47: =L45*$C$11*L33 -> 11571840 | ... AN47: =AN45*$C$11*AN33 -> 94080000
B48: Receita Incremental (Repasse) | D48: =D47 -> 0 | E48: =E47-D47 -> 684902.4 | F48: =F47-E47 -> 790272 | G48: =G47-F47 -> 925747.2 | H48: =H47-G47 -> 1035820.8 | I48: =I47-H47 -> 1573017.6 | J48: =J47-I47 -> 1654240 | K48: =K47-J47 -> 2304960 | L48: =L47-K47 -> 2602880 | ... AN48: =AN47-AM47 -> 0
A50: . | B50: DRE
B52: Receita | D52: =D48 -> 0 | E52: =E48 -> 684902.4 | F52: =F48 -> 790272 | G52: =G48 -> 925747.2 | H52: =H48 -> 1035820.8 | I52: =I48 -> 1573017.6 | J52: =J48 -> 1654240 | K52: =K48 -> 2304960 | ... AN52: =AN48 -> 0
B55: (-) COGS | D55: =D46*$C$13*$C$8 -> 1960000 | E55: =E46*$C$13*$C$8 -> 1097600 | F55: =F46*$C$13*$C$8 -> 784000 | G55: =G46*$C$13*$C$8 -> 705600 | H55: =H46*$C$13*$C$8 -> 960400 | I55: =I46*$C$13*$C$8 -> 1450400 | J55: =J46*$C$13*$C$8 -> 1372000 | K55: =K46*$C$13*$C$8 -> 1862000 | ... AN55: =AN46*$C$13*$C$8 -> 0
B56: Custos Pré-Obra
B57: % da Receita
B59: (=) Lucro Bruto | D59: =D52-D55 -> -1960000 | E59: =E52-E55 -> -412697.6 | F59: =F52-F55 -> 6272 | G59: =G52-G55 -> 220147.2 | H59: =H52-H55 -> 75420.8 | I59: =I52-I55 -> 122617.6 | J59: =J52-J55 -> 282240 | K59: =K52-K55 -> 442960 | ... AN59: =AN52-AN55 -> 0
B60: Margem Bruta [%] | E60: =E59/E52 -> -0.6025641 | F60: =F59/F52 -> 0.0079365079 | G60: =G59/G52 -> 0.23780488 | H60: =H59/H52 -> 0.072812595 | I60: =I59/I52 -> 0.077950558 | J60: =J59/J52 -> 0.17061611 | K60: =K59/K52 -> 0.19217687 | L60: =L59/L52 -> 0.28463855 | ... AK60: =AK59/AK52 -> 0.375
B62: (-) G&A | D62: =$C$21*$C$8/34 -> 86470.588 | E62: =$C$21*$C$8/34 -> 86470.588 | F62: =$C$21*$C$8/34 -> 86470.588 | G62: =$C$21*$C$8/34 -> 86470.588 | H62: =$C$21*$C$8/34 -> 86470.588 | I62: =$C$21*$C$8/34 -> 86470.588 | J62: =$C$21*$C$8/34 -> 86470.588 | K62: =$C$21*$C$8/34 -> 86470.588 | ... AK62: =$C$21*$C$8/34 -> 86470.588
B64: % da Receita
A69: . | B69: (=) EBIT | D69: =D59-D62-D66 -> -2046470.6 | E69: =E59-E62-E66 -> -499168.19 | F69: =F59-F62-F66 -> -80198.588 | G69: =G59-G62-G66 -> 133676.61 | H69: =H59-H62-H66 -> -11049.788 | I69: =I59-I62-I66 -> 36147.012 | J69: =J59-J62-J66 -> 195769.41 | K69: =K59-K62-K66 -> 356489.41 | ... AN69: =AN59-AN62-AN66 -> 0
B72: (-) Taxes | D72: =$C$23*D52 -> 0 | E72: =$C$23*E52 -> 27396.096 | F72: =$C$23*F52 -> 31610.88 | G72: =$C$23*G52 -> 37029.888 | H72: =$C$23*H52 -> 41432.832 | I72: =$C$23*I52 -> 62920.704 | J72: =$C$23*J52 -> 66169.6 | K72: =$C$23*K52 -> 92198.4 | ... AN72: =$C$23*AN52 -> 0
B74: FCFF | D74: 0 | E74: 1 | F74: 2 | G74: 3 | H74: 4 | I74: 5 | J74: 6 | K74: 7 | L74: 8 | M74: 9 | N74: 10 | O74: 11 | P74: 12 | Q74: 13 | R74: 14 | S74: 15 | T74: 16 | U74: 17 | V74: 18 | W74: 19 | X74: 20 | Y74: 21 | Z74: 22 | AA74: 23 | AB74: 24 | AC74: 25 | AD74: 26 | AE74: 27 | AF74: 28 | AG74: =AF74+1 -> 29 | AH74: =AG74+1 -> 30 | AI74: =AH74+1 -> 31 | AJ74: =AI74+1 -> 32 | AK74: =AJ74+1 -> 33 | AL74: =AK74+1 -> 34 | AM74: =AL74+1 -> 35 | AN74: =AM74+1 -> 36
B75: (+) Repasse Líq. | D75: =D48 -> 0 | E75: =E48 -> 684902.4 | F75: =F48 -> 790272 | G75: =G48 -> 925747.2 | H75: =H48 -> 1035820.8 | I75: =I48 -> 1573017.6 | J75: =J48 -> 1654240 | K75: =K48 -> 2304960 | ... AN75: =AN48 -> 0
B76: (-) G&A | D76: =-$C$21*$C$8/34 -> -86470.588 | E76: =-$C$21*$C$8/34 -> -86470.588 | F76: =-$C$21*$C$8/34 -> -86470.588 | G76: =-$C$21*$C$8/34 -> -86470.588 | H76: =-$C$21*$C$8/34 -> -86470.588 | I76: =-$C$21*$C$8/34 -> -86470.588 | J76: =-$C$21*$C$8/34 -> -86470.588 | K76: =-$C$21*$C$8/34 -> -86470.588 | ... AK76: =-$C$21*$C$8/34 -> -86470.588 | AL76: 0 | AM76: 0 | AN76: 0
B77: (-) Sinal Terreno | D77: =-$C$14*$C$8 -> -1960000 | E77: 0 | F77: 0 | G77: 0 | H77: 0 | I77: 0 | J77: 0 | K77: 0 | L77: 0 | M77: 0 | N77: 0 | O77: 0 | P77: 0 | Q77: 0 | R77: 0 | S77: 0 | T77: 0 | U77: 0 | V77: 0 | W77: 0 | X77: 0 | Y77: 0 | Z77: 0 | AA77: 0 | AB77: 0 | AC77: 0 | AD77: 0 | AE77: 0 | AF77: 0 | AG77: 0 | AH77: 0 | AI77: 0 | AJ77: 0 | AK77: 0 | AL77: 0 | AM77: 0 | AN77: 0
B78: (-) Pré-Obra | D78: =-D40*$C$8 -> 0 | E78: =-E40*$C$8 -> 0 | F78: =-F40*$C$8 -> 0 | G78: =-G40*$C$8 -> 0 | H78: =-H40*$C$8 -> 0 | I78: =-I40*$C$8 -> 0 | J78: =-J40*$C$8 -> 0 | K78: =-K40*$C$8 -> 0 | ... AN78: =-AN40*$C$8 -> 0
B79: (-) Obra | D79: =-D38*$C$16*$C$8 -> 0 | E79: =-E38*$C$16*$C$8 -> 0 | F79: =-F38*$C$16*$C$8 -> 0 | G79: =-G38*$C$16*$C$8 -> 0 | H79: =-H38*$C$16*$C$8 -> -490000 | I79: =-I38*$C$16*$C$8 -> -980000 | J79: =-J38*$C$16*$C$8 -> -980000 | K79: =-K38*$C$16*$C$8 -> -1470000 | ... AN79: =-AN38*$C$16*$C$8 -> 0
B80: (-) Permuta | D80: =-D38*$C$8*$C$17 -> 0 | E80: =-E38*$C$8*$C$17 -> 0 | F80: =-F38*$C$8*$C$17 -> 0 | G80: =-G38*$C$8*$C$17 -> 0 | H80: =-H38*$C$8*$C$17 -> -78400 | I80: =-I38*$C$8*$C$17 -> -156800 | J80: =-J38*$C$8*$C$17 -> -156800 | K80: =-K38*$C$8*$C$17 -> -235200 | ... AN80: =-AN38*$C$8*$C$17 -> 0
B82: (-) RET | D82: =-$C$23*D48 -> 0 | E82: =-$C$23*E48 -> -27396.096 | F82: =-$C$23*F48 -> -31610.88 | G82: =-$C$23*G48 -> -37029.888 | H82: =-$C$23*H48 -> -41432.832 | I82: =-$C$23*I48 -> -62920.704 | J82: =-$C$23*J48 -> -66169.6 | K82: =-$C$23*K48 -> -92198.4 | ... AN82: =-$C$23*AN48 -> 0
B83: (-) Juros Obra | D83: =-D38*$C$8*$C$22 -> 0 | E83: =-E38*$C$8*$C$22 -> 0 | F83: =-F38*$C$8*$C$22 -> 0 | G83: =-G38*$C$8*$C$22 -> 0 | H83: =-H38*$C$8*$C$22 -> -19600 | I83: =-I38*$C$8*$C$22 -> -39200 | J83: =-J38*$C$8*$C$22 -> -39200 | K83: =-K38*$C$8*$C$22 -> -58800 | ... AN83: =-AN38*$C$8*$C$22 -> 0
B87: (=) FCFF | D87: =D76+D75+D77+D78+D79+D80+D81+D82+D83+D84 -> -2046470.6 | E87: =E76+E75+E77+E78+E79+E80+E81+E82+E83+E84 -> 571035.72 | F87: =F76+F75+F77+F78+F79+F80+F81+F82+F83+F84 -> 672190.53 | G87: =G76+G75+G77+G78+G79+G80+G81+G82+G83+G84 -> 802246.72 | H87: =H76+H75+H77+H78+H79+H80+H81+H82+H83+H84 -> 319917.38 | I87: =I76+I75+I77+I78+I79+I80+I81+I82+I83+I84 -> 247626.31 | J87: =J76+J75+J77+J78+J79+J80+J81+J82+J83+J84 -> 325599.81 | K87: =K76+K75+K77+K78+K79+K80+K81+K82+K83+K84 -> 362291.01 | ... AN87: =AN76+AN75+AN77+AN78+AN79+AN80+AN81+AN82+AN83+AN84 -> 0
B88: (=) FCFF Acumulado | D88: =D87 -> -2046470.6 | E88: =D88+E87 -> -1475434.9 | F88: =E88+F87 -> -803244.34 | G88: =F88+G87 -> -997.61694 | H88: =G88+H87 -> 318919.76 | I88: =H88+I87 -> 566546.07 | J88: =I88+J87 -> 892145.88 | K88: =J88+K87 -> 1254436.9 | L88: =K88+L87 -> 1902731.1 | ... AN88: =AM88+AN87 -> 26616800
B90: TIR Mensal | D90: =IRR(D87:AN87) -> 0.29007897
B91: TIR Anualizada | D91: =(1+D90)^12 -1 -> 20.251792
B93: Lucro Líquido | D93: =AN88 -> 26616800
B94: Exposição Máxima | D94: =-MIN(D88:AM88) -> 2046470.6
B95: Exposição em Relação ao VGV (%) | D95: =D94/C8 -> 0.020882353
B96: Margem Líquida | D96: =D93/AM47 -> 0.28291667
B97: WACC | D97: 0.1266
B98: WACC Mensal | D98: =(1+D97)^(1/12) - 1 -> 0.0099831901
A99: . | B99: VPL | D99: =D87+NPV(D98,E87:AN87) -> 22235914

Sheet Unit Parcelamento
B6: Premissas do Empreendimento
B8: VGV Total | C8: =C9*C10 -> 80500000 | H8: VGV Liquido = VGV Total - Corretagem
B9: Unidades | C9: 350 | H9: Repasse é pelo VGV Líquido
B10: Ticket Médio | C10: 230000
B11: VGV Líquido | C11: =C8-(C8*C19) -> 77280000 | E11: =C8*C13 -> 49105000
B13: CMV (% VGV) | C13: =C14+C15+C17+(C16*C9/C8) -> 0.61
B14: Sinal / Terreno | C14: 0
B15: Parcelamento Terreno | C15: 0.1
B16: Custo de Obra (R$/unid) | C16: 117300
B17: Permuta | C17: 0
B19: Corretagem | C19: 0.04
B20: G&A | C20: 0.03
B21: Juros de Obra | C21: 0
B22: RET | C22: 0.04
B23: Desp. Incorporação | C23: 0.02
B24: Desp. Comercial Extra | C24: 0.01
D28: 0 | E28: 1 | F28: 2 | G28: 3 | H28: 4 | I28: 5 | J28: 6 | K28: 7 | L28: 8 | M28: 9 | N28: 10 | O28: 11 | P28: 12 | Q28: 13 | R28: 14 | S28: 15 | T28: 16 | U28: 17 | V28: 18 | W28: 19 | X28: 20 | Y28: 21 | Z28: 22 | AA28: 23 | AB28: 24 | AC28: 25 | AD28: 26 | AE28: 27 | AF28: 28 | AG28: =AF28+1 -> 29 | AH28: =AG28+1 -> 30 | AI28: =AH28+1 -> 31 | AJ28: =AI28+1 -> 32 | AK28: =AJ28+1 -> 33 | AL28: =AK28+1 -> 34 | AM28: =AL28+1 -> 35 | AN28: =AM28+1 -> 36
B30: VSO Mensal | D30: 0 | E30: 0.13 | F30: 0.1 | G30: 0.08 | H30: 0.06 | I30: 0.06 | J30: 0.05 | K30: 0.05 | L30: 0.05 | M30: 0.04 | N30: 0.04 | O30: 0.04 | P30: 0.04 | Q30: 0.03 | R30: 0.03 | S30: 0.03 | T30: 0.03 | U30: 0.03 | V30: 0.02 | W30: 0.02 | X30: 0.02 | Y30: 0.01 | Z30: 0.01 | AA30: 0.01 | AB30: 0.01 | AC30: 0.01 | AD30: 0 | AE30: 0 | AF30: 0 | AG30: 0 | AH30: 0 | AI30: 0 | AJ30: 0 | AK30: 0 | AL30: 0 | AM30: 0 | AN30: 0
B32: VSO Acumulado | D32: =D30 -> 0 | E32: =E30+D32 -> 0.13 | F32: =F30+E32 -> 0.23 | G32: =G30+F32 -> 0.31 | H32: =H30+G32 -> 0.37 | I32: =I30+H32 -> 0.43 | J32: =J30+I32 -> 0.48 | K32: =K30+J32 -> 0.53 | L32: =L30+K32 -> 0.58 | ... AN32: =AN30+AM32 -> 1
B33: Un. Vendidas no mês | D33: =$C$9*D30 -> 0 | E33: =$C$9*E30 -> 45.5 | F33: =$C$9*F30 -> 35 | G33: =$C$9*G30 -> 28 | H33: =$C$9*H30 -> 21 | I33: =$C$9*I30 -> 21 | J33: =$C$9*J30 -> 17.5 | K33: =$C$9*K30 -> 17.5 | ... AN33: =$C$9*AN30 -> 0
B34: Un. Vendidas Acumulado | D34: =D33 -> 0 | E34: =E33+D34 -> 45.5 | F34: =F33+E34 -> 80.5 | G34: =G33+F34 -> 108.5 | H34: =H33+G34 -> 129.5 | I34: =I33+H34 -> 150.5 | J34: =J33+I34 -> 168 | K34: =K33+J34 -> 185.5 | L34: =L33+K34 -> 203 | ... AN34: =AN33+AM34 -> 350
B35: VGV Vendido Acumulado | D35: =D32*C8 -> 0 | E35: =E32*$C$8 -> 10465000 | F35: =F32*$C$8 -> 18515000 | G35: =G32*$C$8 -> 24955000 | H35: =H32*$C$8 -> 29785000 | I35: =I32*$C$8 -> 34615000 | J35: =J32*$C$8 -> 38640000 | K35: =K32*$C$8 -> 42665000 | L35: =L32*$C$8 -> 46690000 | ... AN35: =AN32*$C$8 -> 80500000
B37: Avanço de Obra no Trimestre | D37: 0 | E37: 0 | F37: 0 | G37: 0 | H37: 0.02 | I37: 0.03 | J37: 0.04 | K37: 0.05 | L37: 0.06 | M37: 0.07 | N37: 0.08 | O37: 0.08 | P37: 0.09 | Q37: 0.09 | R37: 0.08 | S37: 0.08 | T37: 0.07 | U37: 0.06 | V37: 0.05 | W37: 0.03 | X37: 0.01 | Y37: 0.01 | Z37: 0 | AA37: 0 | AB37: 0 | AC37: 0 | AD37: 0 | AE37: 0 | AF37: 0 | AG37: 0 | AH37: 0 | AI37: 0 | AJ37: 0 | AK37: 0 | AL37: 0 | AM37: 0 | AN37: 0
B38: Obra Acumulada | D38: =D37 -> 0 | E38: =E37+D38 -> 0 | F38: =F37+E38 -> 0 | G38: =G37+F38 -> 0 | H38: =H37+G38 -> 0.02 | I38: =I37+H38 -> 0.05 | J38: =J37+I38 -> 0.09 | K38: =K37+J38 -> 0.14 | L38: =L37+K38 -> 0.2 | ... AN38: =AN37+AM38 -> 1
B39: Pré - Obra | D39: 0 | E39: 0 | F39: 0 | G39: 0 | H39: 0 | I39: 0 | J39: 0 | K39: 0 | L39: 0 | M39: 0 | N39: 0 | O39: 0 | P39: 0 | Q39: 0 | R39: 0 | S39: 0 | T39: 0 | U39: 0 | V39: 0 | W39: 0 | X39: 0 | Y39: 0 | Z39: 0 | AA39: 0 | AB39: 0 | AC39: 0 | AD39: 0 | AE39: 0 | AF39: 0 | AG39: 0 | AH39: 0 | AI39: 0 | AJ39: 0 | AK39: 0 | AL39: 0 | AM39: 0 | AN39: 0
B40: Custo do Terreno | D40: =$C$15*$C$8/37 -> 217567.57 | E40: =$C$15*$C$8/37 -> 217567.57 | F40: =$C$15*$C$8/37 -> 217567.57 | G40: =$C$15*$C$8/37 -> 217567.57 | H40: =$C$15*$C$8/37 -> 217567.57 | I40: =$C$15*$C$8/37 -> 217567.57 | J40: =$C$15*$C$8/37 -> 217567.57 | K40: =$C$15*$C$8/37 -> 217567.57 | ... AN40: =$C$15*$C$8/37 -> 217567.57
B41: Custo Incorrido no Mês | D41: =D40+(D39*$C$8)+(D37*$C$16*$C$9) -> 217567.57 | E41: =E40+(E39*$C$8)+(E37*$C$16*$C$9) -> 217567.57 | F41: =F40+(F39*$C$8)+(F37*$C$16*$C$9) -> 217567.57 | G41: =G40+(G39*$C$8)+(G37*$C$16*$C$9) -> 217567.57 | H41: =H40+(H39*$C$8)+(H37*$C$16*$C$9) -> 1038667.6 | I41: =I40+(I39*$C$8)+(I37*$C$16*$C$9) -> 1449217.6 | J41: =J40+(J39*$C$8)+(J37*$C$16*$C$9) -> 1859767.6 | K41: =K40+(K39*$C$8)+(K37*$C$16*$C$9) -> 2270317.6 | ... AN41: =AN40+(AN39*$C$8)+(AN37*$C$16*$C$9) -> 217567.57
B42: Custo Incorrido Total | D42: =D41 -> 217567.57 | E42: =E41+D42 -> 435135.14 | F42: =F41+E42 -> 652702.7 | G42: =G41+F42 -> 870270.27 | H42: =H41+G42 -> 1908937.8 | I42: =I41+H42 -> 3358155.4 | J42: =J41+I42 -> 5217923 | K42: =K41+J42 -> 7488240.5 | L42: =L41+K42 -> 10169108 | ... AN42: =AN41+AM42 -> 49105000
B44: PoC (Custo Incorrido / Custo Total) | D44: =D42/$E$11 -> 0.0044306602 | E44: =E42/$E$11 -> 0.0088613203 | F44: =F42/$E$11 -> 0.013291981 | G44: =G42/$E$11 -> 0.017722641 | H44: =H42/$E$11 -> 0.038874612 | I44: =I42/$E$11 -> 0.06838724 | J44: =J42/$E$11 -> 0.10626052 | K44: =K42/$E$11 -> 0.15249446 | ... AN44: =AN42/$E$11 -> 1
B45: delta PoC (Incremental) | D45: =D44 -> 0.0044306602 | E45: =E44-D44 -> 0.0044306602 | F45: =F44-E44 -> 0.0044306602 | G45: =G44-F44 -> 0.0044306602 | H45: =H44-G44 -> 0.021151972 | I45: =I44-H44 -> 0.029512627 | J45: =J44-I44 -> 0.037873283 | K45: =K44-J44 -> 0.046233939 | L45: =L44-K44 -> 0.054594595 | ... AN45: =AN44-AM44 -> 0.0044306602
B46: Receita Reconhecida Acumulada | D46: =D44*$C$11*D32 -> 0 | E46: =E44*$C$11*E32 -> 89024.369 | F46: =F44*$C$11*F32 -> 236256.98 | G46: =G44*$C$11*G32 -> 424577.76 | H46: =H44*$C$11*H32 -> 1111565.1 | I46: =I44*$C$11*I32 -> 2272535.3 | J46: =J44*$C$11*J32 -> 3941670.3 | K46: =K44*$C$11*K32 -> 6245929.2 | ... AN46: =AN44*$C$11*AN32 -> 77280000
B47: Receita Incremental (Repasse) | D47: =D46 -> 0 | E47: =E46-D46 -> 89024.369 | F47: =F46-E46 -> 147232.61 | G47: =G46-F46 -> 188320.78 | H47: =H46-G46 -> 686987.36 | I47: =I46-H46 -> 1160970.2 | J47: =J46-I46 -> 1669135 | K47: =K46-J46 -> 2304258.8 | L47: =L46-K46 -> 3036299.4 | ... AN47: =AN46-AM46 -> 342401.42
A49: . | B49: DRE
B51: Receita | D51: =D47 -> 0 | E51: =E47 -> 89024.369 | F51: =F47 -> 147232.61 | G51: =G47 -> 188320.78 | H51: =H47 -> 686987.36 | I51: =I47 -> 1160970.2 | J51: =J47 -> 1669135 | K51: =K47 -> 2304258.8 | ... AN51: =AN47 -> 342401.42
B54: (-) COGS | D54: =D45*$C$13*$C$8 -> 217567.57 | E54: =E45*$C$13*$C$8 -> 217567.57 | F54: =F45*$C$13*$C$8 -> 217567.57 | G54: =G45*$C$13*$C$8 -> 217567.57 | H54: =H45*$C$13*$C$8 -> 1038667.6 | I54: =I45*$C$13*$C$8 -> 1449217.6 | J54: =J45*$C$13*$C$8 -> 1859767.6 | K54: =K45*$C$13*$C$8 -> 2270317.6 | ... AN54: =AN45*$C$13*$C$8 -> 217567.57
B55: Custos Pré-Obra
B56: % da Receita
B58: (=) Lucro Bruto | D58: =D51-D54 -> -217567.57 | E58: =E51-E54 -> -128543.2 | F58: =F51-F54 -> -70334.958 | G58: =G51-G54 -> -29246.788 | H58: =H51-H54 -> -351680.21 | I58: =I51-I54 -> -288247.35 | J58: =J51-J54 -> -190632.56 | K58: =K51-K54 -> 33941.254 | ... AN58: =AN51-AN54 -> 124833.85
B59: Margem Bruta [%] | E59: =IFERROR(E58/E51,0) -> -1.4439103 | F59: =IFERROR(F58/F51,0) -> -0.47771318 | G59: =IFERROR(G58/G51,0) -> -0.15530303 | H59: =IFERROR(H58/H51,0) -> -0.51191657 | I59: =IFERROR(I58/I51,0) -> -0.24828144 | J59: =IFERROR(J58/J51,0) -> -0.11421039 | K59: =IFERROR(K58/K51,0) -> 0.014729792 | L59: =IFERROR(L58/L51,0) -> 0.11706085 | ... AK59: =IFERROR(AK58/AK51,0) -> 0.36458333
B61: (-) G&A | D61: =$C$20*$C$8/27 -> 89444.444 | E61: =$C$20*$C$8/27 -> 89444.444 | F61: =$C$20*$C$8/27 -> 89444.444 | G61: =$C$20*$C$8/27 -> 89444.444 | H61: =$C$20*$C$8/27 -> 89444.444 | I61: =$C$20*$C$8/27 -> 89444.444 | J61: =$C$20*$C$8/27 -> 89444.444 | K61: =$C$20*$C$8/27 -> 89444.444 | ... AD61: =$C$20*$C$8/27 -> 89444.444 | AE61: 0 | AF61: 0 | AG61: 0 | AH61: 0 | AI61: 0 | AJ61: 0 | AK61: 0 | AL61: 0 | AM61: 0 | AN61: 0
B62: (-) Despesas de Incorporação | D62: =$C$23*$C$8*0.075 -> 120750 | E62: =$C$23*$C$8*0.075 -> 120750 | F62: =$C$23*$C$8*0.075 -> 120750 | G62: =$C$23*$C$8*0.075 -> 120750 | H62: =$C$23*$C$8*0.025 -> 40250 | I62: =$C$23*$C$8*0.025 -> 40250 | J62: =$C$23*$C$8*0.025 -> 40250 | K62: =$C$23*$C$8*0.025 -> 40250 | L62: =$C$23*$C$8*0.025 -> 40250 | M62: =$C$23*$C$8*0.025 -> 40250 | N62: =$C$23*$C$8*0.025 -> 40250 | O62: =$C$23*$C$8*0.025 -> 40250 | ... S62: =$C$23*$C$8*0.025 -> 40250 | T62: =$C$23*$C$8*0.0666666666666667 -> 107333.33 | U62: =$C$23*$C$8*0.0666666666666667 -> 107333.33 | V62: =$C$23*$C$8*0.0666666666666667 -> 107333.33 | W62: =$C$23*$C$8*0.0666666666666667 -> 107333.33 | X62: =$C$23*$C$8*0.0666666666666667 -> 107333.33 | Y62: =$C$23*$C$8*0.0666666666666667 -> 107333.33 | Z62: 0 | AA62: 0 | AB62: 0 | AC62: 0 | AD62: 0 | AE62: 0 | AF62: 0 | AG62: 0 | AH62: 0 | AI62: 0 | AJ62: 0 | AK62: 0 | AL62: 0 | AM62: 0 | AN62: 0
B63: (-) Despesas Comerciais Extras | D63: =$C$24*$C$8*0.175 -> 140875 | E63: =$C$24*$C$8*0.175 -> 140875 | F63: =$C$24*$C$8*0.175 -> 140875 | G63: =$C$24*$C$8*0.175 -> 140875 | H63: =$C$24*$C$8*0.0166666666666667 -> 13416.667 | I63: =$C$24*$C$8*0.0166666666666667 -> 13416.667 | J63: =$C$24*$C$8*0.0166666666666667 -> 13416.667 | K63: =$C$24*$C$8*0.0166666666666667 -> 13416.667 | L63: =$C$24*$C$8*0.0166666666666667 -> 13416.667 | M63: =$C$24*$C$8*0.0166666666666667 -> 13416.667 | N63: =$C$24*$C$8*0.0166666666666667 -> 13416.667 | O63: =$C$24*$C$8*0.0166666666666667 -> 13416.667 | ... Y63: =$C$24*$C$8*0.0166666666666667 -> 13416.667 | Z63: 0 | AA63: 0 | AB63: 0 | AC63: 0 | AD63: 0 | AE63: 0 | AF63: 0 | AG63: 0 | AH63: 0 | AI63: 0 | AJ63: 0 | AK63: 0 | AL63: 0 | AM63: 0 | AN63: 0
B65: (-) Juros de Obra | D65: =D37*$C$8*$C$21 -> 0 | E65: =E37*$C$8*$C$21 -> 0 | F65: =F37*$C$8*$C$21 -> 0 | G65: =G37*$C$8*$C$21 -> 0 | H65: =H37*$C$8*$C$21 -> 0 | I65: =I37*$C$8*$C$21 -> 0 | J65: =J37*$C$8*$C$21 -> 0 | K65: =K37*$C$8*$C$21 -> 0 | ... AN65: =AN37*$C$8*$C$21 -> 0
A68: . | B68: (=) EBIT | D68: =D58-D61-D62-D63-D65 -> -568637.01 | E68: =E58-E61-E62-E63-E65 -> -479612.64 | F68: =F58-F61-F62-F63-F65 -> -421404.4 | G68: =G58-G61-G62-G63-G65 -> -380316.23 | H68: =H58-H61-H62-H63-H65 -> -494791.32 | I68: =I58-I61-I62-I63-I65 -> -431358.46 | J68: =J58-J61-J62-J63-J65 -> -333743.67 | K68: =K58-K61-K62-K63-K65 -> -109169.86 | ... AN68: =AN58-AN61-AN62-AN63-AN65 -> 124833.85
B71: (-) Taxes | D71: =$C$22*D51 -> 0 | E71: =$C$22*E51 -> 3560.9747 | F71: =$C$22*F51 -> 5889.3044 | G71: =$C$22*G51 -> 7532.8312 | H71: =$C$22*H51 -> 27479.494 | I71: =$C$22*I51 -> 46438.809 | J71: =$C$22*J51 -> 66765.4 | K71: =$C$22*K51 -> 92170.353 | ... AN71: =$C$22*AN51 -> 13696.057
B73: FCFF | D73: 0 | E73: 1 | F73: 2 | G73: 3 | H73: 4 | I73: 5 | J73: 6 | K73: 7 | L73: 8 | M73: 9 | N73: 10 | O73: 11 | P73: 12 | Q73: 13 | R73: 14 | S73: 15 | T73: 16 | U73: 17 | V73: 18 | W73: 19 | X73: 20 | Y73: 21 | Z73: 22 | AA73: 23 | AB73: 24 | AC73: 25 | AD73: 26 | AE73: 27 | AF73: 28 | AG73: =AF73+1 -> 29 | AH73: =AG73+1 -> 30 | AI73: =AH73+1 -> 31 | AJ73: =AI73+1 -> 32 | AK73: =AJ73+1 -> 33 | AL73: =AK73+1 -> 34 | AM73: =AL73+1 -> 35 | AN73: =AM73+1 -> 36
B74: (+) Repasse Líq. | D74: =D47 -> 0 | E74: =E47 -> 89024.369 | F74: =F47 -> 147232.61 | G74: =G47 -> 188320.78 | H74: =H47 -> 686987.36 | I74: =I47 -> 1160970.2 | J74: =J47 -> 1669135 | K74: =K47 -> 2304258.8 | ... AN74: =AN47 -> 342401.42
B75: (-) G&A | D75: =-$C$20*$C$8/27 -> -89444.444 | E75: =-$C$20*$C$8/27 -> -89444.444 | F75: =-$C$20*$C$8/27 -> -89444.444 | G75: =-$C$20*$C$8/27 -> -89444.444 | H75: =-$C$20*$C$8/27 -> -89444.444 | I75: =-$C$20*$C$8/27 -> -89444.444 | J75: =-$C$20*$C$8/27 -> -89444.444 | K75: =-$C$20*$C$8/27 -> -89444.444 | ... AD75: =-$C$20*$C$8/27 -> -89444.444 | AE75: 0 | AF75: 0 | AG75: 0 | AH75: 0 | AI75: 0 | AJ75: 0 | AK75: 0 | AL75: 0 | AM75: 0 | AN75: 0
B76: (-) Sinal Terreno | D76: =-$C$14*$C$8 -> 0 | E76: 0 | F76: 0 | G76: 0 | H76: 0 | I76: 0 | J76: 0 | K76: 0 | L76: 0 | M76: 0 | N76: 0 | O76: 0 | P76: 0 | Q76: 0 | R76: 0 | S76: 0 | T76: 0 | U76: 0 | V76: 0 | W76: 0 | X76: 0 | Y76: 0 | Z76: 0 | AA76: 0 | AB76: 0 | AC76: 0 | AD76: 0 | AE76: 0 | AF76: 0 | AG76: 0 | AH76: 0 | AI76: 0 | AJ76: 0 | AK76: 0 | AL76: 0 | AM76: 0 | AN76: 0
B77: (-) Pré-Obra | D77: =-D39*$C$8 -> 0 | E77: =-E39*$C$8 -> 0 | F77: =-F39*$C$8 -> 0 | G77: =-G39*$C$8 -> 0 | H77: =-H39*$C$8 -> 0 | I77: =-I39*$C$8 -> 0 | J77: =-J39*$C$8 -> 0 | K77: =-K39*$C$8 -> 0 | ... AN77: =-AN39*$C$8 -> 0
B78: (-) Obra | D78: =-D37*$C$16*$C$9 -> 0 | E78: =-E37*$C$16*$C$9 -> 0 | F78: =-F37*$C$16*$C$9 -> 0 | G78: =-G37*$C$16*$C$9 -> 0 | H78: =-H37*$C$16*$C$9 -> -821100 | I78: =-I37*$C$16*$C$9 -> -1231650 | J78: =-J37*$C$16*$C$9 -> -1642200 | K78: =-K37*$C$16*$C$9 -> -2052750 | ... AN78: =-AN37*$C$16*$C$9 -> 0
B79: (-) Parcelamento Terreno | D79: =-$C$15*$C$8/37 -> -217567.57 | E79: =-$C$15*$C$8/37 -> -217567.57 | F79: =-$C$15*$C$8/37 -> -217567.57 | G79: =-$C$15*$C$8/37 -> -217567.57 | H79: =-$C$15*$C$8/37 -> -217567.57 | I79: =-$C$15*$C$8/37 -> -217567.57 | J79: =-$C$15*$C$8/37 -> -217567.57 | K79: =-$C$15*$C$8/37 -> -217567.57 | ... AN79: =-$C$15*$C$8/37 -> -217567.57
B80: (-) Despesas de Incorporação | D80: =-$C$23*$C$8*0.075 -> -120750 | E80: =-$C$23*$C$8*0.075 -> -120750 | F80: =-$C$23*$C$8*0.075 -> -120750 | G80: =-$C$23*$C$8*0.075 -> -120750 | H80: =-$C$23*$C$8*0.025 -> -40250 | I80: =-$C$23*$C$8*0.025 -> -40250 | J80: =-$C$23*$C$8*0.025 -> -40250 | K80: =-$C$23*$C$8*0.025 -> -40250 | L80: =-$C$23*$C$8*0.025 -> -40250 | M80: =-$C$23*$C$8*0.025 -> -40250 | N80: =-$C$23*$C$8*0.025 -> -40250 | O80: =-$C$23*$C$8*0.025 -> -40250 | ... S80: =-$C$23*$C$8*0.025 -> -40250 | T80: =-$C$23*$C$8*0.0666666666666667 -> -107333.33 | U80: =-$C$23*$C$8*0.0666666666666667 -> -107333.33 | V80: =-$C$23*$C$8*0.0666666666666667 -> -107333.33 | W80: =-$C$23*$C$8*0.0666666666666667 -> -107333.33 | X80: =-$C$23*$C$8*0.0666666666666667 -> -107333.33 | Y80: =-$C$23*$C$8*0.0666666666666667 -> -107333.33 | Z80: 0 | AA80: 0 | AB80: 0 | AC80: 0 | AD80: 0 | AE80: 0 | AF80: 0 | AG80: 0 | AH80: 0 | AI80: 0 | AJ80: 0 | AK80: 0 | AL80: 0 | AM80: 0 | AN80: 0
B81: (-) Despesas Comerciais Extras | D81: =-$C$24*$C$8*0.175 -> -140875 | E81: =-$C$24*$C$8*0.175 -> -140875 | F81: =-$C$24*$C$8*0.175 -> -140875 | G81: =-$C$24*$C$8*0.175 -> -140875 | H81: =-$C$24*$C$8*0.0166666666666667 -> -13416.667 | I81: =-$C$24*$C$8*0.0166666666666667 -> -13416.667 | J81: =-$C$24*$C$8*0.0166666666666667 -> -13416.667 | K81: =-$C$24*$C$8*0.0166666666666667 -> -13416.667 | L81: =-$C$24*$C$8*0.0166666666666667 -> -13416.667 | M81: =-$C$24*$C$8*0.0166666666666667 -> -13416.667 | N81: =-$C$24*$C$8*0.0166666666666667 -> -13416.667 | O81: =-$C$24*$C$8*0.0166666666666667 -> -13416.667 | ... Y81: =-$C$24*$C$8*0.0166666666666667 -> -13416.667 | Z81: 0 | AA81: 0 | AB81: 0 | AC81: 0 | AD81: 0 | AE81: 0 | AF81: 0 | AG81: 0 | AH81: 0 | AI81: 0 | AJ81: 0 | AK81: 0 | AL81: 0 | AM81: 0 | AN81: 0
B82: (-) Juros Obra | D82: =-D37*$C$8*$C$21 -> 0 | E82: =-E37*$C$8*$C$21 -> 0 | F82: =-F37*$C$8*$C$21 -> 0 | G82: =-G37*$C$8*$C$21 -> 0 | H82: =-H37*$C$8*$C$21 -> 0 | I82: =-I37*$C$8*$C$21 -> 0 | J82: =-J37*$C$8*$C$21 -> 0 | K82: =-K37*$C$8*$C$21 -> 0 | ... AN82: =-AN37*$C$8*$C$21 -> 0
B86: (=) FCFF | D86: =D75+D74+D76+D77+D78+D79+D80+D81+D82+D83-D71 -> -568637.01 | E86: =E75+E74+E76+E77+E78+E79+E80+E81+E82+E83-E71 -> -483173.62 | F86: =F75+F74+F76+F77+F78+F79+F80+F81+F82+F83-F71 -> -427293.71 | G86: =G75+G74+G76+G77+G78+G79+G80+G81+G82+G83-G71 -> -387849.06 | H86: =H75+H74+H76+H77+H78+H79+H80+H81+H82+H83-H71 -> -522270.82 | I86: =I75+I74+I76+I77+I78+I79+I80+I81+I82+I83-I71 -> -477797.27 | J86: =J75+J74+J76+J77+J78+J79+J80+J81+J82+J83-J71 -> -400509.07 | K86: =K75+K74+K76+K77+K78+K79+K80+K81+K82+K83-K71 -> -201340.21 | ... AN86: =AN75+AN74+AN76+AN77+AN78+AN79+AN80+AN81+AN82+AN83-AN71 -> 111137.79
B87: (=) FCFF Acumulado | D87: =D86 -> -568637.01 | E87: =D87+E86 -> -1051810.6 | F87: =E87+F86 -> -1479104.3 | G87: =F87+G86 -> -1866953.4 | H87: =G87+H86 -> -2389224.2 | I87: =H87+I86 -> -2867021.5 | J87: =I87+J86 -> -3267530.6 | K87: =J87+K86 -> -3468870.8 | L87: =K87+L86 -> -3378002.1 | ... AN87: =AM87+AN86 -> 20253800
B89: TIR Mensal | D89: =IRR(D86:AN86) -> 0.1583208
B90: TIR Anualizada | D90: =(1+D89)^12 -1 -> 4.8337292
B92: Lucro Líquido | D92: =AN87 -> 20253800
B93: Exposição Máxima | D93: =-MIN(D87:AM87) -> 3468870.8
B94: Exposição em Relação ao VGV (%) | D94: =D93/C8 -> 0.043091562
B95: Margem Líquida | D95: =D92/AN46 -> 0.26208333
B96: WACC | D96: 0.1266
B97: WACC Mensal | D97: =(1+D96)^(1/12) - 1 -> 0.0099831901
A98: . | B98: VPL | D98: =D86+NPV(D97,E86:AN86) -> 16637083
F105: Sensibilidade TIR por CMV x VSO
E107: Margem bruta | F107: =D89 -> 0.1583208 | G107: 0.17 | H107: 0.19 | I107: 0.21 | J107: 0.23 | K107: 0.25
E108: =1-F108 -> 0.33 | F108: 0.67 | G108: 0.11385009 | H108: 0.11385009 | I108: 0.11385009 | J108: 0.11385009 | K108: 0.11385009
E109: =1-F109 -> 0.35 | F109: 0.65 | G109: 0.12836677 | H109: 0.12836677 | I109: 0.12836677 | J109: 0.12836677 | K109: 0.12836677
E110: =1-F110 -> 0.37 | F110: 0.63 | G110: 0.14318161 | H110: 0.14318161 | I110: 0.14318161 | J110: 0.14318161 | K110: 0.14318161
E111: =1-F111 -> 0.39 | F111: 0.61 | G111: 0.1583208 | H111: 0.1583208 | I111: 0.1583208 | J111: 0.1583208 | K111: 0.1583208
E112: =1-F112 -> 0.41 | F112: 0.59 | G112: 0.17381425 | H112: 0.17381425 | I112: 0.17381425 | J112: 0.17381425 | K112: 0.17381425
E113: =1-F113 -> 0.43 | F113: 0.57 | G113: 0.1896964 | H113: 0.1896964 | I113: 0.1896964 | J113: 0.1896964 | K113: 0.1896964
E114: =1-F114 -> 0.45 | F114: 0.55 | G114: 0.20600698 | H114: 0.20600698 | I114: 0.20600698 | J114: 0.20600698 | K114: 0.20600698

Sheet Unit Cury
B6: Premissas do Empreendimento
B8: VGV Total | C8: =C9*C10 -> 112000000 | H8: VGV Liquido = VGV Total - Corretagem
B9: Unidades | C9: 350 | H9: Repasse é pelo VGV Líquido | N9: Margem REF
B10: Ticket Médio | C10: 320000 | N10: Margem Bruta
B11: VGV Líquido | C11: =C8-(C8*C19) -> 107520000 | E11: =C8*C13 -> 67200000 | N11: INCC | O11: 0.06
B13: CMV (% VGV) | C13: =C14+(C16*C9/C8) -> 0.6
B14: Parcelamento Terreno | C14: 0.14
E15: =C14*C8 -> 15680000
B16: Custo de Obra (R$/unid) | C16: 147200 | H16: WACC x g
B19: Corretagem | C19: 0.04
B20: G&A | C20: 0.03
B21: Juros de Obra | C21: 0
B22: RET | C22: 0.04
B23: Desp. Incorporação | C23: 0
B24: Desp. Comercial Extra | C24: 0.01
D28: 0 | E28: 1 | F28: 2 | G28: 3 | H28: 4 | I28: 5 | J28: 6 | K28: 7 | L28: 8 | M28: 9 | N28: 10 | O28: 11 | P28: 12 | Q28: 13 | R28: 14 | S28: 15 | T28: 16 | U28: 17 | V28: 18 | W28: 19 | X28: 20 | Y28: 21 | Z28: 22 | AA28: 23 | AB28: 24 | AC28: 25 | AD28: 26 | AE28: 27 | AF28: 28 | AG28: =AF28+1 -> 29 | AH28: =AG28+1 -> 30 | AI28: =AH28+1 -> 31 | AJ28: =AI28+1 -> 32 | AK28: =AJ28+1 -> 33 | AL28: =AK28+1 -> 34 | AM28: =AL28+1 -> 35 | AN28: =AM28+1 -> 36
B30: VSO Mensal | D30: 0 | E30: 0.2 | F30: 0.16 | G30: 0.12 | H30: 0.09 | I30: 0.08 | J30: 0.07 | K30: 0.06 | L30: 0.05 | M30: 0.04 | N30: 0.04 | O30: 0.03 | P30: 0.02 | Q30: 0.02 | R30: 0.01 | S30: 0.01 | T30: 0 | U30: 0 | V30: 0 | W30: 0 | X30: 0 | Y30: 0 | Z30: 0 | AA30: 0 | AB30: 0 | AC30: 0 | AD30: 0 | AE30: 0 | AF30: 0 | AG30: 0 | AH30: 0 | AI30: 0 | AJ30: 0 | AK30: 0 | AL30: 0 | AM30: 0 | AN30: 0
B32: VSO Acumulado | D32: =D30 -> 0 | E32: =E30+D32 -> 0.2 | F32: =F30+E32 -> 0.36 | G32: =G30+F32 -> 0.48 | H32: =H30+G32 -> 0.57 | I32: =I30+H32 -> 0.65 | J32: =J30+I32 -> 0.72 | K32: =K30+J32 -> 0.78 | L32: =L30+K32 -> 0.83 | ... AN32: =AN30+AM32 -> 1
B33: Un. Vendidas no mês | D33: =$C$9*D30 -> 0 | E33: =$C$9*E30 -> 70 | F33: =$C$9*F30 -> 56 | G33: =$C$9*G30 -> 42 | H33: =$C$9*H30 -> 31.5 | I33: =$C$9*I30 -> 28 | J33: =$C$9*J30 -> 24.5 | K33: =$C$9*K30 -> 21 | ... AN33: =$C$9*AN30 -> 0
B34: Un. Vendidas Acumulado | D34: =D33 -> 0 | E34: =E33+D34 -> 70 | F34: =F33+E34 -> 126 | G34: =G33+F34 -> 168 | H34: =H33+G34 -> 199.5 | I34: =I33+H34 -> 227.5 | J34: =J33+I34 -> 252 | K34: =K33+J34 -> 273 | L34: =L33+K34 -> 290.5 | ... AN34: =AN33+AM34 -> 350
B35: VGV Vendido Acumulado | D35: =D32*C8 -> 0 | E35: =E32*$C$8 -> 22400000 | F35: =F32*$C$8 -> 40320000 | G35: =G32*$C$8 -> 53760000 | H35: =H32*$C$8 -> 63840000 | I35: =I32*$C$8 -> 72800000 | J35: =J32*$C$8 -> 80640000 | K35: =K32*$C$8 -> 87360000 | L35: =L32*$C$8 -> 92960000 | ... AN35: =AN32*$C$8 -> 1.12e+08
B37: Avanço de Obra no Trimestre | D37: 0 | E37: 0 | F37: 0 | G37: 0 | H37: 0.02 | I37: 0.02 | J37: 0.03 | K37: 0.03 | L37: 0.04 | M37: 0.04 | N37: 0.05 | O37: 0.05 | P37: 0.06 | Q37: 0.06 | R37: 0.06 | S37: 0.06 | T37: 0.06 | U37: 0.05 | V37: 0.05 | W37: 0.05 | X37: 0.04 | Y37: 0.04 | Z37: 0.04 | AA37: 0.04 | AB37: 0.03 | AC37: 0.03 | AD37: 0.03 | AE37: 0.02 | AF37: 0 | AG37: 0 | AH37: 0 | AI37: 0 | AJ37: 0 | AK37: 0 | AL37: 0 | AM37: 0 | AN37: 0
B38: Obra Acumulada | D38: =D37 -> 0 | E38: =E37+D38 -> 0 | F38: =F37+E38 -> 0 | G38: =G37+F38 -> 0 | H38: =H37+G38 -> 0.02 | I38: =I37+H38 -> 0.04 | J38: =J37+I38 -> 0.07 | K38: =K37+J38 -> 0.1 | L38: =L37+K38 -> 0.14 | ... AN38: =AN37+AM38 -> 1
B39: Pré - Obra | D39: 0 | E39: 0 | F39: 0 | G39: 0 | H39: 0 | I39: 0 | J39: 0 | K39: 0 | L39: 0 | M39: 0 | N39: 0 | O39: 0 | P39: 0 | Q39: 0 | R39: 0 | S39: 0 | T39: 0 | U39: 0 | V39: 0 | W39: 0 | X39: 0 | Y39: 0 | Z39: 0 | AA39: 0 | AB39: 0 | AC39: 0 | AD39: 0 | AE39: 0 | AF39: 0 | AG39: 0 | AH39: 0 | AI39: 0 | AJ39: 0 | AK39: 0 | AL39: 0 | AM39: 0 | AN39: 0
B40: Custo do Terreno | D40: =$C$14*$C$8/37 -> 423783.78 | E40: =$C$14*$C$8/37 -> 423783.78 | F40: =$C$14*$C$8/37 -> 423783.78 | G40: =$C$14*$C$8/37 -> 423783.78 | H40: =$C$14*$C$8/37 -> 423783.78 | I40: =$C$14*$C$8/37 -> 423783.78 | J40: =$C$14*$C$8/37 -> 423783.78 | K40: =$C$14*$C$8/37 -> 423783.78 | ... AN40: =$C$14*$C$8/37 -> 423783.78
B41: Custo Incorrido no Mês | D41: =D40+(D39*$C$8)+(D37*$C$16*$C$9) -> 423783.78 | E41: =E40+(E39*$C$8)+(E37*$C$16*$C$9) -> 423783.78 | F41: =F40+(F39*$C$8)+(F37*$C$16*$C$9) -> 423783.78 | G41: =G40+(G39*$C$8)+(G37*$C$16*$C$9) -> 423783.78 | H41: =H40+(H39*$C$8)+(H37*$C$16*$C$9) -> 1454183.8 | I41: =I40+(I39*$C$8)+(I37*$C$16*$C$9) -> 1454183.8 | J41: =J40+(J39*$C$8)+(J37*$C$16*$C$9) -> 1969383.8 | K41: =K40+(K39*$C$8)+(K37*$C$16*$C$9) -> 1969383.8 | ... AN41: =AN40+(AN39*$C$8)+(AN37*$C$16*$C$9) -> 423783.78
B42: Custo Incorrido Total | D42: =D41 -> 423783.78 | E42: =E41+D42 -> 847567.57 | F42: =F41+E42 -> 1271351.4 | G42: =G41+F42 -> 1695135.1 | H42: =H41+G42 -> 3149318.9 | I42: =I41+H42 -> 4603502.7 | J42: =J41+I42 -> 6572886.5 | K42: =K41+J42 -> 8542270.3 | L42: =L41+K42 -> 11026854 | ... AN42: =AN41+AM42 -> 67200000
B44: PoC (Custo Incorrido / Custo Total) | D44: =D42/$E$11 -> 0.0063063063 | E44: =E42/$E$11 -> 0.012612613 | F44: =F42/$E$11 -> 0.018918919 | G44: =G42/$E$11 -> 0.025225225 | H44: =H42/$E$11 -> 0.046864865 | I44: =I42/$E$11 -> 0.068504505 | J44: =J42/$E$11 -> 0.097810811 | K44: =K42/$E$11 -> 0.12711712 | ... AN44: =AN42/$E$11 -> 1
B45: delta PoC (Incremental) | D45: =D44 -> 0.0063063063 | E45: =E44-D44 -> 0.0063063063 | F45: =F44-E44 -> 0.0063063063 | G45: =G44-F44 -> 0.0063063063 | H45: =H44-G44 -> 0.02163964 | I45: =I44-H44 -> 0.02163964 | J45: =J44-I44 -> 0.029306306 | K45: =K44-J44 -> 0.029306306 | L45: =L44-K44 -> 0.036972973 | ... AN45: =AN44-AM44 -> 0.0063063063
B46: Receita Reconhecida Acumulada | D46: =D44*$C$11*D32 -> 0 | E46: =E44*$C$11*E32 -> 271221.62 | F46: =F44*$C$11*F32 -> 732298.38 | G46: =G44*$C$11*G32 -> 1301863.8 | H46: =H44*$C$11*H32 -> 2872178.9 | I46: =I44*$C$11*I32 -> 4787642.8 | J46: =J44*$C$11*J32 -> 7571965.2 | K46: =K44*$C$11*K32 -> 10660753 | ... AN46: =AN44*$C$11*AN32 -> 1.0752e+08
B47: Receita Incremental (Repasse) | D47: =D46 -> 0 | E47: =E46-D46 -> 271221.62 | F47: =F46-E46 -> 461076.76 | G47: =G46-F46 -> 569565.41 | H47: =H46-G46 -> 1570315.1 | I47: =I46-H46 -> 1915464 | J47: =J46-I46 -> 2784322.4 | K47: =K46-J46 -> 3088788.1 | L47: =L46-K46 -> 3982908.9 | ... AN47: =AN46-AM46 -> 678054.05
A49: . | B49: DRE
B51: Receita | D51: =D47 -> 0 | E51: =E47 -> 271221.62 | F51: =F47 -> 461076.76 | G51: =G47 -> 569565.41 | H51: =H47 -> 1570315.1 | I51: =I47 -> 1915464 | J51: =J47 -> 2784322.4 | K51: =K47 -> 3088788.1 | ... AN51: =AN47 -> 678054.05
B54: (-) COGS | D54: =D45*$C$13*$C$8 -> 423783.78 | E54: =E45*$C$13*$C$8 -> 423783.78 | F54: =F45*$C$13*$C$8 -> 423783.78 | G54: =G45*$C$13*$C$8 -> 423783.78 | H54: =H45*$C$13*$C$8 -> 1454183.8 | I54: =I45*$C$13*$C$8 -> 1454183.8 | J54: =J45*$C$13*$C$8 -> 1969383.8 | K54: =K45*$C$13*$C$8 -> 1969383.8 | ... AN54: =AN45*$C$13*$C$8 -> 423783.78
B55: Custos Pré-Obra
B56: % da Receita
B58: (=) Lucro Bruto | D58: =D51-D54 -> -423783.78 | E58: =E51-E54 -> -152562.16 | F58: =F51-F54 -> 37292.973 | G58: =G51-G54 -> 145781.62 | H58: =H51-H54 -> 116131.29 | I58: =I51-I54 -> 461280.17 | J58: =J51-J54 -> 814938.64 | K58: =K51-K54 -> 1119404.3 | ... AN58: =AN51-AN54 -> 254270.27
B59: Margem Bruta [%] | E59: =IFERROR(E58/E51,0) -> -0.5625 | F59: =IFERROR(F58/F51,0) -> 0.080882353 | G59: =IFERROR(G58/G51,0) -> 0.25595238 | H59: =IFERROR(H58/H51,0) -> 0.073954131 | I59: =IFERROR(I58/I51,0) -> 0.24081903 | J59: =IFERROR(J58/J51,0) -> 0.29268831 | K59: =IFERROR(K58/K51,0) -> 0.3624089 | L59: =IFERROR(L58/L51,0) -> 0.37618865 | ... AK59: =IFERROR(AK58/AK51,0) -> 0.375
B61: (-) G&A | D61: =$C$20*$C$8/31 -> 108387.1 | E61: =$C$20*$C$8/31 -> 108387.1 | F61: =$C$20*$C$8/31 -> 108387.1 | G61: =$C$20*$C$8/31 -> 108387.1 | H61: =$C$20*$C$8/31 -> 108387.1 | I61: =$C$20*$C$8/31 -> 108387.1 | J61: =$C$20*$C$8/31 -> 108387.1 | K61: =$C$20*$C$8/31 -> 108387.1 | ... AH61: =$C$20*$C$8/31 -> 108387.1 | AI61: 0 | AJ61: 0 | AK61: 0 | AL61: 0 | AM61: 0 | AN61: 0
B62: (-) Despesas de Incorporação | D62: =$C$23*$C$8*0.075 -> 0 | E62: =$C$23*$C$8*0.075 -> 0 | F62: =$C$23*$C$8*0.075 -> 0 | G62: =$C$23*$C$8*0.075 -> 0 | H62: =$C$23*$C$8*0.0166666666666667 -> 0 | I62: =$C$23*$C$8*0.0166666666666667 -> 0 | J62: =$C$23*$C$8*0.0166666666666667 -> 0 | K62: =$C$23*$C$8*0.0166666666666667 -> 0 | L62: =$C$23*$C$8*0.0166666666666667 -> 0 | M62: =$C$23*$C$8*0.0166666666666667 -> 0 | N62: =$C$23*$C$8*0.0166666666666667 -> 0 | O62: =$C$23*$C$8*0.0166666666666667 -> 0 | ... Y62: =$C$23*$C$8*0.0166666666666667 -> 0 | Z62: =$C$23*$C$8*0.0666666666666667 -> 0 | AA62: =$C$23*$C$8*0.0666666666666667 -> 0 | AB62: =$C$23*$C$8*0.0666666666666667 -> 0 | AC62: =$C$23*$C$8*0.0666666666666667 -> 0 | AD62: =$C$23*$C$8*0.0666666666666667 -> 0 | AE62: =$C$23*$C$8*0.0666666666666667 -> 0 | AF62: 0 | AG62: 0 | AH62: 0 | AI62: 0 | AJ62: 0 | AK62: 0 | AL62: 0 | AM62: 0 | AN62: 0
B63: (-) Despesas Comerciais Extras | D63: =$C$24*$C$8*0.175 -> 196000 | E63: =$C$24*$C$8*0.175 -> 196000 | F63: =$C$24*$C$8*0.175 -> 196000 | G63: =$C$24*$C$8*0.175 -> 196000 | H63: =$C$24*$C$8*0.0125 -> 14000 | I63: =$C$24*$C$8*0.0125 -> 14000 | J63: =$C$24*$C$8*0.0125 -> 14000 | K63: =$C$24*$C$8*0.0125 -> 14000 | L63: =$C$24*$C$8*0.0125 -> 14000 | M63: =$C$24*$C$8*0.0125 -> 14000 | N63: =$C$24*$C$8*0.0125 -> 14000 | O63: =$C$24*$C$8*0.0125 -> 14000 | ... AE63: =$C$24*$C$8*0.0125 -> 14000 | AF63: 0 | AG63: 0 | AH63: 0 | AI63: 0 | AJ63: 0 | AK63: 0 | AL63: 0 | AM63: 0 | AN63: 0
B65: (-) Juros de Obra | D65: =D37*$C$8*$C$21 -> 0 | E65: =E37*$C$8*$C$21 -> 0 | F65: =F37*$C$8*$C$21 -> 0 | G65: =G37*$C$8*$C$21 -> 0 | H65: =H37*$C$8*$C$21 -> 0 | I65: =I37*$C$8*$C$21 -> 0 | J65: =J37*$C$8*$C$21 -> 0 | K65: =K37*$C$8*$C$21 -> 0 | ... AN65: =AN37*$C$8*$C$21 -> 0
A68: . | B68: (=) EBIT | D68: =D58-D61-D62-D63-D65 -> -728170.88 | E68: =E58-E61-E62-E63-E65 -> -456949.26 | F68: =F58-F61-F62-F63-F65 -> -267094.12 | G68: =G58-G61-G62-G63-G65 -> -158605.48 | H68: =H58-H61-H62-H63-H65 -> -6255.8103 | I68: =I58-I61-I62-I63-I65 -> 338893.08 | J68: =J58-J61-J62-J63-J65 -> 692551.54 | K68: =K58-K61-K62-K63-K65 -> 997017.18 | ... AN68: =AN58-AN61-AN62-AN63-AN65 -> 254270.27
B71: (-) Taxes | D71: =$C$22*D51 -> 0 | E71: =$C$22*E51 -> 10848.865 | F71: =$C$22*F51 -> 18443.07 | G71: =$C$22*G51 -> 22782.616 | H71: =$C$22*H51 -> 62812.603 | I71: =$C$22*I51 -> 76618.558 | J71: =$C$22*J51 -> 111372.9 | K71: =$C$22*K51 -> 123551.52 | ... AN71: =$C$22*AN51 -> 27122.162
B73: FCFF | D73: 0 | E73: 1 | F73: 2 | G73: 3 | H73: 4 | I73: 5 | J73: 6 | K73: 7 | L73: 8 | M73: 9 | N73: 10 | O73: 11 | P73: 12 | Q73: 13 | R73: 14 | S73: 15 | T73: 16 | U73: 17 | V73: 18 | W73: 19 | X73: 20 | Y73: 21 | Z73: 22 | AA73: 23 | AB73: 24 | AC73: 25 | AD73: 26 | AE73: 27 | AF73: 28 | AG73: =AF73+1 -> 29 | AH73: =AG73+1 -> 30 | AI73: =AH73+1 -> 31 | AJ73: =AI73+1 -> 32 | AK73: =AJ73+1 -> 33 | AL73: =AK73+1 -> 34 | AM73: =AL73+1 -> 35 | AN73: =AM73+1 -> 36
B74: (+) Repasse Líq. | D74: =D47 -> 0 | E74: =E47 -> 271221.62 | F74: =F47 -> 461076.76 | G74: =G47 -> 569565.41 | H74: =H47 -> 1570315.1 | I74: =I47 -> 1915464 | J74: =J47 -> 2784322.4 | K74: =K47 -> 3088788.1 | ... AN74: =AN47 -> 678054.05
B75: (-) G&A | D75: =-$C$20*$C$8/31 -> -108387.1 | E75: =-$C$20*$C$8/31 -> -108387.1 | F75: =-$C$20*$C$8/31 -> -108387.1 | G75: =-$C$20*$C$8/31 -> -108387.1 | H75: =-$C$20*$C$8/31 -> -108387.1 | I75: =-$C$20*$C$8/31 -> -108387.1 | J75: =-$C$20*$C$8/31 -> -108387.1 | K75: =-$C$20*$C$8/31 -> -108387.1 | ... AH75: =-$C$20*$C$8/31 -> -108387.1 | AI75: 0 | AJ75: 0 | AK75: 0 | AL75: 0 | AM75: 0 | AN75: 0
B76: (-) Custo Terreno | D76: =-$C$14*$C$8/37 -> -423783.78 | E76: =-$C$14*$C$8/37 -> -423783.78 | F76: =-$C$14*$C$8/37 -> -423783.78 | G76: =-$C$14*$C$8/37 -> -423783.78 | H76: =-$C$14*$C$8/37 -> -423783.78 | I76: =-$C$14*$C$8/37 -> -423783.78 | J76: =-$C$14*$C$8/37 -> -423783.78 | K76: =-$C$14*$C$8/37 -> -423783.78 | ... AN76: =-$C$14*$C$8/37 -> -423783.78
B77: (-) Pré-Obra | D77: =-D39*$C$8 -> 0 | E77: =-E39*$C$8 -> 0 | F77: =-F39*$C$8 -> 0 | G77: =-G39*$C$8 -> 0 | H77: =-H39*$C$8 -> 0 | I77: =-I39*$C$8 -> 0 | J77: =-J39*$C$8 -> 0 | K77: =-K39*$C$8 -> 0 | ... AN77: =-AN39*$C$8 -> 0
B78: (-) Obra | D78: =-D37*$C$16*$C$9 -> 0 | E78: =-E37*$C$16*$C$9 -> 0 | F78: =-F37*$C$16*$C$9 -> 0 | G78: =-G37*$C$16*$C$9 -> 0 | H78: =-H37*$C$16*$C$9 -> -1030400 | I78: =-I37*$C$16*$C$9 -> -1030400 | J78: =-J37*$C$16*$C$9 -> -1545600 | K78: =-K37*$C$16*$C$9 -> -1545600 | ... AN78: =-AN37*$C$16*$C$9 -> 0
B79: (-) Permuta | D79: =-D37*$C$8*$C$17 -> 0 | E79: =-E37*$C$8*$C$17 -> 0 | F79: =-F37*$C$8*$C$17 -> 0 | G79: =-G37*$C$8*$C$17 -> 0 | H79: =-H37*$C$8*$C$17 -> 0 | I79: =-I37*$C$8*$C$17 -> 0 | J79: =-J37*$C$8*$C$17 -> 0 | K79: =-K37*$C$8*$C$17 -> 0 | ... AN79: =-AN37*$C$8*$C$17 -> 0
B80: (-) Despesas de Incorporação | D80: =-$C$23*$C$8*0.075 -> 0 | E80: =-$C$23*$C$8*0.075 -> 0 | F80: =-$C$23*$C$8*0.075 -> 0 | G80: =-$C$23*$C$8*0.075 -> 0 | H80: =-$C$23*$C$8*0.0166666666666667 -> 0 | I80: =-$C$23*$C$8*0.0166666666666667 -> 0 | J80: =-$C$23*$C$8*0.0166666666666667 -> 0 | K80: =-$C$23*$C$8*0.0166666666666667 -> 0 | L80: =-$C$23*$C$8*0.0166666666666667 -> 0 | M80: =-$C$23*$C$8*0.0166666666666667 -> 0 | N80: =-$C$23*$C$8*0.0166666666666667 -> 0 | O80: =-$C$23*$C$8*0.0166666666666667 -> 0 | ... Y80: =-$C$23*$C$8*0.0166666666666667 -> 0 | Z80: =-$C$23*$C$8*0.0666666666666667 -> 0 | AA80: =-$C$23*$C$8*0.0666666666666667 -> 0 | AB80: =-$C$23*$C$8*0.0666666666666667 -> 0 | AC80: =-$C$23*$C$8*0.0666666666666667 -> 0 | AD80: =-$C$23*$C$8*0.0666666666666667 -> 0 | AE80: =-$C$23*$C$8*0.0666666666666667 -> 0 | AF80: 0 | AG80: 0 | AH80: 0 | AI80: 0 | AJ80: 0 | AK80: 0 | AL80: 0 | AM80: 0 | AN80: 0
B81: (-) Despesas Comerciais Extras | D81: =-$C$24*$C$8*0.175 -> -196000 | E81: =-$C$24*$C$8*0.175 -> -196000 | F81: =-$C$24*$C$8*0.175 -> -196000 | G81: =-$C$24*$C$8*0.175 -> -196000 | H81: =-$C$24*$C$8*0.0125 -> -14000 | I81: =-$C$24*$C$8*0.0125 -> -14000 | J81: =-$C$24*$C$8*0.0125 -> -14000 | K81: =-$C$24*$C$8*0.0125 -> -14000 | L81: =-$C$24*$C$8*0.0125 -> -14000 | M81: =-$C$24*$C$8*0.0125 -> -14000 | N81: =-$C$24*$C$8*0.0125 -> -14000 | O81: =-$C$24*$C$8*0.0125 -> -14000 | ... AE81: =-$C$24*$C$8*0.0125 -> -14000 | AF81: 0 | AG81: 0 | AH81: 0 | AI81: 0 | AJ81: 0 | AK81: 0 | AL81: 0 | AM81: 0 | AN81: 0
B82: (-) Juros Obra | D82: =-D37*$C$8*$C$21 -> 0 | E82: =-E37*$C$8*$C$21 -> 0 | F82: =-F37*$C$8*$C$21 -> 0 | G82: =-G37*$C$8*$C$21 -> 0 | H82: =-H37*$C$8*$C$21 -> 0 | I82: =-I37*$C$8*$C$21 -> 0 | J82: =-J37*$C$8*$C$21 -> 0 | K82: =-K37*$C$8*$C$21 -> 0 | ... AN82: =-AN37*$C$8*$C$21 -> 0
B83: (-) RET | D83: =-D47*$C$22 -> 0 | E83: =-E47*$C$22 -> -10848.865 | F83: =-F47*$C$22 -> -18443.07 | G83: =-G47*$C$22 -> -22782.616 | H83: =-H47*$C$22 -> -62812.603 | I83: =-I47*$C$22 -> -76618.558 | J83: =-J47*$C$22 -> -111372.9 | K83: =-K47*$C$22 -> -123551.52 | ... AN83: =-AN47*$C$22 -> -27122.162
B86: (=) FCFF | D86: =D75+D74+D76+D77+D78+D79+D80+D81+D82+D83-D71 -> -728170.88 | E86: =E75+E74+E76+E77+E78+E79+E80+E81+E82+E83-E71 -> -478646.99 | F86: =F75+F74+F76+F77+F78+F79+F80+F81+F82+F83-F71 -> -303980.26 | G86: =G75+G74+G76+G77+G78+G79+G80+G81+G82+G83-G71 -> -204170.71 | H86: =H75+H74+H76+H77+H78+H79+H80+H81+H82+H83-H71 -> -131881.02 | I86: =I75+I74+I76+I77+I78+I79+I80+I81+I82+I83-I71 -> 185655.96 | J86: =J75+J74+J76+J77+J78+J79+J80+J81+J82+J83-J71 -> 469805.75 | K86: =K75+K74+K76+K77+K78+K79+K80+K81+K82+K83-K71 -> 749914.14 | ... AN86: =AN75+AN74+AN76+AN77+AN78+AN79+AN80+AN81+AN82+AN83-AN71 -> 200025.95
B87: (=) FCFF Acumulado | D87: =D86 -> -728170.88 | E87: =D87+E86 -> -1206817.9 | F87: =E87+F86 -> -1510798.1 | G87: =F87+G86 -> -1714968.8 | H87: =G87+H86 -> -1846849.9 | I87: =H87+I86 -> -1661193.9 | J87: =I87+J86 -> -1191388.2 | K87: =J87+K86 -> -441474.01 | L87: =K87+L86 -> 615831.28 | ... AN87: =AM87+AN86 -> 27238400
B89: TIR Mensal | D89: =IRR(D86:AN86) -> 0.25953135
B90: TIR Anualizada | D90: =(1+D89)^12 -1 -> 14.940714
B92: Lucro Líquido | D92: =AN87 -> 27238400
B93: Exposição Máxima | D93: =-MIN(D87:AM87) -> 1846849.9
B94: Exposição em Relação ao VGV (%) | D94: =D93/C8 -> 0.016489731
B95: Margem Líquida | D95: =D92/AN46 -> 0.25333333
B96: WACC | D96: 0.1266
B97: WACC Mensal | D97: =(1+D96)^(1/12) - 1 -> 0.0099831901
A98: . | B98: VPL | D98: =D86+NPV(D97,E86:AN86) -> 22916738
F105: Sensibilidade TIR por CMV x VSO
E107: Margem bruta | F107: =D89 -> 0.25953135 | G107: 0.17 | H107: 0.19 | I107: 0.21 | J107: 0.23 | K107: 0.25
E108: =1-F108 -> 0.33 | F108: 0.67 | G108: 0.22010433 | H108: 0.22010433 | I108: 0.22010433 | J108: 0.22010433 | K108: 0.22010433
E109: =1-F109 -> 0.35 | F109: 0.65 | G109: 0.2401096 | H109: 0.2401096 | I109: 0.2401096 | J109: 0.2401096 | K109: 0.2401096
E110: =1-F110 -> 0.37 | F110: 0.63 | G110: 0.26003921 | H110: 0.26003921 | I110: 0.26003921 | J110: 0.26003921 | K110: 0.26003921
E111: =1-F111 -> 0.39 | F111: 0.61 | G111: 0.280025 | H111: 0.280025 | I111: 0.280025 | J111: 0.280025 | K111: 0.280025
E112: =1-F112 -> 0.41 | F112: 0.59 | G112: 0.30019477 | H112: 0.30019477 | I112: 0.30019477 | J112: 0.30019477 | K112: 0.30019477
E113: =1-F113 -> 0.43 | F113: 0.57 | G113: 0.32067542 | H113: 0.32067542 | I113: 0.32067542 | J113: 0.32067542 | K113: 0.32067542
E114: =1-F114 -> 0.45 | F114: 0.55 | G114: 0.34159601 | H114: 0.34159601 | I114: 0.34159601 | J114: 0.34159601 | K114: 0.34159601
